Workbook

Sheet Leads
A1: N° du lead | B1: Date et heure de réception | C1: Date et heure du 1er contact | D1: Délai de 1er contact (min) | E1: Prénom | F1: Nom | G1: Courriel | H1: Téléphone | I1: Entreprise | J1: Type de client | K1: Type d'événement | L1: Date de l'événement | M1: Ville | N1: Nombre d'invités | O1: Budget déclaré | P1: Route (formulaire) | Q1: Pointage (0-100) | R1: Étape du pipeline | S1: Raison de perte / disqualification | T1: Forfait proposé | U1: Montant proposé ($) | V1: Montant gagné ($) | W1: Date et heure du dépôt | X1: utm_source | Y1: utm_medium | Z1: utm_campaign | AA1: utm_content | AB1: utm_term | AC1: gclid (Google) | AD1: msclkid (Microsoft) | AE1: fbclid (Meta) | AF1: oppref (ChatGPT) | AG1: event_id (déduplication) | AH1: Consentement marketing | AI1: Consentement mesure | AJ1: Date du consentement | AK1: Désabonné | AL1: Conseiller | AM1: Notes | AN1: Rôle dans la décision | AO1: Échéance de décision | AP1: Source / campagne (forcer) | AQ1: Campagne (calculée) | AR1: Segment | AS1: Route selon les règles | AT1: Route retenue | AU1: Lead qualifié (A ou B) 1/0 | AV1: Gagné (dépôt payé ou plus) 1/0 | AW1: Priorité de rappel | AX1: Valeur de conversion provisoire ($) | AY1: Valeur ($) : gagnée ou pondérée | AZ1: Ligne EXEMPLE 1/0 | BA1: Rang import Google
A2: lead_id | B2: date_heure_reception | C2: date_heure_1er_contact | D2: delai_min | E2: prenom | F2: nom | G2: courriel | H2: telephone | I2: entreprise | J2: type_client | K2: type_evenement | L2: date_evenement | M2: ville | N2: nb_invites | O2: budget_declare | P2: route | Q2: lead_score | R2: etape | S2: raison_perte | T2: forfait_propose | U2: montant_propose | V2: montant_gagne | W2: date_depot | X2: utm_source | Y2: utm_medium | Z2: utm_campaign | AA2: utm_content | AB2: utm_term | AC2: gclid | AD2: msclkid | AE2: fbclid | AF2: oppref | AG2: event_id | AH2: consent_marketing | AI2: consent_mesure | AJ2: date_consentement | AK2: desabonne | AL2: conseiller | AM2: notes | AN2: role_decision | AO2: echeance_decision | AP2: campagne_manuelle | AQ2: campagne | AR2: segment | AS2: route_calculee | AT2: route_effective | AU2: qualifie | AV2: gagne | AW2: priorite_rappel | AX2: valeur_conv_provisoire | AY2: valeur | AZ2: est_exemple | BA2: rang_import
A3: EXEMPLE-001 | B3: 46296.425 | C3: 46296.428 | D3: =IF(OR(B3="",C3=""),"",ROUND((C3-B3)*1440,0)) | E3: Exemple | F3: Corpo-Party | G3: exemple1@exemple.com | H3: +15145550101 | I3: Entreprise Exemple inc. | J3: entreprise | K3: corpo_party | L3: 46367 | M3: Laval | N3: 75_149 | O3: 2500_4999 | P3: A | Q3: =IF(A3="","",IFERROR(VLOOKUP(O3,Listes!$R$3:$T$8,2,FALSE),0)+IFERROR(VLOOKUP(J3,Listes!$J$3:$L$6,2,FALSE),0)+IFERROR(VLOOKUP(N3,Listes!$N$3:$P$6,2,FALSE),0)+IF(OR(L3="",B3=""),0,IF(L3-INT(B3)<10,8,IF(L3-INT(B3)<=90,10,5)))+IFERROR(VLOOKUP(AN3,Listes!$V$3:$W$5,2,FALSE),0)+IFERROR(VLOOKUP(AO3,Listes!$Y$3:$Z$5,2,FALSE),0)) | R3: Dépôt payé (gagné) | T3: Gala Signature (2 495 $) | U3: 2495 | V3: 2495 | W3: 46298.604 | X3: google | Y3: cpc | Z3: gads_corpo_fetes | AA3: rsa_prixfixe_v1 | AB3: party de bureau | AC3: EXEMPLE-GCLID-001 | AG3: ex-0001 | AH3: oui | AI3: oui | AJ3: 46296.425 | AK3: non | AL3: Alexandre | AM3: EXEMPLE : supprimer cette ligne avant l'usage réel. | AN3: Je décide | AO3: Cette semaine | AQ3: =IF(A3="","",IF(AP3<>"",AP3,IF(LEFT(Z3,11)="gads_marque","Google Search – Marque",IF(LEFT(Z3,12)="gads_mariage","Google Search – Mariage et privé",IF(LEFT(Z3,10)="gads_corpo","Google Search – Corporatif",IF(LEFT(Z3,5)="meta_","Meta – Leads",IF(LEFT(Z3,5)="msft_","Microsoft Ads",IF(LEFT(Z3,8)="chatgpt_","ChatGPT Ads – Test",IF(X3="gbp","Fiche Google (organique)","Autre / non payé"))))))))) | AR3: =IF(K3="","",IFERROR(VLOOKUP(K3,Listes!$F$3:$H$8,3,FALSE),"")) | AS3: =IF(O3="","",IF(AND(M3="Autre (plus de 40 km)",OR(O3="lt600",O3="600_999",O3="1000_2499")),"D",IF(OR(O3="lt600",AND(O3="600_999",K3<>"mariage",K3<>"prive")),"C",IF(OR(O3="2500_4999",O3="5000p",J3="entreprise",J3="organisme",J3="agence"),"A",IF(OR(O3="1000_2499",O3="600_999"),"B",IF(O3="inconnu",IF(OR(N3="75_149",N3="150p"),"A","B"),"")))))) | AT3: =IF(A3="","",IF(P3<>"",P3,AS3)) | AU3: =IF(A3="","",IF(OR(AT3="A",AT3="B"),1,0)) | AV3: =IF(A3="","",IF(OR(R3="Dépôt payé (gagné)",R3="Événement livré",R3="Avis obtenu"),1,0)) | AW3: =IF(A3="","",IF(Q3>70,"Immédiat – propriétaire",IF(Q3>=40,"15 min – personne de garde","Selon la route"))) | AX3: =IF(A3="","",IF(AT3="A",400,IF(AT3="B",150,0))) | AY3: =IF(A3="","",IF(AV3=1,N(V3),IF(N(U3)>0,ROUND(N(U3)*IFERROR(VLOOKUP(R3,Listes!$AE$3:$AG$12,2,FALSE),0),0),0))) | AZ3: =IF(LEFT(A3,7)="EXEMPLE",1,0) | BA3: =IF(AND(AV3=1,AZ3=0,AC3<>"",W3<>"",N(V3)>0),COUNTIFS($AV$3:AV3,1,$AZ$3:AZ3,0,$AC$3:AC3,"<>",$W$3:W3,"<>",$V$3:V3,">0"),"")
A4: EXEMPLE-002 | B4: 46297.819 | C4: 46297.835 | D4: =IF(OR(B4="",C4=""),"",ROUND((C4-B4)*1440,0)) | E4: Exemple | F4: Mariage | G4: exemple2@exemple.com | H4: +14505550102 | J4: particulier | K4: mariage | L4: 46585 | M4: Mirabel | N4: 75_149 | O4: 1000_2499 | P4: B | Q4: =IF(A4="","",IFERROR(VLOOKUP(O4,Listes!$R$3:$T$8,2,FALSE),0)+IFERROR(VLOOKUP(J4,Listes!$J$3:$L$6,2,FALSE),0)+IFERROR(VLOOKUP(N4,Listes!$N$3:$P$6,2,FALSE),0)+IF(OR(L4="",B4=""),0,IF(L4-INT(B4)<10,8,IF(L4-INT(B4)<=90,10,5)))+IFERROR(VLOOKUP(AN4,Listes!$V$3:$W$5,2,FALSE),0)+IFERROR(VLOOKUP(AO4,Listes!$Y$3:$Z$5,2,FALSE),0)) | R4: Proposition envoyée | T4: Soirée Signature (1 449 $) | U4: 1449 | X4: google | Y4: cpc | Z4: gads_mariage_deco | AA4: rsa_dates_v1 | AB4: decor mariage | AC4: EXEMPLE-GCLID-002 | AG4: ex-0002 | AH4: non | AI4: oui | AJ4: 46297.819 | AK4: non | AL4: Alexandre | AM4: EXEMPLE : délai de 22 min sur une route B, la ligne est signalée en rouge. | AN4: Je décide | AO4: D'ici 30 jours | AQ4: =IF(A4="","",IF(AP4<>"",AP4,IF(LEFT(Z4,11)="gads_marque","Google Search – Marque",IF(LEFT(Z4,12)="gads_mariage","Google Search – Mariage et privé",IF(LEFT(Z4,10)="gads_corpo","Google Search – Corporatif",IF(LEFT(Z4,5)="meta_","Meta – Leads",IF(LEFT(Z4,5)="msft_","Microsoft Ads",IF(LEFT(Z4,8)="chatgpt_","ChatGPT Ads – Test",IF(X4="gbp","Fiche Google (organique)","Autre / non payé"))))))))) | AR4: =IF(K4="","",IFERROR(VLOOKUP(K4,Listes!$F$3:$H$8,3,FALSE),"")) | AS4: =IF(O4="","",IF(AND(M4="Autre (plus de 40 km)",OR(O4="lt600",O4="600_999",O4="1000_2499")),"D",IF(OR(O4="lt600",AND(O4="600_999",K4<>"mariage",K4<>"prive")),"C",IF(OR(O4="2500_4999",O4="5000p",J4="entreprise",J4="organisme",J4="agence"),"A",IF(OR(O4="1000_2499",O4="600_999"),"B",IF(O4="inconnu",IF(OR(N4="75_149",N4="150p"),"A","B"),"")))))) | AT4: =IF(A4="","",IF(P4<>"",P4,AS4)) | AU4: =IF(A4="","",IF(OR(AT4="A",AT4="B"),1,0)) | AV4: =IF(A4="","",IF(OR(R4="Dépôt payé (gagné)",R4="Événement livré",R4="Avis obtenu"),1,0)) | AW4: =IF(A4="","",IF(Q4>70,"Immédiat – propriétaire",IF(Q4>=40,"15 min – personne de garde","Selon la route"))) | AX4: =IF(A4="","",IF(AT4="A",400,IF(AT4="B",150,0))) | AY4: =IF(A4="","",IF(AV4=1,N(V4),IF(N(U4)>0,ROUND(N(U4)*IFERROR(VLOOKUP(R4,Listes!$AE$3:$AG$12,2,FALSE),0),0),0))) | AZ4: =IF(LEFT(A4,7)="EXEMPLE",1,0) | BA4: =IF(AND(AV4=1,AZ4=0,AC4<>"",W4<>"",N(V4)>0),COUNTIFS($AV$3:AV4,1,$AZ$3:AZ4,0,$AC$3:AC4,"<>",$W$3:W4,"<>",$V$3:V4,">0"),"")
A5: EXEMPLE-003 | B5: 46298.462 | D5: =IF(OR(B5="",C5=""),"",ROUND((C5-B5)*1440,0)) | E5: Exemple | F5: Privé | G5: exemple3@exemple.com | H5: +15145550103 | J5: particulier | K5: prive | L5: 46333 | M5: Boisbriand | N5: lt30 | O5: lt600 | P5: C | Q5: =IF(A5="","",IFERROR(VLOOKUP(O5,Listes!$R$3:$T$8,2,FALSE),0)+IFERROR(VLOOKUP(J5,Listes!$J$3:$L$6,2,FALSE),0)+IFERROR(VLOOKUP(N5,Listes!$N$3:$P$6,2,FALSE),0)+IF(OR(L5="",B5=""),0,IF(L5-INT(B5)<10,8,IF(L5-INT(B5)<=90,10,5)))+IFERROR(VLOOKUP(AN5,Listes!$V$3:$W$5,2,FALSE),0)+IFERROR(VLOOKUP(AO5,Listes!$Y$3:$Z$5,2,FALSE),0)) | R5: Disqualifié | S5: Disqualifié – budget < seuil | X5: meta | Y5: paid_social | Z5: meta_mariage_deco | AA5: reel_avantapres_v2 | AE5: EXEMPLE-FBCLID-003 | AG5: ex-0003 | AH5: non | AI5: non | AK5: non | AL5: Alexandre | AM5: EXEMPLE : route C, redirigé vers la boutique. | AN5: Je décide | AO5: Cette semaine | AQ5: =IF(A5="","",IF(AP5<>"",AP5,IF(LEFT(Z5,11)="gads_marque","Google Search – Marque",IF(LEFT(Z5,12)="gads_mariage","Google Search – Mariage et privé",IF(LEFT(Z5,10)="gads_corpo","Google Search – Corporatif",IF(LEFT(Z5,5)="meta_","Meta – Leads",IF(LEFT(Z5,5)="msft_","Microsoft Ads",IF(LEFT(Z5,8)="chatgpt_","ChatGPT Ads – Test",IF(X5="gbp","Fiche Google (organique)","Autre / non payé"))))))))) | AR5: =IF(K5="","",IFERROR(VLOOKUP(K5,Listes!$F$3:$H$8,3,FALSE),"")) | AS5: =IF(O5="","",IF(AND(M5="Autre (plus de 40 km)",OR(O5="lt600",O5="600_999",O5="1000_2499")),"D",IF(OR(O5="lt600",AND(O5="600_999",K5<>"mariage",K5<>"prive")),"C",IF(OR(O5="2500_4999",O5="5000p",J5="entreprise",J5="organisme",J5="agence"),"A",IF(OR(O5="1000_2499",O5="600_999"),"B",IF(O5="inconnu",IF(OR(N5="75_149",N5="150p"),"A","B"),"")))))) | AT5: =IF(A5="","",IF(P5<>"",P5,AS5)) | AU5: =IF(A5="","",IF(OR(AT5="A",AT5="B"),1,0)) | AV5: =IF(A5="","",IF(OR(R5="Dépôt payé (gagné)",R5="Événement livré",R5="Avis obtenu"),1,0)) | AW5: =IF(A5="","",IF(Q5>70,"Immédiat – propriétaire",IF(Q5>=40,"15 min – personne de garde","Selon la route"))) | AX5: =IF(A5="","",IF(AT5="A",400,IF(AT5="B",150,0))) | AY5: =IF(A5="","",IF(AV5=1,N(V5),IF(N(U5)>0,ROUND(N(U5)*IFERROR(VLOOKUP(R5,Listes!$AE$3:$AG$12,2,FALSE),0),0),0))) | AZ5: =IF(LEFT(A5,7)="EXEMPLE",1,0) | BA5: =IF(AND(AV5=1,AZ5=0,AC5<>"",W5<>"",N(V5)>0),COUNTIFS($AV$3:AV5,1,$AZ$3:AZ5,0,$AC$3:AC5,"<>",$W$3:W5,"<>",$V$3:V5,">0"),"")
A6: EXEMPLE-004 | B6: 46300.396 | C6: 46300.398 | D6: =IF(OR(B6="",C6=""),"",ROUND((C6-B6)*1440,0)) | E6: Exemple | F6: Gala | G6: exemple4@exemple.com | H6: +14505550104 | I6: Ville Exemple | J6: organisme | K6: corpo_gala | L6: 46438 | M6: Terrebonne | N6: 150p | O6: 5000p | P6: A | Q6: =IF(A6="","",IFERROR(VLOOKUP(O6,Listes!$R$3:$T$8,2,FALSE),0)+IFERROR(VLOOKUP(J6,Listes!$J$3:$L$6,2,FALSE),0)+IFERROR(VLOOKUP(N6,Listes!$N$3:$P$6,2,FALSE),0)+IF(OR(L6="",B6=""),0,IF(L6-INT(B6)<10,8,IF(L6-INT(B6)<=90,10,5)))+IFERROR(VLOOKUP(AN6,Listes!$V$3:$W$5,2,FALSE),0)+IFERROR(VLOOKUP(AO6,Listes!$Y$3:$Z$5,2,FALSE),0)) | R6: Négociation | T6: Sur mesure | U6: 3200 | X6: chatgpt | Y6: cpc | Z6: chatgpt_corpo_fetes | AA6: card_dates_dec_v1 | AF6: EXEMPLE-OPPREF-004 | AG6: ex-0004 | AH6: oui | AI6: non | AJ6: 46300.396 | AK6: non | AL6: Alexandre | AM6: EXEMPLE : comité, relance la veille de la réunion. | AN6: Je compare des options pour un comité | AO6: D'ici 30 jours | AQ6: =IF(A6="","",IF(AP6<>"",AP6,IF(LEFT(Z6,11)="gads_marque","Google Search – Marque",IF(LEFT(Z6,12)="gads_mariage","Google Search – Mariage et privé",IF(LEFT(Z6,10)="gads_corpo","Google Search – Corporatif",IF(LEFT(Z6,5)="meta_","Meta – Leads",IF(LEFT(Z6,5)="msft_","Microsoft Ads",IF(LEFT(Z6,8)="chatgpt_","ChatGPT Ads – Test",IF(X6="gbp","Fiche Google (organique)","Autre / non payé"))))))))) | AR6: =IF(K6="","",IFERROR(VLOOKUP(K6,Listes!$F$3:$H$8,3,FALSE),"")) | AS6: =IF(O6="","",IF(AND(M6="Autre (plus de 40 km)",OR(O6="lt600",O6="600_999",O6="1000_2499")),"D",IF(OR(O6="lt600",AND(O6="600_999",K6<>"mariage",K6<>"prive")),"C",IF(OR(O6="2500_4999",O6="5000p",J6="entreprise",J6="organisme",J6="agence"),"A",IF(OR(O6="1000_2499",O6="600_999"),"B",IF(O6="inconnu",IF(OR(N6="75_149",N6="150p"),"A","B"),"")))))) | AT6: =IF(A6="","",IF(P6<>"",P6,AS6)) | AU6: =IF(A6="","",IF(OR(AT6="A",AT6="B"),1,0)) | AV6: =IF(A6="","",IF(OR(R6="Dépôt payé (gagné)",R6="Événement livré",R6="Avis obtenu"),1,0)) | AW6: =IF(A6="","",IF(Q6>70,"Immédiat – propriétaire",IF(Q6>=40,"15 min – personne de garde","Selon la route"))) | AX6: =IF(A6="","",IF(AT6="A",400,IF(AT6="B",150,0))) | AY6: =IF(A6="","",IF(AV6=1,N(V6),IF(N(U6)>0,ROUND(N(U6)*IFERROR(VLOOKUP(R6,Listes!$AE$3:$AG$12,2,FALSE),0),0),0))) | AZ6: =IF(LEFT(A6,7)="EXEMPLE",1,0) | BA6: =IF(AND(AV6=1,AZ6=0,AC6<>"",W6<>"",N(V6)>0),COUNTIFS($AV$3:AV6,1,$AZ$3:AZ6,0,$AC$3:AC6,"<>",$W$3:W6,"<>",$V$3:V6,">0"),"")
A7: EXEMPLE-005 | B7: 46301.576 | C7: 46301.582 | D7: =IF(OR(B7="",C7=""),"",ROUND((C7-B7)*1440,0)) | E7: Exemple | F7: 5à7 | G7: exemple5@exemple.com | H7: +15145550105 | I7: PME Exemple | J7: entreprise | K7: corpo_5a7 | L7: 46352 | M7: Montréal – centre-ville | N7: 30_74 | O7: 1000_2499 | P7: A | Q7: =IF(A7="","",IFERROR(VLOOKUP(O7,Listes!$R$3:$T$8,2,FALSE),0)+IFERROR(VLOOKUP(J7,Listes!$J$3:$L$6,2,FALSE),0)+IFERROR(VLOOKUP(N7,Listes!$N$3:$P$6,2,FALSE),0)+IF(OR(L7="",B7=""),0,IF(L7-INT(B7)<10,8,IF(L7-INT(B7)<=90,10,5)))+IFERROR(VLOOKUP(AN7,Listes!$V$3:$W$5,2,FALSE),0)+IFERROR(VLOOKUP(AO7,Listes!$Y$3:$Z$5,2,FALSE),0)) | R7: Perdu | S7: Perdu – concurrent | T7: 5 à 7 (1 195 $) | U7: 1195 | X7: bing | Y7: cpc | Z7: msft_corpo | AA7: rsa_prixfixe_v1 | AB7: 5 a 7 entreprise | AD7: EXEMPLE-MSCLKID-005 | AG7: ex-0005 | AH7: non | AI7: non | AK7: non | AL7: Alexandre | AM7: EXEMPLE : concurrent = [nom] ; noter lequel. | AN7: Je recommande, quelqu'un d'autre approuve | AO7: Cette semaine | AQ7: =IF(A7="","",IF(AP7<>"",AP7,IF(LEFT(Z7,11)="gads_marque","Google Search – Marque",IF(LEFT(Z7,12)="gads_mariage","Google Search – Mariage et privé",IF(LEFT(Z7,10)="gads_corpo","Google Search – Corporatif",IF(LEFT(Z7,5)="meta_","Meta – Leads",IF(LEFT(Z7,5)="msft_","Microsoft Ads",IF(LEFT(Z7,8)="chatgpt_","ChatGPT Ads – Test",IF(X7="gbp","Fiche Google (organique)","Autre / non payé"))))))))) | AR7: =IF(K7="","",IFERROR(VLOOKUP(K7,Listes!$F$3:$H$8,3,FALSE),"")) | AS7: =IF(O7="","",IF(AND(M7="Autre (plus de 40 km)",OR(O7="lt600",O7="600_999",O7="1000_2499")),"D",IF(OR(O7="lt600",AND(O7="600_999",K7<>"mariage",K7<>"prive")),"C",IF(OR(O7="2500_4999",O7="5000p",J7="entreprise",J7="organisme",J7="agence"),"A",IF(OR(O7="1000_2499",O7="600_999"),"B",IF(O7="inconnu",IF(OR(N7="75_149",N7="150p"),"A","B"),"")))))) | AT7: =IF(A7="","",IF(P7<>"",P7,AS7)) | AU7: =IF(A7="","",IF(OR(AT7="A",AT7="B"),1,0)) | AV7: =IF(A7="","",IF(OR(R7="Dépôt payé (gagné)",R7="Événement livré",R7="Avis obtenu"),1,0)) | AW7: =IF(A7="","",IF(Q7>70,"Immédiat – propriétaire",IF(Q7>=40,"15 min – personne de garde","Selon la route"))) | AX7: =IF(A7="","",IF(AT7="A",400,IF(AT7="B",150,0))) | AY7: =IF(A7="","",IF(AV7=1,N(V7),IF(N(U7)>0,ROUND(N(U7)*IFERROR(VLOOKUP(R7,Listes!$AE$3:$AG$12,2,FALSE),0),0),0))) | AZ7: =IF(LEFT(A7,7)="EXEMPLE",1,0) | BA7: =IF(AND(AV7=1,AZ7=0,AC7<>"",W7<>"",N(V7)>0),COUNTIFS($AV$3:AV7,1,$AZ$3:AZ7,0,$AC$3:AC7,"<>",$W$3:W7,"<>",$V$3:V7,">0"),"")
D8: =IF(OR(B8="",C8=""),"",ROUND((C8-B8)*1440,0)) | Q8: =IF(A8="","",IFERROR(VLOOKUP(O8,Listes!$R$3:$T$8,2,FALSE),0)+IFERROR(VLOOKUP(J8,Listes!$J$3:$L$6,2,FALSE),0)+IFERROR(VLOOKUP(N8,Listes!$N$3:$P$6,2,FALSE),0)+IF(OR(L8="",B8=""),0,IF(L8-INT(B8)<10,8,IF(L8-INT(B8)<=90,10,5)))+IFERROR(VLOOKUP(AN8,Listes!$V$3:$W$5,2,FALSE),0)+IFERROR(VLOOKUP(AO8,Listes!$Y$3:$Z$5,2,FALSE),0)) | AQ8: =IF(A8="","",IF(AP8<>"",AP8,IF(LEFT(Z8,11)="gads_marque","Google Search – Marque",IF(LEFT(Z8,12)="gads_mariage","Google Search – Mariage et privé",IF(LEFT(Z8,10)="gads_corpo","Google Search – Corporatif",IF(LEFT(Z8,5)="meta_","Meta – Leads",IF(LEFT(Z8,5)="msft_","Microsoft Ads",IF(LEFT(Z8,8)="chatgpt_","ChatGPT Ads – Test",IF(X8="gbp","Fiche Google (organique)","Autre / non payé"))))))))) | AR8: =IF(K8="","",IFERROR(VLOOKUP(K8,Listes!$F$3:$H$8,3,FALSE),"")) | AS8: =IF(O8="","",IF(AND(M8="Autre (plus de 40 km)",OR(O8="lt600",O8="600_999",O8="1000_2499")),"D",IF(OR(O8="lt600",AND(O8="600_999",K8<>"mariage",K8<>"prive")),"C",IF(OR(O8="2500_4999",O8="5000p",J8="entreprise",J8="organisme",J8="agence"),"A",IF(OR(O8="1000_2499",O8="600_999"),"B",IF(O8="inconnu",IF(OR(N8="75_149",N8="150p"),"A","B"),"")))))) | AT8: =IF(A8="","",IF(P8<>"",P8,AS8)) | AU8: =IF(A8="","",IF(OR(AT8="A",AT8="B"),1,0)) | AV8: =IF(A8="","",IF(OR(R8="Dépôt payé (gagné)",R8="Événement livré",R8="Avis obtenu"),1,0)) | AW8: =IF(A8="","",IF(Q8>70,"Immédiat – propriétaire",IF(Q8>=40,"15 min – personne de garde","Selon la route"))) | AX8: =IF(A8="","",IF(AT8="A",400,IF(AT8="B",150,0))) | AY8: =IF(A8="","",IF(AV8=1,N(V8),IF(N(U8)>0,ROUND(N(U8)*IFERROR(VLOOKUP(R8,Listes!$AE$3:$AG$12,2,FALSE),0),0),0))) | AZ8: =IF(LEFT(A8,7)="EXEMPLE",1,0) | BA8: =IF(AND(AV8=1,AZ8=0,AC8<>"",W8<>"",N(V8)>0),COUNTIFS($AV$3:AV8,1,$AZ$3:AZ8,0,$AC$3:AC8,"<>",$W$3:W8,"<>",$V$3:V8,">0"),"")
D9: =IF(OR(B9="",C9=""),"",ROUND((C9-B9)*1440,0)) | Q9: =IF(A9="","",IFERROR(VLOOKUP(O9,Listes!$R$3:$T$8,2,FALSE),0)+IFERROR(VLOOKUP(J9,Listes!$J$3:$L$6,2,FALSE),0)+IFERROR(VLOOKUP(N9,Listes!$N$3:$P$6,2,FALSE),0)+IF(OR(L9="",B9=""),0,IF(L9-INT(B9)<10,8,IF(L9-INT(B9)<=90,10,5)))+IFERROR(VLOOKUP(AN9,Listes!$V$3:$W$5,2,FALSE),0)+IFERROR(VLOOKUP(AO9,Listes!$Y$3:$Z$5,2,FALSE),0)) | AQ9: =IF(A9="","",IF(AP9<>"",AP9,IF(LEFT(Z9,11)="gads_marque","Google Search – Marque",IF(LEFT(Z9,12)="gads_mariage","Google Search – Mariage et privé",IF(LEFT(Z9,10)="gads_corpo","Google Search – Corporatif",IF(LEFT(Z9,5)="meta_","Meta – Leads",IF(LEFT(Z9,5)="msft_","Microsoft Ads",IF(LEFT(Z9,8)="chatgpt_","ChatGPT Ads – Test",IF(X9="gbp","Fiche Google (organique)","Autre / non payé"))))))))) | AR9: =IF(K9="","",IFERROR(VLOOKUP(K9,Listes!$F$3:$H$8,3,FALSE),"")) | AS9: =IF(O9="","",IF(AND(M9="Autre (plus de 40 km)",OR(O9="lt600",O9="600_999",O9="1000_2499")),"D",IF(OR(O9="lt600",AND(O9="600_999",K9<>"mariage",K9<>"prive")),"C",IF(OR(O9="2500_4999",O9="5000p",J9="entreprise",J9="organisme",J9="agence"),"A",IF(OR(O9="1000_2499",O9="600_999"),"B",IF(O9="inconnu",IF(OR(N9="75_149",N9="150p"),"A","B"),"")))))) | AT9: =IF(A9="","",IF(P9<>"",P9,AS9)) | AU9: =IF(A9="","",IF(OR(AT9="A",AT9="B"),1,0)) | AV9: =IF(A9="","",IF(OR(R9="Dépôt payé (gagné)",R9="Événement livré",R9="Avis obtenu"),1,0)) | AW9: =IF(A9="","",IF(Q9>70,"Immédiat – propriétaire",IF(Q9>=40,"15 min – personne de garde","Selon la route"))) | AX9: =IF(A9="","",IF(AT9="A",400,IF(AT9="B",150,0))) | AY9: =IF(A9="","",IF(AV9=1,N(V9),IF(N(U9)>0,ROUND(N(U9)*IFERROR(VLOOKUP(R9,Listes!$AE$3:$AG$12,2,FALSE),0),0),0))) | AZ9: =IF(LEFT(A9,7)="EXEMPLE",1,0) | BA9: =IF(AND(AV9=1,AZ9=0,AC9<>"",W9<>"",N(V9)>0),COUNTIFS($AV$3:AV9,1,$AZ$3:AZ9,0,$AC$3:AC9,"<>",$W$3:W9,"<>",$V$3:V9,">0"),"")
D10: =IF(OR(B10="",C10=""),"",ROUND((C10-B10)*1440,0)) | Q10: =IF(A10="","",IFERROR(VLOOKUP(O10,Listes!$R$3:$T$8,2,FALSE),0)+IFERROR(VLOOKUP(J10,Listes!$J$3:$L$6,2,FALSE),0)+IFERROR(VLOOKUP(N10,Listes!$N$3:$P$6,2,FALSE),0)+IF(OR(L10="",B10=""),0,IF(L10-INT(B10)<10,8,IF(L10-INT(B10)<=90,10,5)))+IFERROR(VLOOKUP(AN10,Listes!$V$3:$W$5,2,FALSE),0)+IFERROR(VLOOKUP(AO10,Listes!$Y$3:$Z$5,2,FALSE),0)) | AQ10: =IF(A10="","",IF(AP10<>"",AP10,IF(LEFT(Z10,11)="gads_marque","Google Search – Marque",IF(LEFT(Z10,12)="gads_mariage","Google Search – Mariage et privé",IF(LEFT(Z10,10)="gads_corpo","Google Search – Corporatif",IF(LEFT(Z10,5)="meta_","Meta – Leads",IF(LEFT(Z10,5)="msft_","Microsoft Ads",IF(LEFT(Z10,8)="chatgpt_","ChatGPT Ads – Test",IF(X10="gbp","Fiche Google (organique)","Autre / non payé"))))))))) | AR10: =IF(K10="","",IFERROR(VLOOKUP(K10,Listes!$F$3:$H$8,3,FALSE),"")) | AS10: =IF(O10="","",IF(AND(M10="Autre (plus de 40 km)",OR(O10="lt600",O10="600_999",O10="1000_2499")),"D",IF(OR(O10="lt600",AND(O10="600_999",K10<>"mariage",K10<>"prive")),"C",IF(OR(O10="2500_4999",O10="5000p",J10="entreprise",J10="organisme",J10="agence"),"A",IF(OR(O10="1000_2499",O10="600_999"),"B",IF(O10="inconnu",IF(OR(N10="75_149",N10="150p"),"A","B"),"")))))) | AT10: =IF(A10="","",IF(P10<>"",P10,AS10)) | AU10: =IF(A10="","",IF(OR(AT10="A",AT10="B"),1,0)) | AV10: =IF(A10="","",IF(OR(R10="Dépôt payé (gagné)",R10="Événement livré",R10="Avis obtenu"),1,0)) | AW10: =IF(A10="","",IF(Q10>70,"Immédiat – propriétaire",IF(Q10>=40,"15 min – personne de garde","Selon la route"))) | AX10: =IF(A10="","",IF(AT10="A",400,IF(AT10="B",150,0))) | AY10: =IF(A10="","",IF(AV10=1,N(V10),IF(N(U10)>0,ROUND(N(U10)*IFERROR(VLOOKUP(R10,Listes!$AE$3:$AG$12,2,FALSE),0),0),0))) | AZ10: =IF(LEFT(A10,7)="EXEMPLE",1,0) | BA10: =IF(AND(AV10=1,AZ10=0,AC10<>"",W10<>"",N(V10)>0),COUNTIFS($AV$3:AV10,1,$AZ$3:AZ10,0,$AC$3:AC10,"<>",$W$3:W10,"<>",$V$3:V10,">0"),"")
D11: =IF(OR(B11="",C11=""),"",ROUND((C11-B11)*1440,0)) | Q11: =IF(A11="","",IFERROR(VLOOKUP(O11,Listes!$R$3:$T$8,2,FALSE),0)+IFERROR(VLOOKUP(J11,Listes!$J$3:$L$6,2,FALSE),0)+IFERROR(VLOOKUP(N11,Listes!$N$3:$P$6,2,FALSE),0)+IF(OR(L11="",B11=""),0,IF(L11-INT(B11)<10,8,IF(L11-INT(B11)<=90,10,5)))+IFERROR(VLOOKUP(AN11,Listes!$V$3:$W$5,2,FALSE),0)+IFERROR(VLOOKUP(AO11,Listes!$Y$3:$Z$5,2,FALSE),0)) | AQ11: =IF(A11="","",IF(AP11<>"",AP11,IF(LEFT(Z11,11)="gads_marque","Google Search – Marque",IF(LEFT(Z11,12)="gads_mariage","Google Search – Mariage et privé",IF(LEFT(Z11,10)="gads_corpo","Google Search – Corporatif",IF(LEFT(Z11,5)="meta_","Meta – Leads",IF(LEFT(Z11,5)="msft_","Microsoft Ads",IF(LEFT(Z11,8)="chatgpt_","ChatGPT Ads – Test",IF(X11="gbp","Fiche Google (organique)","Autre / non payé"))))))))) | AR11: =IF(K11="","",IFERROR(VLOOKUP(K11,Listes!$F$3:$H$8,3,FALSE),"")) | AS11: =IF(O11="","",IF(AND(M11="Autre (plus de 40 km)",OR(O11="lt600",O11="600_999",O11="1000_2499")),"D",IF(OR(O11="lt600",AND(O11="600_999",K11<>"mariage",K11<>"prive")),"C",IF(OR(O11="2500_4999",O11="5000p",J11="entreprise",J11="organisme",J11="agence"),"A",IF(OR(O11="1000_2499",O11="600_999"),"B",IF(O11="inconnu",IF(OR(N11="75_149",N11="150p"),"A","B"),"")))))) | AT11: =IF(A11="","",IF(P11<>"",P11,AS11)) | AU11: =IF(A11="","",IF(OR(AT11="A",AT11="B"),1,0)) | AV11: =IF(A11="","",IF(OR(R11="Dépôt payé (gagné)",R11="Événement livré",R11="Avis obtenu"),1,0)) | AW11: =IF(A11="","",IF(Q11>70,"Immédiat – propriétaire",IF(Q11>=40,"15 min – personne de garde","Selon la route"))) | AX11: =IF(A11="","",IF(AT11="A",400,IF(AT11="B",150,0))) | AY11: =IF(A11="","",IF(AV11=1,N(V11),IF(N(U11)>0,ROUND(N(U11)*IFERROR(VLOOKUP(R11,Listes!$AE$3:$AG$12,2,FALSE),0),0),0))) | AZ11: =IF(LEFT(A11,7)="EXEMPLE",1,0) | BA11: =IF(AND(AV11=1,AZ11=0,AC11<>"",W11<>"",N(V11)>0),COUNTIFS($AV$3:AV11,1,$AZ$3:AZ11,0,$AC$3:AC11,"<>",$W$3:W11,"<>",$V$3:V11,">0"),"")
D12: =IF(OR(B12="",C12=""),"",ROUND((C12-B12)*1440,0)) | Q12: =IF(A12="","",IFERROR(VLOOKUP(O12,Listes!$R$3:$T$8,2,FALSE),0)+IFERROR(VLOOKUP(J12,Listes!$J$3:$L$6,2,FALSE),0)+IFERROR(VLOOKUP(N12,Listes!$N$3:$P$6,2,FALSE),0)+IF(OR(L12="",B12=""),0,IF(L12-INT(B12)<10,8,IF(L12-INT(B12)<=90,10,5)))+IFERROR(VLOOKUP(AN12,Listes!$V$3:$W$5,2,FALSE),0)+IFERROR(VLOOKUP(AO12,Listes!$Y$3:$Z$5,2,FALSE),0)) | AQ12: =IF(A12="","",IF(AP12<>"",AP12,IF(LEFT(Z12,11)="gads_marque","Google Search – Marque",IF(LEFT(Z12,12)="gads_mariage","Google Search – Mariage et privé",IF(LEFT(Z12,10)="gads_corpo","Google Search – Corporatif",IF(LEFT(Z12,5)="meta_","Meta – Leads",IF(LEFT(Z12,5)="msft_","Microsoft Ads",IF(LEFT(Z12,8)="chatgpt_","ChatGPT Ads – Test",IF(X12="gbp","Fiche Google (organique)","Autre / non payé"))))))))) | AR12: =IF(K12="","",IFERROR(VLOOKUP(K12,Listes!$F$3:$H$8,3,FALSE),"")) | AS12: =IF(O12="","",IF(AND(M12="Autre (plus de 40 km)",OR(O12="lt600",O12="600_999",O12="1000_2499")),"D",IF(OR(O12="lt600",AND(O12="600_999",K12<>"mariage",K12<>"prive")),"C",IF(OR(O12="2500_4999",O12="5000p",J12="entreprise",J12="organisme",J12="agence"),"A",IF(OR(O12="1000_2499",O12="600_999"),"B",IF(O12="inconnu",IF(OR(N12="75_149",N12="150p"),"A","B"),"")))))) | AT12: =IF(A12="","",IF(P12<>"",P12,AS12)) | AU12: =IF(A12="","",IF(OR(AT12="A",AT12="B"),1,0)) | AV12: =IF(A12="","",IF(OR(R12="Dépôt payé (gagné)",R12="Événement livré",R12="Avis obtenu"),1,0)) | AW12: =IF(A12="","",IF(Q12>70,"Immédiat – propriétaire",IF(Q12>=40,"15 min – personne de garde","Selon la route"))) | AX12: =IF(A12="","",IF(AT12="A",400,IF(AT12="B",150,0))) | AY12: =IF(A12="","",IF(AV12=1,N(V12),IF(N(U12)>0,ROUND(N(U12)*IFERROR(VLOOKUP(R12,Listes!$AE$3:$AG$12,2,FALSE),0),0),0))) | AZ12: =IF(LEFT(A12,7)="EXEMPLE",1,0) | BA12: =IF(AND(AV12=1,AZ12=0,AC12<>"",W12<>"",N(V12)>0),COUNTIFS($AV$3:AV12,1,$AZ$3:AZ12,0,$AC$3:AC12,"<>",$W$3:W12,"<>",$V$3:V12,">0"),"")
D13: =IF(OR(B13="",C13=""),"",ROUND((C13-B13)*1440,0)) | Q13: =IF(A13="","",IFERROR(VLOOKUP(O13,Listes!$R$3:$T$8,2,FALSE),0)+IFERROR(VLOOKUP(J13,Listes!$J$3:$L$6,2,FALSE),0)+IFERROR(VLOOKUP(N13,Listes!$N$3:$P$6,2,FALSE),0)+IF(OR(L13="",B13=""),0,IF(L13-INT(B13)<10,8,IF(L13-INT(B13)<=90,10,5)))+IFERROR(VLOOKUP(AN13,Listes!$V$3:$W$5,2,FALSE),0)+IFERROR(VLOOKUP(AO13,Listes!$Y$3:$Z$5,2,FALSE),0)) | AQ13: =IF(A13="","",IF(AP13<>"",AP13,IF(LEFT(Z13,11)="gads_marque","Google Search – Marque",IF(LEFT(Z13,12)="gads_mariage","Google Search – Mariage et privé",IF(LEFT(Z13,10)="gads_corpo","Google Search – Corporatif",IF(LEFT(Z13,5)="meta_","Meta – Leads",IF(LEFT(Z13,5)="msft_","Microsoft Ads",IF(LEFT(Z13,8)="chatgpt_","ChatGPT Ads – Test",IF(X13="gbp","Fiche Google (organique)","Autre / non payé"))))))))) | AR13: =IF(K13="","",IFERROR(VLOOKUP(K13,Listes!$F$3:$H$8,3,FALSE),"")) | AS13: =IF(O13="","",IF(AND(M13="Autre (plus de 40 km)",OR(O13="lt600",O13="600_999",O13="1000_2499")),"D",IF(OR(O13="lt600",AND(O13="600_999",K13<>"mariage",K13<>"prive")),"C",IF(OR(O13="2500_4999",O13="5000p",J13="entreprise",J13="organisme",J13="agence"),"A",IF(OR(O13="1000_2499",O13="600_999"),"B",IF(O13="inconnu",IF(OR(N13="75_149",N13="150p"),"A","B"),"")))))) | AT13: =IF(A13="","",IF(P13<>"",P13,AS13)) | AU13: =IF(A13="","",IF(OR(AT13="A",AT13="B"),1,0)) | AV13: =IF(A13="","",IF(OR(R13="Dépôt payé (gagné)",R13="Événement livré",R13="Avis obtenu"),1,0)) | AW13: =IF(A13="","",IF(Q13>70,"Immédiat – propriétaire",IF(Q13>=40,"15 min – personne de garde","Selon la route"))) | AX13: =IF(A13="","",IF(AT13="A",400,IF(AT13="B",150,0))) | AY13: =IF(A13="","",IF(AV13=1,N(V13),IF(N(U13)>0,ROUND(N(U13)*IFERROR(VLOOKUP(R13,Listes!$AE$3:$AG$12,2,FALSE),0),0),0))) | AZ13: =IF(LEFT(A13,7)="EXEMPLE",1,0) | BA13: =IF(AND(AV13=1,AZ13=0,AC13<>"",W13<>"",N(V13)>0),COUNTIFS($AV$3:AV13,1,$AZ$3:AZ13,0,$AC$3:AC13,"<>",$W$3:W13,"<>",$V$3:V13,">0"),"")
D14: =IF(OR(B14="",C14=""),"",ROUND((C14-B14)*1440,0)) | Q14: =IF(A14="","",IFERROR(VLOOKUP(O14,Listes!$R$3:$T$8,2,FALSE),0)+IFERROR(VLOOKUP(J14,Listes!$J$3:$L$6,2,FALSE),0)+IFERROR(VLOOKUP(N14,Listes!$N$3:$P$6,2,FALSE),0)+IF(OR(L14="",B14=""),0,IF(L14-INT(B14)<10,8,IF(L14-INT(B14)<=90,10,5)))+IFERROR(VLOOKUP(AN14,Listes!$V$3:$W$5,2,FALSE),0)+IFERROR(VLOOKUP(AO14,Listes!$Y$3:$Z$5,2,FALSE),0)) | AQ14: =IF(A14="","",IF(AP14<>"",AP14,IF(LEFT(Z14,11)="gads_marque","Google Search – Marque",IF(LEFT(Z14,12)="gads_mariage","Google Search – Mariage et privé",IF(LEFT(Z14,10)="gads_corpo","Google Search – Corporatif",IF(LEFT(Z14,5)="meta_","Meta – Leads",IF(LEFT(Z14,5)="msft_","Microsoft Ads",IF(LEFT(Z14,8)="chatgpt_","ChatGPT Ads – Test",IF(X14="gbp","Fiche Google (organique)","Autre / non payé"))))))))) | AR14: =IF(K14="","",IFERROR(VLOOKUP(K14,Listes!$F$3:$H$8,3,FALSE),"")) | AS14: =IF(O14="","",IF(AND(M14="Autre (plus de 40 km)",OR(O14="lt600",O14="600_999",O14="1000_2499")),"D",IF(OR(O14="lt600",AND(O14="600_999",K14<>"mariage",K14<>"prive")),"C",IF(OR(O14="2500_4999",O14="5000p",J14="entreprise",J14="organisme",J14="agence"),"A",IF(OR(O14="1000_2499",O14="600_999"),"B",IF(O14="inconnu",IF(OR(N14="75_149",N14="150p"),"A","B"),"")))))) | AT14: =IF(A14="","",IF(P14<>"",P14,AS14)) | AU14: =IF(A14="","",IF(OR(AT14="A",AT14="B"),1,0)) | AV14: =IF(A14="","",IF(OR(R14="Dépôt payé (gagné)",R14="Événement livré",R14="Avis obtenu"),1,0)) | AW14: =IF(A14="","",IF(Q14>70,"Immédiat – propriétaire",IF(Q14>=40,"15 min – personne de garde","Selon la route"))) | AX14: =IF(A14="","",IF(AT14="A",400,IF(AT14="B",150,0))) | AY14: =IF(A14="","",IF(AV14=1,N(V14),IF(N(U14)>0,ROUND(N(U14)*IFERROR(VLOOKUP(R14,Listes!$AE$3:$AG$12,2,FALSE),0),0),0))) | AZ14: =IF(LEFT(A14,7)="EXEMPLE",1,0) | BA14: =IF(AND(AV14=1,AZ14=0,AC14<>"",W14<>"",N(V14)>0),COUNTIFS($AV$3:AV14,1,$AZ$3:AZ14,0,$AC$3:AC14,"<>",$W$3:W14,"<>",$V$3:V14,">0"),"")
D15: =IF(OR(B15="",C15=""),"",ROUND((C15-B15)*1440,0)) | Q15: =IF(A15="","",IFERROR(VLOOKUP(O15,Listes!$R$3:$T$8,2,FALSE),0)+IFERROR(VLOOKUP(J15,Listes!$J$3:$L$6,2,FALSE),0)+IFERROR(VLOOKUP(N15,Listes!$N$3:$P$6,2,FALSE),0)+IF(OR(L15="",B15=""),0,IF(L15-INT(B15)<10,8,IF(L15-INT(B15)<=90,10,5)))+IFERROR(VLOOKUP(AN15,Listes!$V$3:$W$5,2,FALSE),0)+IFERROR(VLOOKUP(AO15,Listes!$Y$3:$Z$5,2,FALSE),0)) | AQ15: =IF(A15="","",IF(AP15<>"",AP15,IF(LEFT(Z15,11)="gads_marque","Google Search – Marque",IF(LEFT(Z15,12)="gads_mariage","Google Search – Mariage et privé",IF(LEFT(Z15,10)="gads_corpo","Google Search – Corporatif",IF(LEFT(Z15,5)="meta_","Meta – Leads",IF(LEFT(Z15,5)="msft_","Microsoft Ads",IF(LEFT(Z15,8)="chatgpt_","ChatGPT Ads – Test",IF(X15="gbp","Fiche Google (organique)","Autre / non payé"))))))))) | AR15: =IF(K15="","",IFERROR(VLOOKUP(K15,Listes!$F$3:$H$8,3,FALSE),"")) | AS15: =IF(O15="","",IF(AND(M15="Autre (plus de 40 km)",OR(O15="lt600",O15="600_999",O15="1000_2499")),"D",IF(OR(O15="lt600",AND(O15="600_999",K15<>"mariage",K15<>"prive")),"C",IF(OR(O15="2500_4999",O15="5000p",J15="entreprise",J15="organisme",J15="agence"),"A",IF(OR(O15="1000_2499",O15="600_999"),"B",IF(O15="inconnu",IF(OR(N15="75_149",N15="150p"),"A","B"),"")))))) | AT15: =IF(A15="","",IF(P15<>"",P15,AS15)) | AU15: =IF(A15="","",IF(OR(AT15="A",AT15="B"),1,0)) | AV15: =IF(A15="","",IF(OR(R15="Dépôt payé (gagné)",R15="Événement livré",R15="Avis obtenu"),1,0)) | AW15: =IF(A15="","",IF(Q15>70,"Immédiat – propriétaire",IF(Q15>=40,"15 min – personne de garde","Selon la route"))) | AX15: =IF(A15="","",IF(AT15="A",400,IF(AT15="B",150,0))) | AY15: =IF(A15="","",IF(AV15=1,N(V15),IF(N(U15)>0,ROUND(N(U15)*IFERROR(VLOOKUP(R15,Listes!$AE$3:$AG$12,2,FALSE),0),0),0))) | AZ15: =IF(LEFT(A15,7)="EXEMPLE",1,0) | BA15: =IF(AND(AV15=1,AZ15=0,AC15<>"",W15<>"",N(V15)>0),COUNTIFS($AV$3:AV15,1,$AZ$3:AZ15,0,$AC$3:AC15,"<>",$W$3:W15,"<>",$V$3:V15,">0"),"")
D16: =IF(OR(B16="",C16=""),"",ROUND((C16-B16)*1440,0)) | Q16: =IF(A16="","",IFERROR(VLOOKUP(O16,Listes!$R$3:$T$8,2,FALSE),0)+IFERROR(VLOOKUP(J16,Listes!$J$3:$L$6,2,FALSE),0)+IFERROR(VLOOKUP(N16,Listes!$N$3:$P$6,2,FALSE),0)+IF(OR(L16="",B16=""),0,IF(L16-INT(B16)<10,8,IF(L16-INT(B16)<=90,10,5)))+IFERROR(VLOOKUP(AN16,Listes!$V$3:$W$5,2,FALSE),0)+IFERROR(VLOOKUP(AO16,Listes!$Y$3:$Z$5,2,FALSE),0)) | AQ16: =IF(A16="","",IF(AP16<>"",AP16,IF(LEFT(Z16,11)="gads_marque","Google Search – Marque",IF(LEFT(Z16,12)="gads_mariage","Google Search – Mariage et privé",IF(LEFT(Z16,10)="gads_corpo","Google Search – Corporatif",IF(LEFT(Z16,5)="meta_","Meta – Leads",IF(LEFT(Z16,5)="msft_","Microsoft Ads",IF(LEFT(Z16,8)="chatgpt_","ChatGPT Ads – Test",IF(X16="gbp","Fiche Google (organique)","Autre / non payé"))))))))) | AR16: =IF(K16="","",IFERROR(VLOOKUP(K16,Listes!$F$3:$H$8,3,FALSE),"")) | AS16: =IF(O16="","",IF(AND(M16="Autre (plus de 40 km)",OR(O16="lt600",O16="600_999",O16="1000_2499")),"D",IF(OR(O16="lt600",AND(O16="600_999",K16<>"mariage",K16<>"prive")),"C",IF(OR(O16="2500_4999",O16="5000p",J16="entreprise",J16="organisme",J16="agence"),"A",IF(OR(O16="1000_2499",O16="600_999"),"B",IF(O16="inconnu",IF(OR(N16="75_149",N16="150p"),"A","B"),"")))))) | AT16: =IF(A16="","",IF(P16<>"",P16,AS16)) | AU16: =IF(A16="","",IF(OR(AT16="A",AT16="B"),1,0)) | AV16: =IF(A16="","",IF(OR(R16="Dépôt payé (gagné)",R16="Événement livré",R16="Avis obtenu"),1,0)) | AW16: =IF(A16="","",IF(Q16>70,"Immédiat – propriétaire",IF(Q16>=40,"15 min – personne de garde","Selon la route"))) | AX16: =IF(A16="","",IF(AT16="A",400,IF(AT16="B",150,0))) | AY16: =IF(A16="","",IF(AV16=1,N(V16),IF(N(U16)>0,ROUND(N(U16)*IFERROR(VLOOKUP(R16,Listes!$AE$3:$AG$12,2,FALSE),0),0),0))) | AZ16: =IF(LEFT(A16,7)="EXEMPLE",1,0) | BA16: =IF(AND(AV16=1,AZ16=0,AC16<>"",W16<>"",N(V16)>0),COUNTIFS($AV$3:AV16,1,$AZ$3:AZ16,0,$AC$3:AC16,"<>",$W$3:W16,"<>",$V$3:V16,">0"),"")
D17: =IF(OR(B17="",C17=""),"",ROUND((C17-B17)*1440,0)) | Q17: =IF(A17="","",IFERROR(VLOOKUP(O17,Listes!$R$3:$T$8,2,FALSE),0)+IFERROR(VLOOKUP(J17,Listes!$J$3:$L$6,2,FALSE),0)+IFERROR(VLOOKUP(N17,Listes!$N$3:$P$6,2,FALSE),0)+IF(OR(L17="",B17=""),0,IF(L17-INT(B17)<10,8,IF(L17-INT(B17)<=90,10,5)))+IFERROR(VLOOKUP(AN17,Listes!$V$3:$W$5,2,FALSE),0)+IFERROR(VLOOKUP(AO17,Listes!$Y$3:$Z$5,2,FALSE),0)) | AQ17: =IF(A17="","",IF(AP17<>"",AP17,IF(LEFT(Z17,11)="gads_marque","Google Search – Marque",IF(LEFT(Z17,12)="gads_mariage","Google Search – Mariage et privé",IF(LEFT(Z17,10)="gads_corpo","Google Search – Corporatif",IF(LEFT(Z17,5)="meta_","Meta – Leads",IF(LEFT(Z17,5)="msft_","Microsoft Ads",IF(LEFT(Z17,8)="chatgpt_","ChatGPT Ads – Test",IF(X17="gbp","Fiche Google (organique)","Autre / non payé"))))))))) | AR17: =IF(K17="","",IFERROR(VLOOKUP(K17,Listes!$F$3:$H$8,3,FALSE),"")) | AS17: =IF(O17="","",IF(AND(M17="Autre (plus de 40 km)",OR(O17="lt600",O17="600_999",O17="1000_2499")),"D",IF(OR(O17="lt600",AND(O17="600_999",K17<>"mariage",K17<>"prive")),"C",IF(OR(O17="2500_4999",O17="5000p",J17="entreprise",J17="organisme",J17="agence"),"A",IF(OR(O17="1000_2499",O17="600_999"),"B",IF(O17="inconnu",IF(OR(N17="75_149",N17="150p"),"A","B"),"")))))) | AT17: =IF(A17="","",IF(P17<>"",P17,AS17)) | AU17: =IF(A17="","",IF(OR(AT17="A",AT17="B"),1,0)) | AV17: =IF(A17="","",IF(OR(R17="Dépôt payé (gagné)",R17="Événement livré",R17="Avis obtenu"),1,0)) | AW17: =IF(A17="","",IF(Q17>70,"Immédiat – propriétaire",IF(Q17>=40,"15 min – personne de garde","Selon la route"))) | AX17: =IF(A17="","",IF(AT17="A",400,IF(AT17="B",150,0))) | AY17: =IF(A17="","",IF(AV17=1,N(V17),IF(N(U17)>0,ROUND(N(U17)*IFERROR(VLOOKUP(R17,Listes!$AE$3:$AG$12,2,FALSE),0),0),0))) | AZ17: =IF(LEFT(A17,7)="EXEMPLE",1,0) | BA17: =IF(AND(AV17=1,AZ17=0,AC17<>"",W17<>"",N(V17)>0),COUNTIFS($AV$3:AV17,1,$AZ$3:AZ17,0,$AC$3:AC17,"<>",$W$3:W17,"<>",$V$3:V17,">0"),"")
D18: =IF(OR(B18="",C18=""),"",ROUND((C18-B18)*1440,0)) | Q18: =IF(A18="","",IFERROR(VLOOKUP(O18,Listes!$R$3:$T$8,2,FALSE),0)+IFERROR(VLOOKUP(J18,Listes!$J$3:$L$6,2,FALSE),0)+IFERROR(VLOOKUP(N18,Listes!$N$3:$P$6,2,FALSE),0)+IF(OR(L18="",B18=""),0,IF(L18-INT(B18)<10,8,IF(L18-INT(B18)<=90,10,5)))+IFERROR(VLOOKUP(AN18,Listes!$V$3:$W$5,2,FALSE),0)+IFERROR(VLOOKUP(AO18,Listes!$Y$3:$Z$5,2,FALSE),0)) | AQ18: =IF(A18="","",IF(AP18<>"",AP18,IF(LEFT(Z18,11)="gads_marque","Google Search – Marque",IF(LEFT(Z18,12)="gads_mariage","Google Search – Mariage et privé",IF(LEFT(Z18,10)="gads_corpo","Google Search – Corporatif",IF(LEFT(Z18,5)="meta_","Meta – Leads",IF(LEFT(Z18,5)="msft_","Microsoft Ads",IF(LEFT(Z18,8)="chatgpt_","ChatGPT Ads – Test",IF(X18="gbp","Fiche Google (organique)","Autre / non payé"))))))))) | AR18: =IF(K18="","",IFERROR(VLOOKUP(K18,Listes!$F$3:$H$8,3,FALSE),"")) | AS18: =IF(O18="","",IF(AND(M18="Autre (plus de 40 km)",OR(O18="lt600",O18="600_999",O18="1000_2499")),"D",IF(OR(O18="lt600",AND(O18="600_999",K18<>"mariage",K18<>"prive")),"C",IF(OR(O18="2500_4999",O18="5000p",J18="entreprise",J18="organisme",J18="agence"),"A",IF(OR(O18="1000_2499",O18="600_999"),"B",IF(O18="inconnu",IF(OR(N18="75_149",N18="150p"),"A","B"),"")))))) | AT18: =IF(A18="","",IF(P18<>"",P18,AS18)) | AU18: =IF(A18="","",IF(OR(AT18="A",AT18="B"),1,0)) | AV18: =IF(A18="","",IF(OR(R18="Dépôt payé (gagné)",R18="Événement livré",R18="Avis obtenu"),1,0)) | AW18: =IF(A18="","",IF(Q18>70,"Immédiat – propriétaire",IF(Q18>=40,"15 min – personne de garde","Selon la route"))) | AX18: =IF(A18="","",IF(AT18="A",400,IF(AT18="B",150,0))) | AY18: =IF(A18="","",IF(AV18=1,N(V18),IF(N(U18)>0,ROUND(N(U18)*IFERROR(VLOOKUP(R18,Listes!$AE$3:$AG$12,2,FALSE),0),0),0))) | AZ18: =IF(LEFT(A18,7)="EXEMPLE",1,0) | BA18: =IF(AND(AV18=1,AZ18=0,AC18<>"",W18<>"",N(V18)>0),COUNTIFS($AV$3:AV18,1,$AZ$3:AZ18,0,$AC$3:AC18,"<>",$W$3:W18,"<>",$V$3:V18,">0"),"")
D19: =IF(OR(B19="",C19=""),"",ROUND((C19-B19)*1440,0)) | Q19: =IF(A19="","",IFERROR(VLOOKUP(O19,Listes!$R$3:$T$8,2,FALSE),0)+IFERROR(VLOOKUP(J19,Listes!$J$3:$L$6,2,FALSE),0)+IFERROR(VLOOKUP(N19,Listes!$N$3:$P$6,2,FALSE),0)+IF(OR(L19="",B19=""),0,IF(L19-INT(B19)<10,8,IF(L19-INT(B19)<=90,10,5)))+IFERROR(VLOOKUP(AN19,Listes!$V$3:$W$5,2,FALSE),0)+IFERROR(VLOOKUP(AO19,Listes!$Y$3:$Z$5,2,FALSE),0)) | AQ19: =IF(A19="","",IF(AP19<>"",AP19,IF(LEFT(Z19,11)="gads_marque","Google Search – Marque",IF(LEFT(Z19,12)="gads_mariage","Google Search – Mariage et privé",IF(LEFT(Z19,10)="gads_corpo","Google Search – Corporatif",IF(LEFT(Z19,5)="meta_","Meta – Leads",IF(LEFT(Z19,5)="msft_","Microsoft Ads",IF(LEFT(Z19,8)="chatgpt_","ChatGPT Ads – Test",IF(X19="gbp","Fiche Google (organique)","Autre / non payé"))))))))) | AR19: =IF(K19="","",IFERROR(VLOOKUP(K19,Listes!$F$3:$H$8,3,FALSE),"")) | AS19: =IF(O19="","",IF(AND(M19="Autre (plus de 40 km)",OR(O19="lt600",O19="600_999",O19="1000_2499")),"D",IF(OR(O19="lt600",AND(O19="600_999",K19<>"mariage",K19<>"prive")),"C",IF(OR(O19="2500_4999",O19="5000p",J19="entreprise",J19="organisme",J19="agence"),"A",IF(OR(O19="1000_2499",O19="600_999"),"B",IF(O19="inconnu",IF(OR(N19="75_149",N19="150p"),"A","B"),"")))))) | AT19: =IF(A19="","",IF(P19<>"",P19,AS19)) | AU19: =IF(A19="","",IF(OR(AT19="A",AT19="B"),1,0)) | AV19: =IF(A19="","",IF(OR(R19="Dépôt payé (gagné)",R19="Événement livré",R19="Avis obtenu"),1,0)) | AW19: =IF(A19="","",IF(Q19>70,"Immédiat – propriétaire",IF(Q19>=40,"15 min – personne de garde","Selon la route"))) | AX19: =IF(A19="","",IF(AT19="A",400,IF(AT19="B",150,0))) | AY19: =IF(A19="","",IF(AV19=1,N(V19),IF(N(U19)>0,ROUND(N(U19)*IFERROR(VLOOKUP(R19,Listes!$AE$3:$AG$12,2,FALSE),0),0),0))) | AZ19: =IF(LEFT(A19,7)="EXEMPLE",1,0) | BA19: =IF(AND(AV19=1,AZ19=0,AC19<>"",W19<>"",N(V19)>0),COUNTIFS($AV$3:AV19,1,$AZ$3:AZ19,0,$AC$3:AC19,"<>",$W$3:W19,"<>",$V$3:V19,">0"),"")
... D1002: =IF(OR(B1002="",C1002=""),"",ROUND((C1002-B1002)*1440,0)) | Q1002: =IF(A1002="","",IFERROR(VLOOKUP(O1002,Listes!$R$3:$T$8,2,FALSE),0)+IFERROR(VLOOKUP(J1002,Listes!$J$3:$L$6,2,FALSE),0)+IFERROR(VLOOKUP(N1002,Listes!$N$3:$P$6,2,FALSE),0)+IF(OR(L1002="",B1002=""),0,IF(L1002-INT(B1002)<10,8,IF(L1002-INT(B1002)<=90,10,5)))+IFERROR(VLOOKUP(AN1002,Listes!$V$3:$W$5,2,FALSE),0)+IFERROR(VLOOKUP(AO1002,Listes!$Y$3:$Z$5,2,FALSE),0)) | AQ1002: =IF(A1002="","",IF(AP1002<>"",AP1002,IF(LEFT(Z1002,11)="gads_marque","Google Search – Marque",IF(LEFT(Z1002,12)="gads_mariage","Google Search – Mariage et privé",IF(LEFT(Z1002,10)="gads_corpo","Google Search – Corporatif",IF(LEFT(Z1002,5)="meta_","Meta – Leads",IF(LEFT(Z1002,5)="msft_","Microsoft Ads",IF(LEFT(Z1002,8)="chatgpt_","ChatGPT Ads – Test",IF(X1002="gbp","Fiche Google (organique)","Autre / non payé"))))))))) | AR1002: =IF(K1002="","",IFERROR(VLOOKUP(K1002,Listes!$F$3:$H$8,3,FALSE),"")) | AS1002: =IF(O1002="","",IF(AND(M1002="Autre (plus de 40 km)",OR(O1002="lt600",O1002="600_999",O1002="1000_2499")),"D",IF(OR(O1002="lt600",AND(O1002="600_999",K1002<>"mariage",K1002<>"prive")),"C",IF(OR(O1002="2500_4999",O1002="5000p",J1002="entreprise",J1002="organisme",J1002="agence"),"A",IF(OR(O1002="1000_2499",O1002="600_999"),"B",IF(O1002="inconnu",IF(OR(N1002="75_149",N1002="150p"),"A","B"),"")))))) | AT1002: =IF(A1002="","",IF(P1002<>"",P1002,AS1002)) | AU1002: =IF(A1002="","",IF(OR(AT1002="A",AT1002="B"),1,0)) | AV1002: =IF(A1002="","",IF(OR(R1002="Dépôt payé (gagné)",R1002="Événement livré",R1002="Avis obtenu"),1,0)) | AW1002: =IF(A1002="","",IF(Q1002>70,"Immédiat – propriétaire",IF(Q1002>=40,"15 min – personne de garde","Selon la route"))) | AX1002: =IF(A1002="","",IF(AT1002="A",400,IF(AT1002="B",150,0))) | AY1002: =IF(A1002="","",IF(AV1002=1,N(V1002),IF(N(U1002)>0,ROUND(N(U1002)*IFERROR(VLOOKUP(R1002,Listes!$AE$3:$AG$12,2,FALSE),0),0),0))) | AZ1002: =IF(LEFT(A1002,7)="EXEMPLE",1,0) | BA1002: =IF(AND(AV1002=1,AZ1002=0,AC1002<>"",W1002<>"",N(V1002)>0),COUNTIFS($AV$3:AV1002,1,$AZ$3:AZ1002,0,$AC$3:AC1002,"<>",$W$3:W1002,"<>",$V$3:V1002,">0"),"")

Sheet Dépenses
A1: Dépenses publicitaires quotidiennes par campagne ($ CA, avant taxes)
A2: Saisir chaque matin la dépense de la veille (rapport de chaque plateforme). Cellules jaunes = saisie.
B3: Budget cible ($/jour) | C3: 100 | D3: 80 | E3: 60 | F3: 30 | G3: 20 | H3: 10 | I3: =SUM(C3:H3) | J3: ← total visé : 300 $/jour. Ajuster lors de la bascule saisonnière (COMPTE-RENDU.md).
B4: Dépensé (cumul) | C4: =SUM(C8:C464) | D4: =SUM(D8:D464) | E4: =SUM(E8:E464) | F4: =SUM(F8:F464) | G4: =SUM(G8:G464) | H4: =SUM(H8:H464) | I4: =SUM(C4:H4)
B5: Budget des jours saisis | C5: =C3*COUNT(C8:C464) | D5: =D3*COUNT(D8:D464) | E5: =E3*COUNT(E8:E464) | F5: =F3*COUNT(F8:F464) | G5: =G3*COUNT(G8:G464) | H5: =H3*COUNT(H8:H464) | I5: =SUM(C5:H5)
B6: Écart cumulé ($) | C6: =C4-C5 | D6: =D4-D5 | E6: =E4-E5 | F6: =F4-F5 | G6: =G4-G5 | H6: =H4-H5 | I6: =I4-I5
A7: Date | B7: Jour | C7: Google Search – Corporatif | D7: Meta – Leads | E7: Google Search – Mariage et privé | F7: ChatGPT Ads – Test | G7: Microsoft Ads | H7: Google Search – Marque | I7: Total réel | J7: Budget cible du jour | K7: Écart ($) | L7: Écart (%) | M7: Notes
A8: 46296 | B8: =CHOOSE(WEEKDAY(A8,2),"lundi","mardi","mercredi","jeudi","vendredi","samedi","dimanche") | I8: =IF(COUNT(C8:H8)=0,"",SUM(C8:H8)) | J8: =$I$3 | K8: =IF(I8="","",I8-J8) | L8: =IF(OR(I8="",N(J8)=0),"",K8/J8)
A9: 46297 | B9: =CHOOSE(WEEKDAY(A9,2),"lundi","mardi","mercredi","jeudi","vendredi","samedi","dimanche") | I9: =IF(COUNT(C9:H9)=0,"",SUM(C9:H9)) | J9: =$I$3 | K9: =IF(I9="","",I9-J9) | L9: =IF(OR(I9="",N(J9)=0),"",K9/J9)
A10: 46298 | B10: =CHOOSE(WEEKDAY(A10,2),"lundi","mardi","mercredi","jeudi","vendredi","samedi","dimanche") | I10: =IF(COUNT(C10:H10)=0,"",SUM(C10:H10)) | J10: =$I$3 | K10: =IF(I10="","",I10-J10) | L10: =IF(OR(I10="",N(J10)=0),"",K10/J10)
A11: 46299 | B11: =CHOOSE(WEEKDAY(A11,2),"lundi","mardi","mercredi","jeudi","vendredi","samedi","dimanche") | I11: =IF(COUNT(C11:H11)=0,"",SUM(C11:H11)) | J11: =$I$3 | K11: =IF(I11="","",I11-J11) | L11: =IF(OR(I11="",N(J11)=0),"",K11/J11)
A12: 46300 | B12: =CHOOSE(WEEKDAY(A12,2),"lundi","mardi","mercredi","jeudi","vendredi","samedi","dimanche") | I12: =IF(COUNT(C12:H12)=0,"",SUM(C12:H12)) | J12: =$I$3 | K12: =IF(I12="","",I12-J12) | L12: =IF(OR(I12="",N(J12)=0),"",K12/J12)
A13: 46301 | B13: =CHOOSE(WEEKDAY(A13,2),"lundi","mardi","mercredi","jeudi","vendredi","samedi","dimanche") | I13: =IF(COUNT(C13:H13)=0,"",SUM(C13:H13)) | J13: =$I$3 | K13: =IF(I13="","",I13-J13) | L13: =IF(OR(I13="",N(J13)=0),"",K13/J13)
A14: 46302 | B14: =CHOOSE(WEEKDAY(A14,2),"lundi","mardi","mercredi","jeudi","vendredi","samedi","dimanche") | I14: =IF(COUNT(C14:H14)=0,"",SUM(C14:H14)) | J14: =$I$3 | K14: =IF(I14="","",I14-J14) | L14: =IF(OR(I14="",N(J14)=0),"",K14/J14)
A15: 46303 | B15: =CHOOSE(WEEKDAY(A15,2),"lundi","mardi","mercredi","jeudi","vendredi","samedi","dimanche") | I15: =IF(COUNT(C15:H15)=0,"",SUM(C15:H15)) | J15: =$I$3 | K15: =IF(I15="","",I15-J15) | L15: =IF(OR(I15="",N(J15)=0),"",K15/J15)
A16: 46304 | B16: =CHOOSE(WEEKDAY(A16,2),"lundi","mardi","mercredi","jeudi","vendredi","samedi","dimanche") | I16: =IF(COUNT(C16:H16)=0,"",SUM(C16:H16)) | J16: =$I$3 | K16: =IF(I16="","",I16-J16) | L16: =IF(OR(I16="",N(J16)=0),"",K16/J16)
A17: 46305 | B17: =CHOOSE(WEEKDAY(A17,2),"lundi","mardi","mercredi","jeudi","vendredi","samedi","dimanche") | I17: =IF(COUNT(C17:H17)=0,"",SUM(C17:H17)) | J17: =$I$3 | K17: =IF(I17="","",I17-J17) | L17: =IF(OR(I17="",N(J17)=0),"",K17/J17)
A18: 46306 | B18: =CHOOSE(WEEKDAY(A18,2),"lundi","mardi","mercredi","jeudi","vendredi","samedi","dimanche") | I18: =IF(COUNT(C18:H18)=0,"",SUM(C18:H18)) | J18: =$I$3 | K18: =IF(I18="","",I18-J18) | L18: =IF(OR(I18="",N(J18)=0),"",K18/J18)
A19: 46307 | B19: =CHOOSE(WEEKDAY(A19,2),"lundi","mardi","mercredi","jeudi","vendredi","samedi","dimanche") | I19: =IF(COUNT(C19:H19)=0,"",SUM(C19:H19)) | J19: =$I$3 | K19: =IF(I19="","",I19-J19) | L19: =IF(OR(I19="",N(J19)=0),"",K19/J19)
... A464: 46752 | B464: =CHOOSE(WEEKDAY(A464,2),"lundi","mardi","mercredi","jeudi","vendredi","samedi","dimanche") | I464: =IF(COUNT(C464:H464)=0,"",SUM(C464:H464)) | J464: =$I$3 | K464: =IF(I464="","",I464-J464) | L464: =IF(OR(I464="",N(J464)=0),"",K464/J464)

Sheet Tableau de bord
B1: Tableau de bord des indicateurs — Évenox (revue chaque lundi, 9 h)
B2: Leads comptés par date de réception (cohorte) ; contrats, revenu et ROAS = leads de la même cohorte qui ont atteint « Dépôt payé (gagné) » ou plus. Lead qualifié (LQ) = route A ou B.
F3: Cibles et seuils (tracking-setup.md §10, COMPTE-RENDU.md §4)
B4: Semaine débutant le (lundi) | C4: =TODAY()-WEEKDAY(TODAY(),2)+1 | D4: Formule par défaut = lundi de la semaine en cours ; inscrire une date pour une autre semaine. | F4: Coût par lead qualifié (max) | I4: 150
B5: Mois analysé (1er jour du mois) | C5: =DATE(YEAR(TODAY()),MONTH(TODAY()),1) | D5: Formule par défaut = mois en cours ; inscrire le 1er d'un mois (ex. 2026-11-01). | F5: % de leads qualifiés (min) | I5: 0.4
B6: Inclure les lignes EXEMPLE? | C6: Non | F6: Taux de signature des LQ (min) | I6: 0.25
B7: (critère interne, ne pas modifier) | C7: =IF(C6="Oui",1,0) | F7: Panier moyen (min) | I7: 1500
F8: ROAS (min) | I8: 2.5
F9: Règle « Réduire 30 % » : coût par LQ > | I9: =2*$I$4
F10: Dépense minimale avant décision (par campagne) | I10: 300
F11: Règle « Augmenter +20 % » : coût par LQ < | I11: 100
F12: ChatGPT au jour 30 : LQ minimum | I12: 2
F13: ChatGPT : dépense de référence (≈ 30 jours × 30 $) | I13: 900
F14: Délai de réponse médian visé (min), routes A et B | I14: 5
B16: Décision hebdo (tracking-setup.md §10) : « Réduire 30 % » si coût par LQ > 2 × la cible 2 semaines de suite et ≥ 300 $ dépensés ; « Augmenter +20 % » si coût par LQ < 100 $ et signature ≥ 25 %.
B17: Semaine : du lundi indiqué en C4 au dimanche suivant
B18: Campagne | C18: Dépenses | D18: Budget cible (jours saisis) | E18: Écart vs budget | F18: Leads (tous) | G18: Leads qualifiés (LQ) | H18: % qualifiés | I18: Coût par lead | J18: Coût par LQ | K18: Contrats (dépôts) | L18: Taux de signature | M18: Revenu (montant gagné) | N18: Panier moyen | O18: ROAS | P18: Pipeline pondéré | Q18: Décision | R18: Sem. préc. : dépenses | S18: Sem. préc. : LQ
B19: Google Search – Corporatif | C19: =SUMIFS('Dépenses'!$C$8:$C$464,'Dépenses'!$A$8:$A$464,">="&$C$4,'Dépenses'!$A$8:$A$464,"<"&($C$4+7)) | D19: ='Dépenses'!$C$3*COUNTIFS('Dépenses'!$A$8:$A$464,">="&$C$4,'Dépenses'!$A$8:$A$464,"<"&($C$4+7),'Dépenses'!$C$8:$C$464,"<>") | E19: =C19-D19 | F19: =COUNTIFS(Leads!$AQ$3:$AQ$1002,$B19,Leads!$B$3:$B$1002,">="&$C$4,Leads!$B$3:$B$1002,"<"&($C$4+7),Leads!$AZ$3:$AZ$1002,"<="&$C$7) | G19: =COUNTIFS(Leads!$AQ$3:$AQ$1002,$B19,Leads!$B$3:$B$1002,">="&$C$4,Leads!$B$3:$B$1002,"<"&($C$4+7),Leads!$AZ$3:$AZ$1002,"<="&$C$7,Leads!$AU$3:$AU$1002,1) | H19: =IF(F19=0,"—",G19/F19) | I19: =IF(OR(F19=0,C19=0),"—",C19/F19) | J19: =IF(OR(G19=0,C19=0),"—",C19/G19) | K19: =COUNTIFS(Leads!$AQ$3:$AQ$1002,$B19,Leads!$B$3:$B$1002,">="&$C$4,Leads!$B$3:$B$1002,"<"&($C$4+7),Leads!$AZ$3:$AZ$1002,"<="&$C$7,Leads!$AV$3:$AV$1002,1) | L19: =IF(G19=0,"—",K19/G19) | M19: =SUMIFS(Leads!$V$3:$V$1002,Leads!$AQ$3:$AQ$1002,$B19,Leads!$B$3:$B$1002,">="&$C$4,Leads!$B$3:$B$1002,"<"&($C$4+7),Leads!$AZ$3:$AZ$1002,"<="&$C$7,Leads!$AV$3:$AV$1002,1) | N19: =IF(K19=0,"—",M19/K19) | O19: =IF(C19=0,"—",M19/C19) | P19: =SUMIFS(Leads!$AY$3:$AY$1002,Leads!$AQ$3:$AQ$1002,$B19,Leads!$B$3:$B$1002,">="&$C$4,Leads!$B$3:$B$1002,"<"&($C$4+7),Leads!$AZ$3:$AZ$1002,"<="&$C$7) | Q19: =IF(AND(C19+R19>=$I$10,AND(C19>0,IFERROR(C19/G19,1E+99)>$I$9),AND(R19>0,IFERROR(R19/S19,1E+99)>$I$9)),"Réduire 30 %",IF(AND(C19>0,G19>0,IFERROR(C19/G19,1E+99)<$I$11,IFERROR(K19/G19,0)>=$I$6),"Augmenter +20 %",IF(C19+R19<$I$10,"Garder (données insuffisantes)","Garder"))) | R19: =SUMIFS('Dépenses'!$C$8:$C$464,'Dépenses'!$A$8:$A$464,">="&($C$4-7),'Dépenses'!$A$8:$A$464,"<"&$C$4) | S19: =COUNTIFS(Leads!$AQ$3:$AQ$1002,$B19,Leads!$B$3:$B$1002,">="&($C$4-7),Leads!$B$3:$B$1002,"<"&$C$4,Leads!$AZ$3:$AZ$1002,"<="&$C$7,Leads!$AU$3:$AU$1002,1)
B20: Meta – Leads | C20: =SUMIFS('Dépenses'!$D$8:$D$464,'Dépenses'!$A$8:$A$464,">="&$C$4,'Dépenses'!$A$8:$A$464,"<"&($C$4+7)) | D20: ='Dépenses'!$D$3*COUNTIFS('Dépenses'!$A$8:$A$464,">="&$C$4,'Dépenses'!$A$8:$A$464,"<"&($C$4+7),'Dépenses'!$D$8:$D$464,"<>") | E20: =C20-D20 | F20: =COUNTIFS(Leads!$AQ$3:$AQ$1002,$B20,Leads!$B$3:$B$1002,">="&$C$4,Leads!$B$3:$B$1002,"<"&($C$4+7),Leads!$AZ$3:$AZ$1002,"<="&$C$7) | G20: =COUNTIFS(Leads!$AQ$3:$AQ$1002,$B20,Leads!$B$3:$B$1002,">="&$C$4,Leads!$B$3:$B$1002,"<"&($C$4+7),Leads!$AZ$3:$AZ$1002,"<="&$C$7,Leads!$AU$3:$AU$1002,1) | H20: =IF(F20=0,"—",G20/F20) | I20: =IF(OR(F20=0,C20=0),"—",C20/F20) | J20: =IF(OR(G20=0,C20=0),"—",C20/G20) | K20: =COUNTIFS(Leads!$AQ$3:$AQ$1002,$B20,Leads!$B$3:$B$1002,">="&$C$4,Leads!$B$3:$B$1002,"<"&($C$4+7),Leads!$AZ$3:$AZ$1002,"<="&$C$7,Leads!$AV$3:$AV$1002,1) | L20: =IF(G20=0,"—",K20/G20) | M20: =SUMIFS(Leads!$V$3:$V$1002,Leads!$AQ$3:$AQ$1002,$B20,Leads!$B$3:$B$1002,">="&$C$4,Leads!$B$3:$B$1002,"<"&($C$4+7),Leads!$AZ$3:$AZ$1002,"<="&$C$7,Leads!$AV$3:$AV$1002,1) | N20: =IF(K20=0,"—",M20/K20) | O20: =IF(C20=0,"—",M20/C20) | P20: =SUMIFS(Leads!$AY$3:$AY$1002,Leads!$AQ$3:$AQ$1002,$B20,Leads!$B$3:$B$1002,">="&$C$4,Leads!$B$3:$B$1002,"<"&($C$4+7),Leads!$AZ$3:$AZ$1002,"<="&$C$7) | Q20: =IF(AND(C20+R20>=$I$10,AND(C20>0,IFERROR(C20/G20,1E+99)>$I$9),AND(R20>0,IFERROR(R20/S20,1E+99)>$I$9)),"Réduire 30 %",IF(AND(C20>0,G20>0,IFERROR(C20/G20,1E+99)<$I$11,IFERROR(K20/G20,0)>=$I$6),"Augmenter +20 %",IF(C20+R20<$I$10,"Garder (données insuffisantes)","Garder"))) | R20: =SUMIFS('Dépenses'!$D$8:$D$464,'Dépenses'!$A$8:$A$464,">="&($C$4-7),'Dépenses'!$A$8:$A$464,"<"&$C$4) | S20: =COUNTIFS(Leads!$AQ$3:$AQ$1002,$B20,Leads!$B$3:$B$1002,">="&($C$4-7),Leads!$B$3:$B$1002,"<"&$C$4,Leads!$AZ$3:$AZ$1002,"<="&$C$7,Leads!$AU$3:$AU$1002,1)
B21: Google Search – Mariage et privé | C21: =SUMIFS('Dépenses'!$E$8:$E$464,'Dépenses'!$A$8:$A$464,">="&$C$4,'Dépenses'!$A$8:$A$464,"<"&($C$4+7)) | D21: ='Dépenses'!$E$3*COUNTIFS('Dépenses'!$A$8:$A$464,">="&$C$4,'Dépenses'!$A$8:$A$464,"<"&($C$4+7),'Dépenses'!$E$8:$E$464,"<>") | E21: =C21-D21 | F21: =COUNTIFS(Leads!$AQ$3:$AQ$1002,$B21,Leads!$B$3:$B$1002,">="&$C$4,Leads!$B$3:$B$1002,"<"&($C$4+7),Leads!$AZ$3:$AZ$1002,"<="&$C$7) | G21: =COUNTIFS(Leads!$AQ$3:$AQ$1002,$B21,Leads!$B$3:$B$1002,">="&$C$4,Leads!$B$3:$B$1002,"<"&($C$4+7),Leads!$AZ$3:$AZ$1002,"<="&$C$7,Leads!$AU$3:$AU$1002,1) | H21: =IF(F21=0,"—",G21/F21) | I21: =IF(OR(F21=0,C21=0),"—",C21/F21) | J21: =IF(OR(G21=0,C21=0),"—",C21/G21) | K21: =COUNTIFS(Leads!$AQ$3:$AQ$1002,$B21,Leads!$B$3:$B$1002,">="&$C$4,Leads!$B$3:$B$1002,"<"&($C$4+7),Leads!$AZ$3:$AZ$1002,"<="&$C$7,Leads!$AV$3:$AV$1002,1) | L21: =IF(G21=0,"—",K21/G21) | M21: =SUMIFS(Leads!$V$3:$V$1002,Leads!$AQ$3:$AQ$1002,$B21,Leads!$B$3:$B$1002,">="&$C$4,Leads!$B$3:$B$1002,"<"&($C$4+7),Leads!$AZ$3:$AZ$1002,"<="&$C$7,Leads!$AV$3:$AV$1002,1) | N21: =IF(K21=0,"—",M21/K21) | O21: =IF(C21=0,"—",M21/C21) | P21: =SUMIFS(Leads!$AY$3:$AY$1002,Leads!$AQ$3:$AQ$1002,$B21,Leads!$B$3:$B$1002,">="&$C$4,Leads!$B$3:$B$1002,"<"&($C$4+7),Leads!$AZ$3:$AZ$1002,"<="&$C$7) | Q21: =IF(AND(C21+R21>=$I$10,AND(C21>0,IFERROR(C21/G21,1E+99)>$I$9),AND(R21>0,IFERROR(R21/S21,1E+99)>$I$9)),"Réduire 30 %",IF(AND(C21>0,G21>0,IFERROR(C21/G21,1E+99)<$I$11,IFERROR(K21/G21,0)>=$I$6),"Augmenter +20 %",IF(C21+R21<$I$10,"Garder (données insuffisantes)","Garder"))) | R21: =SUMIFS('Dépenses'!$E$8:$E$464,'Dépenses'!$A$8:$A$464,">="&($C$4-7),'Dépenses'!$A$8:$A$464,"<"&$C$4) | S21: =COUNTIFS(Leads!$AQ$3:$AQ$1002,$B21,Leads!$B$3:$B$1002,">="&($C$4-7),Leads!$B$3:$B$1002,"<"&$C$4,Leads!$AZ$3:$AZ$1002,"<="&$C$7,Leads!$AU$3:$AU$1002,1)
B22: ChatGPT Ads – Test | C22: =SUMIFS('Dépenses'!$F$8:$F$464,'Dépenses'!$A$8:$A$464,">="&$C$4,'Dépenses'!$A$8:$A$464,"<"&($C$4+7)) | D22: ='Dépenses'!$F$3*COUNTIFS('Dépenses'!$A$8:$A$464,">="&$C$4,'Dépenses'!$A$8:$A$464,"<"&($C$4+7),'Dépenses'!$F$8:$F$464,"<>") | E22: =C22-D22 | F22: =COUNTIFS(Leads!$AQ$3:$AQ$1002,$B22,Leads!$B$3:$B$1002,">="&$C$4,Leads!$B$3:$B$1002,"<"&($C$4+7),Leads!$AZ$3:$AZ$1002,"<="&$C$7) | G22: =COUNTIFS(Leads!$AQ$3:$AQ$1002,$B22,Leads!$B$3:$B$1002,">="&$C$4,Leads!$B$3:$B$1002,"<"&($C$4+7),Leads!$AZ$3:$AZ$1002,"<="&$C$7,Leads!$AU$3:$AU$1002,1) | H22: =IF(F22=0,"—",G22/F22) | I22: =IF(OR(F22=0,C22=0),"—",C22/F22) | J22: =IF(OR(G22=0,C22=0),"—",C22/G22) | K22: =COUNTIFS(Leads!$AQ$3:$AQ$1002,$B22,Leads!$B$3:$B$1002,">="&$C$4,Leads!$B$3:$B$1002,"<"&($C$4+7),Leads!$AZ$3:$AZ$1002,"<="&$C$7,Leads!$AV$3:$AV$1002,1) | L22: =IF(G22=0,"—",K22/G22) | M22: =SUMIFS(Leads!$V$3:$V$1002,Leads!$AQ$3:$AQ$1002,$B22,Leads!$B$3:$B$1002,">="&$C$4,Leads!$B$3:$B$1002,"<"&($C$4+7),Leads!$AZ$3:$AZ$1002,"<="&$C$7,Leads!$AV$3:$AV$1002,1) | N22: =IF(K22=0,"—",M22/K22) | O22: =IF(C22=0,"—",M22/C22) | P22: =SUMIFS(Leads!$AY$3:$AY$1002,Leads!$AQ$3:$AQ$1002,$B22,Leads!$B$3:$B$1002,">="&$C$4,Leads!$B$3:$B$1002,"<"&($C$4+7),Leads!$AZ$3:$AZ$1002,"<="&$C$7) | Q22: =IF(AND(C22+R22>=$I$10,AND(C22>0,IFERROR(C22/G22,1E+99)>$I$9),AND(R22>0,IFERROR(R22/S22,1E+99)>$I$9)),"Réduire 30 %",IF(AND(C22>0,G22>0,IFERROR(C22/G22,1E+99)<$I$11,IFERROR(K22/G22,0)>=$I$6),"Augmenter +20 %",IF(C22+R22<$I$10,"Garder (données insuffisantes)","Garder"))) | R22: =SUMIFS('Dépenses'!$F$8:$F$464,'Dépenses'!$A$8:$A$464,">="&($C$4-7),'Dépenses'!$A$8:$A$464,"<"&$C$4) | S22: =COUNTIFS(Leads!$AQ$3:$AQ$1002,$B22,Leads!$B$3:$B$1002,">="&($C$4-7),Leads!$B$3:$B$1002,"<"&$C$4,Leads!$AZ$3:$AZ$1002,"<="&$C$7,Leads!$AU$3:$AU$1002,1)
B23: Microsoft Ads | C23: =SUMIFS('Dépenses'!$G$8:$G$464,'Dépenses'!$A$8:$A$464,">="&$C$4,'Dépenses'!$A$8:$A$464,"<"&($C$4+7)) | D23: ='Dépenses'!$G$3*COUNTIFS('Dépenses'!$A$8:$A$464,">="&$C$4,'Dépenses'!$A$8:$A$464,"<"&($C$4+7),'Dépenses'!$G$8:$G$464,"<>") | E23: =C23-D23 | F23: =COUNTIFS(Leads!$AQ$3:$AQ$1002,$B23,Leads!$B$3:$B$1002,">="&$C$4,Leads!$B$3:$B$1002,"<"&($C$4+7),Leads!$AZ$3:$AZ$1002,"<="&$C$7) | G23: =COUNTIFS(Leads!$AQ$3:$AQ$1002,$B23,Leads!$B$3:$B$1002,">="&$C$4,Leads!$B$3:$B$1002,"<"&($C$4+7),Leads!$AZ$3:$AZ$1002,"<="&$C$7,Leads!$AU$3:$AU$1002,1) | H23: =IF(F23=0,"—",G23/F23) | I23: =IF(OR(F23=0,C23=0),"—",C23/F23) | J23: =IF(OR(G23=0,C23=0),"—",C23/G23) | K23: =COUNTIFS(Leads!$AQ$3:$AQ$1002,$B23,Leads!$B$3:$B$1002,">="&$C$4,Leads!$B$3:$B$1002,"<"&($C$4+7),Leads!$AZ$3:$AZ$1002,"<="&$C$7,Leads!$AV$3:$AV$1002,1) | L23: =IF(G23=0,"—",K23/G23) | M23: =SUMIFS(Leads!$V$3:$V$1002,Leads!$AQ$3:$AQ$1002,$B23,Leads!$B$3:$B$1002,">="&$C$4,Leads!$B$3:$B$1002,"<"&($C$4+7),Leads!$AZ$3:$AZ$1002,"<="&$C$7,Leads!$AV$3:$AV$1002,1) | N23: =IF(K23=0,"—",M23/K23) | O23: =IF(C23=0,"—",M23/C23) | P23: =SUMIFS(Leads!$AY$3:$AY$1002,Leads!$AQ$3:$AQ$1002,$B23,Leads!$B$3:$B$1002,">="&$C$4,Leads!$B$3:$B$1002,"<"&($C$4+7),Leads!$AZ$3:$AZ$1002,"<="&$C$7) | Q23: =IF(AND(C23+R23>=$I$10,AND(C23>0,IFERROR(C23/G23,1E+99)>$I$9),AND(R23>0,IFERROR(R23/S23,1E+99)>$I$9)),"Réduire 30 %",IF(AND(C23>0,G23>0,IFERROR(C23/G23,1E+99)<$I$11,IFERROR(K23/G23,0)>=$I$6),"Augmenter +20 %",IF(C23+R23<$I$10,"Garder (données insuffisantes)","Garder"))) | R23: =SUMIFS('Dépenses'!$G$8:$G$464,'Dépenses'!$A$8:$A$464,">="&($C$4-7),'Dépenses'!$A$8:$A$464,"<"&$C$4) | S23: =COUNTIFS(Leads!$AQ$3:$AQ$1002,$B23,Leads!$B$3:$B$1002,">="&($C$4-7),Leads!$B$3:$B$1002,"<"&$C$4,Leads!$AZ$3:$AZ$1002,"<="&$C$7,Leads!$AU$3:$AU$1002,1)
B24: Google Search – Marque | C24: =SUMIFS('Dépenses'!$H$8:$H$464,'Dépenses'!$A$8:$A$464,">="&$C$4,'Dépenses'!$A$8:$A$464,"<"&($C$4+7)) | D24: ='Dépenses'!$H$3*COUNTIFS('Dépenses'!$A$8:$A$464,">="&$C$4,'Dépenses'!$A$8:$A$464,"<"&($C$4+7),'Dépenses'!$H$8:$H$464,"<>") | E24: =C24-D24 | F24: =COUNTIFS(Leads!$AQ$3:$AQ$1002,$B24,Leads!$B$3:$B$1002,">="&$C$4,Leads!$B$3:$B$1002,"<"&($C$4+7),Leads!$AZ$3:$AZ$1002,"<="&$C$7) | G24: =COUNTIFS(Leads!$AQ$3:$AQ$1002,$B24,Leads!$B$3:$B$1002,">="&$C$4,Leads!$B$3:$B$1002,"<"&($C$4+7),Leads!$AZ$3:$AZ$1002,"<="&$C$7,Leads!$AU$3:$AU$1002,1) | H24: =IF(F24=0,"—",G24/F24) | I24: =IF(OR(F24=0,C24=0),"—",C24/F24) | J24: =IF(OR(G24=0,C24=0),"—",C24/G24) | K24: =COUNTIFS(Leads!$AQ$3:$AQ$1002,$B24,Leads!$B$3:$B$1002,">="&$C$4,Leads!$B$3:$B$1002,"<"&($C$4+7),Leads!$AZ$3:$AZ$1002,"<="&$C$7,Leads!$AV$3:$AV$1002,1) | L24: =IF(G24=0,"—",K24/G24) | M24: =SUMIFS(Leads!$V$3:$V$1002,Leads!$AQ$3:$AQ$1002,$B24,Leads!$B$3:$B$1002,">="&$C$4,Leads!$B$3:$B$1002,"<"&($C$4+7),Leads!$AZ$3:$AZ$1002,"<="&$C$7,Leads!$AV$3:$AV$1002,1) | N24: =IF(K24=0,"—",M24/K24) | O24: =IF(C24=0,"—",M24/C24) | P24: =SUMIFS(Leads!$AY$3:$AY$1002,Leads!$AQ$3:$AQ$1002,$B24,Leads!$B$3:$B$1002,">="&$C$4,Leads!$B$3:$B$1002,"<"&($C$4+7),Leads!$AZ$3:$AZ$1002,"<="&$C$7) | Q24: =IF(AND(C24+R24>=$I$10,AND(C24>0,IFERROR(C24/G24,1E+99)>$I$9),AND(R24>0,IFERROR(R24/S24,1E+99)>$I$9)),"Réduire 30 %",IF(AND(C24>0,G24>0,IFERROR(C24/G24,1E+99)<$I$11,IFERROR(K24/G24,0)>=$I$6),"Augmenter +20 %",IF(C24+R24<$I$10,"Garder (données insuffisantes)","Garder"))) | R24: =SUMIFS('Dépenses'!$H$8:$H$464,'Dépenses'!$A$8:$A$464,">="&($C$4-7),'Dépenses'!$A$8:$A$464,"<"&$C$4) | S24: =COUNTIFS(Leads!$AQ$3:$AQ$1002,$B24,Leads!$B$3:$B$1002,">="&($C$4-7),Leads!$B$3:$B$1002,"<"&$C$4,Leads!$AZ$3:$AZ$1002,"<="&$C$7,Leads!$AU$3:$AU$1002,1)
B25: Autres sources (non payées) | C25: 0 | D25: 0 | E25: =C25-D25 | F25: =COUNTIFS(Leads!$B$3:$B$1002,">="&$C$4,Leads!$B$3:$B$1002,"<"&($C$4+7),Leads!$AZ$3:$AZ$1002,"<="&$C$7)-SUM(F19:F24) | G25: =COUNTIFS(Leads!$B$3:$B$1002,">="&$C$4,Leads!$B$3:$B$1002,"<"&($C$4+7),Leads!$AZ$3:$AZ$1002,"<="&$C$7,Leads!$AU$3:$AU$1002,1)-SUM(G19:G24) | H25: =IF(F25=0,"—",G25/F25) | I25: =IF(OR(F25=0,C25=0),"—",C25/F25) | J25: =IF(OR(G25=0,C25=0),"—",C25/G25) | K25: =COUNTIFS(Leads!$B$3:$B$1002,">="&$C$4,Leads!$B$3:$B$1002,"<"&($C$4+7),Leads!$AZ$3:$AZ$1002,"<="&$C$7,Leads!$AV$3:$AV$1002,1)-SUM(K19:K24) | L25: =IF(G25=0,"—",K25/G25) | M25: =SUMIFS(Leads!$V$3:$V$1002,Leads!$B$3:$B$1002,">="&$C$4,Leads!$B$3:$B$1002,"<"&($C$4+7),Leads!$AZ$3:$AZ$1002,"<="&$C$7,Leads!$AV$3:$AV$1002,1)-SUM(M19:M24) | N25: =IF(K25=0,"—",M25/K25) | O25: =IF(C25=0,"—",M25/C25) | P25: =SUMIFS(Leads!$AY$3:$AY$1002,Leads!$B$3:$B$1002,">="&$C$4,Leads!$B$3:$B$1002,"<"&($C$4+7),Leads!$AZ$3:$AZ$1002,"<="&$C$7)-SUM(P19:P24) | Q25: — | R25: 0 | S25: =COUNTIFS(Leads!$B$3:$B$1002,">="&($C$4-7),Leads!$B$3:$B$1002,"<"&$C$4,Leads!$AZ$3:$AZ$1002,"<="&$C$7,Leads!$AU$3:$AU$1002,1)-SUM(S19:S24)
B26: Total | C26: =SUM(C19:C25) | D26: =SUM(D19:D25) | E26: =C26-D26 | F26: =SUM(F19:F25) | G26: =SUM(G19:G25) | H26: =IF(F26=0,"—",G26/F26) | I26: =IF(OR(F26=0,C26=0),"—",C26/F26) | J26: =IF(OR(G26=0,C26=0),"—",C26/G26) | K26: =SUM(K19:K25) | L26: =IF(G26=0,"—",K26/G26) | M26: =SUM(M19:M25) | N26: =IF(K26=0,"—",M26/K26) | O26: =IF(C26=0,"—",M26/C26) | P26: =SUM(P19:P25) | Q26: — | R26: =SUM(R19:R25) | S26: =SUM(S19:S25)
B29: Coût par LQ de Google Search (Corporatif + Mariage), pour la règle ChatGPT : | C29: =IFERROR((C32+C34)/(G32+G34),1E+99) | D29: (1E+99 = aucun LQ Google ce mois-ci)
B30: Mois : du 1er jour indiqué en C5 à la fin du mois
B31: Campagne | C31: Dépenses | D31: Budget cible (jours saisis) | E31: Écart vs budget | F31: Leads (tous) | G31: Leads qualifiés (LQ) | H31: % qualifiés | I31: Coût par lead | J31: Coût par LQ | K31: Contrats (dépôts) | L31: Taux de signature | M31: Revenu (montant gagné) | N31: Panier moyen | O31: ROAS | P31: Pipeline pondéré | Q31: Décision
B32: Google Search – Corporatif | C32: =SUMIFS('Dépenses'!$C$8:$C$464,'Dépenses'!$A$8:$A$464,">="&$C$5,'Dépenses'!$A$8:$A$464,"<"&EDATE($C$5,1)) | D32: ='Dépenses'!$C$3*COUNTIFS('Dépenses'!$A$8:$A$464,">="&$C$5,'Dépenses'!$A$8:$A$464,"<"&EDATE($C$5,1),'Dépenses'!$C$8:$C$464,"<>") | E32: =C32-D32 | F32: =COUNTIFS(Leads!$AQ$3:$AQ$1002,$B32,Leads!$B$3:$B$1002,">="&$C$5,Leads!$B$3:$B$1002,"<"&EDATE($C$5,1),Leads!$AZ$3:$AZ$1002,"<="&$C$7) | G32: =COUNTIFS(Leads!$AQ$3:$AQ$1002,$B32,Leads!$B$3:$B$1002,">="&$C$5,Leads!$B$3:$B$1002,"<"&EDATE($C$5,1),Leads!$AZ$3:$AZ$1002,"<="&$C$7,Leads!$AU$3:$AU$1002,1) | H32: =IF(F32=0,"—",G32/F32) | I32: =IF(OR(F32=0,C32=0),"—",C32/F32) | J32: =IF(OR(G32=0,C32=0),"—",C32/G32) | K32: =COUNTIFS(Leads!$AQ$3:$AQ$1002,$B32,Leads!$B$3:$B$1002,">="&$C$5,Leads!$B$3:$B$1002,"<"&EDATE($C$5,1),Leads!$AZ$3:$AZ$1002,"<="&$C$7,Leads!$AV$3:$AV$1002,1) | L32: =IF(G32=0,"—",K32/G32) | M32: =SUMIFS(Leads!$V$3:$V$1002,Leads!$AQ$3:$AQ$1002,$B32,Leads!$B$3:$B$1002,">="&$C$5,Leads!$B$3:$B$1002,"<"&EDATE($C$5,1),Leads!$AZ$3:$AZ$1002,"<="&$C$7,Leads!$AV$3:$AV$1002,1) | N32: =IF(K32=0,"—",M32/K32) | O32: =IF(C32=0,"—",M32/C32) | P32: =SUMIFS(Leads!$AY$3:$AY$1002,Leads!$AQ$3:$AQ$1002,$B32,Leads!$B$3:$B$1002,">="&$C$5,Leads!$B$3:$B$1002,"<"&EDATE($C$5,1),Leads!$AZ$3:$AZ$1002,"<="&$C$7) | Q32: =IF(C32<$I$10,"Garder (données insuffisantes)",IF(IFERROR(C32/G32,1E+99)>$I$9,"Réduire 30 %",IF(AND(G32>0,IFERROR(C32/G32,1E+99)<$I$11,IFERROR(K32/G32,0)>=$I$6),"Augmenter +20 %","Garder")))
B33: Meta – Leads | C33: =SUMIFS('Dépenses'!$D$8:$D$464,'Dépenses'!$A$8:$A$464,">="&$C$5,'Dépenses'!$A$8:$A$464,"<"&EDATE($C$5,1)) | D33: ='Dépenses'!$D$3*COUNTIFS('Dépenses'!$A$8:$A$464,">="&$C$5,'Dépenses'!$A$8:$A$464,"<"&EDATE($C$5,1),'Dépenses'!$D$8:$D$464,"<>") | E33: =C33-D33 | F33: =COUNTIFS(Leads!$AQ$3:$AQ$1002,$B33,Leads!$B$3:$B$1002,">="&$C$5,Leads!$B$3:$B$1002,"<"&EDATE($C$5,1),Leads!$AZ$3:$AZ$1002,"<="&$C$7) | G33: =COUNTIFS(Leads!$AQ$3:$AQ$1002,$B33,Leads!$B$3:$B$1002,">="&$C$5,Leads!$B$3:$B$1002,"<"&EDATE($C$5,1),Leads!$AZ$3:$AZ$1002,"<="&$C$7,Leads!$AU$3:$AU$1002,1) | H33: =IF(F33=0,"—",G33/F33) | I33: =IF(OR(F33=0,C33=0),"—",C33/F33) | J33: =IF(OR(G33=0,C33=0),"—",C33/G33) | K33: =COUNTIFS(Leads!$AQ$3:$AQ$1002,$B33,Leads!$B$3:$B$1002,">="&$C$5,Leads!$B$3:$B$1002,"<"&EDATE($C$5,1),Leads!$AZ$3:$AZ$1002,"<="&$C$7,Leads!$AV$3:$AV$1002,1) | L33: =IF(G33=0,"—",K33/G33) | M33: =SUMIFS(Leads!$V$3:$V$1002,Leads!$AQ$3:$AQ$1002,$B33,Leads!$B$3:$B$1002,">="&$C$5,Leads!$B$3:$B$1002,"<"&EDATE($C$5,1),Leads!$AZ$3:$AZ$1002,"<="&$C$7,Leads!$AV$3:$AV$1002,1) | N33: =IF(K33=0,"—",M33/K33) | O33: =IF(C33=0,"—",M33/C33) | P33: =SUMIFS(Leads!$AY$3:$AY$1002,Leads!$AQ$3:$AQ$1002,$B33,Leads!$B$3:$B$1002,">="&$C$5,Leads!$B$3:$B$1002,"<"&EDATE($C$5,1),Leads!$AZ$3:$AZ$1002,"<="&$C$7) | Q33: =IF(C33<$I$10,"Garder (données insuffisantes)",IF(IFERROR(C33/G33,1E+99)>$I$9,"Réduire 30 %",IF(AND(G33>0,IFERROR(C33/G33,1E+99)<$I$11,IFERROR(K33/G33,0)>=$I$6),"Augmenter +20 %","Garder")))
B34: Google Search – Mariage et privé | C34: =SUMIFS('Dépenses'!$E$8:$E$464,'Dépenses'!$A$8:$A$464,">="&$C$5,'Dépenses'!$A$8:$A$464,"<"&EDATE($C$5,1)) | D34: ='Dépenses'!$E$3*COUNTIFS('Dépenses'!$A$8:$A$464,">="&$C$5,'Dépenses'!$A$8:$A$464,"<"&EDATE($C$5,1),'Dépenses'!$E$8:$E$464,"<>") | E34: =C34-D34 | F34: =COUNTIFS(Leads!$AQ$3:$AQ$1002,$B34,Leads!$B$3:$B$1002,">="&$C$5,Leads!$B$3:$B$1002,"<"&EDATE($C$5,1),Leads!$AZ$3:$AZ$1002,"<="&$C$7) | G34: =COUNTIFS(Leads!$AQ$3:$AQ$1002,$B34,Leads!$B$3:$B$1002,">="&$C$5,Leads!$B$3:$B$1002,"<"&EDATE($C$5,1),Leads!$AZ$3:$AZ$1002,"<="&$C$7,Leads!$AU$3:$AU$1002,1) | H34: =IF(F34=0,"—",G34/F34) | I34: =IF(OR(F34=0,C34=0),"—",C34/F34) | J34: =IF(OR(G34=0,C34=0),"—",C34/G34) | K34: =COUNTIFS(Leads!$AQ$3:$AQ$1002,$B34,Leads!$B$3:$B$1002,">="&$C$5,Leads!$B$3:$B$1002,"<"&EDATE($C$5,1),Leads!$AZ$3:$AZ$1002,"<="&$C$7,Leads!$AV$3:$AV$1002,1) | L34: =IF(G34=0,"—",K34/G34) | M34: =SUMIFS(Leads!$V$3:$V$1002,Leads!$AQ$3:$AQ$1002,$B34,Leads!$B$3:$B$1002,">="&$C$5,Leads!$B$3:$B$1002,"<"&EDATE($C$5,1),Leads!$AZ$3:$AZ$1002,"<="&$C$7,Leads!$AV$3:$AV$1002,1) | N34: =IF(K34=0,"—",M34/K34) | O34: =IF(C34=0,"—",M34/C34) | P34: =SUMIFS(Leads!$AY$3:$AY$1002,Leads!$AQ$3:$AQ$1002,$B34,Leads!$B$3:$B$1002,">="&$C$5,Leads!$B$3:$B$1002,"<"&EDATE($C$5,1),Leads!$AZ$3:$AZ$1002,"<="&$C$7) | Q34: =IF(C34<$I$10,"Garder (données insuffisantes)",IF(IFERROR(C34/G34,1E+99)>$I$9,"Réduire 30 %",IF(AND(G34>0,IFERROR(C34/G34,1E+99)<$I$11,IFERROR(K34/G34,0)>=$I$6),"Augmenter +20 %","Garder")))
B35: ChatGPT Ads – Test | C35: =SUMIFS('Dépenses'!$F$8:$F$464,'Dépenses'!$A$8:$A$464,">="&$C$5,'Dépenses'!$A$8:$A$464,"<"&EDATE($C$5,1)) | D35: ='Dépenses'!$F$3*COUNTIFS('Dépenses'!$A$8:$A$464,">="&$C$5,'Dépenses'!$A$8:$A$464,"<"&EDATE($C$5,1),'Dépenses'!$F$8:$F$464,"<>") | E35: =C35-D35 | F35: =COUNTIFS(Leads!$AQ$3:$AQ$1002,$B35,Leads!$B$3:$B$1002,">="&$C$5,Leads!$B$3:$B$1002,"<"&EDATE($C$5,1),Leads!$AZ$3:$AZ$1002,"<="&$C$7) | G35: =COUNTIFS(Leads!$AQ$3:$AQ$1002,$B35,Leads!$B$3:$B$1002,">="&$C$5,Leads!$B$3:$B$1002,"<"&EDATE($C$5,1),Leads!$AZ$3:$AZ$1002,"<="&$C$7,Leads!$AU$3:$AU$1002,1) | H35: =IF(F35=0,"—",G35/F35) | I35: =IF(OR(F35=0,C35=0),"—",C35/F35) | J35: =IF(OR(G35=0,C35=0),"—",C35/G35) | K35: =COUNTIFS(Leads!$AQ$3:$AQ$1002,$B35,Leads!$B$3:$B$1002,">="&$C$5,Leads!$B$3:$B$1002,"<"&EDATE($C$5,1),Leads!$AZ$3:$AZ$1002,"<="&$C$7,Leads!$AV$3:$AV$1002,1) | L35: =IF(G35=0,"—",K35/G35) | M35: =SUMIFS(Leads!$V$3:$V$1002,Leads!$AQ$3:$AQ$1002,$B35,Leads!$B$3:$B$1002,">="&$C$5,Leads!$B$3:$B$1002,"<"&EDATE($C$5,1),Leads!$AZ$3:$AZ$1002,"<="&$C$7,Leads!$AV$3:$AV$1002,1) | N35: =IF(K35=0,"—",M35/K35) | O35: =IF(C35=0,"—",M35/C35) | P35: =SUMIFS(Leads!$AY$3:$AY$1002,Leads!$AQ$3:$AQ$1002,$B35,Leads!$B$3:$B$1002,">="&$C$5,Leads!$B$3:$B$1002,"<"&EDATE($C$5,1),Leads!$AZ$3:$AZ$1002,"<="&$C$7) | Q35: =IF(C35<$I$10,"Garder (données insuffisantes)",IF(AND(C35>=$I$13,OR(G35<$I$12,IFERROR(C35/G35,1E+99)>2*$C$29)),"Couper",IF(IFERROR(C35/G35,1E+99)>$I$9,"Réduire 30 %",IF(AND(G35>0,IFERROR(C35/G35,1E+99)<$I$11,IFERROR(K35/G35,0)>=$I$6),"Augmenter +20 %","Garder"))))
B36: Microsoft Ads | C36: =SUMIFS('Dépenses'!$G$8:$G$464,'Dépenses'!$A$8:$A$464,">="&$C$5,'Dépenses'!$A$8:$A$464,"<"&EDATE($C$5,1)) | D36: ='Dépenses'!$G$3*COUNTIFS('Dépenses'!$A$8:$A$464,">="&$C$5,'Dépenses'!$A$8:$A$464,"<"&EDATE($C$5,1),'Dépenses'!$G$8:$G$464,"<>") | E36: =C36-D36 | F36: =COUNTIFS(Leads!$AQ$3:$AQ$1002,$B36,Leads!$B$3:$B$1002,">="&$C$5,Leads!$B$3:$B$1002,"<"&EDATE($C$5,1),Leads!$AZ$3:$AZ$1002,"<="&$C$7) | G36: =COUNTIFS(Leads!$AQ$3:$AQ$1002,$B36,Leads!$B$3:$B$1002,">="&$C$5,Leads!$B$3:$B$1002,"<"&EDATE($C$5,1),Leads!$AZ$3:$AZ$1002,"<="&$C$7,Leads!$AU$3:$AU$1002,1) | H36: =IF(F36=0,"—",G36/F36) | I36: =IF(OR(F36=0,C36=0),"—",C36/F36) | J36: =IF(OR(G36=0,C36=0),"—",C36/G36) | K36: =COUNTIFS(Leads!$AQ$3:$AQ$1002,$B36,Leads!$B$3:$B$1002,">="&$C$5,Leads!$B$3:$B$1002,"<"&EDATE($C$5,1),Leads!$AZ$3:$AZ$1002,"<="&$C$7,Leads!$AV$3:$AV$1002,1) | L36: =IF(G36=0,"—",K36/G36) | M36: =SUMIFS(Leads!$V$3:$V$1002,Leads!$AQ$3:$AQ$1002,$B36,Leads!$B$3:$B$1002,">="&$C$5,Leads!$B$3:$B$1002,"<"&EDATE($C$5,1),Leads!$AZ$3:$AZ$1002,"<="&$C$7,Leads!$AV$3:$AV$1002,1) | N36: =IF(K36=0,"—",M36/K36) | O36: =IF(C36=0,"—",M36/C36) | P36: =SUMIFS(Leads!$AY$3:$AY$1002,Leads!$AQ$3:$AQ$1002,$B36,Leads!$B$3:$B$1002,">="&$C$5,Leads!$B$3:$B$1002,"<"&EDATE($C$5,1),Leads!$AZ$3:$AZ$1002,"<="&$C$7) | Q36: =IF(C36<$I$10,"Garder (données insuffisantes)",IF(IFERROR(C36/G36,1E+99)>$I$9,"Réduire 30 %",IF(AND(G36>0,IFERROR(C36/G36,1E+99)<$I$11,IFERROR(K36/G36,0)>=$I$6),"Augmenter +20 %","Garder")))
B37: Google Search – Marque | C37: =SUMIFS('Dépenses'!$H$8:$H$464,'Dépenses'!$A$8:$A$464,">="&$C$5,'Dépenses'!$A$8:$A$464,"<"&EDATE($C$5,1)) | D37: ='Dépenses'!$H$3*COUNTIFS('Dépenses'!$A$8:$A$464,">="&$C$5,'Dépenses'!$A$8:$A$464,"<"&EDATE($C$5,1),'Dépenses'!$H$8:$H$464,"<>") | E37: =C37-D37 | F37: =COUNTIFS(Leads!$AQ$3:$AQ$1002,$B37,Leads!$B$3:$B$1002,">="&$C$5,Leads!$B$3:$B$1002,"<"&EDATE($C$5,1),Leads!$AZ$3:$AZ$1002,"<="&$C$7) | G37: =COUNTIFS(Leads!$AQ$3:$AQ$1002,$B37,Leads!$B$3:$B$1002,">="&$C$5,Leads!$B$3:$B$1002,"<"&EDATE($C$5,1),Leads!$AZ$3:$AZ$1002,"<="&$C$7,Leads!$AU$3:$AU$1002,1) | H37: =IF(F37=0,"—",G37/F37) | I37: =IF(OR(F37=0,C37=0),"—",C37/F37) | J37: =IF(OR(G37=0,C37=0),"—",C37/G37) | K37: =COUNTIFS(Leads!$AQ$3:$AQ$1002,$B37,Leads!$B$3:$B$1002,">="&$C$5,Leads!$B$3:$B$1002,"<"&EDATE($C$5,1),Leads!$AZ$3:$AZ$1002,"<="&$C$7,Leads!$AV$3:$AV$1002,1) | L37: =IF(G37=0,"—",K37/G37) | M37: =SUMIFS(Leads!$V$3:$V$1002,Leads!$AQ$3:$AQ$1002,$B37,Leads!$B$3:$B$1002,">="&$C$5,Leads!$B$3:$B$1002,"<"&EDATE($C$5,1),Leads!$AZ$3:$AZ$1002,"<="&$C$7,Leads!$AV$3:$AV$1002,1) | N37: =IF(K37=0,"—",M37/K37) | O37: =IF(C37=0,"—",M37/C37) | P37: =SUMIFS(Leads!$AY$3:$AY$1002,Leads!$AQ$3:$AQ$1002,$B37,Leads!$B$3:$B$1002,">="&$C$5,Leads!$B$3:$B$1002,"<"&EDATE($C$5,1),Leads!$AZ$3:$AZ$1002,"<="&$C$7) | Q37: =IF(C37<$I$10,"Garder (données insuffisantes)",IF(IFERROR(C37/G37,1E+99)>$I$9,"Réduire 30 %",IF(AND(G37>0,IFERROR(C37/G37,1E+99)<$I$11,IFERROR(K37/G37,0)>=$I$6),"Augmenter +20 %","Garder")))
B38: Autres sources (non payées) | C38: 0 | D38: 0 | E38: =C38-D38 | F38: =COUNTIFS(Leads!$B$3:$B$1002,">="&$C$5,Leads!$B$3:$B$1002,"<"&EDATE($C$5,1),Leads!$AZ$3:$AZ$1002,"<="&$C$7)-SUM(F32:F37) | G38: =COUNTIFS(Leads!$B$3:$B$1002,">="&$C$5,Leads!$B$3:$B$1002,"<"&EDATE($C$5,1),Leads!$AZ$3:$AZ$1002,"<="&$C$7,Leads!$AU$3:$AU$1002,1)-SUM(G32:G37) | H38: =IF(F38=0,"—",G38/F38) | I38: =IF(OR(F38=0,C38=0),"—",C38/F38) | J38: =IF(OR(G38=0,C38=0),"—",C38/G38) | K38: =COUNTIFS(Leads!$B$3:$B$1002,">="&$C$5,Leads!$B$3:$B$1002,"<"&EDATE($C$5,1),Leads!$AZ$3:$AZ$1002,"<="&$C$7,Leads!$AV$3:$AV$1002,1)-SUM(K32:K37) | L38: =IF(G38=0,"—",K38/G38) | M38: =SUMIFS(Leads!$V$3:$V$1002,Leads!$B$3:$B$1002,">="&$C$5,Leads!$B$3:$B$1002,"<"&EDATE($C$5,1),Leads!$AZ$3:$AZ$1002,"<="&$C$7,Leads!$AV$3:$AV$1002,1)-SUM(M32:M37) | N38: =IF(K38=0,"—",M38/K38) | O38: =IF(C38=0,"—",M38/C38) | P38: =SUMIFS(Leads!$AY$3:$AY$1002,Leads!$B$3:$B$1002,">="&$C$5,Leads!$B$3:$B$1002,"<"&EDATE($C$5,1),Leads!$AZ$3:$AZ$1002,"<="&$C$7)-SUM(P32:P37) | Q38: —
B39: Total | C39: =SUM(C32:C38) | D39: =SUM(D32:D38) | E39: =C39-D39 | F39: =SUM(F32:F38) | G39: =SUM(G32:G38) | H39: =IF(F39=0,"—",G39/F39) | I39: =IF(OR(F39=0,C39=0),"—",C39/F39) | J39: =IF(OR(G39=0,C39=0),"—",C39/G39) | K39: =SUM(K32:K38) | L39: =IF(G39=0,"—",K39/G39) | M39: =SUM(M32:M38) | N39: =IF(K39=0,"—",M39/K39) | O39: =IF(C39=0,"—",M39/C39) | P39: =SUM(P32:P38) | Q39: —
B40: Décision mensuelle (COMPTE-RENDU.md, jour 30) : Couper = ChatGPT avec ≥ 900 $ dépensés et moins de 2 LQ ou un coût par LQ > 2 × Google Search (les 30 $ vont au Google Corporatif) · Réduire 30 % = aucun LQ ou coût par LQ > 300 $ · Augmenter +20 % (max par semaine) = coût par LQ < 100 $ et signature ≥ 25 % · sinon Garder. Moins de 300 $ dépensés = données insuffisantes. Le total reste à 300 $/jour : toute hausse est financée par la campagne au pire coût par LQ.
B44: Répartition par segment (mois analysé) — cible : corporatif ≥ 50 % de la valeur
B45: Segment | C45: Leads (tous) | D45: LQ | E45: Contrats | F45: Revenu | G45: % de la valeur | H45: ROAS (non attribué)
B46: Corporatif | C46: =COUNTIFS(Leads!$AR$3:$AR$1002,$B46,Leads!$B$3:$B$1002,">="&$C$5,Leads!$B$3:$B$1002,"<"&EDATE($C$5,1),Leads!$AZ$3:$AZ$1002,"<="&$C$7) | D46: =COUNTIFS(Leads!$AR$3:$AR$1002,$B46,Leads!$B$3:$B$1002,">="&$C$5,Leads!$B$3:$B$1002,"<"&EDATE($C$5,1),Leads!$AZ$3:$AZ$1002,"<="&$C$7,Leads!$AU$3:$AU$1002,1) | E46: =COUNTIFS(Leads!$AR$3:$AR$1002,$B46,Leads!$B$3:$B$1002,">="&$C$5,Leads!$B$3:$B$1002,"<"&EDATE($C$5,1),Leads!$AZ$3:$AZ$1002,"<="&$C$7,Leads!$AV$3:$AV$1002,1) | F46: =SUMIFS(Leads!$V$3:$V$1002,Leads!$AR$3:$AR$1002,$B46,Leads!$B$3:$B$1002,">="&$C$5,Leads!$B$3:$B$1002,"<"&EDATE($C$5,1),Leads!$AZ$3:$AZ$1002,"<="&$C$7,Leads!$AV$3:$AV$1002,1) | G46: =IF($F$50=0,"—",F46/$F$50) | H46: —
B47: Municipal / scolaire | C47: =COUNTIFS(Leads!$AR$3:$AR$1002,$B47,Leads!$B$3:$B$1002,">="&$C$5,Leads!$B$3:$B$1002,"<"&EDATE($C$5,1),Leads!$AZ$3:$AZ$1002,"<="&$C$7) | D47: =COUNTIFS(Leads!$AR$3:$AR$1002,$B47,Leads!$B$3:$B$1002,">="&$C$5,Leads!$B$3:$B$1002,"<"&EDATE($C$5,1),Leads!$AZ$3:$AZ$1002,"<="&$C$7,Leads!$AU$3:$AU$1002,1) | E47: =COUNTIFS(Leads!$AR$3:$AR$1002,$B47,Leads!$B$3:$B$1002,">="&$C$5,Leads!$B$3:$B$1002,"<"&EDATE($C$5,1),Leads!$AZ$3:$AZ$1002,"<="&$C$7,Leads!$AV$3:$AV$1002,1) | F47: =SUMIFS(Leads!$V$3:$V$1002,Leads!$AR$3:$AR$1002,$B47,Leads!$B$3:$B$1002,">="&$C$5,Leads!$B$3:$B$1002,"<"&EDATE($C$5,1),Leads!$AZ$3:$AZ$1002,"<="&$C$7,Leads!$AV$3:$AV$1002,1) | G47: =IF($F$50=0,"—",F47/$F$50) | H47: —
B48: Mariage | C48: =COUNTIFS(Leads!$AR$3:$AR$1002,$B48,Leads!$B$3:$B$1002,">="&$C$5,Leads!$B$3:$B$1002,"<"&EDATE($C$5,1),Leads!$AZ$3:$AZ$1002,"<="&$C$7) | D48: =COUNTIFS(Leads!$AR$3:$AR$1002,$B48,Leads!$B$3:$B$1002,">="&$C$5,Leads!$B$3:$B$1002,"<"&EDATE($C$5,1),Leads!$AZ$3:$AZ$1002,"<="&$C$7,Leads!$AU$3:$AU$1002,1) | E48: =COUNTIFS(Leads!$AR$3:$AR$1002,$B48,Leads!$B$3:$B$1002,">="&$C$5,Leads!$B$3:$B$1002,"<"&EDATE($C$5,1),Leads!$AZ$3:$AZ$1002,"<="&$C$7,Leads!$AV$3:$AV$1002,1) | F48: =SUMIFS(Leads!$V$3:$V$1002,Leads!$AR$3:$AR$1002,$B48,Leads!$B$3:$B$1002,">="&$C$5,Leads!$B$3:$B$1002,"<"&EDATE($C$5,1),Leads!$AZ$3:$AZ$1002,"<="&$C$7,Leads!$AV$3:$AV$1002,1) | G48: =IF($F$50=0,"—",F48/$F$50) | H48: —
B49: Privé | C49: =COUNTIFS(Leads!$AR$3:$AR$1002,$B49,Leads!$B$3:$B$1002,">="&$C$5,Leads!$B$3:$B$1002,"<"&EDATE($C$5,1),Leads!$AZ$3:$AZ$1002,"<="&$C$7) | D49: =COUNTIFS(Leads!$AR$3:$AR$1002,$B49,Leads!$B$3:$B$1002,">="&$C$5,Leads!$B$3:$B$1002,"<"&EDATE($C$5,1),Leads!$AZ$3:$AZ$1002,"<="&$C$7,Leads!$AU$3:$AU$1002,1) | E49: =COUNTIFS(Leads!$AR$3:$AR$1002,$B49,Leads!$B$3:$B$1002,">="&$C$5,Leads!$B$3:$B$1002,"<"&EDATE($C$5,1),Leads!$AZ$3:$AZ$1002,"<="&$C$7,Leads!$AV$3:$AV$1002,1) | F49: =SUMIFS(Leads!$V$3:$V$1002,Leads!$AR$3:$AR$1002,$B49,Leads!$B$3:$B$1002,">="&$C$5,Leads!$B$3:$B$1002,"<"&EDATE($C$5,1),Leads!$AZ$3:$AZ$1002,"<="&$C$7,Leads!$AV$3:$AV$1002,1) | G49: =IF($F$50=0,"—",F49/$F$50) | H49: —
B50: Total | C50: =SUM(C46:C49) | D50: =SUM(D46:D49) | E50: =SUM(E46:E49) | F50: =SUM(F46:F49) | G50: =IF($F$50=0,"—",F50/$F$50) | H50: =IF(C39=0,"—",F50/C39)
B53: Procédure de réponse (semaine analysée, LQ = routes A et B) — suivi-leads.md §10
B54: Indicateur | C54: Valeur | D54: Cible
B55: Délai médian de 1er contact (min) | C55: {=IFERROR(MEDIAN(IF((Leads!$B$3:$B$1002>=$C$4)*(Leads!$B$3:$B$1002<($C$4+7))*(Leads!$AU$3:$AU$1002=1)*ISNUMBER(Leads!$D$3:$D$1002)*(Leads!$AZ$3:$AZ$1002<=$C$7),Leads!$D$3:$D$1002)),"—")} | D55: 5 minutes au maximum (heures d'ouverture)
B56: % des LQ contactés en 5 min ou moins | C56: =IF(G26=0,"—",COUNTIFS(Leads!$B$3:$B$1002,">="&$C$4,Leads!$B$3:$B$1002,"<"&($C$4+7),Leads!$AZ$3:$AZ$1002,"<="&$C$7,Leads!$AU$3:$AU$1002,1,Leads!$D$3:$D$1002,"<=5")/G26) | D56: Le plus près de 100 %
B57: % des LQ contactés en plus de 15 min (ou pas encore) | C57: =IF(G26=0,"—",1-COUNTIFS(Leads!$B$3:$B$1002,">="&$C$4,Leads!$B$3:$B$1002,"<"&($C$4+7),Leads!$AZ$3:$AZ$1002,"<="&$C$7,Leads!$AU$3:$AU$1002,1,Leads!$D$3:$D$1002,"<=15")/G26) | D57: 0 % (au-dessus de 15 min : corriger la procédure avant d'augmenter le budget)

Sheet Import conversions Google
A1: Google Click ID | B1: Conversion Name | C1: Conversion Time | D1: Conversion Value | E1: Conversion Currency | G1: lead_id | H1: Campagne | I1: consent_mesure | J1: date_depot (brute) | L1: Comment utiliser cette feuille
A2: =IF(G2="","",INDEX(Leads!$AC$3:$AC$1002,MATCH(1,Leads!$BA$3:$BA$1002,0))) | B2: =IF(G2="","","depot_paye") | C2: =IF(G2="","",YEAR(J2)&"-"&RIGHT("0"&MONTH(J2),2)&"-"&RIGHT("0"&DAY(J2),2)&" "&RIGHT("0"&HOUR(J2),2)&":"&RIGHT("0"&MINUTE(J2),2)&":"&RIGHT("0"&SECOND(J2),2)&IF(AND(J2>=DATE(YEAR(J2),3,8)+MOD(8-WEEKDAY(DATE(YEAR(J2),3,8)),7)+2/24,J2<DATE(YEAR(J2),11,1)+MOD(8-WEEKDAY(DATE(YEAR(J2),11,1)),7)+2/24),"-04:00","-05:00")) | D2: =IF(G2="","",INDEX(Leads!$V$3:$V$1002,MATCH(1,Leads!$BA$3:$BA$1002,0))) | E2: =IF(G2="","","CAD") | G2: =IFERROR(INDEX(Leads!$A$3:$A$1002,MATCH(1,Leads!$BA$3:$BA$1002,0)),"") | H2: =IF(G2="","",INDEX(Leads!$AQ$3:$AQ$1002,MATCH(1,Leads!$BA$3:$BA$1002,0))) | I2: =IF(G2="","",INDEX(Leads!$AI$3:$AI$1002,MATCH(1,Leads!$BA$3:$BA$1002,0))&"") | J2: =IF(G2="","",INDEX(Leads!$W$3:$W$1002,MATCH(1,Leads!$BA$3:$BA$1002,0)))
A3: =IF(G3="","",INDEX(Leads!$AC$3:$AC$1002,MATCH(2,Leads!$BA$3:$BA$1002,0))) | B3: =IF(G3="","","depot_paye") | C3: =IF(G3="","",YEAR(J3)&"-"&RIGHT("0"&MONTH(J3),2)&"-"&RIGHT("0"&DAY(J3),2)&" "&RIGHT("0"&HOUR(J3),2)&":"&RIGHT("0"&MINUTE(J3),2)&":"&RIGHT("0"&SECOND(J3),2)&IF(AND(J3>=DATE(YEAR(J3),3,8)+MOD(8-WEEKDAY(DATE(YEAR(J3),3,8)),7)+2/24,J3<DATE(YEAR(J3),11,1)+MOD(8-WEEKDAY(DATE(YEAR(J3),11,1)),7)+2/24),"-04:00","-05:00")) | D3: =IF(G3="","",INDEX(Leads!$V$3:$V$1002,MATCH(2,Leads!$BA$3:$BA$1002,0))) | E3: =IF(G3="","","CAD") | G3: =IFERROR(INDEX(Leads!$A$3:$A$1002,MATCH(2,Leads!$BA$3:$BA$1002,0)),"") | H3: =IF(G3="","",INDEX(Leads!$AQ$3:$AQ$1002,MATCH(2,Leads!$BA$3:$BA$1002,0))) | I3: =IF(G3="","",INDEX(Leads!$AI$3:$AI$1002,MATCH(2,Leads!$BA$3:$BA$1002,0))&"") | J3: =IF(G3="","",INDEX(Leads!$W$3:$W$1002,MATCH(2,Leads!$BA$3:$BA$1002,0))) | L3: 1. Ne rien saisir ici : les lignes se remplissent seules à partir de la feuille Leads.
A4: =IF(G4="","",INDEX(Leads!$AC$3:$AC$1002,MATCH(3,Leads!$BA$3:$BA$1002,0))) | B4: =IF(G4="","","depot_paye") | C4: =IF(G4="","",YEAR(J4)&"-"&RIGHT("0"&MONTH(J4),2)&"-"&RIGHT("0"&DAY(J4),2)&" "&RIGHT("0"&HOUR(J4),2)&":"&RIGHT("0"&MINUTE(J4),2)&":"&RIGHT("0"&SECOND(J4),2)&IF(AND(J4>=DATE(YEAR(J4),3,8)+MOD(8-WEEKDAY(DATE(YEAR(J4),3,8)),7)+2/24,J4<DATE(YEAR(J4),11,1)+MOD(8-WEEKDAY(DATE(YEAR(J4),11,1)),7)+2/24),"-04:00","-05:00")) | D4: =IF(G4="","",INDEX(Leads!$V$3:$V$1002,MATCH(3,Leads!$BA$3:$BA$1002,0))) | E4: =IF(G4="","","CAD") | G4: =IFERROR(INDEX(Leads!$A$3:$A$1002,MATCH(3,Leads!$BA$3:$BA$1002,0)),"") | H4: =IF(G4="","",INDEX(Leads!$AQ$3:$AQ$1002,MATCH(3,Leads!$BA$3:$BA$1002,0))) | I4: =IF(G4="","",INDEX(Leads!$AI$3:$AI$1002,MATCH(3,Leads!$BA$3:$BA$1002,0))&"") | J4: =IF(G4="","",INDEX(Leads!$W$3:$W$1002,MATCH(3,Leads!$BA$3:$BA$1002,0)))
A5: =IF(G5="","",INDEX(Leads!$AC$3:$AC$1002,MATCH(4,Leads!$BA$3:$BA$1002,0))) | B5: =IF(G5="","","depot_paye") | C5: =IF(G5="","",YEAR(J5)&"-"&RIGHT("0"&MONTH(J5),2)&"-"&RIGHT("0"&DAY(J5),2)&" "&RIGHT("0"&HOUR(J5),2)&":"&RIGHT("0"&MINUTE(J5),2)&":"&RIGHT("0"&SECOND(J5),2)&IF(AND(J5>=DATE(YEAR(J5),3,8)+MOD(8-WEEKDAY(DATE(YEAR(J5),3,8)),7)+2/24,J5<DATE(YEAR(J5),11,1)+MOD(8-WEEKDAY(DATE(YEAR(J5),11,1)),7)+2/24),"-04:00","-05:00")) | D5: =IF(G5="","",INDEX(Leads!$V$3:$V$1002,MATCH(4,Leads!$BA$3:$BA$1002,0))) | E5: =IF(G5="","","CAD") | G5: =IFERROR(INDEX(Leads!$A$3:$A$1002,MATCH(4,Leads!$BA$3:$BA$1002,0)),"") | H5: =IF(G5="","",INDEX(Leads!$AQ$3:$AQ$1002,MATCH(4,Leads!$BA$3:$BA$1002,0))) | I5: =IF(G5="","",INDEX(Leads!$AI$3:$AI$1002,MATCH(4,Leads!$BA$3:$BA$1002,0))&"") | J5: =IF(G5="","",INDEX(Leads!$W$3:$W$1002,MATCH(4,Leads!$BA$3:$BA$1002,0))) | L5: 2. Une ligne apparaît quand un lead (non EXEMPLE) est à l'étape « Dépôt payé (gagné) » ou plus, avec un gclid, une date de dépôt et un montant gagné.
A6: =IF(G6="","",INDEX(Leads!$AC$3:$AC$1002,MATCH(5,Leads!$BA$3:$BA$1002,0))) | B6: =IF(G6="","","depot_paye") | C6: =IF(G6="","",YEAR(J6)&"-"&RIGHT("0"&MONTH(J6),2)&"-"&RIGHT("0"&DAY(J6),2)&" "&RIGHT("0"&HOUR(J6),2)&":"&RIGHT("0"&MINUTE(J6),2)&":"&RIGHT("0"&SECOND(J6),2)&IF(AND(J6>=DATE(YEAR(J6),3,8)+MOD(8-WEEKDAY(DATE(YEAR(J6),3,8)),7)+2/24,J6<DATE(YEAR(J6),11,1)+MOD(8-WEEKDAY(DATE(YEAR(J6),11,1)),7)+2/24),"-04:00","-05:00")) | D6: =IF(G6="","",INDEX(Leads!$V$3:$V$1002,MATCH(5,Leads!$BA$3:$BA$1002,0))) | E6: =IF(G6="","","CAD") | G6: =IFERROR(INDEX(Leads!$A$3:$A$1002,MATCH(5,Leads!$BA$3:$BA$1002,0)),"") | H6: =IF(G6="","",INDEX(Leads!$AQ$3:$AQ$1002,MATCH(5,Leads!$BA$3:$BA$1002,0))) | I6: =IF(G6="","",INDEX(Leads!$AI$3:$AI$1002,MATCH(5,Leads!$BA$3:$BA$1002,0))&"") | J6: =IF(G6="","",INDEX(Leads!$W$3:$W$1002,MATCH(5,Leads!$BA$3:$BA$1002,0)))
A7: =IF(G7="","",INDEX(Leads!$AC$3:$AC$1002,MATCH(6,Leads!$BA$3:$BA$1002,0))) | B7: =IF(G7="","","depot_paye") | C7: =IF(G7="","",YEAR(J7)&"-"&RIGHT("0"&MONTH(J7),2)&"-"&RIGHT("0"&DAY(J7),2)&" "&RIGHT("0"&HOUR(J7),2)&":"&RIGHT("0"&MINUTE(J7),2)&":"&RIGHT("0"&SECOND(J7),2)&IF(AND(J7>=DATE(YEAR(J7),3,8)+MOD(8-WEEKDAY(DATE(YEAR(J7),3,8)),7)+2/24,J7<DATE(YEAR(J7),11,1)+MOD(8-WEEKDAY(DATE(YEAR(J7),11,1)),7)+2/24),"-04:00","-05:00")) | D7: =IF(G7="","",INDEX(Leads!$V$3:$V$1002,MATCH(6,Leads!$BA$3:$BA$1002,0))) | E7: =IF(G7="","","CAD") | G7: =IFERROR(INDEX(Leads!$A$3:$A$1002,MATCH(6,Leads!$BA$3:$BA$1002,0)),"") | H7: =IF(G7="","",INDEX(Leads!$AQ$3:$AQ$1002,MATCH(6,Leads!$BA$3:$BA$1002,0))) | I7: =IF(G7="","",INDEX(Leads!$AI$3:$AI$1002,MATCH(6,Leads!$BA$3:$BA$1002,0))&"") | J7: =IF(G7="","",INDEX(Leads!$W$3:$W$1002,MATCH(6,Leads!$BA$3:$BA$1002,0))) | L7: 3. Colonnes A à E = format d'import hors ligne de Google Ads (Google Click ID, Conversion Name, Conversion Time, Conversion Value, Conversion Currency). Heure de l'Est, décalage -05:00 / -04:00 (heure avancée) calculé.
A8: =IF(G8="","",INDEX(Leads!$AC$3:$AC$1002,MATCH(7,Leads!$BA$3:$BA$1002,0))) | B8: =IF(G8="","","depot_paye") | C8: =IF(G8="","",YEAR(J8)&"-"&RIGHT("0"&MONTH(J8),2)&"-"&RIGHT("0"&DAY(J8),2)&" "&RIGHT("0"&HOUR(J8),2)&":"&RIGHT("0"&MINUTE(J8),2)&":"&RIGHT("0"&SECOND(J8),2)&IF(AND(J8>=DATE(YEAR(J8),3,8)+MOD(8-WEEKDAY(DATE(YEAR(J8),3,8)),7)+2/24,J8<DATE(YEAR(J8),11,1)+MOD(8-WEEKDAY(DATE(YEAR(J8),11,1)),7)+2/24),"-04:00","-05:00")) | D8: =IF(G8="","",INDEX(Leads!$V$3:$V$1002,MATCH(7,Leads!$BA$3:$BA$1002,0))) | E8: =IF(G8="","","CAD") | G8: =IFERROR(INDEX(Leads!$A$3:$A$1002,MATCH(7,Leads!$BA$3:$BA$1002,0)),"") | H8: =IF(G8="","",INDEX(Leads!$AQ$3:$AQ$1002,MATCH(7,Leads!$BA$3:$BA$1002,0))) | I8: =IF(G8="","",INDEX(Leads!$AI$3:$AI$1002,MATCH(7,Leads!$BA$3:$BA$1002,0))&"") | J8: =IF(G8="","",INDEX(Leads!$W$3:$W$1002,MATCH(7,Leads!$BA$3:$BA$1002,0)))
A9: =IF(G9="","",INDEX(Leads!$AC$3:$AC$1002,MATCH(8,Leads!$BA$3:$BA$1002,0))) | B9: =IF(G9="","","depot_paye") | C9: =IF(G9="","",YEAR(J9)&"-"&RIGHT("0"&MONTH(J9),2)&"-"&RIGHT("0"&DAY(J9),2)&" "&RIGHT("0"&HOUR(J9),2)&":"&RIGHT("0"&MINUTE(J9),2)&":"&RIGHT("0"&SECOND(J9),2)&IF(AND(J9>=DATE(YEAR(J9),3,8)+MOD(8-WEEKDAY(DATE(YEAR(J9),3,8)),7)+2/24,J9<DATE(YEAR(J9),11,1)+MOD(8-WEEKDAY(DATE(YEAR(J9),11,1)),7)+2/24),"-04:00","-05:00")) | D9: =IF(G9="","",INDEX(Leads!$V$3:$V$1002,MATCH(8,Leads!$BA$3:$BA$1002,0))) | E9: =IF(G9="","","CAD") | G9: =IFERROR(INDEX(Leads!$A$3:$A$1002,MATCH(8,Leads!$BA$3:$BA$1002,0)),"") | H9: =IF(G9="","",INDEX(Leads!$AQ$3:$AQ$1002,MATCH(8,Leads!$BA$3:$BA$1002,0))) | I9: =IF(G9="","",INDEX(Leads!$AI$3:$AI$1002,MATCH(8,Leads!$BA$3:$BA$1002,0))&"") | J9: =IF(G9="","",INDEX(Leads!$W$3:$W$1002,MATCH(8,Leads!$BA$3:$BA$1002,0))) | L9: 4. Exporter A1:E de cette feuille seulement (Fichier → Enregistrer sous → CSV), ou copier dans la feuille Google Sheets du téléversement planifié (Objectifs → Conversions → Téléversements → Planifier).
A10: =IF(G10="","",INDEX(Leads!$AC$3:$AC$1002,MATCH(9,Leads!$BA$3:$BA$1002,0))) | B10: =IF(G10="","","depot_paye") | C10: =IF(G10="","",YEAR(J10)&"-"&RIGHT("0"&MONTH(J10),2)&"-"&RIGHT("0"&DAY(J10),2)&" "&RIGHT("0"&HOUR(J10),2)&":"&RIGHT("0"&MINUTE(J10),2)&":"&RIGHT("0"&SECOND(J10),2)&IF(AND(J10>=DATE(YEAR(J10),3,8)+MOD(8-WEEKDAY(DATE(YEAR(J10),3,8)),7)+2/24,J10<DATE(YEAR(J10),11,1)+MOD(8-WEEKDAY(DATE(YEAR(J10),11,1)),7)+2/24),"-04:00","-05:00")) | D10: =IF(G10="","",INDEX(Leads!$V$3:$V$1002,MATCH(9,Leads!$BA$3:$BA$1002,0))) | E10: =IF(G10="","","CAD") | G10: =IFERROR(INDEX(Leads!$A$3:$A$1002,MATCH(9,Leads!$BA$3:$BA$1002,0)),"") | H10: =IF(G10="","",INDEX(Leads!$AQ$3:$AQ$1002,MATCH(9,Leads!$BA$3:$BA$1002,0))) | I10: =IF(G10="","",INDEX(Leads!$AI$3:$AI$1002,MATCH(9,Leads!$BA$3:$BA$1002,0))&"") | J10: =IF(G10="","",INDEX(Leads!$W$3:$W$1002,MATCH(9,Leads!$BA$3:$BA$1002,0)))
A11: =IF(G11="","",INDEX(Leads!$AC$3:$AC$1002,MATCH(10,Leads!$BA$3:$BA$1002,0))) | B11: =IF(G11="","","depot_paye") | C11: =IF(G11="","",YEAR(J11)&"-"&RIGHT("0"&MONTH(J11),2)&"-"&RIGHT("0"&DAY(J11),2)&" "&RIGHT("0"&HOUR(J11),2)&":"&RIGHT("0"&MINUTE(J11),2)&":"&RIGHT("0"&SECOND(J11),2)&IF(AND(J11>=DATE(YEAR(J11),3,8)+MOD(8-WEEKDAY(DATE(YEAR(J11),3,8)),7)+2/24,J11<DATE(YEAR(J11),11,1)+MOD(8-WEEKDAY(DATE(YEAR(J11),11,1)),7)+2/24),"-04:00","-05:00")) | D11: =IF(G11="","",INDEX(Leads!$V$3:$V$1002,MATCH(10,Leads!$BA$3:$BA$1002,0))) | E11: =IF(G11="","","CAD") | G11: =IFERROR(INDEX(Leads!$A$3:$A$1002,MATCH(10,Leads!$BA$3:$BA$1002,0)),"") | H11: =IF(G11="","",INDEX(Leads!$AQ$3:$AQ$1002,MATCH(10,Leads!$BA$3:$BA$1002,0))) | I11: =IF(G11="","",INDEX(Leads!$AI$3:$AI$1002,MATCH(10,Leads!$BA$3:$BA$1002,0))&"") | J11: =IF(G11="","",INDEX(Leads!$W$3:$W$1002,MATCH(10,Leads!$BA$3:$BA$1002,0))) | L11: 5. Conversion Name doit être identique à l'action Google Ads : depot_paye. Délai maximal : 90 jours après le clic.
A12: =IF(G12="","",INDEX(Leads!$AC$3:$AC$1002,MATCH(11,Leads!$BA$3:$BA$1002,0))) | B12: =IF(G12="","","depot_paye") | C12: =IF(G12="","",YEAR(J12)&"-"&RIGHT("0"&MONTH(J12),2)&"-"&RIGHT("0"&DAY(J12),2)&" "&RIGHT("0"&HOUR(J12),2)&":"&RIGHT("0"&MINUTE(J12),2)&":"&RIGHT("0"&SECOND(J12),2)&IF(AND(J12>=DATE(YEAR(J12),3,8)+MOD(8-WEEKDAY(DATE(YEAR(J12),3,8)),7)+2/24,J12<DATE(YEAR(J12),11,1)+MOD(8-WEEKDAY(DATE(YEAR(J12),11,1)),7)+2/24),"-04:00","-05:00")) | D12: =IF(G12="","",INDEX(Leads!$V$3:$V$1002,MATCH(11,Leads!$BA$3:$BA$1002,0))) | E12: =IF(G12="","","CAD") | G12: =IFERROR(INDEX(Leads!$A$3:$A$1002,MATCH(11,Leads!$BA$3:$BA$1002,0)),"") | H12: =IF(G12="","",INDEX(Leads!$AQ$3:$AQ$1002,MATCH(11,Leads!$BA$3:$BA$1002,0))) | I12: =IF(G12="","",INDEX(Leads!$AI$3:$AI$1002,MATCH(11,Leads!$BA$3:$BA$1002,0))&"") | J12: =IF(G12="","",INDEX(Leads!$W$3:$W$1002,MATCH(11,Leads!$BA$3:$BA$1002,0)))
A13: =IF(G13="","",INDEX(Leads!$AC$3:$AC$1002,MATCH(12,Leads!$BA$3:$BA$1002,0))) | B13: =IF(G13="","","depot_paye") | C13: =IF(G13="","",YEAR(J13)&"-"&RIGHT("0"&MONTH(J13),2)&"-"&RIGHT("0"&DAY(J13),2)&" "&RIGHT("0"&HOUR(J13),2)&":"&RIGHT("0"&MINUTE(J13),2)&":"&RIGHT("0"&SECOND(J13),2)&IF(AND(J13>=DATE(YEAR(J13),3,8)+MOD(8-WEEKDAY(DATE(YEAR(J13),3,8)),7)+2/24,J13<DATE(YEAR(J13),11,1)+MOD(8-WEEKDAY(DATE(YEAR(J13),11,1)),7)+2/24),"-04:00","-05:00")) | D13: =IF(G13="","",INDEX(Leads!$V$3:$V$1002,MATCH(12,Leads!$BA$3:$BA$1002,0))) | E13: =IF(G13="","","CAD") | G13: =IFERROR(INDEX(Leads!$A$3:$A$1002,MATCH(12,Leads!$BA$3:$BA$1002,0)),"") | H13: =IF(G13="","",INDEX(Leads!$AQ$3:$AQ$1002,MATCH(12,Leads!$BA$3:$BA$1002,0))) | I13: =IF(G13="","",INDEX(Leads!$AI$3:$AI$1002,MATCH(12,Leads!$BA$3:$BA$1002,0))&"") | J13: =IF(G13="","",INDEX(Leads!$W$3:$W$1002,MATCH(12,Leads!$BA$3:$BA$1002,0))) | L13: 6. Courriel et téléphone hachés (SHA-256) : tracking-setup.md §3 les prévoit seulement si consent_mesure = oui. Excel ne sait pas hacher ; ajouter Email / Phone Number hachés dans Google Sheets (Apps Script) ou dans Make, jamais en clair.
A14: =IF(G14="","",INDEX(Leads!$AC$3:$AC$1002,MATCH(13,Leads!$BA$3:$BA$1002,0))) | B14: =IF(G14="","","depot_paye") | C14: =IF(G14="","",YEAR(J14)&"-"&RIGHT("0"&MONTH(J14),2)&"-"&RIGHT("0"&DAY(J14),2)&" "&RIGHT("0"&HOUR(J14),2)&":"&RIGHT("0"&MINUTE(J14),2)&":"&RIGHT("0"&SECOND(J14),2)&IF(AND(J14>=DATE(YEAR(J14),3,8)+MOD(8-WEEKDAY(DATE(YEAR(J14),3,8)),7)+2/24,J14<DATE(YEAR(J14),11,1)+MOD(8-WEEKDAY(DATE(YEAR(J14),11,1)),7)+2/24),"-04:00","-05:00")) | D14: =IF(G14="","",INDEX(Leads!$V$3:$V$1002,MATCH(13,Leads!$BA$3:$BA$1002,0))) | E14: =IF(G14="","","CAD") | G14: =IFERROR(INDEX(Leads!$A$3:$A$1002,MATCH(13,Leads!$BA$3:$BA$1002,0)),"") | H14: =IF(G14="","",INDEX(Leads!$AQ$3:$AQ$1002,MATCH(13,Leads!$BA$3:$BA$1002,0))) | I14: =IF(G14="","",INDEX(Leads!$AI$3:$AI$1002,MATCH(13,Leads!$BA$3:$BA$1002,0))&"") | J14: =IF(G14="","",INDEX(Leads!$W$3:$W$1002,MATCH(13,Leads!$BA$3:$BA$1002,0)))
A15: =IF(G15="","",INDEX(Leads!$AC$3:$AC$1002,MATCH(14,Leads!$BA$3:$BA$1002,0))) | B15: =IF(G15="","","depot_paye") | C15: =IF(G15="","",YEAR(J15)&"-"&RIGHT("0"&MONTH(J15),2)&"-"&RIGHT("0"&DAY(J15),2)&" "&RIGHT("0"&HOUR(J15),2)&":"&RIGHT("0"&MINUTE(J15),2)&":"&RIGHT("0"&SECOND(J15),2)&IF(AND(J15>=DATE(YEAR(J15),3,8)+MOD(8-WEEKDAY(DATE(YEAR(J15),3,8)),7)+2/24,J15<DATE(YEAR(J15),11,1)+MOD(8-WEEKDAY(DATE(YEAR(J15),11,1)),7)+2/24),"-04:00","-05:00")) | D15: =IF(G15="","",INDEX(Leads!$V$3:$V$1002,MATCH(14,Leads!$BA$3:$BA$1002,0))) | E15: =IF(G15="","","CAD") | G15: =IFERROR(INDEX(Leads!$A$3:$A$1002,MATCH(14,Leads!$BA$3:$BA$1002,0)),"") | H15: =IF(G15="","",INDEX(Leads!$AQ$3:$AQ$1002,MATCH(14,Leads!$BA$3:$BA$1002,0))) | I15: =IF(G15="","",INDEX(Leads!$AI$3:$AI$1002,MATCH(14,Leads!$BA$3:$BA$1002,0))&"") | J15: =IF(G15="","",INDEX(Leads!$W$3:$W$1002,MATCH(14,Leads!$BA$3:$BA$1002,0))) | L15: 7. Colonnes G à J = contrôle (ne pas téléverser). Microsoft : même logique avec le msclkid (import hebdomadaire).
A16: =IF(G16="","",INDEX(Leads!$AC$3:$AC$1002,MATCH(15,Leads!$BA$3:$BA$1002,0))) | B16: =IF(G16="","","depot_paye") | C16: =IF(G16="","",YEAR(J16)&"-"&RIGHT("0"&MONTH(J16),2)&"-"&RIGHT("0"&DAY(J16),2)&" "&RIGHT("0"&HOUR(J16),2)&":"&RIGHT("0"&MINUTE(J16),2)&":"&RIGHT("0"&SECOND(J16),2)&IF(AND(J16>=DATE(YEAR(J16),3,8)+MOD(8-WEEKDAY(DATE(YEAR(J16),3,8)),7)+2/24,J16<DATE(YEAR(J16),11,1)+MOD(8-WEEKDAY(DATE(YEAR(J16),11,1)),7)+2/24),"-04:00","-05:00")) | D16: =IF(G16="","",INDEX(Leads!$V$3:$V$1002,MATCH(15,Leads!$BA$3:$BA$1002,0))) | E16: =IF(G16="","","CAD") | G16: =IFERROR(INDEX(Leads!$A$3:$A$1002,MATCH(15,Leads!$BA$3:$BA$1002,0)),"") | H16: =IF(G16="","",INDEX(Leads!$AQ$3:$AQ$1002,MATCH(15,Leads!$BA$3:$BA$1002,0))) | I16: =IF(G16="","",INDEX(Leads!$AI$3:$AI$1002,MATCH(15,Leads!$BA$3:$BA$1002,0))&"") | J16: =IF(G16="","",INDEX(Leads!$W$3:$W$1002,MATCH(15,Leads!$BA$3:$BA$1002,0)))
A17: =IF(G17="","",INDEX(Leads!$AC$3:$AC$1002,MATCH(16,Leads!$BA$3:$BA$1002,0))) | B17: =IF(G17="","","depot_paye") | C17: =IF(G17="","",YEAR(J17)&"-"&RIGHT("0"&MONTH(J17),2)&"-"&RIGHT("0"&DAY(J17),2)&" "&RIGHT("0"&HOUR(J17),2)&":"&RIGHT("0"&MINUTE(J17),2)&":"&RIGHT("0"&SECOND(J17),2)&IF(AND(J17>=DATE(YEAR(J17),3,8)+MOD(8-WEEKDAY(DATE(YEAR(J17),3,8)),7)+2/24,J17<DATE(YEAR(J17),11,1)+MOD(8-WEEKDAY(DATE(YEAR(J17),11,1)),7)+2/24),"-04:00","-05:00")) | D17: =IF(G17="","",INDEX(Leads!$V$3:$V$1002,MATCH(16,Leads!$BA$3:$BA$1002,0))) | E17: =IF(G17="","","CAD") | G17: =IFERROR(INDEX(Leads!$A$3:$A$1002,MATCH(16,Leads!$BA$3:$BA$1002,0)),"") | H17: =IF(G17="","",INDEX(Leads!$AQ$3:$AQ$1002,MATCH(16,Leads!$BA$3:$BA$1002,0))) | I17: =IF(G17="","",INDEX(Leads!$AI$3:$AI$1002,MATCH(16,Leads!$BA$3:$BA$1002,0))&"") | J17: =IF(G17="","",INDEX(Leads!$W$3:$W$1002,MATCH(16,Leads!$BA$3:$BA$1002,0)))
A18: =IF(G18="","",INDEX(Leads!$AC$3:$AC$1002,MATCH(17,Leads!$BA$3:$BA$1002,0))) | B18: =IF(G18="","","depot_paye") | C18: =IF(G18="","",YEAR(J18)&"-"&RIGHT("0"&MONTH(J18),2)&"-"&RIGHT("0"&DAY(J18),2)&" "&RIGHT("0"&HOUR(J18),2)&":"&RIGHT("0"&MINUTE(J18),2)&":"&RIGHT("0"&SECOND(J18),2)&IF(AND(J18>=DATE(YEAR(J18),3,8)+MOD(8-WEEKDAY(DATE(YEAR(J18),3,8)),7)+2/24,J18<DATE(YEAR(J18),11,1)+MOD(8-WEEKDAY(DATE(YEAR(J18),11,1)),7)+2/24),"-04:00","-05:00")) | D18: =IF(G18="","",INDEX(Leads!$V$3:$V$1002,MATCH(17,Leads!$BA$3:$BA$1002,0))) | E18: =IF(G18="","","CAD") | G18: =IFERROR(INDEX(Leads!$A$3:$A$1002,MATCH(17,Leads!$BA$3:$BA$1002,0)),"") | H18: =IF(G18="","",INDEX(Leads!$AQ$3:$AQ$1002,MATCH(17,Leads!$BA$3:$BA$1002,0))) | I18: =IF(G18="","",INDEX(Leads!$AI$3:$AI$1002,MATCH(17,Leads!$BA$3:$BA$1002,0))&"") | J18: =IF(G18="","",INDEX(Leads!$W$3:$W$1002,MATCH(17,Leads!$BA$3:$BA$1002,0)))
A19: =IF(G19="","",INDEX(Leads!$AC$3:$AC$1002,MATCH(18,Leads!$BA$3:$BA$1002,0))) | B19: =IF(G19="","","depot_paye") | C19: =IF(G19="","",YEAR(J19)&"-"&RIGHT("0"&MONTH(J19),2)&"-"&RIGHT("0"&DAY(J19),2)&" "&RIGHT("0"&HOUR(J19),2)&":"&RIGHT("0"&MINUTE(J19),2)&":"&RIGHT("0"&SECOND(J19),2)&IF(AND(J19>=DATE(YEAR(J19),3,8)+MOD(8-WEEKDAY(DATE(YEAR(J19),3,8)),7)+2/24,J19<DATE(YEAR(J19),11,1)+MOD(8-WEEKDAY(DATE(YEAR(J19),11,1)),7)+2/24),"-04:00","-05:00")) | D19: =IF(G19="","",INDEX(Leads!$V$3:$V$1002,MATCH(18,Leads!$BA$3:$BA$1002,0))) | E19: =IF(G19="","","CAD") | G19: =IFERROR(INDEX(Leads!$A$3:$A$1002,MATCH(18,Leads!$BA$3:$BA$1002,0)),"") | H19: =IF(G19="","",INDEX(Leads!$AQ$3:$AQ$1002,MATCH(18,Leads!$BA$3:$BA$1002,0))) | I19: =IF(G19="","",INDEX(Leads!$AI$3:$AI$1002,MATCH(18,Leads!$BA$3:$BA$1002,0))&"") | J19: =IF(G19="","",INDEX(Leads!$W$3:$W$1002,MATCH(18,Leads!$BA$3:$BA$1002,0)))
A20: =IF(G20="","",INDEX(Leads!$AC$3:$AC$1002,MATCH(19,Leads!$BA$3:$BA$1002,0))) | B20: =IF(G20="","","depot_paye") | C20: =IF(G20="","",YEAR(J20)&"-"&RIGHT("0"&MONTH(J20),2)&"-"&RIGHT("0"&DAY(J20),2)&" "&RIGHT("0"&HOUR(J20),2)&":"&RIGHT("0"&MINUTE(J20),2)&":"&RIGHT("0"&SECOND(J20),2)&IF(AND(J20>=DATE(YEAR(J20),3,8)+MOD(8-WEEKDAY(DATE(YEAR(J20),3,8)),7)+2/24,J20<DATE(YEAR(J20),11,1)+MOD(8-WEEKDAY(DATE(YEAR(J20),11,1)),7)+2/24),"-04:00","-05:00")) | D20: =IF(G20="","",INDEX(Leads!$V$3:$V$1002,MATCH(19,Leads!$BA$3:$BA$1002,0))) | E20: =IF(G20="","","CAD") | G20: =IFERROR(INDEX(Leads!$A$3:$A$1002,MATCH(19,Leads!$BA$3:$BA$1002,0)),"") | H20: =IF(G20="","",INDEX(Leads!$AQ$3:$AQ$1002,MATCH(19,Leads!$BA$3:$BA$1002,0))) | I20: =IF(G20="","",INDEX(Leads!$AI$3:$AI$1002,MATCH(19,Leads!$BA$3:$BA$1002,0))&"") | J20: =IF(G20="","",INDEX(Leads!$W$3:$W$1002,MATCH(19,Leads!$BA$3:$BA$1002,0)))
A21: =IF(G21="","",INDEX(Leads!$AC$3:$AC$1002,MATCH(20,Leads!$BA$3:$BA$1002,0))) | B21: =IF(G21="","","depot_paye") | C21: =IF(G21="","",YEAR(J21)&"-"&RIGHT("0"&MONTH(J21),2)&"-"&RIGHT("0"&DAY(J21),2)&" "&RIGHT("0"&HOUR(J21),2)&":"&RIGHT("0"&MINUTE(J21),2)&":"&RIGHT("0"&SECOND(J21),2)&IF(AND(J21>=DATE(YEAR(J21),3,8)+MOD(8-WEEKDAY(DATE(YEAR(J21),3,8)),7)+2/24,J21<DATE(YEAR(J21),11,1)+MOD(8-WEEKDAY(DATE(YEAR(J21),11,1)),7)+2/24),"-04:00","-05:00")) | D21: =IF(G21="","",INDEX(Leads!$V$3:$V$1002,MATCH(20,Leads!$BA$3:$BA$1002,0))) | E21: =IF(G21="","","CAD") | G21: =IFERROR(INDEX(Leads!$A$3:$A$1002,MATCH(20,Leads!$BA$3:$BA$1002,0)),"") | H21: =IF(G21="","",INDEX(Leads!$AQ$3:$AQ$1002,MATCH(20,Leads!$BA$3:$BA$1002,0))) | I21: =IF(G21="","",INDEX(Leads!$AI$3:$AI$1002,MATCH(20,Leads!$BA$3:$BA$1002,0))&"") | J21: =IF(G21="","",INDEX(Leads!$W$3:$W$1002,MATCH(20,Leads!$BA$3:$BA$1002,0)))
A22: =IF(G22="","",INDEX(Leads!$AC$3:$AC$1002,MATCH(21,Leads!$BA$3:$BA$1002,0))) | B22: =IF(G22="","","depot_paye") | C22: =IF(G22="","",YEAR(J22)&"-"&RIGHT("0"&MONTH(J22),2)&"-"&RIGHT("0"&DAY(J22),2)&" "&RIGHT("0"&HOUR(J22),2)&":"&RIGHT("0"&MINUTE(J22),2)&":"&RIGHT("0"&SECOND(J22),2)&IF(AND(J22>=DATE(YEAR(J22),3,8)+MOD(8-WEEKDAY(DATE(YEAR(J22),3,8)),7)+2/24,J22<DATE(YEAR(J22),11,1)+MOD(8-WEEKDAY(DATE(YEAR(J22),11,1)),7)+2/24),"-04:00","-05:00")) | D22: =IF(G22="","",INDEX(Leads!$V$3:$V$1002,MATCH(21,Leads!$BA$3:$BA$1002,0))) | E22: =IF(G22="","","CAD") | G22: =IFERROR(INDEX(Leads!$A$3:$A$1002,MATCH(21,Leads!$BA$3:$BA$1002,0)),"") | H22: =IF(G22="","",INDEX(Leads!$AQ$3:$AQ$1002,MATCH(21,Leads!$BA$3:$BA$1002,0))) | I22: =IF(G22="","",INDEX(Leads!$AI$3:$AI$1002,MATCH(21,Leads!$BA$3:$BA$1002,0))&"") | J22: =IF(G22="","",INDEX(Leads!$W$3:$W$1002,MATCH(21,Leads!$BA$3:$BA$1002,0)))
A23: =IF(G23="","",INDEX(Leads!$AC$3:$AC$1002,MATCH(22,Leads!$BA$3:$BA$1002,0))) | B23: =IF(G23="","","depot_paye") | C23: =IF(G23="","",YEAR(J23)&"-"&RIGHT("0"&MONTH(J23),2)&"-"&RIGHT("0"&DAY(J23),2)&" "&RIGHT("0"&HOUR(J23),2)&":"&RIGHT("0"&MINUTE(J23),2)&":"&RIGHT("0"&SECOND(J23),2)&IF(AND(J23>=DATE(YEAR(J23),3,8)+MOD(8-WEEKDAY(DATE(YEAR(J23),3,8)),7)+2/24,J23<DATE(YEAR(J23),11,1)+MOD(8-WEEKDAY(DATE(YEAR(J23),11,1)),7)+2/24),"-04:00","-05:00")) | D23: =IF(G23="","",INDEX(Leads!$V$3:$V$1002,MATCH(22,Leads!$BA$3:$BA$1002,0))) | E23: =IF(G23="","","CAD") | G23: =IFERROR(INDEX(Leads!$A$3:$A$1002,MATCH(22,Leads!$BA$3:$BA$1002,0)),"") | H23: =IF(G23="","",INDEX(Leads!$AQ$3:$AQ$1002,MATCH(22,Leads!$BA$3:$BA$1002,0))) | I23: =IF(G23="","",INDEX(Leads!$AI$3:$AI$1002,MATCH(22,Leads!$BA$3:$BA$1002,0))&"") | J23: =IF(G23="","",INDEX(Leads!$W$3:$W$1002,MATCH(22,Leads!$BA$3:$BA$1002,0)))
A24: =IF(G24="","",INDEX(Leads!$AC$3:$AC$1002,MATCH(23,Leads!$BA$3:$BA$1002,0))) | B24: =IF(G24="","","depot_paye") | C24: =IF(G24="","",YEAR(J24)&"-"&RIGHT("0"&MONTH(J24),2)&"-"&RIGHT("0"&DAY(J24),2)&" "&RIGHT("0"&HOUR(J24),2)&":"&RIGHT("0"&MINUTE(J24),2)&":"&RIGHT("0"&SECOND(J24),2)&IF(AND(J24>=DATE(YEAR(J24),3,8)+MOD(8-WEEKDAY(DATE(YEAR(J24),3,8)),7)+2/24,J24<DATE(YEAR(J24),11,1)+MOD(8-WEEKDAY(DATE(YEAR(J24),11,1)),7)+2/24),"-04:00","-05:00")) | D24: =IF(G24="","",INDEX(Leads!$V$3:$V$1002,MATCH(23,Leads!$BA$3:$BA$1002,0))) | E24: =IF(G24="","","CAD") | G24: =IFERROR(INDEX(Leads!$A$3:$A$1002,MATCH(23,Leads!$BA$3:$BA$1002,0)),"") | H24: =IF(G24="","",INDEX(Leads!$AQ$3:$AQ$1002,MATCH(23,Leads!$BA$3:$BA$1002,0))) | I24: =IF(G24="","",INDEX(Leads!$AI$3:$AI$1002,MATCH(23,Leads!$BA$3:$BA$1002,0))&"") | J24: =IF(G24="","",INDEX(Leads!$W$3:$W$1002,MATCH(23,Leads!$BA$3:$BA$1002,0)))
A25: =IF(G25="","",INDEX(Leads!$AC$3:$AC$1002,MATCH(24,Leads!$BA$3:$BA$1002,0))) | B25: =IF(G25="","","depot_paye") | C25: =IF(G25="","",YEAR(J25)&"-"&RIGHT("0"&MONTH(J25),2)&"-"&RIGHT("0"&DAY(J25),2)&" "&RIGHT("0"&HOUR(J25),2)&":"&RIGHT("0"&MINUTE(J25),2)&":"&RIGHT("0"&SECOND(J25),2)&IF(AND(J25>=DATE(YEAR(J25),3,8)+MOD(8-WEEKDAY(DATE(YEAR(J25),3,8)),7)+2/24,J25<DATE(YEAR(J25),11,1)+MOD(8-WEEKDAY(DATE(YEAR(J25),11,1)),7)+2/24),"-04:00","-05:00")) | D25: =IF(G25="","",INDEX(Leads!$V$3:$V$1002,MATCH(24,Leads!$BA$3:$BA$1002,0))) | E25: =IF(G25="","","CAD") | G25: =IFERROR(INDEX(Leads!$A$3:$A$1002,MATCH(24,Leads!$BA$3:$BA$1002,0)),"") | H25: =IF(G25="","",INDEX(Leads!$AQ$3:$AQ$1002,MATCH(24,Leads!$BA$3:$BA$1002,0))) | I25: =IF(G25="","",INDEX(Leads!$AI$3:$AI$1002,MATCH(24,Leads!$BA$3:$BA$1002,0))&"") | J25: =IF(G25="","",INDEX(Leads!$W$3:$W$1002,MATCH(24,Leads!$BA$3:$BA$1002,0)))
A26: =IF(G26="","",INDEX(Leads!$AC$3:$AC$1002,MATCH(25,Leads!$BA$3:$BA$1002,0))) | B26: =IF(G26="","","depot_paye") | C26: =IF(G26="","",YEAR(J26)&"-"&RIGHT("0"&MONTH(J26),2)&"-"&RIGHT("0"&DAY(J26),2)&" "&RIGHT("0"&HOUR(J26),2)&":"&RIGHT("0"&MINUTE(J26),2)&":"&RIGHT("0"&SECOND(J26),2)&IF(AND(J26>=DATE(YEAR(J26),3,8)+MOD(8-WEEKDAY(DATE(YEAR(J26),3,8)),7)+2/24,J26<DATE(YEAR(J26),11,1)+MOD(8-WEEKDAY(DATE(YEAR(J26),11,1)),7)+2/24),"-04:00","-05:00")) | D26: =IF(G26="","",INDEX(Leads!$V$3:$V$1002,MATCH(25,Leads!$BA$3:$BA$1002,0))) | E26: =IF(G26="","","CAD") | G26: =IFERROR(INDEX(Leads!$A$3:$A$1002,MATCH(25,Leads!$BA$3:$BA$1002,0)),"") | H26: =IF(G26="","",INDEX(Leads!$AQ$3:$AQ$1002,MATCH(25,Leads!$BA$3:$BA$1002,0))) | I26: =IF(G26="","",INDEX(Leads!$AI$3:$AI$1002,MATCH(25,Leads!$BA$3:$BA$1002,0))&"") | J26: =IF(G26="","",INDEX(Leads!$W$3:$W$1002,MATCH(25,Leads!$BA$3:$BA$1002,0)))
A27: =IF(G27="","",INDEX(Leads!$AC$3:$AC$1002,MATCH(26,Leads!$BA$3:$BA$1002,0))) | B27: =IF(G27="","","depot_paye") | C27: =IF(G27="","",YEAR(J27)&"-"&RIGHT("0"&MONTH(J27),2)&"-"&RIGHT("0"&DAY(J27),2)&" "&RIGHT("0"&HOUR(J27),2)&":"&RIGHT("0"&MINUTE(J27),2)&":"&RIGHT("0"&SECOND(J27),2)&IF(AND(J27>=DATE(YEAR(J27),3,8)+MOD(8-WEEKDAY(DATE(YEAR(J27),3,8)),7)+2/24,J27<DATE(YEAR(J27),11,1)+MOD(8-WEEKDAY(DATE(YEAR(J27),11,1)),7)+2/24),"-04:00","-05:00")) | D27: =IF(G27="","",INDEX(Leads!$V$3:$V$1002,MATCH(26,Leads!$BA$3:$BA$1002,0))) | E27: =IF(G27="","","CAD") | G27: =IFERROR(INDEX(Leads!$A$3:$A$1002,MATCH(26,Leads!$BA$3:$BA$1002,0)),"") | H27: =IF(G27="","",INDEX(Leads!$AQ$3:$AQ$1002,MATCH(26,Leads!$BA$3:$BA$1002,0))) | I27: =IF(G27="","",INDEX(Leads!$AI$3:$AI$1002,MATCH(26,Leads!$BA$3:$BA$1002,0))&"") | J27: =IF(G27="","",INDEX(Leads!$W$3:$W$1002,MATCH(26,Leads!$BA$3:$BA$1002,0)))
A28: =IF(G28="","",INDEX(Leads!$AC$3:$AC$1002,MATCH(27,Leads!$BA$3:$BA$1002,0))) | B28: =IF(G28="","","depot_paye") | C28: =IF(G28="","",YEAR(J28)&"-"&RIGHT("0"&MONTH(J28),2)&"-"&RIGHT("0"&DAY(J28),2)&" "&RIGHT("0"&HOUR(J28),2)&":"&RIGHT("0"&MINUTE(J28),2)&":"&RIGHT("0"&SECOND(J28),2)&IF(AND(J28>=DATE(YEAR(J28),3,8)+MOD(8-WEEKDAY(DATE(YEAR(J28),3,8)),7)+2/24,J28<DATE(YEAR(J28),11,1)+MOD(8-WEEKDAY(DATE(YEAR(J28),11,1)),7)+2/24),"-04:00","-05:00")) | D28: =IF(G28="","",INDEX(Leads!$V$3:$V$1002,MATCH(27,Leads!$BA$3:$BA$1002,0))) | E28: =IF(G28="","","CAD") | G28: =IFERROR(INDEX(Leads!$A$3:$A$1002,MATCH(27,Leads!$BA$3:$BA$1002,0)),"") | H28: =IF(G28="","",INDEX(Leads!$AQ$3:$AQ$1002,MATCH(27,Leads!$BA$3:$BA$1002,0))) | I28: =IF(G28="","",INDEX(Leads!$AI$3:$AI$1002,MATCH(27,Leads!$BA$3:$BA$1002,0))&"") | J28: =IF(G28="","",INDEX(Leads!$W$3:$W$1002,MATCH(27,Leads!$BA$3:$BA$1002,0)))
A29: =IF(G29="","",INDEX(Leads!$AC$3:$AC$1002,MATCH(28,Leads!$BA$3:$BA$1002,0))) | B29: =IF(G29="","","depot_paye") | C29: =IF(G29="","",YEAR(J29)&"-"&RIGHT("0"&MONTH(J29),2)&"-"&RIGHT("0"&DAY(J29),2)&" "&RIGHT("0"&HOUR(J29),2)&":"&RIGHT("0"&MINUTE(J29),2)&":"&RIGHT("0"&SECOND(J29),2)&IF(AND(J29>=DATE(YEAR(J29),3,8)+MOD(8-WEEKDAY(DATE(YEAR(J29),3,8)),7)+2/24,J29<DATE(YEAR(J29),11,1)+MOD(8-WEEKDAY(DATE(YEAR(J29),11,1)),7)+2/24),"-04:00","-05:00")) | D29: =IF(G29="","",INDEX(Leads!$V$3:$V$1002,MATCH(28,Leads!$BA$3:$BA$1002,0))) | E29: =IF(G29="","","CAD") | G29: =IFERROR(INDEX(Leads!$A$3:$A$1002,MATCH(28,Leads!$BA$3:$BA$1002,0)),"") | H29: =IF(G29="","",INDEX(Leads!$AQ$3:$AQ$1002,MATCH(28,Leads!$BA$3:$BA$1002,0))) | I29: =IF(G29="","",INDEX(Leads!$AI$3:$AI$1002,MATCH(28,Leads!$BA$3:$BA$1002,0))&"") | J29: =IF(G29="","",INDEX(Leads!$W$3:$W$1002,MATCH(28,Leads!$BA$3:$BA$1002,0)))
A30: =IF(G30="","",INDEX(Leads!$AC$3:$AC$1002,MATCH(29,Leads!$BA$3:$BA$1002,0))) | B30: =IF(G30="","","depot_paye") | C30: =IF(G30="","",YEAR(J30)&"-"&RIGHT("0"&MONTH(J30),2)&"-"&RIGHT("0"&DAY(J30),2)&" "&RIGHT("0"&HOUR(J30),2)&":"&RIGHT("0"&MINUTE(J30),2)&":"&RIGHT("0"&SECOND(J30),2)&IF(AND(J30>=DATE(YEAR(J30),3,8)+MOD(8-WEEKDAY(DATE(YEAR(J30),3,8)),7)+2/24,J30<DATE(YEAR(J30),11,1)+MOD(8-WEEKDAY(DATE(YEAR(J30),11,1)),7)+2/24),"-04:00","-05:00")) | D30: =IF(G30="","",INDEX(Leads!$V$3:$V$1002,MATCH(29,Leads!$BA$3:$BA$1002,0))) | E30: =IF(G30="","","CAD") | G30: =IFERROR(INDEX(Leads!$A$3:$A$1002,MATCH(29,Leads!$BA$3:$BA$1002,0)),"") | H30: =IF(G30="","",INDEX(Leads!$AQ$3:$AQ$1002,MATCH(29,Leads!$BA$3:$BA$1002,0))) | I30: =IF(G30="","",INDEX(Leads!$AI$3:$AI$1002,MATCH(29,Leads!$BA$3:$BA$1002,0))&"") | J30: =IF(G30="","",INDEX(Leads!$W$3:$W$1002,MATCH(29,Leads!$BA$3:$BA$1002,0)))
A31: =IF(G31="","",INDEX(Leads!$AC$3:$AC$1002,MATCH(30,Leads!$BA$3:$BA$1002,0))) | B31: =IF(G31="","","depot_paye") | C31: =IF(G31="","",YEAR(J31)&"-"&RIGHT("0"&MONTH(J31),2)&"-"&RIGHT("0"&DAY(J31),2)&" "&RIGHT("0"&HOUR(J31),2)&":"&RIGHT("0"&MINUTE(J31),2)&":"&RIGHT("0"&SECOND(J31),2)&IF(AND(J31>=DATE(YEAR(J31),3,8)+MOD(8-WEEKDAY(DATE(YEAR(J31),3,8)),7)+2/24,J31<DATE(YEAR(J31),11,1)+MOD(8-WEEKDAY(DATE(YEAR(J31),11,1)),7)+2/24),"-04:00","-05:00")) | D31: =IF(G31="","",INDEX(Leads!$V$3:$V$1002,MATCH(30,Leads!$BA$3:$BA$1002,0))) | E31: =IF(G31="","","CAD") | G31: =IFERROR(INDEX(Leads!$A$3:$A$1002,MATCH(30,Leads!$BA$3:$BA$1002,0)),"") | H31: =IF(G31="","",INDEX(Leads!$AQ$3:$AQ$1002,MATCH(30,Leads!$BA$3:$BA$1002,0))) | I31: =IF(G31="","",INDEX(Leads!$AI$3:$AI$1002,MATCH(30,Leads!$BA$3:$BA$1002,0))&"") | J31: =IF(G31="","",INDEX(Leads!$W$3:$W$1002,MATCH(30,Leads!$BA$3:$BA$1002,0)))
A32: =IF(G32="","",INDEX(Leads!$AC$3:$AC$1002,MATCH(31,Leads!$BA$3:$BA$1002,0))) | B32: =IF(G32="","","depot_paye") | C32: =IF(G32="","",YEAR(J32)&"-"&RIGHT("0"&MONTH(J32),2)&"-"&RIGHT("0"&DAY(J32),2)&" "&RIGHT("0"&HOUR(J32),2)&":"&RIGHT("0"&MINUTE(J32),2)&":"&RIGHT("0"&SECOND(J32),2)&IF(AND(J32>=DATE(YEAR(J32),3,8)+MOD(8-WEEKDAY(DATE(YEAR(J32),3,8)),7)+2/24,J32<DATE(YEAR(J32),11,1)+MOD(8-WEEKDAY(DATE(YEAR(J32),11,1)),7)+2/24),"-04:00","-05:00")) | D32: =IF(G32="","",INDEX(Leads!$V$3:$V$1002,MATCH(31,Leads!$BA$3:$BA$1002,0))) | E32: =IF(G32="","","CAD") | G32: =IFERROR(INDEX(Leads!$A$3:$A$1002,MATCH(31,Leads!$BA$3:$BA$1002,0)),"") | H32: =IF(G32="","",INDEX(Leads!$AQ$3:$AQ$1002,MATCH(31,Leads!$BA$3:$BA$1002,0))) | I32: =IF(G32="","",INDEX(Leads!$AI$3:$AI$1002,MATCH(31,Leads!$BA$3:$BA$1002,0))&"") | J32: =IF(G32="","",INDEX(Leads!$W$3:$W$1002,MATCH(31,Leads!$BA$3:$BA$1002,0)))
A33: =IF(G33="","",INDEX(Leads!$AC$3:$AC$1002,MATCH(32,Leads!$BA$3:$BA$1002,0))) | B33: =IF(G33="","","depot_paye") | C33: =IF(G33="","",YEAR(J33)&"-"&RIGHT("0"&MONTH(J33),2)&"-"&RIGHT("0"&DAY(J33),2)&" "&RIGHT("0"&HOUR(J33),2)&":"&RIGHT("0"&MINUTE(J33),2)&":"&RIGHT("0"&SECOND(J33),2)&IF(AND(J33>=DATE(YEAR(J33),3,8)+MOD(8-WEEKDAY(DATE(YEAR(J33),3,8)),7)+2/24,J33<DATE(YEAR(J33),11,1)+MOD(8-WEEKDAY(DATE(YEAR(J33),11,1)),7)+2/24),"-04:00","-05:00")) | D33: =IF(G33="","",INDEX(Leads!$V$3:$V$1002,MATCH(32,Leads!$BA$3:$BA$1002,0))) | E33: =IF(G33="","","CAD") | G33: =IFERROR(INDEX(Leads!$A$3:$A$1002,MATCH(32,Leads!$BA$3:$BA$1002,0)),"") | H33: =IF(G33="","",INDEX(Leads!$AQ$3:$AQ$1002,MATCH(32,Leads!$BA$3:$BA$1002,0))) | I33: =IF(G33="","",INDEX(Leads!$AI$3:$AI$1002,MATCH(32,Leads!$BA$3:$BA$1002,0))&"") | J33: =IF(G33="","",INDEX(Leads!$W$3:$W$1002,MATCH(32,Leads!$BA$3:$BA$1002,0)))
A34: =IF(G34="","",INDEX(Leads!$AC$3:$AC$1002,MATCH(33,Leads!$BA$3:$BA$1002,0))) | B34: =IF(G34="","","depot_paye") | C34: =IF(G34="","",YEAR(J34)&"-"&RIGHT("0"&MONTH(J34),2)&"-"&RIGHT("0"&DAY(J34),2)&" "&RIGHT("0"&HOUR(J34),2)&":"&RIGHT("0"&MINUTE(J34),2)&":"&RIGHT("0"&SECOND(J34),2)&IF(AND(J34>=DATE(YEAR(J34),3,8)+MOD(8-WEEKDAY(DATE(YEAR(J34),3,8)),7)+2/24,J34<DATE(YEAR(J34),11,1)+MOD(8-WEEKDAY(DATE(YEAR(J34),11,1)),7)+2/24),"-04:00","-05:00")) | D34: =IF(G34="","",INDEX(Leads!$V$3:$V$1002,MATCH(33,Leads!$BA$3:$BA$1002,0))) | E34: =IF(G34="","","CAD") | G34: =IFERROR(INDEX(Leads!$A$3:$A$1002,MATCH(33,Leads!$BA$3:$BA$1002,0)),"") | H34: =IF(G34="","",INDEX(Leads!$AQ$3:$AQ$1002,MATCH(33,Leads!$BA$3:$BA$1002,0))) | I34: =IF(G34="","",INDEX(Leads!$AI$3:$AI$1002,MATCH(33,Leads!$BA$3:$BA$1002,0))&"") | J34: =IF(G34="","",INDEX(Leads!$W$3:$W$1002,MATCH(33,Leads!$BA$3:$BA$1002,0)))
A35: =IF(G35="","",INDEX(Leads!$AC$3:$AC$1002,MATCH(34,Leads!$BA$3:$BA$1002,0))) | B35: =IF(G35="","","depot_paye") | C35: =IF(G35="","",YEAR(J35)&"-"&RIGHT("0"&MONTH(J35),2)&"-"&RIGHT("0"&DAY(J35),2)&" "&RIGHT("0"&HOUR(J35),2)&":"&RIGHT("0"&MINUTE(J35),2)&":"&RIGHT("0"&SECOND(J35),2)&IF(AND(J35>=DATE(YEAR(J35),3,8)+MOD(8-WEEKDAY(DATE(YEAR(J35),3,8)),7)+2/24,J35<DATE(YEAR(J35),11,1)+MOD(8-WEEKDAY(DATE(YEAR(J35),11,1)),7)+2/24),"-04:00","-05:00")) | D35: =IF(G35="","",INDEX(Leads!$V$3:$V$1002,MATCH(34,Leads!$BA$3:$BA$1002,0))) | E35: =IF(G35="","","CAD") | G35: =IFERROR(INDEX(Leads!$A$3:$A$1002,MATCH(34,Leads!$BA$3:$BA$1002,0)),"") | H35: =IF(G35="","",INDEX(Leads!$AQ$3:$AQ$1002,MATCH(34,Leads!$BA$3:$BA$1002,0))) | I35: =IF(G35="","",INDEX(Leads!$AI$3:$AI$1002,MATCH(34,Leads!$BA$3:$BA$1002,0))&"") | J35: =IF(G35="","",INDEX(Leads!$W$3:$W$1002,MATCH(34,Leads!$BA$3:$BA$1002,0)))
A36: =IF(G36="","",INDEX(Leads!$AC$3:$AC$1002,MATCH(35,Leads!$BA$3:$BA$1002,0))) | B36: =IF(G36="","","depot_paye") | C36: =IF(G36="","",YEAR(J36)&"-"&RIGHT("0"&MONTH(J36),2)&"-"&RIGHT("0"&DAY(J36),2)&" "&RIGHT("0"&HOUR(J36),2)&":"&RIGHT("0"&MINUTE(J36),2)&":"&RIGHT("0"&SECOND(J36),2)&IF(AND(J36>=DATE(YEAR(J36),3,8)+MOD(8-WEEKDAY(DATE(YEAR(J36),3,8)),7)+2/24,J36<DATE(YEAR(J36),11,1)+MOD(8-WEEKDAY(DATE(YEAR(J36),11,1)),7)+2/24),"-04:00","-05:00")) | D36: =IF(G36="","",INDEX(Leads!$V$3:$V$1002,MATCH(35,Leads!$BA$3:$BA$1002,0))) | E36: =IF(G36="","","CAD") | G36: =IFERROR(INDEX(Leads!$A$3:$A$1002,MATCH(35,Leads!$BA$3:$BA$1002,0)),"") | H36: =IF(G36="","",INDEX(Leads!$AQ$3:$AQ$1002,MATCH(35,Leads!$BA$3:$BA$1002,0))) | I36: =IF(G36="","",INDEX(Leads!$AI$3:$AI$1002,MATCH(35,Leads!$BA$3:$BA$1002,0))&"") | J36: =IF(G36="","",INDEX(Leads!$W$3:$W$1002,MATCH(35,Leads!$BA$3:$BA$1002,0)))
A37: =IF(G37="","",INDEX(Leads!$AC$3:$AC$1002,MATCH(36,Leads!$BA$3:$BA$1002,0))) | B37: =IF(G37="","","depot_paye") | C37: =IF(G37="","",YEAR(J37)&"-"&RIGHT("0"&MONTH(J37),2)&"-"&RIGHT("0"&DAY(J37),2)&" "&RIGHT("0"&HOUR(J37),2)&":"&RIGHT("0"&MINUTE(J37),2)&":"&RIGHT("0"&SECOND(J37),2)&IF(AND(J37>=DATE(YEAR(J37),3,8)+MOD(8-WEEKDAY(DATE(YEAR(J37),3,8)),7)+2/24,J37<DATE(YEAR(J37),11,1)+MOD(8-WEEKDAY(DATE(YEAR(J37),11,1)),7)+2/24),"-04:00","-05:00")) | D37: =IF(G37="","",INDEX(Leads!$V$3:$V$1002,MATCH(36,Leads!$BA$3:$BA$1002,0))) | E37: =IF(G37="","","CAD") | G37: =IFERROR(INDEX(Leads!$A$3:$A$1002,MATCH(36,Leads!$BA$3:$BA$1002,0)),"") | H37: =IF(G37="","",INDEX(Leads!$AQ$3:$AQ$1002,MATCH(36,Leads!$BA$3:$BA$1002,0))) | I37: =IF(G37="","",INDEX(Leads!$AI$3:$AI$1002,MATCH(36,Leads!$BA$3:$BA$1002,0))&"") | J37: =IF(G37="","",INDEX(Leads!$W$3:$W$1002,MATCH(36,Leads!$BA$3:$BA$1002,0)))
A38: =IF(G38="","",INDEX(Leads!$AC$3:$AC$1002,MATCH(37,Leads!$BA$3:$BA$1002,0))) | B38: =IF(G38="","","depot_paye") | C38: =IF(G38="","",YEAR(J38)&"-"&RIGHT("0"&MONTH(J38),2)&"-"&RIGHT("0"&DAY(J38),2)&" "&RIGHT("0"&HOUR(J38),2)&":"&RIGHT("0"&MINUTE(J38),2)&":"&RIGHT("0"&SECOND(J38),2)&IF(AND(J38>=DATE(YEAR(J38),3,8)+MOD(8-WEEKDAY(DATE(YEAR(J38),3,8)),7)+2/24,J38<DATE(YEAR(J38),11,1)+MOD(8-WEEKDAY(DATE(YEAR(J38),11,1)),7)+2/24),"-04:00","-05:00")) | D38: =IF(G38="","",INDEX(Leads!$V$3:$V$1002,MATCH(37,Leads!$BA$3:$BA$1002,0))) | E38: =IF(G38="","","CAD") | G38: =IFERROR(INDEX(Leads!$A$3:$A$1002,MATCH(37,Leads!$BA$3:$BA$1002,0)),"") | H38: =IF(G38="","",INDEX(Leads!$AQ$3:$AQ$1002,MATCH(37,Leads!$BA$3:$BA$1002,0))) | I38: =IF(G38="","",INDEX(Leads!$AI$3:$AI$1002,MATCH(37,Leads!$BA$3:$BA$1002,0))&"") | J38: =IF(G38="","",INDEX(Leads!$W$3:$W$1002,MATCH(37,Leads!$BA$3:$BA$1002,0)))
A39: =IF(G39="","",INDEX(Leads!$AC$3:$AC$1002,MATCH(38,Leads!$BA$3:$BA$1002,0))) | B39: =IF(G39="","","depot_paye") | C39: =IF(G39="","",YEAR(J39)&"-"&RIGHT("0"&MONTH(J39),2)&"-"&RIGHT("0"&DAY(J39),2)&" "&RIGHT("0"&HOUR(J39),2)&":"&RIGHT("0"&MINUTE(J39),2)&":"&RIGHT("0"&SECOND(J39),2)&IF(AND(J39>=DATE(YEAR(J39),3,8)+MOD(8-WEEKDAY(DATE(YEAR(J39),3,8)),7)+2/24,J39<DATE(YEAR(J39),11,1)+MOD(8-WEEKDAY(DATE(YEAR(J39),11,1)),7)+2/24),"-04:00","-05:00")) | D39: =IF(G39="","",INDEX(Leads!$V$3:$V$1002,MATCH(38,Leads!$BA$3:$BA$1002,0))) | E39: =IF(G39="","","CAD") | G39: =IFERROR(INDEX(Leads!$A$3:$A$1002,MATCH(38,Leads!$BA$3:$BA$1002,0)),"") | H39: =IF(G39="","",INDEX(Leads!$AQ$3:$AQ$1002,MATCH(38,Leads!$BA$3:$BA$1002,0))) | I39: =IF(G39="","",INDEX(Leads!$AI$3:$AI$1002,MATCH(38,Leads!$BA$3:$BA$1002,0))&"") | J39: =IF(G39="","",INDEX(Leads!$W$3:$W$1002,MATCH(38,Leads!$BA$3:$BA$1002,0)))
A40: =IF(G40="","",INDEX(Leads!$AC$3:$AC$1002,MATCH(39,Leads!$BA$3:$BA$1002,0))) | B40: =IF(G40="","","depot_paye") | C40: =IF(G40="","",YEAR(J40)&"-"&RIGHT("0"&MONTH(J40),2)&"-"&RIGHT("0"&DAY(J40),2)&" "&RIGHT("0"&HOUR(J40),2)&":"&RIGHT("0"&MINUTE(J40),2)&":"&RIGHT("0"&SECOND(J40),2)&IF(AND(J40>=DATE(YEAR(J40),3,8)+MOD(8-WEEKDAY(DATE(YEAR(J40),3,8)),7)+2/24,J40<DATE(YEAR(J40),11,1)+MOD(8-WEEKDAY(DATE(YEAR(J40),11,1)),7)+2/24),"-04:00","-05:00")) | D40: =IF(G40="","",INDEX(Leads!$V$3:$V$1002,MATCH(39,Leads!$BA$3:$BA$1002,0))) | E40: =IF(G40="","","CAD") | G40: =IFERROR(INDEX(Leads!$A$3:$A$1002,MATCH(39,Leads!$BA$3:$BA$1002,0)),"") | H40: =IF(G40="","",INDEX(Leads!$AQ$3:$AQ$1002,MATCH(39,Leads!$BA$3:$BA$1002,0))) | I40: =IF(G40="","",INDEX(Leads!$AI$3:$AI$1002,MATCH(39,Leads!$BA$3:$BA$1002,0))&"") | J40: =IF(G40="","",INDEX(Leads!$W$3:$W$1002,MATCH(39,Leads!$BA$3:$BA$1002,0)))
A41: =IF(G41="","",INDEX(Leads!$AC$3:$AC$1002,MATCH(40,Leads!$BA$3:$BA$1002,0))) | B41: =IF(G41="","","depot_paye") | C41: =IF(G41="","",YEAR(J41)&"-"&RIGHT("0"&MONTH(J41),2)&"-"&RIGHT("0"&DAY(J41),2)&" "&RIGHT("0"&HOUR(J41),2)&":"&RIGHT("0"&MINUTE(J41),2)&":"&RIGHT("0"&SECOND(J41),2)&IF(AND(J41>=DATE(YEAR(J41),3,8)+MOD(8-WEEKDAY(DATE(YEAR(J41),3,8)),7)+2/24,J41<DATE(YEAR(J41),11,1)+MOD(8-WEEKDAY(DATE(YEAR(J41),11,1)),7)+2/24),"-04:00","-05:00")) | D41: =IF(G41="","",INDEX(Leads!$V$3:$V$1002,MATCH(40,Leads!$BA$3:$BA$1002,0))) | E41: =IF(G41="","","CAD") | G41: =IFERROR(INDEX(Leads!$A$3:$A$1002,MATCH(40,Leads!$BA$3:$BA$1002,0)),"") | H41: =IF(G41="","",INDEX(Leads!$AQ$3:$AQ$1002,MATCH(40,Leads!$BA$3:$BA$1002,0))) | I41: =IF(G41="","",INDEX(Leads!$AI$3:$AI$1002,MATCH(40,Leads!$BA$3:$BA$1002,0))&"") | J41: =IF(G41="","",INDEX(Leads!$W$3:$W$1002,MATCH(40,Leads!$BA$3:$BA$1002,0)))
A42: =IF(G42="","",INDEX(Leads!$AC$3:$AC$1002,MATCH(41,Leads!$BA$3:$BA$1002,0))) | B42: =IF(G42="","","depot_paye") | C42: =IF(G42="","",YEAR(J42)&"-"&RIGHT("0"&MONTH(J42),2)&"-"&RIGHT("0"&DAY(J42),2)&" "&RIGHT("0"&HOUR(J42),2)&":"&RIGHT("0"&MINUTE(J42),2)&":"&RIGHT("0"&SECOND(J42),2)&IF(AND(J42>=DATE(YEAR(J42),3,8)+MOD(8-WEEKDAY(DATE(YEAR(J42),3,8)),7)+2/24,J42<DATE(YEAR(J42),11,1)+MOD(8-WEEKDAY(DATE(YEAR(J42),11,1)),7)+2/24),"-04:00","-05:00")) | D42: =IF(G42="","",INDEX(Leads!$V$3:$V$1002,MATCH(41,Leads!$BA$3:$BA$1002,0))) | E42: =IF(G42="","","CAD") | G42: =IFERROR(INDEX(Leads!$A$3:$A$1002,MATCH(41,Leads!$BA$3:$BA$1002,0)),"") | H42: =IF(G42="","",INDEX(Leads!$AQ$3:$AQ$1002,MATCH(41,Leads!$BA$3:$BA$1002,0))) | I42: =IF(G42="","",INDEX(Leads!$AI$3:$AI$1002,MATCH(41,Leads!$BA$3:$BA$1002,0))&"") | J42: =IF(G42="","",INDEX(Leads!$W$3:$W$1002,MATCH(41,Leads!$BA$3:$BA$1002,0)))
A43: =IF(G43="","",INDEX(Leads!$AC$3:$AC$1002,MATCH(42,Leads!$BA$3:$BA$1002,0))) | B43: =IF(G43="","","depot_paye") | C43: =IF(G43="","",YEAR(J43)&"-"&RIGHT("0"&MONTH(J43),2)&"-"&RIGHT("0"&DAY(J43),2)&" "&RIGHT("0"&HOUR(J43),2)&":"&RIGHT("0"&MINUTE(J43),2)&":"&RIGHT("0"&SECOND(J43),2)&IF(AND(J43>=DATE(YEAR(J43),3,8)+MOD(8-WEEKDAY(DATE(YEAR(J43),3,8)),7)+2/24,J43<DATE(YEAR(J43),11,1)+MOD(8-WEEKDAY(DATE(YEAR(J43),11,1)),7)+2/24),"-04:00","-05:00")) | D43: =IF(G43="","",INDEX(Leads!$V$3:$V$1002,MATCH(42,Leads!$BA$3:$BA$1002,0))) | E43: =IF(G43="","","CAD") | G43: =IFERROR(INDEX(Leads!$A$3:$A$1002,MATCH(42,Leads!$BA$3:$BA$1002,0)),"") | H43: =IF(G43="","",INDEX(Leads!$AQ$3:$AQ$1002,MATCH(42,Leads!$BA$3:$BA$1002,0))) | I43: =IF(G43="","",INDEX(Leads!$AI$3:$AI$1002,MATCH(42,Leads!$BA$3:$BA$1002,0))&"") | J43: =IF(G43="","",INDEX(Leads!$W$3:$W$1002,MATCH(42,Leads!$BA$3:$BA$1002,0)))
A44: =IF(G44="","",INDEX(Leads!$AC$3:$AC$1002,MATCH(43,Leads!$BA$3:$BA$1002,0))) | B44: =IF(G44="","","depot_paye") | C44: =IF(G44="","",YEAR(J44)&"-"&RIGHT("0"&MONTH(J44),2)&"-"&RIGHT("0"&DAY(J44),2)&" "&RIGHT("0"&HOUR(J44),2)&":"&RIGHT("0"&MINUTE(J44),2)&":"&RIGHT("0"&SECOND(J44),2)&IF(AND(J44>=DATE(YEAR(J44),3,8)+MOD(8-WEEKDAY(DATE(YEAR(J44),3,8)),7)+2/24,J44<DATE(YEAR(J44),11,1)+MOD(8-WEEKDAY(DATE(YEAR(J44),11,1)),7)+2/24),"-04:00","-05:00")) | D44: =IF(G44="","",INDEX(Leads!$V$3:$V$1002,MATCH(43,Leads!$BA$3:$BA$1002,0))) | E44: =IF(G44="","","CAD") | G44: =IFERROR(INDEX(Leads!$A$3:$A$1002,MATCH(43,Leads!$BA$3:$BA$1002,0)),"") | H44: =IF(G44="","",INDEX(Leads!$AQ$3:$AQ$1002,MATCH(43,Leads!$BA$3:$BA$1002,0))) | I44: =IF(G44="","",INDEX(Leads!$AI$3:$AI$1002,MATCH(43,Leads!$BA$3:$BA$1002,0))&"") | J44: =IF(G44="","",INDEX(Leads!$W$3:$W$1002,MATCH(43,Leads!$BA$3:$BA$1002,0)))
A45: =IF(G45="","",INDEX(Leads!$AC$3:$AC$1002,MATCH(44,Leads!$BA$3:$BA$1002,0))) | B45: =IF(G45="","","depot_paye") | C45: =IF(G45="","",YEAR(J45)&"-"&RIGHT("0"&MONTH(J45),2)&"-"&RIGHT("0"&DAY(J45),2)&" "&RIGHT("0"&HOUR(J45),2)&":"&RIGHT("0"&MINUTE(J45),2)&":"&RIGHT("0"&SECOND(J45),2)&IF(AND(J45>=DATE(YEAR(J45),3,8)+MOD(8-WEEKDAY(DATE(YEAR(J45),3,8)),7)+2/24,J45<DATE(YEAR(J45),11,1)+MOD(8-WEEKDAY(DATE(YEAR(J45),11,1)),7)+2/24),"-04:00","-05:00")) | D45: =IF(G45="","",INDEX(Leads!$V$3:$V$1002,MATCH(44,Leads!$BA$3:$BA$1002,0))) | E45: =IF(G45="","","CAD") | G45: =IFERROR(INDEX(Leads!$A$3:$A$1002,MATCH(44,Leads!$BA$3:$BA$1002,0)),"") | H45: =IF(G45="","",INDEX(Leads!$AQ$3:$AQ$1002,MATCH(44,Leads!$BA$3:$BA$1002,0))) | I45: =IF(G45="","",INDEX(Leads!$AI$3:$AI$1002,MATCH(44,Leads!$BA$3:$BA$1002,0))&"") | J45: =IF(G45="","",INDEX(Leads!$W$3:$W$1002,MATCH(44,Leads!$BA$3:$BA$1002,0)))
A46: =IF(G46="","",INDEX(Leads!$AC$3:$AC$1002,MATCH(45,Leads!$BA$3:$BA$1002,0))) | B46: =IF(G46="","","depot_paye") | C46: =IF(G46="","",YEAR(J46)&"-"&RIGHT("0"&MONTH(J46),2)&"-"&RIGHT("0"&DAY(J46),2)&" "&RIGHT("0"&HOUR(J46),2)&":"&RIGHT("0"&MINUTE(J46),2)&":"&RIGHT("0"&SECOND(J46),2)&IF(AND(J46>=DATE(YEAR(J46),3,8)+MOD(8-WEEKDAY(DATE(YEAR(J46),3,8)),7)+2/24,J46<DATE(YEAR(J46),11,1)+MOD(8-WEEKDAY(DATE(YEAR(J46),11,1)),7)+2/24),"-04:00","-05:00")) | D46: =IF(G46="","",INDEX(Leads!$V$3:$V$1002,MATCH(45,Leads!$BA$3:$BA$1002,0))) | E46: =IF(G46="","","CAD") | G46: =IFERROR(INDEX(Leads!$A$3:$A$1002,MATCH(45,Leads!$BA$3:$BA$1002,0)),"") | H46: =IF(G46="","",INDEX(Leads!$AQ$3:$AQ$1002,MATCH(45,Leads!$BA$3:$BA$1002,0))) | I46: =IF(G46="","",INDEX(Leads!$AI$3:$AI$1002,MATCH(45,Leads!$BA$3:$BA$1002,0))&"") | J46: =IF(G46="","",INDEX(Leads!$W$3:$W$1002,MATCH(45,Leads!$BA$3:$BA$1002,0)))
A47: =IF(G47="","",INDEX(Leads!$AC$3:$AC$1002,MATCH(46,Leads!$BA$3:$BA$1002,0))) | B47: =IF(G47="","","depot_paye") | C47: =IF(G47="","",YEAR(J47)&"-"&RIGHT("0"&MONTH(J47),2)&"-"&RIGHT("0"&DAY(J47),2)&" "&RIGHT("0"&HOUR(J47),2)&":"&RIGHT("0"&MINUTE(J47),2)&":"&RIGHT("0"&SECOND(J47),2)&IF(AND(J47>=DATE(YEAR(J47),3,8)+MOD(8-WEEKDAY(DATE(YEAR(J47),3,8)),7)+2/24,J47<DATE(YEAR(J47),11,1)+MOD(8-WEEKDAY(DATE(YEAR(J47),11,1)),7)+2/24),"-04:00","-05:00")) | D47: =IF(G47="","",INDEX(Leads!$V$3:$V$1002,MATCH(46,Leads!$BA$3:$BA$1002,0))) | E47: =IF(G47="","","CAD") | G47: =IFERROR(INDEX(Leads!$A$3:$A$1002,MATCH(46,Leads!$BA$3:$BA$1002,0)),"") | H47: =IF(G47="","",INDEX(Leads!$AQ$3:$AQ$1002,MATCH(46,Leads!$BA$3:$BA$1002,0))) | I47: =IF(G47="","",INDEX(Leads!$AI$3:$AI$1002,MATCH(46,Leads!$BA$3:$BA$1002,0))&"") | J47: =IF(G47="","",INDEX(Leads!$W$3:$W$1002,MATCH(46,Leads!$BA$3:$BA$1002,0)))
A48: =IF(G48="","",INDEX(Leads!$AC$3:$AC$1002,MATCH(47,Leads!$BA$3:$BA$1002,0))) | B48: =IF(G48="","","depot_paye") | C48: =IF(G48="","",YEAR(J48)&"-"&RIGHT("0"&MONTH(J48),2)&"-"&RIGHT("0"&DAY(J48),2)&" "&RIGHT("0"&HOUR(J48),2)&":"&RIGHT("0"&MINUTE(J48),2)&":"&RIGHT("0"&SECOND(J48),2)&IF(AND(J48>=DATE(YEAR(J48),3,8)+MOD(8-WEEKDAY(DATE(YEAR(J48),3,8)),7)+2/24,J48<DATE(YEAR(J48),11,1)+MOD(8-WEEKDAY(DATE(YEAR(J48),11,1)),7)+2/24),"-04:00","-05:00")) | D48: =IF(G48="","",INDEX(Leads!$V$3:$V$1002,MATCH(47,Leads!$BA$3:$BA$1002,0))) | E48: =IF(G48="","","CAD") | G48: =IFERROR(INDEX(Leads!$A$3:$A$1002,MATCH(47,Leads!$BA$3:$BA$1002,0)),"") | H48: =IF(G48="","",INDEX(Leads!$AQ$3:$AQ$1002,MATCH(47,Leads!$BA$3:$BA$1002,0))) | I48: =IF(G48="","",INDEX(Leads!$AI$3:$AI$1002,MATCH(47,Leads!$BA$3:$BA$1002,0))&"") | J48: =IF(G48="","",INDEX(Leads!$W$3:$W$1002,MATCH(47,Leads!$BA$3:$BA$1002,0)))
A49: =IF(G49="","",INDEX(Leads!$AC$3:$AC$1002,MATCH(48,Leads!$BA$3:$BA$1002,0))) | B49: =IF(G49="","","depot_paye") | C49: =IF(G49="","",YEAR(J49)&"-"&RIGHT("0"&MONTH(J49),2)&"-"&RIGHT("0"&DAY(J49),2)&" "&RIGHT("0"&HOUR(J49),2)&":"&RIGHT("0"&MINUTE(J49),2)&":"&RIGHT("0"&SECOND(J49),2)&IF(AND(J49>=DATE(YEAR(J49),3,8)+MOD(8-WEEKDAY(DATE(YEAR(J49),3,8)),7)+2/24,J49<DATE(YEAR(J49),11,1)+MOD(8-WEEKDAY(DATE(YEAR(J49),11,1)),7)+2/24),"-04:00","-05:00")) | D49: =IF(G49="","",INDEX(Leads!$V$3:$V$1002,MATCH(48,Leads!$BA$3:$BA$1002,0))) | E49: =IF(G49="","","CAD") | G49: =IFERROR(INDEX(Leads!$A$3:$A$1002,MATCH(48,Leads!$BA$3:$BA$1002,0)),"") | H49: =IF(G49="","",INDEX(Leads!$AQ$3:$AQ$1002,MATCH(48,Leads!$BA$3:$BA$1002,0))) | I49: =IF(G49="","",INDEX(Leads!$AI$3:$AI$1002,MATCH(48,Leads!$BA$3:$BA$1002,0))&"") | J49: =IF(G49="","",INDEX(Leads!$W$3:$W$1002,MATCH(48,Leads!$BA$3:$BA$1002,0)))
A50: =IF(G50="","",INDEX(Leads!$AC$3:$AC$1002,MATCH(49,Leads!$BA$3:$BA$1002,0))) | B50: =IF(G50="","","depot_paye") | C50: =IF(G50="","",YEAR(J50)&"-"&RIGHT("0"&MONTH(J50),2)&"-"&RIGHT("0"&DAY(J50),2)&" "&RIGHT("0"&HOUR(J50),2)&":"&RIGHT("0"&MINUTE(J50),2)&":"&RIGHT("0"&SECOND(J50),2)&IF(AND(J50>=DATE(YEAR(J50),3,8)+MOD(8-WEEKDAY(DATE(YEAR(J50),3,8)),7)+2/24,J50<DATE(YEAR(J50),11,1)+MOD(8-WEEKDAY(DATE(YEAR(J50),11,1)),7)+2/24),"-04:00","-05:00")) | D50: =IF(G50="","",INDEX(Leads!$V$3:$V$1002,MATCH(49,Leads!$BA$3:$BA$1002,0))) | E50: =IF(G50="","","CAD") | G50: =IFERROR(INDEX(Leads!$A$3:$A$1002,MATCH(49,Leads!$BA$3:$BA$1002,0)),"") | H50: =IF(G50="","",INDEX(Leads!$AQ$3:$AQ$1002,MATCH(49,Leads!$BA$3:$BA$1002,0))) | I50: =IF(G50="","",INDEX(Leads!$AI$3:$AI$1002,MATCH(49,Leads!$BA$3:$BA$1002,0))&"") | J50: =IF(G50="","",INDEX(Leads!$W$3:$W$1002,MATCH(49,Leads!$BA$3:$BA$1002,0)))
A51: =IF(G51="","",INDEX(Leads!$AC$3:$AC$1002,MATCH(50,Leads!$BA$3:$BA$1002,0))) | B51: =IF(G51="","","depot_paye") | C51: =IF(G51="","",YEAR(J51)&"-"&RIGHT("0"&MONTH(J51),2)&"-"&RIGHT("0"&DAY(J51),2)&" "&RIGHT("0"&HOUR(J51),2)&":"&RIGHT("0"&MINUTE(J51),2)&":"&RIGHT("0"&SECOND(J51),2)&IF(AND(J51>=DATE(YEAR(J51),3,8)+MOD(8-WEEKDAY(DATE(YEAR(J51),3,8)),7)+2/24,J51<DATE(YEAR(J51),11,1)+MOD(8-WEEKDAY(DATE(YEAR(J51),11,1)),7)+2/24),"-04:00","-05:00")) | D51: =IF(G51="","",INDEX(Leads!$V$3:$V$1002,MATCH(50,Leads!$BA$3:$BA$1002,0))) | E51: =IF(G51="","","CAD") | G51: =IFERROR(INDEX(Leads!$A$3:$A$1002,MATCH(50,Leads!$BA$3:$BA$1002,0)),"") | H51: =IF(G51="","",INDEX(Leads!$AQ$3:$AQ$1002,MATCH(50,Leads!$BA$3:$BA$1002,0))) | I51: =IF(G51="","",INDEX(Leads!$AI$3:$AI$1002,MATCH(50,Leads!$BA$3:$BA$1002,0))&"") | J51: =IF(G51="","",INDEX(Leads!$W$3:$W$1002,MATCH(50,Leads!$BA$3:$BA$1002,0)))
A52: =IF(G52="","",INDEX(Leads!$AC$3:$AC$1002,MATCH(51,Leads!$BA$3:$BA$1002,0))) | B52: =IF(G52="","","depot_paye") | C52: =IF(G52="","",YEAR(J52)&"-"&RIGHT("0"&MONTH(J52),2)&"-"&RIGHT("0"&DAY(J52),2)&" "&RIGHT("0"&HOUR(J52),2)&":"&RIGHT("0"&MINUTE(J52),2)&":"&RIGHT("0"&SECOND(J52),2)&IF(AND(J52>=DATE(YEAR(J52),3,8)+MOD(8-WEEKDAY(DATE(YEAR(J52),3,8)),7)+2/24,J52<DATE(YEAR(J52),11,1)+MOD(8-WEEKDAY(DATE(YEAR(J52),11,1)),7)+2/24),"-04:00","-05:00")) | D52: =IF(G52="","",INDEX(Leads!$V$3:$V$1002,MATCH(51,Leads!$BA$3:$BA$1002,0))) | E52: =IF(G52="","","CAD") | G52: =IFERROR(INDEX(Leads!$A$3:$A$1002,MATCH(51,Leads!$BA$3:$BA$1002,0)),"") | H52: =IF(G52="","",INDEX(Leads!$AQ$3:$AQ$1002,MATCH(51,Leads!$BA$3:$BA$1002,0))) | I52: =IF(G52="","",INDEX(Leads!$AI$3:$AI$1002,MATCH(51,Leads!$BA$3:$BA$1002,0))&"") | J52: =IF(G52="","",INDEX(Leads!$W$3:$W$1002,MATCH(51,Leads!$BA$3:$BA$1002,0)))
A53: =IF(G53="","",INDEX(Leads!$AC$3:$AC$1002,MATCH(52,Leads!$BA$3:$BA$1002,0))) | B53: =IF(G53="","","depot_paye") | C53: =IF(G53="","",YEAR(J53)&"-"&RIGHT("0"&MONTH(J53),2)&"-"&RIGHT("0"&DAY(J53),2)&" "&RIGHT("0"&HOUR(J53),2)&":"&RIGHT("0"&MINUTE(J53),2)&":"&RIGHT("0"&SECOND(J53),2)&IF(AND(J53>=DATE(YEAR(J53),3,8)+MOD(8-WEEKDAY(DATE(YEAR(J53),3,8)),7)+2/24,J53<DATE(YEAR(J53),11,1)+MOD(8-WEEKDAY(DATE(YEAR(J53),11,1)),7)+2/24),"-04:00","-05:00")) | D53: =IF(G53="","",INDEX(Leads!$V$3:$V$1002,MATCH(52,Leads!$BA$3:$BA$1002,0))) | E53: =IF(G53="","","CAD") | G53: =IFERROR(INDEX(Leads!$A$3:$A$1002,MATCH(52,Leads!$BA$3:$BA$1002,0)),"") | H53: =IF(G53="","",INDEX(Leads!$AQ$3:$AQ$1002,MATCH(52,Leads!$BA$3:$BA$1002,0))) | I53: =IF(G53="","",INDEX(Leads!$AI$3:$AI$1002,MATCH(52,Leads!$BA$3:$BA$1002,0))&"") | J53: =IF(G53="","",INDEX(Leads!$W$3:$W$1002,MATCH(52,Leads!$BA$3:$BA$1002,0)))
A54: =IF(G54="","",INDEX(Leads!$AC$3:$AC$1002,MATCH(53,Leads!$BA$3:$BA$1002,0))) | B54: =IF(G54="","","depot_paye") | C54: =IF(G54="","",YEAR(J54)&"-"&RIGHT("0"&MONTH(J54),2)&"-"&RIGHT("0"&DAY(J54),2)&" "&RIGHT("0"&HOUR(J54),2)&":"&RIGHT("0"&MINUTE(J54),2)&":"&RIGHT("0"&SECOND(J54),2)&IF(AND(J54>=DATE(YEAR(J54),3,8)+MOD(8-WEEKDAY(DATE(YEAR(J54),3,8)),7)+2/24,J54<DATE(YEAR(J54),11,1)+MOD(8-WEEKDAY(DATE(YEAR(J54),11,1)),7)+2/24),"-04:00","-05:00")) | D54: =IF(G54="","",INDEX(Leads!$V$3:$V$1002,MATCH(53,Leads!$BA$3:$BA$1002,0))) | E54: =IF(G54="","","CAD") | G54: =IFERROR(INDEX(Leads!$A$3:$A$1002,MATCH(53,Leads!$BA$3:$BA$1002,0)),"") | H54: =IF(G54="","",INDEX(Leads!$AQ$3:$AQ$1002,MATCH(53,Leads!$BA$3:$BA$1002,0))) | I54: =IF(G54="","",INDEX(Leads!$AI$3:$AI$1002,MATCH(53,Leads!$BA$3:$BA$1002,0))&"") | J54: =IF(G54="","",INDEX(Leads!$W$3:$W$1002,MATCH(53,Leads!$BA$3:$BA$1002,0)))
A55: =IF(G55="","",INDEX(Leads!$AC$3:$AC$1002,MATCH(54,Leads!$BA$3:$BA$1002,0))) | B55: =IF(G55="","","depot_paye") | C55: =IF(G55="","",YEAR(J55)&"-"&RIGHT("0"&MONTH(J55),2)&"-"&RIGHT("0"&DAY(J55),2)&" "&RIGHT("0"&HOUR(J55),2)&":"&RIGHT("0"&MINUTE(J55),2)&":"&RIGHT("0"&SECOND(J55),2)&IF(AND(J55>=DATE(YEAR(J55),3,8)+MOD(8-WEEKDAY(DATE(YEAR(J55),3,8)),7)+2/24,J55<DATE(YEAR(J55),11,1)+MOD(8-WEEKDAY(DATE(YEAR(J55),11,1)),7)+2/24),"-04:00","-05:00")) | D55: =IF(G55="","",INDEX(Leads!$V$3:$V$1002,MATCH(54,Leads!$BA$3:$BA$1002,0))) | E55: =IF(G55="","","CAD") | G55: =IFERROR(INDEX(Leads!$A$3:$A$1002,MATCH(54,Leads!$BA$3:$BA$1002,0)),"") | H55: =IF(G55="","",INDEX(Leads!$AQ$3:$AQ$1002,MATCH(54,Leads!$BA$3:$BA$1002,0))) | I55: =IF(G55="","",INDEX(Leads!$AI$3:$AI$1002,MATCH(54,Leads!$BA$3:$BA$1002,0))&"") | J55: =IF(G55="","",INDEX(Leads!$W$3:$W$1002,MATCH(54,Leads!$BA$3:$BA$1002,0)))
A56: =IF(G56="","",INDEX(Leads!$AC$3:$AC$1002,MATCH(55,Leads!$BA$3:$BA$1002,0))) | B56: =IF(G56="","","depot_paye") | C56: =IF(G56="","",YEAR(J56)&"-"&RIGHT("0"&MONTH(J56),2)&"-"&RIGHT("0"&DAY(J56),2)&" "&RIGHT("0"&HOUR(J56),2)&":"&RIGHT("0"&MINUTE(J56),2)&":"&RIGHT("0"&SECOND(J56),2)&IF(AND(J56>=DATE(YEAR(J56),3,8)+MOD(8-WEEKDAY(DATE(YEAR(J56),3,8)),7)+2/24,J56<DATE(YEAR(J56),11,1)+MOD(8-WEEKDAY(DATE(YEAR(J56),11,1)),7)+2/24),"-04:00","-05:00")) | D56: =IF(G56="","",INDEX(Leads!$V$3:$V$1002,MATCH(55,Leads!$BA$3:$BA$1002,0))) | E56: =IF(G56="","","CAD") | G56: =IFERROR(INDEX(Leads!$A$3:$A$1002,MATCH(55,Leads!$BA$3:$BA$1002,0)),"") | H56: =IF(G56="","",INDEX(Leads!$AQ$3:$AQ$1002,MATCH(55,Leads!$BA$3:$BA$1002,0))) | I56: =IF(G56="","",INDEX(Leads!$AI$3:$AI$1002,MATCH(55,Leads!$BA$3:$BA$1002,0))&"") | J56: =IF(G56="","",INDEX(Leads!$W$3:$W$1002,MATCH(55,Leads!$BA$3:$BA$1002,0)))
A57: =IF(G57="","",INDEX(Leads!$AC$3:$AC$1002,MATCH(56,Leads!$BA$3:$BA$1002,0))) | B57: =IF(G57="","","depot_paye") | C57: =IF(G57="","",YEAR(J57)&"-"&RIGHT("0"&MONTH(J57),2)&"-"&RIGHT("0"&DAY(J57),2)&" "&RIGHT("0"&HOUR(J57),2)&":"&RIGHT("0"&MINUTE(J57),2)&":"&RIGHT("0"&SECOND(J57),2)&IF(AND(J57>=DATE(YEAR(J57),3,8)+MOD(8-WEEKDAY(DATE(YEAR(J57),3,8)),7)+2/24,J57<DATE(YEAR(J57),11,1)+MOD(8-WEEKDAY(DATE(YEAR(J57),11,1)),7)+2/24),"-04:00","-05:00")) | D57: =IF(G57="","",INDEX(Leads!$V$3:$V$1002,MATCH(56,Leads!$BA$3:$BA$1002,0))) | E57: =IF(G57="","","CAD") | G57: =IFERROR(INDEX(Leads!$A$3:$A$1002,MATCH(56,Leads!$BA$3:$BA$1002,0)),"") | H57: =IF(G57="","",INDEX(Leads!$AQ$3:$AQ$1002,MATCH(56,Leads!$BA$3:$BA$1002,0))) | I57: =IF(G57="","",INDEX(Leads!$AI$3:$AI$1002,MATCH(56,Leads!$BA$3:$BA$1002,0))&"") | J57: =IF(G57="","",INDEX(Leads!$W$3:$W$1002,MATCH(56,Leads!$BA$3:$BA$1002,0)))
A58: =IF(G58="","",INDEX(Leads!$AC$3:$AC$1002,MATCH(57,Leads!$BA$3:$BA$1002,0))) | B58: =IF(G58="","","depot_paye") | C58: =IF(G58="","",YEAR(J58)&"-"&RIGHT("0"&MONTH(J58),2)&"-"&RIGHT("0"&DAY(J58),2)&" "&RIGHT("0"&HOUR(J58),2)&":"&RIGHT("0"&MINUTE(J58),2)&":"&RIGHT("0"&SECOND(J58),2)&IF(AND(J58>=DATE(YEAR(J58),3,8)+MOD(8-WEEKDAY(DATE(YEAR(J58),3,8)),7)+2/24,J58<DATE(YEAR(J58),11,1)+MOD(8-WEEKDAY(DATE(YEAR(J58),11,1)),7)+2/24),"-04:00","-05:00")) | D58: =IF(G58="","",INDEX(Leads!$V$3:$V$1002,MATCH(57,Leads!$BA$3:$BA$1002,0))) | E58: =IF(G58="","","CAD") | G58: =IFERROR(INDEX(Leads!$A$3:$A$1002,MATCH(57,Leads!$BA$3:$BA$1002,0)),"") | H58: =IF(G58="","",INDEX(Leads!$AQ$3:$AQ$1002,MATCH(57,Leads!$BA$3:$BA$1002,0))) | I58: =IF(G58="","",INDEX(Leads!$AI$3:$AI$1002,MATCH(57,Leads!$BA$3:$BA$1002,0))&"") | J58: =IF(G58="","",INDEX(Leads!$W$3:$W$1002,MATCH(57,Leads!$BA$3:$BA$1002,0)))
A59: =IF(G59="","",INDEX(Leads!$AC$3:$AC$1002,MATCH(58,Leads!$BA$3:$BA$1002,0))) | B59: =IF(G59="","","depot_paye") | C59: =IF(G59="","",YEAR(J59)&"-"&RIGHT("0"&MONTH(J59),2)&"-"&RIGHT("0"&DAY(J59),2)&" "&RIGHT("0"&HOUR(J59),2)&":"&RIGHT("0"&MINUTE(J59),2)&":"&RIGHT("0"&SECOND(J59),2)&IF(AND(J59>=DATE(YEAR(J59),3,8)+MOD(8-WEEKDAY(DATE(YEAR(J59),3,8)),7)+2/24,J59<DATE(YEAR(J59),11,1)+MOD(8-WEEKDAY(DATE(YEAR(J59),11,1)),7)+2/24),"-04:00","-05:00")) | D59: =IF(G59="","",INDEX(Leads!$V$3:$V$1002,MATCH(58,Leads!$BA$3:$BA$1002,0))) | E59: =IF(G59="","","CAD") | G59: =IFERROR(INDEX(Leads!$A$3:$A$1002,MATCH(58,Leads!$BA$3:$BA$1002,0)),"") | H59: =IF(G59="","",INDEX(Leads!$AQ$3:$AQ$1002,MATCH(58,Leads!$BA$3:$BA$1002,0))) | I59: =IF(G59="","",INDEX(Leads!$AI$3:$AI$1002,MATCH(58,Leads!$BA$3:$BA$1002,0))&"") | J59: =IF(G59="","",INDEX(Leads!$W$3:$W$1002,MATCH(58,Leads!$BA$3:$BA$1002,0)))
A60: =IF(G60="","",INDEX(Leads!$AC$3:$AC$1002,MATCH(59,Leads!$BA$3:$BA$1002,0))) | B60: =IF(G60="","","depot_paye") | C60: =IF(G60="","",YEAR(J60)&"-"&RIGHT("0"&MONTH(J60),2)&"-"&RIGHT("0"&DAY(J60),2)&" "&RIGHT("0"&HOUR(J60),2)&":"&RIGHT("0"&MINUTE(J60),2)&":"&RIGHT("0"&SECOND(J60),2)&IF(AND(J60>=DATE(YEAR(J60),3,8)+MOD(8-WEEKDAY(DATE(YEAR(J60),3,8)),7)+2/24,J60<DATE(YEAR(J60),11,1)+MOD(8-WEEKDAY(DATE(YEAR(J60),11,1)),7)+2/24),"-04:00","-05:00")) | D60: =IF(G60="","",INDEX(Leads!$V$3:$V$1002,MATCH(59,Leads!$BA$3:$BA$1002,0))) | E60: =IF(G60="","","CAD") | G60: =IFERROR(INDEX(Leads!$A$3:$A$1002,MATCH(59,Leads!$BA$3:$BA$1002,0)),"") | H60: =IF(G60="","",INDEX(Leads!$AQ$3:$AQ$1002,MATCH(59,Leads!$BA$3:$BA$1002,0))) | I60: =IF(G60="","",INDEX(Leads!$AI$3:$AI$1002,MATCH(59,Leads!$BA$3:$BA$1002,0))&"") | J60: =IF(G60="","",INDEX(Leads!$W$3:$W$1002,MATCH(59,Leads!$BA$3:$BA$1002,0)))
A61: =IF(G61="","",INDEX(Leads!$AC$3:$AC$1002,MATCH(60,Leads!$BA$3:$BA$1002,0))) | B61: =IF(G61="","","depot_paye") | C61: =IF(G61="","",YEAR(J61)&"-"&RIGHT("0"&MONTH(J61),2)&"-"&RIGHT("0"&DAY(J61),2)&" "&RIGHT("0"&HOUR(J61),2)&":"&RIGHT("0"&MINUTE(J61),2)&":"&RIGHT("0"&SECOND(J61),2)&IF(AND(J61>=DATE(YEAR(J61),3,8)+MOD(8-WEEKDAY(DATE(YEAR(J61),3,8)),7)+2/24,J61<DATE(YEAR(J61),11,1)+MOD(8-WEEKDAY(DATE(YEAR(J61),11,1)),7)+2/24),"-04:00","-05:00")) | D61: =IF(G61="","",INDEX(Leads!$V$3:$V$1002,MATCH(60,Leads!$BA$3:$BA$1002,0))) | E61: =IF(G61="","","CAD") | G61: =IFERROR(INDEX(Leads!$A$3:$A$1002,MATCH(60,Leads!$BA$3:$BA$1002,0)),"") | H61: =IF(G61="","",INDEX(Leads!$AQ$3:$AQ$1002,MATCH(60,Leads!$BA$3:$BA$1002,0))) | I61: =IF(G61="","",INDEX(Leads!$AI$3:$AI$1002,MATCH(60,Leads!$BA$3:$BA$1002,0))&"") | J61: =IF(G61="","",INDEX(Leads!$W$3:$W$1002,MATCH(60,Leads!$BA$3:$BA$1002,0)))
A62: =IF(G62="","",INDEX(Leads!$AC$3:$AC$1002,MATCH(61,Leads!$BA$3:$BA$1002,0))) | B62: =IF(G62="","","depot_paye") | C62: =IF(G62="","",YEAR(J62)&"-"&RIGHT("0"&MONTH(J62),2)&"-"&RIGHT("0"&DAY(J62),2)&" "&RIGHT("0"&HOUR(J62),2)&":"&RIGHT("0"&MINUTE(J62),2)&":"&RIGHT("0"&SECOND(J62),2)&IF(AND(J62>=DATE(YEAR(J62),3,8)+MOD(8-WEEKDAY(DATE(YEAR(J62),3,8)),7)+2/24,J62<DATE(YEAR(J62),11,1)+MOD(8-WEEKDAY(DATE(YEAR(J62),11,1)),7)+2/24),"-04:00","-05:00")) | D62: =IF(G62="","",INDEX(Leads!$V$3:$V$1002,MATCH(61,Leads!$BA$3:$BA$1002,0))) | E62: =IF(G62="","","CAD") | G62: =IFERROR(INDEX(Leads!$A$3:$A$1002,MATCH(61,Leads!$BA$3:$BA$1002,0)),"") | H62: =IF(G62="","",INDEX(Leads!$AQ$3:$AQ$1002,MATCH(61,Leads!$BA$3:$BA$1002,0))) | I62: =IF(G62="","",INDEX(Leads!$AI$3:$AI$1002,MATCH(61,Leads!$BA$3:$BA$1002,0))&"") | J62: =IF(G62="","",INDEX(Leads!$W$3:$W$1002,MATCH(61,Leads!$BA$3:$BA$1002,0)))
A63: =IF(G63="","",INDEX(Leads!$AC$3:$AC$1002,MATCH(62,Leads!$BA$3:$BA$1002,0))) | B63: =IF(G63="","","depot_paye") | C63: =IF(G63="","",YEAR(J63)&"-"&RIGHT("0"&MONTH(J63),2)&"-"&RIGHT("0"&DAY(J63),2)&" "&RIGHT("0"&HOUR(J63),2)&":"&RIGHT("0"&MINUTE(J63),2)&":"&RIGHT("0"&SECOND(J63),2)&IF(AND(J63>=DATE(YEAR(J63),3,8)+MOD(8-WEEKDAY(DATE(YEAR(J63),3,8)),7)+2/24,J63<DATE(YEAR(J63),11,1)+MOD(8-WEEKDAY(DATE(YEAR(J63),11,1)),7)+2/24),"-04:00","-05:00")) | D63: =IF(G63="","",INDEX(Leads!$V$3:$V$1002,MATCH(62,Leads!$BA$3:$BA$1002,0))) | E63: =IF(G63="","","CAD") | G63: =IFERROR(INDEX(Leads!$A$3:$A$1002,MATCH(62,Leads!$BA$3:$BA$1002,0)),"") | H63: =IF(G63="","",INDEX(Leads!$AQ$3:$AQ$1002,MATCH(62,Leads!$BA$3:$BA$1002,0))) | I63: =IF(G63="","",INDEX(Leads!$AI$3:$AI$1002,MATCH(62,Leads!$BA$3:$BA$1002,0))&"") | J63: =IF(G63="","",INDEX(Leads!$W$3:$W$1002,MATCH(62,Leads!$BA$3:$BA$1002,0)))
A64: =IF(G64="","",INDEX(Leads!$AC$3:$AC$1002,MATCH(63,Leads!$BA$3:$BA$1002,0))) | B64: =IF(G64="","","depot_paye") | C64: =IF(G64="","",YEAR(J64)&"-"&RIGHT("0"&MONTH(J64),2)&"-"&RIGHT("0"&DAY(J64),2)&" "&RIGHT("0"&HOUR(J64),2)&":"&RIGHT("0"&MINUTE(J64),2)&":"&RIGHT("0"&SECOND(J64),2)&IF(AND(J64>=DATE(YEAR(J64),3,8)+MOD(8-WEEKDAY(DATE(YEAR(J64),3,8)),7)+2/24,J64<DATE(YEAR(J64),11,1)+MOD(8-WEEKDAY(DATE(YEAR(J64),11,1)),7)+2/24),"-04:00","-05:00")) | D64: =IF(G64="","",INDEX(Leads!$V$3:$V$1002,MATCH(63,Leads!$BA$3:$BA$1002,0))) | E64: =IF(G64="","","CAD") | G64: =IFERROR(INDEX(Leads!$A$3:$A$1002,MATCH(63,Leads!$BA$3:$BA$1002,0)),"") | H64: =IF(G64="","",INDEX(Leads!$AQ$3:$AQ$1002,MATCH(63,Leads!$BA$3:$BA$1002,0))) | I64: =IF(G64="","",INDEX(Leads!$AI$3:$AI$1002,MATCH(63,Leads!$BA$3:$BA$1002,0))&"") | J64: =IF(G64="","",INDEX(Leads!$W$3:$W$1002,MATCH(63,Leads!$BA$3:$BA$1002,0)))
A65: =IF(G65="","",INDEX(Leads!$AC$3:$AC$1002,MATCH(64,Leads!$BA$3:$BA$1002,0))) | B65: =IF(G65="","","depot_paye") | C65: =IF(G65="","",YEAR(J65)&"-"&RIGHT("0"&MONTH(J65),2)&"-"&RIGHT("0"&DAY(J65),2)&" "&RIGHT("0"&HOUR(J65),2)&":"&RIGHT("0"&MINUTE(J65),2)&":"&RIGHT("0"&SECOND(J65),2)&IF(AND(J65>=DATE(YEAR(J65),3,8)+MOD(8-WEEKDAY(DATE(YEAR(J65),3,8)),7)+2/24,J65<DATE(YEAR(J65),11,1)+MOD(8-WEEKDAY(DATE(YEAR(J65),11,1)),7)+2/24),"-04:00","-05:00")) | D65: =IF(G65="","",INDEX(Leads!$V$3:$V$1002,MATCH(64,Leads!$BA$3:$BA$1002,0))) | E65: =IF(G65="","","CAD") | G65: =IFERROR(INDEX(Leads!$A$3:$A$1002,MATCH(64,Leads!$BA$3:$BA$1002,0)),"") | H65: =IF(G65="","",INDEX(Leads!$AQ$3:$AQ$1002,MATCH(64,Leads!$BA$3:$BA$1002,0))) | I65: =IF(G65="","",INDEX(Leads!$AI$3:$AI$1002,MATCH(64,Leads!$BA$3:$BA$1002,0))&"") | J65: =IF(G65="","",INDEX(Leads!$W$3:$W$1002,MATCH(64,Leads!$BA$3:$BA$1002,0)))
A66: =IF(G66="","",INDEX(Leads!$AC$3:$AC$1002,MATCH(65,Leads!$BA$3:$BA$1002,0))) | B66: =IF(G66="","","depot_paye") | C66: =IF(G66="","",YEAR(J66)&"-"&RIGHT("0"&MONTH(J66),2)&"-"&RIGHT("0"&DAY(J66),2)&" "&RIGHT("0"&HOUR(J66),2)&":"&RIGHT("0"&MINUTE(J66),2)&":"&RIGHT("0"&SECOND(J66),2)&IF(AND(J66>=DATE(YEAR(J66),3,8)+MOD(8-WEEKDAY(DATE(YEAR(J66),3,8)),7)+2/24,J66<DATE(YEAR(J66),11,1)+MOD(8-WEEKDAY(DATE(YEAR(J66),11,1)),7)+2/24),"-04:00","-05:00")) | D66: =IF(G66="","",INDEX(Leads!$V$3:$V$1002,MATCH(65,Leads!$BA$3:$BA$1002,0))) | E66: =IF(G66="","","CAD") | G66: =IFERROR(INDEX(Leads!$A$3:$A$1002,MATCH(65,Leads!$BA$3:$BA$1002,0)),"") | H66: =IF(G66="","",INDEX(Leads!$AQ$3:$AQ$1002,MATCH(65,Leads!$BA$3:$BA$1002,0))) | I66: =IF(G66="","",INDEX(Leads!$AI$3:$AI$1002,MATCH(65,Leads!$BA$3:$BA$1002,0))&"") | J66: =IF(G66="","",INDEX(Leads!$W$3:$W$1002,MATCH(65,Leads!$BA$3:$BA$1002,0)))
A67: =IF(G67="","",INDEX(Leads!$AC$3:$AC$1002,MATCH(66,Leads!$BA$3:$BA$1002,0))) | B67: =IF(G67="","","depot_paye") | C67: =IF(G67="","",YEAR(J67)&"-"&RIGHT("0"&MONTH(J67),2)&"-"&RIGHT("0"&DAY(J67),2)&" "&RIGHT("0"&HOUR(J67),2)&":"&RIGHT("0"&MINUTE(J67),2)&":"&RIGHT("0"&SECOND(J67),2)&IF(AND(J67>=DATE(YEAR(J67),3,8)+MOD(8-WEEKDAY(DATE(YEAR(J67),3,8)),7)+2/24,J67<DATE(YEAR(J67),11,1)+MOD(8-WEEKDAY(DATE(YEAR(J67),11,1)),7)+2/24),"-04:00","-05:00")) | D67: =IF(G67="","",INDEX(Leads!$V$3:$V$1002,MATCH(66,Leads!$BA$3:$BA$1002,0))) | E67: =IF(G67="","","CAD") | G67: =IFERROR(INDEX(Leads!$A$3:$A$1002,MATCH(66,Leads!$BA$3:$BA$1002,0)),"") | H67: =IF(G67="","",INDEX(Leads!$AQ$3:$AQ$1002,MATCH(66,Leads!$BA$3:$BA$1002,0))) | I67: =IF(G67="","",INDEX(Leads!$AI$3:$AI$1002,MATCH(66,Leads!$BA$3:$BA$1002,0))&"") | J67: =IF(G67="","",INDEX(Leads!$W$3:$W$1002,MATCH(66,Leads!$BA$3:$BA$1002,0)))
A68: =IF(G68="","",INDEX(Leads!$AC$3:$AC$1002,MATCH(67,Leads!$BA$3:$BA$1002,0))) | B68: =IF(G68="","","depot_paye") | C68: =IF(G68="","",YEAR(J68)&"-"&RIGHT("0"&MONTH(J68),2)&"-"&RIGHT("0"&DAY(J68),2)&" "&RIGHT("0"&HOUR(J68),2)&":"&RIGHT("0"&MINUTE(J68),2)&":"&RIGHT("0"&SECOND(J68),2)&IF(AND(J68>=DATE(YEAR(J68),3,8)+MOD(8-WEEKDAY(DATE(YEAR(J68),3,8)),7)+2/24,J68<DATE(YEAR(J68),11,1)+MOD(8-WEEKDAY(DATE(YEAR(J68),11,1)),7)+2/24),"-04:00","-05:00")) | D68: =IF(G68="","",INDEX(Leads!$V$3:$V$1002,MATCH(67,Leads!$BA$3:$BA$1002,0))) | E68: =IF(G68="","","CAD") | G68: =IFERROR(INDEX(Leads!$A$3:$A$1002,MATCH(67,Leads!$BA$3:$BA$1002,0)),"") | H68: =IF(G68="","",INDEX(Leads!$AQ$3:$AQ$1002,MATCH(67,Leads!$BA$3:$BA$1002,0))) | I68: =IF(G68="","",INDEX(Leads!$AI$3:$AI$1002,MATCH(67,Leads!$BA$3:$BA$1002,0))&"") | J68: =IF(G68="","",INDEX(Leads!$W$3:$W$1002,MATCH(67,Leads!$BA$3:$BA$1002,0)))
A69: =IF(G69="","",INDEX(Leads!$AC$3:$AC$1002,MATCH(68,Leads!$BA$3:$BA$1002,0))) | B69: =IF(G69="","","depot_paye") | C69: =IF(G69="","",YEAR(J69)&"-"&RIGHT("0"&MONTH(J69),2)&"-"&RIGHT("0"&DAY(J69),2)&" "&RIGHT("0"&HOUR(J69),2)&":"&RIGHT("0"&MINUTE(J69),2)&":"&RIGHT("0"&SECOND(J69),2)&IF(AND(J69>=DATE(YEAR(J69),3,8)+MOD(8-WEEKDAY(DATE(YEAR(J69),3,8)),7)+2/24,J69<DATE(YEAR(J69),11,1)+MOD(8-WEEKDAY(DATE(YEAR(J69),11,1)),7)+2/24),"-04:00","-05:00")) | D69: =IF(G69="","",INDEX(Leads!$V$3:$V$1002,MATCH(68,Leads!$BA$3:$BA$1002,0))) | E69: =IF(G69="","","CAD") | G69: =IFERROR(INDEX(Leads!$A$3:$A$1002,MATCH(68,Leads!$BA$3:$BA$1002,0)),"") | H69: =IF(G69="","",INDEX(Leads!$AQ$3:$AQ$1002,MATCH(68,Leads!$BA$3:$BA$1002,0))) | I69: =IF(G69="","",INDEX(Leads!$AI$3:$AI$1002,MATCH(68,Leads!$BA$3:$BA$1002,0))&"") | J69: =IF(G69="","",INDEX(Leads!$W$3:$W$1002,MATCH(68,Leads!$BA$3:$BA$1002,0)))
A70: =IF(G70="","",INDEX(Leads!$AC$3:$AC$1002,MATCH(69,Leads!$BA$3:$BA$1002,0))) | B70: =IF(G70="","","depot_paye") | C70: =IF(G70="","",YEAR(J70)&"-"&RIGHT("0"&MONTH(J70),2)&"-"&RIGHT("0"&DAY(J70),2)&" "&RIGHT("0"&HOUR(J70),2)&":"&RIGHT("0"&MINUTE(J70),2)&":"&RIGHT("0"&SECOND(J70),2)&IF(AND(J70>=DATE(YEAR(J70),3,8)+MOD(8-WEEKDAY(DATE(YEAR(J70),3,8)),7)+2/24,J70<DATE(YEAR(J70),11,1)+MOD(8-WEEKDAY(DATE(YEAR(J70),11,1)),7)+2/24),"-04:00","-05:00")) | D70: =IF(G70="","",INDEX(Leads!$V$3:$V$1002,MATCH(69,Leads!$BA$3:$BA$1002,0))) | E70: =IF(G70="","","CAD") | G70: =IFERROR(INDEX(Leads!$A$3:$A$1002,MATCH(69,Leads!$BA$3:$BA$1002,0)),"") | H70: =IF(G70="","",INDEX(Leads!$AQ$3:$AQ$1002,MATCH(69,Leads!$BA$3:$BA$1002,0))) | I70: =IF(G70="","",INDEX(Leads!$AI$3:$AI$1002,MATCH(69,Leads!$BA$3:$BA$1002,0))&"") | J70: =IF(G70="","",INDEX(Leads!$W$3:$W$1002,MATCH(69,Leads!$BA$3:$BA$1002,0)))
A71: =IF(G71="","",INDEX(Leads!$AC$3:$AC$1002,MATCH(70,Leads!$BA$3:$BA$1002,0))) | B71: =IF(G71="","","depot_paye") | C71: =IF(G71="","",YEAR(J71)&"-"&RIGHT("0"&MONTH(J71),2)&"-"&RIGHT("0"&DAY(J71),2)&" "&RIGHT("0"&HOUR(J71),2)&":"&RIGHT("0"&MINUTE(J71),2)&":"&RIGHT("0"&SECOND(J71),2)&IF(AND(J71>=DATE(YEAR(J71),3,8)+MOD(8-WEEKDAY(DATE(YEAR(J71),3,8)),7)+2/24,J71<DATE(YEAR(J71),11,1)+MOD(8-WEEKDAY(DATE(YEAR(J71),11,1)),7)+2/24),"-04:00","-05:00")) | D71: =IF(G71="","",INDEX(Leads!$V$3:$V$1002,MATCH(70,Leads!$BA$3:$BA$1002,0))) | E71: =IF(G71="","","CAD") | G71: =IFERROR(INDEX(Leads!$A$3:$A$1002,MATCH(70,Leads!$BA$3:$BA$1002,0)),"") | H71: =IF(G71="","",INDEX(Leads!$AQ$3:$AQ$1002,MATCH(70,Leads!$BA$3:$BA$1002,0))) | I71: =IF(G71="","",INDEX(Leads!$AI$3:$AI$1002,MATCH(70,Leads!$BA$3:$BA$1002,0))&"") | J71: =IF(G71="","",INDEX(Leads!$W$3:$W$1002,MATCH(70,Leads!$BA$3:$BA$1002,0)))
A72: =IF(G72="","",INDEX(Leads!$AC$3:$AC$1002,MATCH(71,Leads!$BA$3:$BA$1002,0))) | B72: =IF(G72="","","depot_paye") | C72: =IF(G72="","",YEAR(J72)&"-"&RIGHT("0"&MONTH(J72),2)&"-"&RIGHT("0"&DAY(J72),2)&" "&RIGHT("0"&HOUR(J72),2)&":"&RIGHT("0"&MINUTE(J72),2)&":"&RIGHT("0"&SECOND(J72),2)&IF(AND(J72>=DATE(YEAR(J72),3,8)+MOD(8-WEEKDAY(DATE(YEAR(J72),3,8)),7)+2/24,J72<DATE(YEAR(J72),11,1)+MOD(8-WEEKDAY(DATE(YEAR(J72),11,1)),7)+2/24),"-04:00","-05:00")) | D72: =IF(G72="","",INDEX(Leads!$V$3:$V$1002,MATCH(71,Leads!$BA$3:$BA$1002,0))) | E72: =IF(G72="","","CAD") | G72: =IFERROR(INDEX(Leads!$A$3:$A$1002,MATCH(71,Leads!$BA$3:$BA$1002,0)),"") | H72: =IF(G72="","",INDEX(Leads!$AQ$3:$AQ$1002,MATCH(71,Leads!$BA$3:$BA$1002,0))) | I72: =IF(G72="","",INDEX(Leads!$AI$3:$AI$1002,MATCH(71,Leads!$BA$3:$BA$1002,0))&"") | J72: =IF(G72="","",INDEX(Leads!$W$3:$W$1002,MATCH(71,Leads!$BA$3:$BA$1002,0)))
A73: =IF(G73="","",INDEX(Leads!$AC$3:$AC$1002,MATCH(72,Leads!$BA$3:$BA$1002,0))) | B73: =IF(G73="","","depot_paye") | C73: =IF(G73="","",YEAR(J73)&"-"&RIGHT("0"&MONTH(J73),2)&"-"&RIGHT("0"&DAY(J73),2)&" "&RIGHT("0"&HOUR(J73),2)&":"&RIGHT("0"&MINUTE(J73),2)&":"&RIGHT("0"&SECOND(J73),2)&IF(AND(J73>=DATE(YEAR(J73),3,8)+MOD(8-WEEKDAY(DATE(YEAR(J73),3,8)),7)+2/24,J73<DATE(YEAR(J73),11,1)+MOD(8-WEEKDAY(DATE(YEAR(J73),11,1)),7)+2/24),"-04:00","-05:00")) | D73: =IF(G73="","",INDEX(Leads!$V$3:$V$1002,MATCH(72,Leads!$BA$3:$BA$1002,0))) | E73: =IF(G73="","","CAD") | G73: =IFERROR(INDEX(Leads!$A$3:$A$1002,MATCH(72,Leads!$BA$3:$BA$1002,0)),"") | H73: =IF(G73="","",INDEX(Leads!$AQ$3:$AQ$1002,MATCH(72,Leads!$BA$3:$BA$1002,0))) | I73: =IF(G73="","",INDEX(Leads!$AI$3:$AI$1002,MATCH(72,Leads!$BA$3:$BA$1002,0))&"") | J73: =IF(G73="","",INDEX(Leads!$W$3:$W$1002,MATCH(72,Leads!$BA$3:$BA$1002,0)))
A74: =IF(G74="","",INDEX(Leads!$AC$3:$AC$1002,MATCH(73,Leads!$BA$3:$BA$1002,0))) | B74: =IF(G74="","","depot_paye") | C74: =IF(G74="","",YEAR(J74)&"-"&RIGHT("0"&MONTH(J74),2)&"-"&RIGHT("0"&DAY(J74),2)&" "&RIGHT("0"&HOUR(J74),2)&":"&RIGHT("0"&MINUTE(J74),2)&":"&RIGHT("0"&SECOND(J74),2)&IF(AND(J74>=DATE(YEAR(J74),3,8)+MOD(8-WEEKDAY(DATE(YEAR(J74),3,8)),7)+2/24,J74<DATE(YEAR(J74),11,1)+MOD(8-WEEKDAY(DATE(YEAR(J74),11,1)),7)+2/24),"-04:00","-05:00")) | D74: =IF(G74="","",INDEX(Leads!$V$3:$V$1002,MATCH(73,Leads!$BA$3:$BA$1002,0))) | E74: =IF(G74="","","CAD") | G74: =IFERROR(INDEX(Leads!$A$3:$A$1002,MATCH(73,Leads!$BA$3:$BA$1002,0)),"") | H74: =IF(G74="","",INDEX(Leads!$AQ$3:$AQ$1002,MATCH(73,Leads!$BA$3:$BA$1002,0))) | I74: =IF(G74="","",INDEX(Leads!$AI$3:$AI$1002,MATCH(73,Leads!$BA$3:$BA$1002,0))&"") | J74: =IF(G74="","",INDEX(Leads!$W$3:$W$1002,MATCH(73,Leads!$BA$3:$BA$1002,0)))
A75: =IF(G75="","",INDEX(Leads!$AC$3:$AC$1002,MATCH(74,Leads!$BA$3:$BA$1002,0))) | B75: =IF(G75="","","depot_paye") | C75: =IF(G75="","",YEAR(J75)&"-"&RIGHT("0"&MONTH(J75),2)&"-"&RIGHT("0"&DAY(J75),2)&" "&RIGHT("0"&HOUR(J75),2)&":"&RIGHT("0"&MINUTE(J75),2)&":"&RIGHT("0"&SECOND(J75),2)&IF(AND(J75>=DATE(YEAR(J75),3,8)+MOD(8-WEEKDAY(DATE(YEAR(J75),3,8)),7)+2/24,J75<DATE(YEAR(J75),11,1)+MOD(8-WEEKDAY(DATE(YEAR(J75),11,1)),7)+2/24),"-04:00","-05:00")) | D75: =IF(G75="","",INDEX(Leads!$V$3:$V$1002,MATCH(74,Leads!$BA$3:$BA$1002,0))) | E75: =IF(G75="","","CAD") | G75: =IFERROR(INDEX(Leads!$A$3:$A$1002,MATCH(74,Leads!$BA$3:$BA$1002,0)),"") | H75: =IF(G75="","",INDEX(Leads!$AQ$3:$AQ$1002,MATCH(74,Leads!$BA$3:$BA$1002,0))) | I75: =IF(G75="","",INDEX(Leads!$AI$3:$AI$1002,MATCH(74,Leads!$BA$3:$BA$1002,0))&"") | J75: =IF(G75="","",INDEX(Leads!$W$3:$W$1002,MATCH(74,Leads!$BA$3:$BA$1002,0)))
A76: =IF(G76="","",INDEX(Leads!$AC$3:$AC$1002,MATCH(75,Leads!$BA$3:$BA$1002,0))) | B76: =IF(G76="","","depot_paye") | C76: =IF(G76="","",YEAR(J76)&"-"&RIGHT("0"&MONTH(J76),2)&"-"&RIGHT("0"&DAY(J76),2)&" "&RIGHT("0"&HOUR(J76),2)&":"&RIGHT("0"&MINUTE(J76),2)&":"&RIGHT("0"&SECOND(J76),2)&IF(AND(J76>=DATE(YEAR(J76),3,8)+MOD(8-WEEKDAY(DATE(YEAR(J76),3,8)),7)+2/24,J76<DATE(YEAR(J76),11,1)+MOD(8-WEEKDAY(DATE(YEAR(J76),11,1)),7)+2/24),"-04:00","-05:00")) | D76: =IF(G76="","",INDEX(Leads!$V$3:$V$1002,MATCH(75,Leads!$BA$3:$BA$1002,0))) | E76: =IF(G76="","","CAD") | G76: =IFERROR(INDEX(Leads!$A$3:$A$1002,MATCH(75,Leads!$BA$3:$BA$1002,0)),"") | H76: =IF(G76="","",INDEX(Leads!$AQ$3:$AQ$1002,MATCH(75,Leads!$BA$3:$BA$1002,0))) | I76: =IF(G76="","",INDEX(Leads!$AI$3:$AI$1002,MATCH(75,Leads!$BA$3:$BA$1002,0))&"") | J76: =IF(G76="","",INDEX(Leads!$W$3:$W$1002,MATCH(75,Leads!$BA$3:$BA$1002,0)))
A77: =IF(G77="","",INDEX(Leads!$AC$3:$AC$1002,MATCH(76,Leads!$BA$3:$BA$1002,0))) | B77: =IF(G77="","","depot_paye") | C77: =IF(G77="","",YEAR(J77)&"-"&RIGHT("0"&MONTH(J77),2)&"-"&RIGHT("0"&DAY(J77),2)&" "&RIGHT("0"&HOUR(J77),2)&":"&RIGHT("0"&MINUTE(J77),2)&":"&RIGHT("0"&SECOND(J77),2)&IF(AND(J77>=DATE(YEAR(J77),3,8)+MOD(8-WEEKDAY(DATE(YEAR(J77),3,8)),7)+2/24,J77<DATE(YEAR(J77),11,1)+MOD(8-WEEKDAY(DATE(YEAR(J77),11,1)),7)+2/24),"-04:00","-05:00")) | D77: =IF(G77="","",INDEX(Leads!$V$3:$V$1002,MATCH(76,Leads!$BA$3:$BA$1002,0))) | E77: =IF(G77="","","CAD") | G77: =IFERROR(INDEX(Leads!$A$3:$A$1002,MATCH(76,Leads!$BA$3:$BA$1002,0)),"") | H77: =IF(G77="","",INDEX(Leads!$AQ$3:$AQ$1002,MATCH(76,Leads!$BA$3:$BA$1002,0))) | I77: =IF(G77="","",INDEX(Leads!$AI$3:$AI$1002,MATCH(76,Leads!$BA$3:$BA$1002,0))&"") | J77: =IF(G77="","",INDEX(Leads!$W$3:$W$1002,MATCH(76,Leads!$BA$3:$BA$1002,0)))
A78: =IF(G78="","",INDEX(Leads!$AC$3:$AC$1002,MATCH(77,Leads!$BA$3:$BA$1002,0))) | B78: =IF(G78="","","depot_paye") | C78: =IF(G78="","",YEAR(J78)&"-"&RIGHT("0"&MONTH(J78),2)&"-"&RIGHT("0"&DAY(J78),2)&" "&RIGHT("0"&HOUR(J78),2)&":"&RIGHT("0"&MINUTE(J78),2)&":"&RIGHT("0"&SECOND(J78),2)&IF(AND(J78>=DATE(YEAR(J78),3,8)+MOD(8-WEEKDAY(DATE(YEAR(J78),3,8)),7)+2/24,J78<DATE(YEAR(J78),11,1)+MOD(8-WEEKDAY(DATE(YEAR(J78),11,1)),7)+2/24),"-04:00","-05:00")) | D78: =IF(G78="","",INDEX(Leads!$V$3:$V$1002,MATCH(77,Leads!$BA$3:$BA$1002,0))) | E78: =IF(G78="","","CAD") | G78: =IFERROR(INDEX(Leads!$A$3:$A$1002,MATCH(77,Leads!$BA$3:$BA$1002,0)),"") | H78: =IF(G78="","",INDEX(Leads!$AQ$3:$AQ$1002,MATCH(77,Leads!$BA$3:$BA$1002,0))) | I78: =IF(G78="","",INDEX(Leads!$AI$3:$AI$1002,MATCH(77,Leads!$BA$3:$BA$1002,0))&"") | J78: =IF(G78="","",INDEX(Leads!$W$3:$W$1002,MATCH(77,Leads!$BA$3:$BA$1002,0)))
A79: =IF(G79="","",INDEX(Leads!$AC$3:$AC$1002,MATCH(78,Leads!$BA$3:$BA$1002,0))) | B79: =IF(G79="","","depot_paye") | C79: =IF(G79="","",YEAR(J79)&"-"&RIGHT("0"&MONTH(J79),2)&"-"&RIGHT("0"&DAY(J79),2)&" "&RIGHT("0"&HOUR(J79),2)&":"&RIGHT("0"&MINUTE(J79),2)&":"&RIGHT("0"&SECOND(J79),2)&IF(AND(J79>=DATE(YEAR(J79),3,8)+MOD(8-WEEKDAY(DATE(YEAR(J79),3,8)),7)+2/24,J79<DATE(YEAR(J79),11,1)+MOD(8-WEEKDAY(DATE(YEAR(J79),11,1)),7)+2/24),"-04:00","-05:00")) | D79: =IF(G79="","",INDEX(Leads!$V$3:$V$1002,MATCH(78,Leads!$BA$3:$BA$1002,0))) | E79: =IF(G79="","","CAD") | G79: =IFERROR(INDEX(Leads!$A$3:$A$1002,MATCH(78,Leads!$BA$3:$BA$1002,0)),"") | H79: =IF(G79="","",INDEX(Leads!$AQ$3:$AQ$1002,MATCH(78,Leads!$BA$3:$BA$1002,0))) | I79: =IF(G79="","",INDEX(Leads!$AI$3:$AI$1002,MATCH(78,Leads!$BA$3:$BA$1002,0))&"") | J79: =IF(G79="","",INDEX(Leads!$W$3:$W$1002,MATCH(78,Leads!$BA$3:$BA$1002,0)))
A80: =IF(G80="","",INDEX(Leads!$AC$3:$AC$1002,MATCH(79,Leads!$BA$3:$BA$1002,0))) | B80: =IF(G80="","","depot_paye") | C80: =IF(G80="","",YEAR(J80)&"-"&RIGHT("0"&MONTH(J80),2)&"-"&RIGHT("0"&DAY(J80),2)&" "&RIGHT("0"&HOUR(J80),2)&":"&RIGHT("0"&MINUTE(J80),2)&":"&RIGHT("0"&SECOND(J80),2)&IF(AND(J80>=DATE(YEAR(J80),3,8)+MOD(8-WEEKDAY(DATE(YEAR(J80),3,8)),7)+2/24,J80<DATE(YEAR(J80),11,1)+MOD(8-WEEKDAY(DATE(YEAR(J80),11,1)),7)+2/24),"-04:00","-05:00")) | D80: =IF(G80="","",INDEX(Leads!$V$3:$V$1002,MATCH(79,Leads!$BA$3:$BA$1002,0))) | E80: =IF(G80="","","CAD") | G80: =IFERROR(INDEX(Leads!$A$3:$A$1002,MATCH(79,Leads!$BA$3:$BA$1002,0)),"") | H80: =IF(G80="","",INDEX(Leads!$AQ$3:$AQ$1002,MATCH(79,Leads!$BA$3:$BA$1002,0))) | I80: =IF(G80="","",INDEX(Leads!$AI$3:$AI$1002,MATCH(79,Leads!$BA$3:$BA$1002,0))&"") | J80: =IF(G80="","",INDEX(Leads!$W$3:$W$1002,MATCH(79,Leads!$BA$3:$BA$1002,0)))
A81: =IF(G81="","",INDEX(Leads!$AC$3:$AC$1002,MATCH(80,Leads!$BA$3:$BA$1002,0))) | B81: =IF(G81="","","depot_paye") | C81: =IF(G81="","",YEAR(J81)&"-"&RIGHT("0"&MONTH(J81),2)&"-"&RIGHT("0"&DAY(J81),2)&" "&RIGHT("0"&HOUR(J81),2)&":"&RIGHT("0"&MINUTE(J81),2)&":"&RIGHT("0"&SECOND(J81),2)&IF(AND(J81>=DATE(YEAR(J81),3,8)+MOD(8-WEEKDAY(DATE(YEAR(J81),3,8)),7)+2/24,J81<DATE(YEAR(J81),11,1)+MOD(8-WEEKDAY(DATE(YEAR(J81),11,1)),7)+2/24),"-04:00","-05:00")) | D81: =IF(G81="","",INDEX(Leads!$V$3:$V$1002,MATCH(80,Leads!$BA$3:$BA$1002,0))) | E81: =IF(G81="","","CAD") | G81: =IFERROR(INDEX(Leads!$A$3:$A$1002,MATCH(80,Leads!$BA$3:$BA$1002,0)),"") | H81: =IF(G81="","",INDEX(Leads!$AQ$3:$AQ$1002,MATCH(80,Leads!$BA$3:$BA$1002,0))) | I81: =IF(G81="","",INDEX(Leads!$AI$3:$AI$1002,MATCH(80,Leads!$BA$3:$BA$1002,0))&"") | J81: =IF(G81="","",INDEX(Leads!$W$3:$W$1002,MATCH(80,Leads!$BA$3:$BA$1002,0)))
A82: =IF(G82="","",INDEX(Leads!$AC$3:$AC$1002,MATCH(81,Leads!$BA$3:$BA$1002,0))) | B82: =IF(G82="","","depot_paye") | C82: =IF(G82="","",YEAR(J82)&"-"&RIGHT("0"&MONTH(J82),2)&"-"&RIGHT("0"&DAY(J82),2)&" "&RIGHT("0"&HOUR(J82),2)&":"&RIGHT("0"&MINUTE(J82),2)&":"&RIGHT("0"&SECOND(J82),2)&IF(AND(J82>=DATE(YEAR(J82),3,8)+MOD(8-WEEKDAY(DATE(YEAR(J82),3,8)),7)+2/24,J82<DATE(YEAR(J82),11,1)+MOD(8-WEEKDAY(DATE(YEAR(J82),11,1)),7)+2/24),"-04:00","-05:00")) | D82: =IF(G82="","",INDEX(Leads!$V$3:$V$1002,MATCH(81,Leads!$BA$3:$BA$1002,0))) | E82: =IF(G82="","","CAD") | G82: =IFERROR(INDEX(Leads!$A$3:$A$1002,MATCH(81,Leads!$BA$3:$BA$1002,0)),"") | H82: =IF(G82="","",INDEX(Leads!$AQ$3:$AQ$1002,MATCH(81,Leads!$BA$3:$BA$1002,0))) | I82: =IF(G82="","",INDEX(Leads!$AI$3:$AI$1002,MATCH(81,Leads!$BA$3:$BA$1002,0))&"") | J82: =IF(G82="","",INDEX(Leads!$W$3:$W$1002,MATCH(81,Leads!$BA$3:$BA$1002,0)))
A83: =IF(G83="","",INDEX(Leads!$AC$3:$AC$1002,MATCH(82,Leads!$BA$3:$BA$1002,0))) | B83: =IF(G83="","","depot_paye") | C83: =IF(G83="","",YEAR(J83)&"-"&RIGHT("0"&MONTH(J83),2)&"-"&RIGHT("0"&DAY(J83),2)&" "&RIGHT("0"&HOUR(J83),2)&":"&RIGHT("0"&MINUTE(J83),2)&":"&RIGHT("0"&SECOND(J83),2)&IF(AND(J83>=DATE(YEAR(J83),3,8)+MOD(8-WEEKDAY(DATE(YEAR(J83),3,8)),7)+2/24,J83<DATE(YEAR(J83),11,1)+MOD(8-WEEKDAY(DATE(YEAR(J83),11,1)),7)+2/24),"-04:00","-05:00")) | D83: =IF(G83="","",INDEX(Leads!$V$3:$V$1002,MATCH(82,Leads!$BA$3:$BA$1002,0))) | E83: =IF(G83="","","CAD") | G83: =IFERROR(INDEX(Leads!$A$3:$A$1002,MATCH(82,Leads!$BA$3:$BA$1002,0)),"") | H83: =IF(G83="","",INDEX(Leads!$AQ$3:$AQ$1002,MATCH(82,Leads!$BA$3:$BA$1002,0))) | I83: =IF(G83="","",INDEX(Leads!$AI$3:$AI$1002,MATCH(82,Leads!$BA$3:$BA$1002,0))&"") | J83: =IF(G83="","",INDEX(Leads!$W$3:$W$1002,MATCH(82,Leads!$BA$3:$BA$1002,0)))
A84: =IF(G84="","",INDEX(Leads!$AC$3:$AC$1002,MATCH(83,Leads!$BA$3:$BA$1002,0))) | B84: =IF(G84="","","depot_paye") | C84: =IF(G84="","",YEAR(J84)&"-"&RIGHT("0"&MONTH(J84),2)&"-"&RIGHT("0"&DAY(J84),2)&" "&RIGHT("0"&HOUR(J84),2)&":"&RIGHT("0"&MINUTE(J84),2)&":"&RIGHT("0"&SECOND(J84),2)&IF(AND(J84>=DATE(YEAR(J84),3,8)+MOD(8-WEEKDAY(DATE(YEAR(J84),3,8)),7)+2/24,J84<DATE(YEAR(J84),11,1)+MOD(8-WEEKDAY(DATE(YEAR(J84),11,1)),7)+2/24),"-04:00","-05:00")) | D84: =IF(G84="","",INDEX(Leads!$V$3:$V$1002,MATCH(83,Leads!$BA$3:$BA$1002,0))) | E84: =IF(G84="","","CAD") | G84: =IFERROR(INDEX(Leads!$A$3:$A$1002,MATCH(83,Leads!$BA$3:$BA$1002,0)),"") | H84: =IF(G84="","",INDEX(Leads!$AQ$3:$AQ$1002,MATCH(83,Leads!$BA$3:$BA$1002,0))) | I84: =IF(G84="","",INDEX(Leads!$AI$3:$AI$1002,MATCH(83,Leads!$BA$3:$BA$1002,0))&"") | J84: =IF(G84="","",INDEX(Leads!$W$3:$W$1002,MATCH(83,Leads!$BA$3:$BA$1002,0)))
A85: =IF(G85="","",INDEX(Leads!$AC$3:$AC$1002,MATCH(84,Leads!$BA$3:$BA$1002,0))) | B85: =IF(G85="","","depot_paye") | C85: =IF(G85="","",YEAR(J85)&"-"&RIGHT("0"&MONTH(J85),2)&"-"&RIGHT("0"&DAY(J85),2)&" "&RIGHT("0"&HOUR(J85),2)&":"&RIGHT("0"&MINUTE(J85),2)&":"&RIGHT("0"&SECOND(J85),2)&IF(AND(J85>=DATE(YEAR(J85),3,8)+MOD(8-WEEKDAY(DATE(YEAR(J85),3,8)),7)+2/24,J85<DATE(YEAR(J85),11,1)+MOD(8-WEEKDAY(DATE(YEAR(J85),11,1)),7)+2/24),"-04:00","-05:00")) | D85: =IF(G85="","",INDEX(Leads!$V$3:$V$1002,MATCH(84,Leads!$BA$3:$BA$1002,0))) | E85: =IF(G85="","","CAD") | G85: =IFERROR(INDEX(Leads!$A$3:$A$1002,MATCH(84,Leads!$BA$3:$BA$1002,0)),"") | H85: =IF(G85="","",INDEX(Leads!$AQ$3:$AQ$1002,MATCH(84,Leads!$BA$3:$BA$1002,0))) | I85: =IF(G85="","",INDEX(Leads!$AI$3:$AI$1002,MATCH(84,Leads!$BA$3:$BA$1002,0))&"") | J85: =IF(G85="","",INDEX(Leads!$W$3:$W$1002,MATCH(84,Leads!$BA$3:$BA$1002,0)))
A86: =IF(G86="","",INDEX(Leads!$AC$3:$AC$1002,MATCH(85,Leads!$BA$3:$BA$1002,0))) | B86: =IF(G86="","","depot_paye") | C86: =IF(G86="","",YEAR(J86)&"-"&RIGHT("0"&MONTH(J86),2)&"-"&RIGHT("0"&DAY(J86),2)&" "&RIGHT("0"&HOUR(J86),2)&":"&RIGHT("0"&MINUTE(J86),2)&":"&RIGHT("0"&SECOND(J86),2)&IF(AND(J86>=DATE(YEAR(J86),3,8)+MOD(8-WEEKDAY(DATE(YEAR(J86),3,8)),7)+2/24,J86<DATE(YEAR(J86),11,1)+MOD(8-WEEKDAY(DATE(YEAR(J86),11,1)),7)+2/24),"-04:00","-05:00")) | D86: =IF(G86="","",INDEX(Leads!$V$3:$V$1002,MATCH(85,Leads!$BA$3:$BA$1002,0))) | E86: =IF(G86="","","CAD") | G86: =IFERROR(INDEX(Leads!$A$3:$A$1002,MATCH(85,Leads!$BA$3:$BA$1002,0)),"") | H86: =IF(G86="","",INDEX(Leads!$AQ$3:$AQ$1002,MATCH(85,Leads!$BA$3:$BA$1002,0))) | I86: =IF(G86="","",INDEX(Leads!$AI$3:$AI$1002,MATCH(85,Leads!$BA$3:$BA$1002,0))&"") | J86: =IF(G86="","",INDEX(Leads!$W$3:$W$1002,MATCH(85,Leads!$BA$3:$BA$1002,0)))
A87: =IF(G87="","",INDEX(Leads!$AC$3:$AC$1002,MATCH(86,Leads!$BA$3:$BA$1002,0))) | B87: =IF(G87="","","depot_paye") | C87: =IF(G87="","",YEAR(J87)&"-"&RIGHT("0"&MONTH(J87),2)&"-"&RIGHT("0"&DAY(J87),2)&" "&RIGHT("0"&HOUR(J87),2)&":"&RIGHT("0"&MINUTE(J87),2)&":"&RIGHT("0"&SECOND(J87),2)&IF(AND(J87>=DATE(YEAR(J87),3,8)+MOD(8-WEEKDAY(DATE(YEAR(J87),3,8)),7)+2/24,J87<DATE(YEAR(J87),11,1)+MOD(8-WEEKDAY(DATE(YEAR(J87),11,1)),7)+2/24),"-04:00","-05:00")) | D87: =IF(G87="","",INDEX(Leads!$V$3:$V$1002,MATCH(86,Leads!$BA$3:$BA$1002,0))) | E87: =IF(G87="","","CAD") | G87: =IFERROR(INDEX(Leads!$A$3:$A$1002,MATCH(86,Leads!$BA$3:$BA$1002,0)),"") | H87: =IF(G87="","",INDEX(Leads!$AQ$3:$AQ$1002,MATCH(86,Leads!$BA$3:$BA$1002,0))) | I87: =IF(G87="","",INDEX(Leads!$AI$3:$AI$1002,MATCH(86,Leads!$BA$3:$BA$1002,0))&"") | J87: =IF(G87="","",INDEX(Leads!$W$3:$W$1002,MATCH(86,Leads!$BA$3:$BA$1002,0)))
A88: =IF(G88="","",INDEX(Leads!$AC$3:$AC$1002,MATCH(87,Leads!$BA$3:$BA$1002,0))) | B88: =IF(G88="","","depot_paye") | C88: =IF(G88="","",YEAR(J88)&"-"&RIGHT("0"&MONTH(J88),2)&"-"&RIGHT("0"&DAY(J88),2)&" "&RIGHT("0"&HOUR(J88),2)&":"&RIGHT("0"&MINUTE(J88),2)&":"&RIGHT("0"&SECOND(J88),2)&IF(AND(J88>=DATE(YEAR(J88),3,8)+MOD(8-WEEKDAY(DATE(YEAR(J88),3,8)),7)+2/24,J88<DATE(YEAR(J88),11,1)+MOD(8-WEEKDAY(DATE(YEAR(J88),11,1)),7)+2/24),"-04:00","-05:00")) | D88: =IF(G88="","",INDEX(Leads!$V$3:$V$1002,MATCH(87,Leads!$BA$3:$BA$1002,0))) | E88: =IF(G88="","","CAD") | G88: =IFERROR(INDEX(Leads!$A$3:$A$1002,MATCH(87,Leads!$BA$3:$BA$1002,0)),"") | H88: =IF(G88="","",INDEX(Leads!$AQ$3:$AQ$1002,MATCH(87,Leads!$BA$3:$BA$1002,0))) | I88: =IF(G88="","",INDEX(Leads!$AI$3:$AI$1002,MATCH(87,Leads!$BA$3:$BA$1002,0))&"") | J88: =IF(G88="","",INDEX(Leads!$W$3:$W$1002,MATCH(87,Leads!$BA$3:$BA$1002,0)))
A89: =IF(G89="","",INDEX(Leads!$AC$3:$AC$1002,MATCH(88,Leads!$BA$3:$BA$1002,0))) | B89: =IF(G89="","","depot_paye") | C89: =IF(G89="","",YEAR(J89)&"-"&RIGHT("0"&MONTH(J89),2)&"-"&RIGHT("0"&DAY(J89),2)&" "&RIGHT("0"&HOUR(J89),2)&":"&RIGHT("0"&MINUTE(J89),2)&":"&RIGHT("0"&SECOND(J89),2)&IF(AND(J89>=DATE(YEAR(J89),3,8)+MOD(8-WEEKDAY(DATE(YEAR(J89),3,8)),7)+2/24,J89<DATE(YEAR(J89),11,1)+MOD(8-WEEKDAY(DATE(YEAR(J89),11,1)),7)+2/24),"-04:00","-05:00")) | D89: =IF(G89="","",INDEX(Leads!$V$3:$V$1002,MATCH(88,Leads!$BA$3:$BA$1002,0))) | E89: =IF(G89="","","CAD") | G89: =IFERROR(INDEX(Leads!$A$3:$A$1002,MATCH(88,Leads!$BA$3:$BA$1002,0)),"") | H89: =IF(G89="","",INDEX(Leads!$AQ$3:$AQ$1002,MATCH(88,Leads!$BA$3:$BA$1002,0))) | I89: =IF(G89="","",INDEX(Leads!$AI$3:$AI$1002,MATCH(88,Leads!$BA$3:$BA$1002,0))&"") | J89: =IF(G89="","",INDEX(Leads!$W$3:$W$1002,MATCH(88,Leads!$BA$3:$BA$1002,0)))
A90: =IF(G90="","",INDEX(Leads!$AC$3:$AC$1002,MATCH(89,Leads!$BA$3:$BA$1002,0))) | B90: =IF(G90="","","depot_paye") | C90: =IF(G90="","",YEAR(J90)&"-"&RIGHT("0"&MONTH(J90),2)&"-"&RIGHT("0"&DAY(J90),2)&" "&RIGHT("0"&HOUR(J90),2)&":"&RIGHT("0"&MINUTE(J90),2)&":"&RIGHT("0"&SECOND(J90),2)&IF(AND(J90>=DATE(YEAR(J90),3,8)+MOD(8-WEEKDAY(DATE(YEAR(J90),3,8)),7)+2/24,J90<DATE(YEAR(J90),11,1)+MOD(8-WEEKDAY(DATE(YEAR(J90),11,1)),7)+2/24),"-04:00","-05:00")) | D90: =IF(G90="","",INDEX(Leads!$V$3:$V$1002,MATCH(89,Leads!$BA$3:$BA$1002,0))) | E90: =IF(G90="","","CAD") | G90: =IFERROR(INDEX(Leads!$A$3:$A$1002,MATCH(89,Leads!$BA$3:$BA$1002,0)),"") | H90: =IF(G90="","",INDEX(Leads!$AQ$3:$AQ$1002,MATCH(89,Leads!$BA$3:$BA$1002,0))) | I90: =IF(G90="","",INDEX(Leads!$AI$3:$AI$1002,MATCH(89,Leads!$BA$3:$BA$1002,0))&"") | J90: =IF(G90="","",INDEX(Leads!$W$3:$W$1002,MATCH(89,Leads!$BA$3:$BA$1002,0)))
A91: =IF(G91="","",INDEX(Leads!$AC$3:$AC$1002,MATCH(90,Leads!$BA$3:$BA$1002,0))) | B91: =IF(G91="","","depot_paye") | C91: =IF(G91="","",YEAR(J91)&"-"&RIGHT("0"&MONTH(J91),2)&"-"&RIGHT("0"&DAY(J91),2)&" "&RIGHT("0"&HOUR(J91),2)&":"&RIGHT("0"&MINUTE(J91),2)&":"&RIGHT("0"&SECOND(J91),2)&IF(AND(J91>=DATE(YEAR(J91),3,8)+MOD(8-WEEKDAY(DATE(YEAR(J91),3,8)),7)+2/24,J91<DATE(YEAR(J91),11,1)+MOD(8-WEEKDAY(DATE(YEAR(J91),11,1)),7)+2/24),"-04:00","-05:00")) | D91: =IF(G91="","",INDEX(Leads!$V$3:$V$1002,MATCH(90,Leads!$BA$3:$BA$1002,0))) | E91: =IF(G91="","","CAD") | G91: =IFERROR(INDEX(Leads!$A$3:$A$1002,MATCH(90,Leads!$BA$3:$BA$1002,0)),"") | H91: =IF(G91="","",INDEX(Leads!$AQ$3:$AQ$1002,MATCH(90,Leads!$BA$3:$BA$1002,0))) | I91: =IF(G91="","",INDEX(Leads!$AI$3:$AI$1002,MATCH(90,Leads!$BA$3:$BA$1002,0))&"") | J91: =IF(G91="","",INDEX(Leads!$W$3:$W$1002,MATCH(90,Leads!$BA$3:$BA$1002,0)))
A92: =IF(G92="","",INDEX(Leads!$AC$3:$AC$1002,MATCH(91,Leads!$BA$3:$BA$1002,0))) | B92: =IF(G92="","","depot_paye") | C92: =IF(G92="","",YEAR(J92)&"-"&RIGHT("0"&MONTH(J92),2)&"-"&RIGHT("0"&DAY(J92),2)&" "&RIGHT("0"&HOUR(J92),2)&":"&RIGHT("0"&MINUTE(J92),2)&":"&RIGHT("0"&SECOND(J92),2)&IF(AND(J92>=DATE(YEAR(J92),3,8)+MOD(8-WEEKDAY(DATE(YEAR(J92),3,8)),7)+2/24,J92<DATE(YEAR(J92),11,1)+MOD(8-WEEKDAY(DATE(YEAR(J92),11,1)),7)+2/24),"-04:00","-05:00")) | D92: =IF(G92="","",INDEX(Leads!$V$3:$V$1002,MATCH(91,Leads!$BA$3:$BA$1002,0))) | E92: =IF(G92="","","CAD") | G92: =IFERROR(INDEX(Leads!$A$3:$A$1002,MATCH(91,Leads!$BA$3:$BA$1002,0)),"") | H92: =IF(G92="","",INDEX(Leads!$AQ$3:$AQ$1002,MATCH(91,Leads!$BA$3:$BA$1002,0))) | I92: =IF(G92="","",INDEX(Leads!$AI$3:$AI$1002,MATCH(91,Leads!$BA$3:$BA$1002,0))&"") | J92: =IF(G92="","",INDEX(Leads!$W$3:$W$1002,MATCH(91,Leads!$BA$3:$BA$1002,0)))
A93: =IF(G93="","",INDEX(Leads!$AC$3:$AC$1002,MATCH(92,Leads!$BA$3:$BA$1002,0))) | B93: =IF(G93="","","depot_paye") | C93: =IF(G93="","",YEAR(J93)&"-"&RIGHT("0"&MONTH(J93),2)&"-"&RIGHT("0"&DAY(J93),2)&" "&RIGHT("0"&HOUR(J93),2)&":"&RIGHT("0"&MINUTE(J93),2)&":"&RIGHT("0"&SECOND(J93),2)&IF(AND(J93>=DATE(YEAR(J93),3,8)+MOD(8-WEEKDAY(DATE(YEAR(J93),3,8)),7)+2/24,J93<DATE(YEAR(J93),11,1)+MOD(8-WEEKDAY(DATE(YEAR(J93),11,1)),7)+2/24),"-04:00","-05:00")) | D93: =IF(G93="","",INDEX(Leads!$V$3:$V$1002,MATCH(92,Leads!$BA$3:$BA$1002,0))) | E93: =IF(G93="","","CAD") | G93: =IFERROR(INDEX(Leads!$A$3:$A$1002,MATCH(92,Leads!$BA$3:$BA$1002,0)),"") | H93: =IF(G93="","",INDEX(Leads!$AQ$3:$AQ$1002,MATCH(92,Leads!$BA$3:$BA$1002,0))) | I93: =IF(G93="","",INDEX(Leads!$AI$3:$AI$1002,MATCH(92,Leads!$BA$3:$BA$1002,0))&"") | J93: =IF(G93="","",INDEX(Leads!$W$3:$W$1002,MATCH(92,Leads!$BA$3:$BA$1002,0)))
A94: =IF(G94="","",INDEX(Leads!$AC$3:$AC$1002,MATCH(93,Leads!$BA$3:$BA$1002,0))) | B94: =IF(G94="","","depot_paye") | C94: =IF(G94="","",YEAR(J94)&"-"&RIGHT("0"&MONTH(J94),2)&"-"&RIGHT("0"&DAY(J94),2)&" "&RIGHT("0"&HOUR(J94),2)&":"&RIGHT("0"&MINUTE(J94),2)&":"&RIGHT("0"&SECOND(J94),2)&IF(AND(J94>=DATE(YEAR(J94),3,8)+MOD(8-WEEKDAY(DATE(YEAR(J94),3,8)),7)+2/24,J94<DATE(YEAR(J94),11,1)+MOD(8-WEEKDAY(DATE(YEAR(J94),11,1)),7)+2/24),"-04:00","-05:00")) | D94: =IF(G94="","",INDEX(Leads!$V$3:$V$1002,MATCH(93,Leads!$BA$3:$BA$1002,0))) | E94: =IF(G94="","","CAD") | G94: =IFERROR(INDEX(Leads!$A$3:$A$1002,MATCH(93,Leads!$BA$3:$BA$1002,0)),"") | H94: =IF(G94="","",INDEX(Leads!$AQ$3:$AQ$1002,MATCH(93,Leads!$BA$3:$BA$1002,0))) | I94: =IF(G94="","",INDEX(Leads!$AI$3:$AI$1002,MATCH(93,Leads!$BA$3:$BA$1002,0))&"") | J94: =IF(G94="","",INDEX(Leads!$W$3:$W$1002,MATCH(93,Leads!$BA$3:$BA$1002,0)))
A95: =IF(G95="","",INDEX(Leads!$AC$3:$AC$1002,MATCH(94,Leads!$BA$3:$BA$1002,0))) | B95: =IF(G95="","","depot_paye") | C95: =IF(G95="","",YEAR(J95)&"-"&RIGHT("0"&MONTH(J95),2)&"-"&RIGHT("0"&DAY(J95),2)&" "&RIGHT("0"&HOUR(J95),2)&":"&RIGHT("0"&MINUTE(J95),2)&":"&RIGHT("0"&SECOND(J95),2)&IF(AND(J95>=DATE(YEAR(J95),3,8)+MOD(8-WEEKDAY(DATE(YEAR(J95),3,8)),7)+2/24,J95<DATE(YEAR(J95),11,1)+MOD(8-WEEKDAY(DATE(YEAR(J95),11,1)),7)+2/24),"-04:00","-05:00")) | D95: =IF(G95="","",INDEX(Leads!$V$3:$V$1002,MATCH(94,Leads!$BA$3:$BA$1002,0))) | E95: =IF(G95="","","CAD") | G95: =IFERROR(INDEX(Leads!$A$3:$A$1002,MATCH(94,Leads!$BA$3:$BA$1002,0)),"") | H95: =IF(G95="","",INDEX(Leads!$AQ$3:$AQ$1002,MATCH(94,Leads!$BA$3:$BA$1002,0))) | I95: =IF(G95="","",INDEX(Leads!$AI$3:$AI$1002,MATCH(94,Leads!$BA$3:$BA$1002,0))&"") | J95: =IF(G95="","",INDEX(Leads!$W$3:$W$1002,MATCH(94,Leads!$BA$3:$BA$1002,0)))
A96: =IF(G96="","",INDEX(Leads!$AC$3:$AC$1002,MATCH(95,Leads!$BA$3:$BA$1002,0))) | B96: =IF(G96="","","depot_paye") | C96: =IF(G96="","",YEAR(J96)&"-"&RIGHT("0"&MONTH(J96),2)&"-"&RIGHT("0"&DAY(J96),2)&" "&RIGHT("0"&HOUR(J96),2)&":"&RIGHT("0"&MINUTE(J96),2)&":"&RIGHT("0"&SECOND(J96),2)&IF(AND(J96>=DATE(YEAR(J96),3,8)+MOD(8-WEEKDAY(DATE(YEAR(J96),3,8)),7)+2/24,J96<DATE(YEAR(J96),11,1)+MOD(8-WEEKDAY(DATE(YEAR(J96),11,1)),7)+2/24),"-04:00","-05:00")) | D96: =IF(G96="","",INDEX(Leads!$V$3:$V$1002,MATCH(95,Leads!$BA$3:$BA$1002,0))) | E96: =IF(G96="","","CAD") | G96: =IFERROR(INDEX(Leads!$A$3:$A$1002,MATCH(95,Leads!$BA$3:$BA$1002,0)),"") | H96: =IF(G96="","",INDEX(Leads!$AQ$3:$AQ$1002,MATCH(95,Leads!$BA$3:$BA$1002,0))) | I96: =IF(G96="","",INDEX(Leads!$AI$3:$AI$1002,MATCH(95,Leads!$BA$3:$BA$1002,0))&"") | J96: =IF(G96="","",INDEX(Leads!$W$3:$W$1002,MATCH(95,Leads!$BA$3:$BA$1002,0)))
A97: =IF(G97="","",INDEX(Leads!$AC$3:$AC$1002,MATCH(96,Leads!$BA$3:$BA$1002,0))) | B97: =IF(G97="","","depot_paye") | C97: =IF(G97="","",YEAR(J97)&"-"&RIGHT("0"&MONTH(J97),2)&"-"&RIGHT("0"&DAY(J97),2)&" "&RIGHT("0"&HOUR(J97),2)&":"&RIGHT("0"&MINUTE(J97),2)&":"&RIGHT("0"&SECOND(J97),2)&IF(AND(J97>=DATE(YEAR(J97),3,8)+MOD(8-WEEKDAY(DATE(YEAR(J97),3,8)),7)+2/24,J97<DATE(YEAR(J97),11,1)+MOD(8-WEEKDAY(DATE(YEAR(J97),11,1)),7)+2/24),"-04:00","-05:00")) | D97: =IF(G97="","",INDEX(Leads!$V$3:$V$1002,MATCH(96,Leads!$BA$3:$BA$1002,0))) | E97: =IF(G97="","","CAD") | G97: =IFERROR(INDEX(Leads!$A$3:$A$1002,MATCH(96,Leads!$BA$3:$BA$1002,0)),"") | H97: =IF(G97="","",INDEX(Leads!$AQ$3:$AQ$1002,MATCH(96,Leads!$BA$3:$BA$1002,0))) | I97: =IF(G97="","",INDEX(Leads!$AI$3:$AI$1002,MATCH(96,Leads!$BA$3:$BA$1002,0))&"") | J97: =IF(G97="","",INDEX(Leads!$W$3:$W$1002,MATCH(96,Leads!$BA$3:$BA$1002,0)))
A98: =IF(G98="","",INDEX(Leads!$AC$3:$AC$1002,MATCH(97,Leads!$BA$3:$BA$1002,0))) | B98: =IF(G98="","","depot_paye") | C98: =IF(G98="","",YEAR(J98)&"-"&RIGHT("0"&MONTH(J98),2)&"-"&RIGHT("0"&DAY(J98),2)&" "&RIGHT("0"&HOUR(J98),2)&":"&RIGHT("0"&MINUTE(J98),2)&":"&RIGHT("0"&SECOND(J98),2)&IF(AND(J98>=DATE(YEAR(J98),3,8)+MOD(8-WEEKDAY(DATE(YEAR(J98),3,8)),7)+2/24,J98<DATE(YEAR(J98),11,1)+MOD(8-WEEKDAY(DATE(YEAR(J98),11,1)),7)+2/24),"-04:00","-05:00")) | D98: =IF(G98="","",INDEX(Leads!$V$3:$V$1002,MATCH(97,Leads!$BA$3:$BA$1002,0))) | E98: =IF(G98="","","CAD") | G98: =IFERROR(INDEX(Leads!$A$3:$A$1002,MATCH(97,Leads!$BA$3:$BA$1002,0)),"") | H98: =IF(G98="","",INDEX(Leads!$AQ$3:$AQ$1002,MATCH(97,Leads!$BA$3:$BA$1002,0))) | I98: =IF(G98="","",INDEX(Leads!$AI$3:$AI$1002,MATCH(97,Leads!$BA$3:$BA$1002,0))&"") | J98: =IF(G98="","",INDEX(Leads!$W$3:$W$1002,MATCH(97,Leads!$BA$3:$BA$1002,0)))
A99: =IF(G99="","",INDEX(Leads!$AC$3:$AC$1002,MATCH(98,Leads!$BA$3:$BA$1002,0))) | B99: =IF(G99="","","depot_paye") | C99: =IF(G99="","",YEAR(J99)&"-"&RIGHT("0"&MONTH(J99),2)&"-"&RIGHT("0"&DAY(J99),2)&" "&RIGHT("0"&HOUR(J99),2)&":"&RIGHT("0"&MINUTE(J99),2)&":"&RIGHT("0"&SECOND(J99),2)&IF(AND(J99>=DATE(YEAR(J99),3,8)+MOD(8-WEEKDAY(DATE(YEAR(J99),3,8)),7)+2/24,J99<DATE(YEAR(J99),11,1)+MOD(8-WEEKDAY(DATE(YEAR(J99),11,1)),7)+2/24),"-04:00","-05:00")) | D99: =IF(G99="","",INDEX(Leads!$V$3:$V$1002,MATCH(98,Leads!$BA$3:$BA$1002,0))) | E99: =IF(G99="","","CAD") | G99: =IFERROR(INDEX(Leads!$A$3:$A$1002,MATCH(98,Leads!$BA$3:$BA$1002,0)),"") | H99: =IF(G99="","",INDEX(Leads!$AQ$3:$AQ$1002,MATCH(98,Leads!$BA$3:$BA$1002,0))) | I99: =IF(G99="","",INDEX(Leads!$AI$3:$AI$1002,MATCH(98,Leads!$BA$3:$BA$1002,0))&"") | J99: =IF(G99="","",INDEX(Leads!$W$3:$W$1002,MATCH(98,Leads!$BA$3:$BA$1002,0)))
A100: =IF(G100="","",INDEX(Leads!$AC$3:$AC$1002,MATCH(99,Leads!$BA$3:$BA$1002,0))) | B100: =IF(G100="","","depot_paye") | C100: =IF(G100="","",YEAR(J100)&"-"&RIGHT("0"&MONTH(J100),2)&"-"&RIGHT("0"&DAY(J100),2)&" "&RIGHT("0"&HOUR(J100),2)&":"&RIGHT("0"&MINUTE(J100),2)&":"&RIGHT("0"&SECOND(J100),2)&IF(AND(J100>=DATE(YEAR(J100),3,8)+MOD(8-WEEKDAY(DATE(YEAR(J100),3,8)),7)+2/24,J100<DATE(YEAR(J100),11,1)+MOD(8-WEEKDAY(DATE(YEAR(J100),11,1)),7)+2/24),"-04:00","-05:00")) | D100: =IF(G100="","",INDEX(Leads!$V$3:$V$1002,MATCH(99,Leads!$BA$3:$BA$1002,0))) | E100: =IF(G100="","","CAD") | G100: =IFERROR(INDEX(Leads!$A$3:$A$1002,MATCH(99,Leads!$BA$3:$BA$1002,0)),"") | H100: =IF(G100="","",INDEX(Leads!$AQ$3:$AQ$1002,MATCH(99,Leads!$BA$3:$BA$1002,0))) | I100: =IF(G100="","",INDEX(Leads!$AI$3:$AI$1002,MATCH(99,Leads!$BA$3:$BA$1002,0))&"") | J100: =IF(G100="","",INDEX(Leads!$W$3:$W$1002,MATCH(99,Leads!$BA$3:$BA$1002,0)))
...

Sheet Mode d'emploi
B1: CRM et indicateurs Évenox — mode d'emploi
B2: Sources : operations/tracking-setup.md (pipeline, colonnes, indicateurs), formulaire-qualification.md (routes, pointage), suivi-leads.md (procédure), COMPTE-RENDU.md (budget 300 $/jour, règles couper / augmenter).
B4: Avant de commencer
B5: • Supprimer les 5 lignes EXEMPLE (surlignées en jaune) de la feuille Leads. Pour les voir dans le tableau de bord, mettre « Oui » en C6 de « Tableau de bord ». Les lignes EXEMPLE ne vont jamais dans l'import Google.
B6: • Ne pas saisir dans les colonnes grises : ce sont des formules (délai, pointage, campagne, route calculée, valeur, etc.). Pour supprimer un lead, effacer le contenu des cellules de saisie seulement, ou supprimer la ligne entière.
B8: Feuille « Leads » (1 ligne par demande)
B9: • Colonnes A à AM = colonnes de la feuille « Pipeline » de tracking-setup.md §9, dans le même ordre ; ligne 2 = nom technique (mêmes noms que les propriétés HubSpot et les champs du formulaire).
B10: • Dates : AAAA-MM-JJ HH:MM. Le délai de 1er contact est calculé en minutes ; la ligne devient rouge si le délai dépasse 15 min sur une route A ou B.
B11: • type_evenement, type_client, nb_invites et budget_declare utilisent les codes du formulaire (corpo_party, 2500_4999…) : libellés dans la feuille Listes.
B12: • Route : celle envoyée par le formulaire (A, B, C, D). Si elle est vide, la route calculée selon les règles est utilisée. Orange = la route saisie diffère des règles du formulaire.
B13: • Pointage (0 à 100) = section 7 du formulaire (budget, type de client, invités, date, rôle, échéance). Plus de 70 : rappel immédiat par le propriétaire ; 40 à 70 : 15 min par la personne de garde.
B14: • Étape : mettre à jour immédiatement après chaque contact. Perdu ou Disqualifié exige une raison (cellule rouge sinon).
... B33: • Ce fichier contient des renseignements personnels : le garder dans un espace à accès restreint. Respecter desabonne = oui partout. Supprimer ou anonymiser les leads perdus sans relation d'affaires après 24 mois.

Sheet Listes
A1: Campagnes payées | D1: Source / campagne (saisie manuelle) | F1: type_evenement | J1: type_client | N1: nb_invites | R1: budget_declare | V1: role_decision | Y1: echeance_decision | AB1: route | AE1: etape | AI1: raison_perte | AK1: ville | AM1: utm_source | AO1: utm_medium | AQ1: utm_campaign | AS1: forfait_propose | AU1: oui / non
A2: campagne | B2: $/jour | D2: campagne_manuelle | F2: code | G2: libellé | H2: segment | J2: code | K2: points | L2: libellé | N2: code | O2: points | P2: libellé | R2: code | S2: points | T2: libellé | V2: libellé | W2: points | Y2: libellé | Z2: points | AB2: route | AC2: libellé | AE2: étape | AF2: probabilité | AG2: n° | AI2: raison | AK2: ville | AM2: valeur | AO2: valeur | AQ2: valeur | AS2: forfait | AU2: valeur
A3: Google Search – Corporatif | B3: 100 | D3: Google Search – Corporatif | F3: corpo_party | G3: Party de bureau / des Fêtes | H3: Corporatif | J3: entreprise | K3: 20 | L3: Entreprise | N3: lt30 | O3: 0 | P3: Moins de 30 | R3: lt600 | S3: 0 | T3: Moins de 600 $ | V3: Je décide | W3: 10 | Y3: Cette semaine | Z3: 5 | AB3: A | AC3: Appel prioritaire | AE3: Nouveau | AF3: 0.1 | AG3: 1 | AI3: Perdu – prix | AK3: Sainte-Thérèse | AM3: google | AO3: cpc | AQ3: gads_corpo_fetes | AS3: 5 à 7 (1 195 $) | AU3: oui
A4: Meta – Leads | B4: 80 | D4: Meta – Leads | F4: corpo_5a7 | G4: 5 à 7 ou team building | H4: Corporatif | J4: organisme | K4: 15 | L4: Municipalité, école ou OBNL | N4: 30_74 | O4: 6 | P4: 30 à 74 | R4: 600_999 | S4: 10 | T4: 600 à 999 $ | V4: Je recommande, quelqu'un d'autre approuve | W4: 6 | Y4: D'ici 30 jours | Z4: 3 | AB4: B | AC4: Soumission | AE4: Contacté | AF4: 0.2 | AG4: 2 | AI4: Perdu – concurrent | AK4: Blainville | AM4: bing | AO4: paid_social | AQ4: gads_corpo_5a7 | AS4: Party de bureau (1 995 $) | AU4: non
A5: Google Search – Mariage et privé | B5: 60 | D5: Google Search – Mariage et privé | F5: corpo_gala | G5: Gala, remise de prix ou lancement | H5: Corporatif | J5: particulier | K5: 5 | L5: Particulier ou couple | N5: 75_149 | O5: 12 | P5: 75 à 149 | R5: 1000_2499 | S5: 15 | T5: 1 000 à 2 499 $ | V5: Je compare des options pour un comité | W5: 4 | Y5: Plus tard / je m'informe | Z5: 0 | AB5: C | AC5: Boutique | AE5: Qualifié | AF5: 0.4 | AG5: 3 | AI5: Perdu – date | AK5: Boisbriand | AM5: meta | AO5: email | AQ5: gads_mariage_deco | AS5: Gala Signature (2 495 $)
A6: ChatGPT Ads – Test | B6: 30 | D6: ChatGPT Ads – Test | F6: muni_ecole | G6: Événement municipal ou scolaire | H6: Municipal / scolaire | J6: agence | K6: 20 | L6: Planificateur ou agence | N6: 150p | O6: 15 | P6: 150 et plus | R6: 2500_4999 | S6: 30 | T6: 2 500 à 4 999 $ | AB6: D | AC6: Hors zone | AE6: Proposition envoyée | AF6: 0.5 | AG6: 4 | AI6: Perdu – sans réponse | AK6: Rosemère | AM6: chatgpt | AO6: sms | AQ6: gads_marque | AS6: Décor WOW (899 $)
A7: Microsoft Ads | B7: 20 | D7: Microsoft Ads | F7: mariage | G7: Mariage | H7: Mariage | R7: 5000p | S7: 40 | T7: 5 000 $ et plus | AE7: Négociation | AF7: 0.7 | AG7: 5 | AI7: Perdu – projet annulé | AK7: Lorraine | AM7: courriel | AO7: referral | AQ7: meta_corpo_fetes | AS7: Soirée Signature (1 449 $)
A8: Google Search – Marque | B8: 10 | D8: Google Search – Marque | F8: prive | G8: Autre événement privé : anniversaire, shower… | H8: Privé | R8: inconnu | S8: 10 | T8: Je ne sais pas encore | AE8: Dépôt payé (gagné) | AF8: 1 | AG8: 6 | AI8: Disqualifié – budget < seuil | AK8: Bois-des-Filion | AM8: sms | AO8: organic_local | AQ8: meta_mariage_deco | AS8: Mariage Signature (1 899 $)
D9: Fiche Google (organique) | AE9: Événement livré | AF9: 1 | AG9: 7 | AI9: Disqualifié – hors zone | AK9: Mirabel | AM9: gbp | AQ9: msft_corpo | AS9: Photobooth seul (dès 599 $)
D10: Référence / bouche-à-oreille | AE10: Avis obtenu | AF10: 1 | AG10: 8 | AI10: Disqualifié – hors catalogue | AK10: Saint-Eustache | AM10: weddingwire | AQ10: chatgpt_corpo_fetes | AS10: Sur mesure
D11: Appel direct (non attribué) | AE11: Perdu | AF11: 0 | AG11: — | AI11: Disqualifié – pourriel | AK11: Deux-Montagnes | AM11: yelp | AQ11: chatgpt_mariage
D12: Autre / non payé | AE12: Disqualifié | AF12: 0 | AG12: — | AK12: Terrebonne
AK13: Saint-Jérôme
AK14: Laval
AK15: Montréal – centre-ville
AK16: Montréal – autres arrondissements
AK17: Longueuil / Rive-Sud
AK18: Autre (plus de 40 km)
