Workbook
Name Panier_ref: Cibles!$B$11
Name Marge_brute: Cibles!$B$14
Name Plafond_CPL: Cibles!$B$15
Name Plafond_contrat_pct: Cibles!$B$16
Name Plafond_contrat: Cibles!$B$17
Name ROAS_min: Cibles!$B$18
Name ROAS_point_mort: Cibles!$B$19
Name S_MaxConv: Cibles!$B$22
Name S_CPAcible: Cibles!$B$23
Name S_CPAmaj: Cibles!$B$24
Name S_Qualite: Cibles!$B$25
Name S_Valeur: Cibles!$B$26
Name S_CoupeCPLQ: Cibles!$B$27
Name S_CoupeCPC: Cibles!$B$28
Name S_PctQual: Cibles!$B$29
Name S_PerdueClass: Cibles!$B$30
Name S_HausseCPC: Cibles!$B$31
Name S_DG: Cibles!$B$32
Name S_MS: Cibles!$B$33
Name Liste_campagnes: Cibles!$A$36:$A$42
Name Sem_ref: 'Règles'!$B$6
Name Debut4: 'Règles'!$B$7
Name Debut2: 'Règles'!$B$8

Sheet Saisie hebdo
A1: Saisie hebdomadaire — Google Ads × Notion
A2: Chaque lundi : remplir les cellules jaunes de la semaine précédente (lundi au dimanche). Colonnes grises = calcul automatique, ne pas modifier. Le mois est celui du lundi de la semaine.
A3: REPÈRES | E3: SAISIE (cellules jaunes) — Google Ads : Coût → Part perdue · Notion : Leads → Valeur | P3: CALCULS AUTOMATIQUES
A4: Semaine (lundi) | B4: Mois | C4: Campagne | D4: Remarque | E4: Coût | F4: Impressions | G4: Clics | H4: Conversions Google (formulaire + appels) | I4: Part d'impr. perdue (budget) % | J4: Part d'impr. perdue (classement) % | K4: Leads reçus (Notion) | L4: Leads qualifiés A/B/C | M4: Soumissions envoyées | N4: Contrats gagnés | O4: Valeur des contrats $ | P4: CTR | Q4: CPC moyen | R4: Taux de conversion | S4: CPA Google (coût ÷ conv.) | T4: Coût par lead | U4: Coût par lead qualifié | V4: Coût par contrat | W4: % qualifiés | X4: Taux de conclusion (contrats ÷ soumissions) | Y4: ROAS (valeur ÷ coût)
A5: 46307 | B5: =DATE(YEAR(A5),MONTH(A5),1) | C5: S-FR | Marque | D5: EXEMPLE — à effacer | E5: 45.3 | F5: 210 | G5: 38 | H5: 6 | I5: 0 | J5: 0.12 | K5: 5 | L5: 4 | M5: 3 | N5: 1 | O5: 1995 | P5: =IF(N(F5)=0,"",G5/F5) | Q5: =IF(N(G5)=0,"",E5/G5) | R5: =IF(N(G5)=0,"",H5/G5) | S5: =IF(N(H5)=0,"",E5/H5) | T5: =IF(N(K5)=0,"",E5/K5) | U5: =IF(N(L5)=0,"",E5/L5) | V5: =IF(N(N5)=0,"",E5/N5) | W5: =IF(N(K5)=0,"",L5/K5) | X5: =IF(N(M5)=0,"",N5/M5) | Y5: =IF(N(E5)=0,"",O5/E5)
A6: 46307 | B6: =DATE(YEAR(A6),MONTH(A6),1) | C6: S-FR | Corporatif & Fêtes | D6: EXEMPLE — à effacer | E6: 612.4 | F6: 3150 | G6: 168 | H6: 9 | I6: 0.05 | J6: 0.38 | K6: 8 | L6: 5 | M6: 4 | N6: 1 | O6: 2495 | P6: =IF(N(F6)=0,"",G6/F6) | Q6: =IF(N(G6)=0,"",E6/G6) | R6: =IF(N(G6)=0,"",H6/G6) | S6: =IF(N(H6)=0,"",E6/H6) | T6: =IF(N(K6)=0,"",E6/K6) | U6: =IF(N(L6)=0,"",E6/L6) | V6: =IF(N(N6)=0,"",E6/N6) | W6: =IF(N(K6)=0,"",L6/K6) | X6: =IF(N(M6)=0,"",N6/M6) | Y6: =IF(N(E6)=0,"",O6/E6)
A7: 46307 | B7: =DATE(YEAR(A7),MONTH(A7),1) | C7: S-FR | Événements privés | P7: =IF(N(F7)=0,"",G7/F7) | Q7: =IF(N(G7)=0,"",E7/G7) | R7: =IF(N(G7)=0,"",H7/G7) | S7: =IF(N(H7)=0,"",E7/H7) | T7: =IF(N(K7)=0,"",E7/K7) | U7: =IF(N(L7)=0,"",E7/L7) | V7: =IF(N(N7)=0,"",E7/N7) | W7: =IF(N(K7)=0,"",L7/K7) | X7: =IF(N(M7)=0,"",N7/M7) | Y7: =IF(N(E7)=0,"",O7/E7)
A8: 46307 | B8: =DATE(YEAR(A8),MONTH(A8),1) | C8: S-EN | Corporate Montréal | P8: =IF(N(F8)=0,"",G8/F8) | Q8: =IF(N(G8)=0,"",E8/G8) | R8: =IF(N(G8)=0,"",H8/G8) | S8: =IF(N(H8)=0,"",E8/H8) | T8: =IF(N(K8)=0,"",E8/K8) | U8: =IF(N(L8)=0,"",E8/L8) | V8: =IF(N(N8)=0,"",E8/N8) | W8: =IF(N(K8)=0,"",L8/K8) | X8: =IF(N(M8)=0,"",N8/M8) | Y8: =IF(N(E8)=0,"",O8/E8)
A9: 46307 | B9: =DATE(YEAR(A9),MONTH(A9),1) | C9: S-FR | Québec-Lévis (test) | P9: =IF(N(F9)=0,"",G9/F9) | Q9: =IF(N(G9)=0,"",E9/G9) | R9: =IF(N(G9)=0,"",H9/G9) | S9: =IF(N(H9)=0,"",E9/H9) | T9: =IF(N(K9)=0,"",E9/K9) | U9: =IF(N(L9)=0,"",E9/L9) | V9: =IF(N(N9)=0,"",E9/N9) | W9: =IF(N(K9)=0,"",L9/K9) | X9: =IF(N(M9)=0,"",N9/M9) | Y9: =IF(N(E9)=0,"",O9/E9)
A10: 46307 | B10: =DATE(YEAR(A10),MONTH(A10),1) | C10: Demand Gen | P10: =IF(N(F10)=0,"",G10/F10) | Q10: =IF(N(G10)=0,"",E10/G10) | R10: =IF(N(G10)=0,"",H10/G10) | S10: =IF(N(H10)=0,"",E10/H10) | T10: =IF(N(K10)=0,"",E10/K10) | U10: =IF(N(L10)=0,"",E10/L10) | V10: =IF(N(N10)=0,"",E10/N10) | W10: =IF(N(K10)=0,"",L10/K10) | X10: =IF(N(M10)=0,"",N10/M10) | Y10: =IF(N(E10)=0,"",O10/E10)
A11: 46307 | B11: =DATE(YEAR(A11),MONTH(A11),1) | C11: Microsoft Ads | P11: =IF(N(F11)=0,"",G11/F11) | Q11: =IF(N(G11)=0,"",E11/G11) | R11: =IF(N(G11)=0,"",H11/G11) | S11: =IF(N(H11)=0,"",E11/H11) | T11: =IF(N(K11)=0,"",E11/K11) | U11: =IF(N(L11)=0,"",E11/L11) | V11: =IF(N(N11)=0,"",E11/N11) | W11: =IF(N(K11)=0,"",L11/K11) | X11: =IF(N(M11)=0,"",N11/M11) | Y11: =IF(N(E11)=0,"",O11/E11)
A12: 46314 | B12: =DATE(YEAR(A12),MONTH(A12),1) | C12: S-FR | Marque | P12: =IF(N(F12)=0,"",G12/F12) | Q12: =IF(N(G12)=0,"",E12/G12) | R12: =IF(N(G12)=0,"",H12/G12) | S12: =IF(N(H12)=0,"",E12/H12) | T12: =IF(N(K12)=0,"",E12/K12) | U12: =IF(N(L12)=0,"",E12/L12) | V12: =IF(N(N12)=0,"",E12/N12) | W12: =IF(N(K12)=0,"",L12/K12) | X12: =IF(N(M12)=0,"",N12/M12) | Y12: =IF(N(E12)=0,"",O12/E12)
A13: 46314 | B13: =DATE(YEAR(A13),MONTH(A13),1) | C13: S-FR | Corporatif & Fêtes | P13: =IF(N(F13)=0,"",G13/F13) | Q13: =IF(N(G13)=0,"",E13/G13) | R13: =IF(N(G13)=0,"",H13/G13) | S13: =IF(N(H13)=0,"",E13/H13) | T13: =IF(N(K13)=0,"",E13/K13) | U13: =IF(N(L13)=0,"",E13/L13) | V13: =IF(N(N13)=0,"",E13/N13) | W13: =IF(N(K13)=0,"",L13/K13) | X13: =IF(N(M13)=0,"",N13/M13) | Y13: =IF(N(E13)=0,"",O13/E13)
A14: 46314 | B14: =DATE(YEAR(A14),MONTH(A14),1) | C14: S-FR | Événements privés | P14: =IF(N(F14)=0,"",G14/F14) | Q14: =IF(N(G14)=0,"",E14/G14) | R14: =IF(N(G14)=0,"",H14/G14) | S14: =IF(N(H14)=0,"",E14/H14) | T14: =IF(N(K14)=0,"",E14/K14) | U14: =IF(N(L14)=0,"",E14/L14) | V14: =IF(N(N14)=0,"",E14/N14) | W14: =IF(N(K14)=0,"",L14/K14) | X14: =IF(N(M14)=0,"",N14/M14) | Y14: =IF(N(E14)=0,"",O14/E14)
A15: 46314 | B15: =DATE(YEAR(A15),MONTH(A15),1) | C15: S-EN | Corporate Montréal | P15: =IF(N(F15)=0,"",G15/F15) | Q15: =IF(N(G15)=0,"",E15/G15) | R15: =IF(N(G15)=0,"",H15/G15) | S15: =IF(N(H15)=0,"",E15/H15) | T15: =IF(N(K15)=0,"",E15/K15) | U15: =IF(N(L15)=0,"",E15/L15) | V15: =IF(N(N15)=0,"",E15/N15) | W15: =IF(N(K15)=0,"",L15/K15) | X15: =IF(N(M15)=0,"",N15/M15) | Y15: =IF(N(E15)=0,"",O15/E15)
A16: 46314 | B16: =DATE(YEAR(A16),MONTH(A16),1) | C16: S-FR | Québec-Lévis (test) | P16: =IF(N(F16)=0,"",G16/F16) | Q16: =IF(N(G16)=0,"",E16/G16) | R16: =IF(N(G16)=0,"",H16/G16) | S16: =IF(N(H16)=0,"",E16/H16) | T16: =IF(N(K16)=0,"",E16/K16) | U16: =IF(N(L16)=0,"",E16/L16) | V16: =IF(N(N16)=0,"",E16/N16) | W16: =IF(N(K16)=0,"",L16/K16) | X16: =IF(N(M16)=0,"",N16/M16) | Y16: =IF(N(E16)=0,"",O16/E16)
A17: 46314 | B17: =DATE(YEAR(A17),MONTH(A17),1) | C17: Demand Gen | P17: =IF(N(F17)=0,"",G17/F17) | Q17: =IF(N(G17)=0,"",E17/G17) | R17: =IF(N(G17)=0,"",H17/G17) | S17: =IF(N(H17)=0,"",E17/H17) | T17: =IF(N(K17)=0,"",E17/K17) | U17: =IF(N(L17)=0,"",E17/L17) | V17: =IF(N(N17)=0,"",E17/N17) | W17: =IF(N(K17)=0,"",L17/K17) | X17: =IF(N(M17)=0,"",N17/M17) | Y17: =IF(N(E17)=0,"",O17/E17)
A18: 46314 | B18: =DATE(YEAR(A18),MONTH(A18),1) | C18: Microsoft Ads | P18: =IF(N(F18)=0,"",G18/F18) | Q18: =IF(N(G18)=0,"",E18/G18) | R18: =IF(N(G18)=0,"",H18/G18) | S18: =IF(N(H18)=0,"",E18/H18) | T18: =IF(N(K18)=0,"",E18/K18) | U18: =IF(N(L18)=0,"",E18/L18) | V18: =IF(N(N18)=0,"",E18/N18) | W18: =IF(N(K18)=0,"",L18/K18) | X18: =IF(N(M18)=0,"",N18/M18) | Y18: =IF(N(E18)=0,"",O18/E18)
... A361: 46657 | B361: =DATE(YEAR(A361),MONTH(A361),1) | C361: Microsoft Ads | P361: =IF(N(F361)=0,"",G361/F361) | Q361: =IF(N(G361)=0,"",E361/G361) | R361: =IF(N(G361)=0,"",H361/G361) | S361: =IF(N(H361)=0,"",E361/H361) | T361: =IF(N(K361)=0,"",E361/K361) | U361: =IF(N(L361)=0,"",E361/L361) | V361: =IF(N(N361)=0,"",E361/N361) | W361: =IF(N(K361)=0,"",L361/K361) | X361: =IF(N(M361)=0,"",N361/M361) | Y361: =IF(N(E361)=0,"",O361/E361)

Sheet Synthèse mensuelle
A1: Synthèse mensuelle par campagne
A2: Calculée automatiquement à partir de « Saisie hebdo » (une semaine compte dans le mois de son lundi). Parts d'impressions perdues = moyenne simple des semaines saisies. Ne rien saisir ici.
A4: Mois | B4: Campagne | C4: Coût | D4: Impressions | E4: Clics | F4: Conversions Google | G4: Part perdue budget (moy.) | H4: Part perdue classement (moy.) | I4: Leads reçus | J4: Leads qualifiés A/B/C | K4: Soumissions | L4: Contrats gagnés | M4: Valeur des contrats | N4: CTR | O4: CPC moyen | P4: Taux de conversion | Q4: CPA Google (coût ÷ conv.) | R4: Coût par lead | S4: Coût par lead qualifié | T4: Coût par contrat | U4: % qualifiés | V4: Taux de conclusion (contrats ÷ soumissions) | W4: ROAS (valeur ÷ coût)
A5: 46296 | B5: S-FR | Marque | C5: =SUMIFS('Saisie hebdo'!$E$5:$E$2000,'Saisie hebdo'!$B$5:$B$2000,$A5,'Saisie hebdo'!$C$5:$C$2000,$B5) | D5: =SUMIFS('Saisie hebdo'!$F$5:$F$2000,'Saisie hebdo'!$B$5:$B$2000,$A5,'Saisie hebdo'!$C$5:$C$2000,$B5) | E5: =SUMIFS('Saisie hebdo'!$G$5:$G$2000,'Saisie hebdo'!$B$5:$B$2000,$A5,'Saisie hebdo'!$C$5:$C$2000,$B5) | F5: =SUMIFS('Saisie hebdo'!$H$5:$H$2000,'Saisie hebdo'!$B$5:$B$2000,$A5,'Saisie hebdo'!$C$5:$C$2000,$B5) | G5: =IFERROR(AVERAGEIFS('Saisie hebdo'!$I$5:$I$2000,'Saisie hebdo'!$B$5:$B$2000,$A5,'Saisie hebdo'!$C$5:$C$2000,$B5),"") | H5: =IFERROR(AVERAGEIFS('Saisie hebdo'!$J$5:$J$2000,'Saisie hebdo'!$B$5:$B$2000,$A5,'Saisie hebdo'!$C$5:$C$2000,$B5),"") | I5: =SUMIFS('Saisie hebdo'!$K$5:$K$2000,'Saisie hebdo'!$B$5:$B$2000,$A5,'Saisie hebdo'!$C$5:$C$2000,$B5) | J5: =SUMIFS('Saisie hebdo'!$L$5:$L$2000,'Saisie hebdo'!$B$5:$B$2000,$A5,'Saisie hebdo'!$C$5:$C$2000,$B5) | K5: =SUMIFS('Saisie hebdo'!$M$5:$M$2000,'Saisie hebdo'!$B$5:$B$2000,$A5,'Saisie hebdo'!$C$5:$C$2000,$B5) | L5: =SUMIFS('Saisie hebdo'!$N$5:$N$2000,'Saisie hebdo'!$B$5:$B$2000,$A5,'Saisie hebdo'!$C$5:$C$2000,$B5) | M5: =SUMIFS('Saisie hebdo'!$O$5:$O$2000,'Saisie hebdo'!$B$5:$B$2000,$A5,'Saisie hebdo'!$C$5:$C$2000,$B5) | N5: =IF(N(D5)=0,"",E5/D5) | O5: =IF(N(E5)=0,"",C5/E5) | P5: =IF(N(E5)=0,"",F5/E5) | Q5: =IF(N(F5)=0,"",C5/F5) | R5: =IF(N(I5)=0,"",C5/I5) | S5: =IF(N(J5)=0,"",C5/J5) | T5: =IF(N(L5)=0,"",C5/L5) | U5: =IF(N(I5)=0,"",J5/I5) | V5: =IF(N(K5)=0,"",L5/K5) | W5: =IF(N(C5)=0,"",M5/C5)
A6: 46296 | B6: S-FR | Corporatif & Fêtes | C6: =SUMIFS('Saisie hebdo'!$E$5:$E$2000,'Saisie hebdo'!$B$5:$B$2000,$A6,'Saisie hebdo'!$C$5:$C$2000,$B6) | D6: =SUMIFS('Saisie hebdo'!$F$5:$F$2000,'Saisie hebdo'!$B$5:$B$2000,$A6,'Saisie hebdo'!$C$5:$C$2000,$B6) | E6: =SUMIFS('Saisie hebdo'!$G$5:$G$2000,'Saisie hebdo'!$B$5:$B$2000,$A6,'Saisie hebdo'!$C$5:$C$2000,$B6) | F6: =SUMIFS('Saisie hebdo'!$H$5:$H$2000,'Saisie hebdo'!$B$5:$B$2000,$A6,'Saisie hebdo'!$C$5:$C$2000,$B6) | G6: =IFERROR(AVERAGEIFS('Saisie hebdo'!$I$5:$I$2000,'Saisie hebdo'!$B$5:$B$2000,$A6,'Saisie hebdo'!$C$5:$C$2000,$B6),"") | H6: =IFERROR(AVERAGEIFS('Saisie hebdo'!$J$5:$J$2000,'Saisie hebdo'!$B$5:$B$2000,$A6,'Saisie hebdo'!$C$5:$C$2000,$B6),"") | I6: =SUMIFS('Saisie hebdo'!$K$5:$K$2000,'Saisie hebdo'!$B$5:$B$2000,$A6,'Saisie hebdo'!$C$5:$C$2000,$B6) | J6: =SUMIFS('Saisie hebdo'!$L$5:$L$2000,'Saisie hebdo'!$B$5:$B$2000,$A6,'Saisie hebdo'!$C$5:$C$2000,$B6) | K6: =SUMIFS('Saisie hebdo'!$M$5:$M$2000,'Saisie hebdo'!$B$5:$B$2000,$A6,'Saisie hebdo'!$C$5:$C$2000,$B6) | L6: =SUMIFS('Saisie hebdo'!$N$5:$N$2000,'Saisie hebdo'!$B$5:$B$2000,$A6,'Saisie hebdo'!$C$5:$C$2000,$B6) | M6: =SUMIFS('Saisie hebdo'!$O$5:$O$2000,'Saisie hebdo'!$B$5:$B$2000,$A6,'Saisie hebdo'!$C$5:$C$2000,$B6) | N6: =IF(N(D6)=0,"",E6/D6) | O6: =IF(N(E6)=0,"",C6/E6) | P6: =IF(N(E6)=0,"",F6/E6) | Q6: =IF(N(F6)=0,"",C6/F6) | R6: =IF(N(I6)=0,"",C6/I6) | S6: =IF(N(J6)=0,"",C6/J6) | T6: =IF(N(L6)=0,"",C6/L6) | U6: =IF(N(I6)=0,"",J6/I6) | V6: =IF(N(K6)=0,"",L6/K6) | W6: =IF(N(C6)=0,"",M6/C6)
A7: 46296 | B7: S-FR | Événements privés | C7: =SUMIFS('Saisie hebdo'!$E$5:$E$2000,'Saisie hebdo'!$B$5:$B$2000,$A7,'Saisie hebdo'!$C$5:$C$2000,$B7) | D7: =SUMIFS('Saisie hebdo'!$F$5:$F$2000,'Saisie hebdo'!$B$5:$B$2000,$A7,'Saisie hebdo'!$C$5:$C$2000,$B7) | E7: =SUMIFS('Saisie hebdo'!$G$5:$G$2000,'Saisie hebdo'!$B$5:$B$2000,$A7,'Saisie hebdo'!$C$5:$C$2000,$B7) | F7: =SUMIFS('Saisie hebdo'!$H$5:$H$2000,'Saisie hebdo'!$B$5:$B$2000,$A7,'Saisie hebdo'!$C$5:$C$2000,$B7) | G7: =IFERROR(AVERAGEIFS('Saisie hebdo'!$I$5:$I$2000,'Saisie hebdo'!$B$5:$B$2000,$A7,'Saisie hebdo'!$C$5:$C$2000,$B7),"") | H7: =IFERROR(AVERAGEIFS('Saisie hebdo'!$J$5:$J$2000,'Saisie hebdo'!$B$5:$B$2000,$A7,'Saisie hebdo'!$C$5:$C$2000,$B7),"") | I7: =SUMIFS('Saisie hebdo'!$K$5:$K$2000,'Saisie hebdo'!$B$5:$B$2000,$A7,'Saisie hebdo'!$C$5:$C$2000,$B7) | J7: =SUMIFS('Saisie hebdo'!$L$5:$L$2000,'Saisie hebdo'!$B$5:$B$2000,$A7,'Saisie hebdo'!$C$5:$C$2000,$B7) | K7: =SUMIFS('Saisie hebdo'!$M$5:$M$2000,'Saisie hebdo'!$B$5:$B$2000,$A7,'Saisie hebdo'!$C$5:$C$2000,$B7) | L7: =SUMIFS('Saisie hebdo'!$N$5:$N$2000,'Saisie hebdo'!$B$5:$B$2000,$A7,'Saisie hebdo'!$C$5:$C$2000,$B7) | M7: =SUMIFS('Saisie hebdo'!$O$5:$O$2000,'Saisie hebdo'!$B$5:$B$2000,$A7,'Saisie hebdo'!$C$5:$C$2000,$B7) | N7: =IF(N(D7)=0,"",E7/D7) | O7: =IF(N(E7)=0,"",C7/E7) | P7: =IF(N(E7)=0,"",F7/E7) | Q7: =IF(N(F7)=0,"",C7/F7) | R7: =IF(N(I7)=0,"",C7/I7) | S7: =IF(N(J7)=0,"",C7/J7) | T7: =IF(N(L7)=0,"",C7/L7) | U7: =IF(N(I7)=0,"",J7/I7) | V7: =IF(N(K7)=0,"",L7/K7) | W7: =IF(N(C7)=0,"",M7/C7)
A8: 46296 | B8: S-EN | Corporate Montréal | C8: =SUMIFS('Saisie hebdo'!$E$5:$E$2000,'Saisie hebdo'!$B$5:$B$2000,$A8,'Saisie hebdo'!$C$5:$C$2000,$B8) | D8: =SUMIFS('Saisie hebdo'!$F$5:$F$2000,'Saisie hebdo'!$B$5:$B$2000,$A8,'Saisie hebdo'!$C$5:$C$2000,$B8) | E8: =SUMIFS('Saisie hebdo'!$G$5:$G$2000,'Saisie hebdo'!$B$5:$B$2000,$A8,'Saisie hebdo'!$C$5:$C$2000,$B8) | F8: =SUMIFS('Saisie hebdo'!$H$5:$H$2000,'Saisie hebdo'!$B$5:$B$2000,$A8,'Saisie hebdo'!$C$5:$C$2000,$B8) | G8: =IFERROR(AVERAGEIFS('Saisie hebdo'!$I$5:$I$2000,'Saisie hebdo'!$B$5:$B$2000,$A8,'Saisie hebdo'!$C$5:$C$2000,$B8),"") | H8: =IFERROR(AVERAGEIFS('Saisie hebdo'!$J$5:$J$2000,'Saisie hebdo'!$B$5:$B$2000,$A8,'Saisie hebdo'!$C$5:$C$2000,$B8),"") | I8: =SUMIFS('Saisie hebdo'!$K$5:$K$2000,'Saisie hebdo'!$B$5:$B$2000,$A8,'Saisie hebdo'!$C$5:$C$2000,$B8) | J8: =SUMIFS('Saisie hebdo'!$L$5:$L$2000,'Saisie hebdo'!$B$5:$B$2000,$A8,'Saisie hebdo'!$C$5:$C$2000,$B8) | K8: =SUMIFS('Saisie hebdo'!$M$5:$M$2000,'Saisie hebdo'!$B$5:$B$2000,$A8,'Saisie hebdo'!$C$5:$C$2000,$B8) | L8: =SUMIFS('Saisie hebdo'!$N$5:$N$2000,'Saisie hebdo'!$B$5:$B$2000,$A8,'Saisie hebdo'!$C$5:$C$2000,$B8) | M8: =SUMIFS('Saisie hebdo'!$O$5:$O$2000,'Saisie hebdo'!$B$5:$B$2000,$A8,'Saisie hebdo'!$C$5:$C$2000,$B8) | N8: =IF(N(D8)=0,"",E8/D8) | O8: =IF(N(E8)=0,"",C8/E8) | P8: =IF(N(E8)=0,"",F8/E8) | Q8: =IF(N(F8)=0,"",C8/F8) | R8: =IF(N(I8)=0,"",C8/I8) | S8: =IF(N(J8)=0,"",C8/J8) | T8: =IF(N(L8)=0,"",C8/L8) | U8: =IF(N(I8)=0,"",J8/I8) | V8: =IF(N(K8)=0,"",L8/K8) | W8: =IF(N(C8)=0,"",M8/C8)
A9: 46296 | B9: S-FR | Québec-Lévis (test) | C9: =SUMIFS('Saisie hebdo'!$E$5:$E$2000,'Saisie hebdo'!$B$5:$B$2000,$A9,'Saisie hebdo'!$C$5:$C$2000,$B9) | D9: =SUMIFS('Saisie hebdo'!$F$5:$F$2000,'Saisie hebdo'!$B$5:$B$2000,$A9,'Saisie hebdo'!$C$5:$C$2000,$B9) | E9: =SUMIFS('Saisie hebdo'!$G$5:$G$2000,'Saisie hebdo'!$B$5:$B$2000,$A9,'Saisie hebdo'!$C$5:$C$2000,$B9) | F9: =SUMIFS('Saisie hebdo'!$H$5:$H$2000,'Saisie hebdo'!$B$5:$B$2000,$A9,'Saisie hebdo'!$C$5:$C$2000,$B9) | G9: =IFERROR(AVERAGEIFS('Saisie hebdo'!$I$5:$I$2000,'Saisie hebdo'!$B$5:$B$2000,$A9,'Saisie hebdo'!$C$5:$C$2000,$B9),"") | H9: =IFERROR(AVERAGEIFS('Saisie hebdo'!$J$5:$J$2000,'Saisie hebdo'!$B$5:$B$2000,$A9,'Saisie hebdo'!$C$5:$C$2000,$B9),"") | I9: =SUMIFS('Saisie hebdo'!$K$5:$K$2000,'Saisie hebdo'!$B$5:$B$2000,$A9,'Saisie hebdo'!$C$5:$C$2000,$B9) | J9: =SUMIFS('Saisie hebdo'!$L$5:$L$2000,'Saisie hebdo'!$B$5:$B$2000,$A9,'Saisie hebdo'!$C$5:$C$2000,$B9) | K9: =SUMIFS('Saisie hebdo'!$M$5:$M$2000,'Saisie hebdo'!$B$5:$B$2000,$A9,'Saisie hebdo'!$C$5:$C$2000,$B9) | L9: =SUMIFS('Saisie hebdo'!$N$5:$N$2000,'Saisie hebdo'!$B$5:$B$2000,$A9,'Saisie hebdo'!$C$5:$C$2000,$B9) | M9: =SUMIFS('Saisie hebdo'!$O$5:$O$2000,'Saisie hebdo'!$B$5:$B$2000,$A9,'Saisie hebdo'!$C$5:$C$2000,$B9) | N9: =IF(N(D9)=0,"",E9/D9) | O9: =IF(N(E9)=0,"",C9/E9) | P9: =IF(N(E9)=0,"",F9/E9) | Q9: =IF(N(F9)=0,"",C9/F9) | R9: =IF(N(I9)=0,"",C9/I9) | S9: =IF(N(J9)=0,"",C9/J9) | T9: =IF(N(L9)=0,"",C9/L9) | U9: =IF(N(I9)=0,"",J9/I9) | V9: =IF(N(K9)=0,"",L9/K9) | W9: =IF(N(C9)=0,"",M9/C9)
A10: 46296 | B10: Demand Gen | C10: =SUMIFS('Saisie hebdo'!$E$5:$E$2000,'Saisie hebdo'!$B$5:$B$2000,$A10,'Saisie hebdo'!$C$5:$C$2000,$B10) | D10: =SUMIFS('Saisie hebdo'!$F$5:$F$2000,'Saisie hebdo'!$B$5:$B$2000,$A10,'Saisie hebdo'!$C$5:$C$2000,$B10) | E10: =SUMIFS('Saisie hebdo'!$G$5:$G$2000,'Saisie hebdo'!$B$5:$B$2000,$A10,'Saisie hebdo'!$C$5:$C$2000,$B10) | F10: =SUMIFS('Saisie hebdo'!$H$5:$H$2000,'Saisie hebdo'!$B$5:$B$2000,$A10,'Saisie hebdo'!$C$5:$C$2000,$B10) | G10: =IFERROR(AVERAGEIFS('Saisie hebdo'!$I$5:$I$2000,'Saisie hebdo'!$B$5:$B$2000,$A10,'Saisie hebdo'!$C$5:$C$2000,$B10),"") | H10: =IFERROR(AVERAGEIFS('Saisie hebdo'!$J$5:$J$2000,'Saisie hebdo'!$B$5:$B$2000,$A10,'Saisie hebdo'!$C$5:$C$2000,$B10),"") | I10: =SUMIFS('Saisie hebdo'!$K$5:$K$2000,'Saisie hebdo'!$B$5:$B$2000,$A10,'Saisie hebdo'!$C$5:$C$2000,$B10) | J10: =SUMIFS('Saisie hebdo'!$L$5:$L$2000,'Saisie hebdo'!$B$5:$B$2000,$A10,'Saisie hebdo'!$C$5:$C$2000,$B10) | K10: =SUMIFS('Saisie hebdo'!$M$5:$M$2000,'Saisie hebdo'!$B$5:$B$2000,$A10,'Saisie hebdo'!$C$5:$C$2000,$B10) | L10: =SUMIFS('Saisie hebdo'!$N$5:$N$2000,'Saisie hebdo'!$B$5:$B$2000,$A10,'Saisie hebdo'!$C$5:$C$2000,$B10) | M10: =SUMIFS('Saisie hebdo'!$O$5:$O$2000,'Saisie hebdo'!$B$5:$B$2000,$A10,'Saisie hebdo'!$C$5:$C$2000,$B10) | N10: =IF(N(D10)=0,"",E10/D10) | O10: =IF(N(E10)=0,"",C10/E10) | P10: =IF(N(E10)=0,"",F10/E10) | Q10: =IF(N(F10)=0,"",C10/F10) | R10: =IF(N(I10)=0,"",C10/I10) | S10: =IF(N(J10)=0,"",C10/J10) | T10: =IF(N(L10)=0,"",C10/L10) | U10: =IF(N(I10)=0,"",J10/I10) | V10: =IF(N(K10)=0,"",L10/K10) | W10: =IF(N(C10)=0,"",M10/C10)
A11: 46296 | B11: Microsoft Ads | C11: =SUMIFS('Saisie hebdo'!$E$5:$E$2000,'Saisie hebdo'!$B$5:$B$2000,$A11,'Saisie hebdo'!$C$5:$C$2000,$B11) | D11: =SUMIFS('Saisie hebdo'!$F$5:$F$2000,'Saisie hebdo'!$B$5:$B$2000,$A11,'Saisie hebdo'!$C$5:$C$2000,$B11) | E11: =SUMIFS('Saisie hebdo'!$G$5:$G$2000,'Saisie hebdo'!$B$5:$B$2000,$A11,'Saisie hebdo'!$C$5:$C$2000,$B11) | F11: =SUMIFS('Saisie hebdo'!$H$5:$H$2000,'Saisie hebdo'!$B$5:$B$2000,$A11,'Saisie hebdo'!$C$5:$C$2000,$B11) | G11: =IFERROR(AVERAGEIFS('Saisie hebdo'!$I$5:$I$2000,'Saisie hebdo'!$B$5:$B$2000,$A11,'Saisie hebdo'!$C$5:$C$2000,$B11),"") | H11: =IFERROR(AVERAGEIFS('Saisie hebdo'!$J$5:$J$2000,'Saisie hebdo'!$B$5:$B$2000,$A11,'Saisie hebdo'!$C$5:$C$2000,$B11),"") | I11: =SUMIFS('Saisie hebdo'!$K$5:$K$2000,'Saisie hebdo'!$B$5:$B$2000,$A11,'Saisie hebdo'!$C$5:$C$2000,$B11) | J11: =SUMIFS('Saisie hebdo'!$L$5:$L$2000,'Saisie hebdo'!$B$5:$B$2000,$A11,'Saisie hebdo'!$C$5:$C$2000,$B11) | K11: =SUMIFS('Saisie hebdo'!$M$5:$M$2000,'Saisie hebdo'!$B$5:$B$2000,$A11,'Saisie hebdo'!$C$5:$C$2000,$B11) | L11: =SUMIFS('Saisie hebdo'!$N$5:$N$2000,'Saisie hebdo'!$B$5:$B$2000,$A11,'Saisie hebdo'!$C$5:$C$2000,$B11) | M11: =SUMIFS('Saisie hebdo'!$O$5:$O$2000,'Saisie hebdo'!$B$5:$B$2000,$A11,'Saisie hebdo'!$C$5:$C$2000,$B11) | N11: =IF(N(D11)=0,"",E11/D11) | O11: =IF(N(E11)=0,"",C11/E11) | P11: =IF(N(E11)=0,"",F11/E11) | Q11: =IF(N(F11)=0,"",C11/F11) | R11: =IF(N(I11)=0,"",C11/I11) | S11: =IF(N(J11)=0,"",C11/J11) | T11: =IF(N(L11)=0,"",C11/L11) | U11: =IF(N(I11)=0,"",J11/I11) | V11: =IF(N(K11)=0,"",L11/K11) | W11: =IF(N(C11)=0,"",M11/C11)
A12: 46296 | B12: Total du compte | C12: =SUMIFS('Saisie hebdo'!$E$5:$E$2000,'Saisie hebdo'!$B$5:$B$2000,$A12) | D12: =SUMIFS('Saisie hebdo'!$F$5:$F$2000,'Saisie hebdo'!$B$5:$B$2000,$A12) | E12: =SUMIFS('Saisie hebdo'!$G$5:$G$2000,'Saisie hebdo'!$B$5:$B$2000,$A12) | F12: =SUMIFS('Saisie hebdo'!$H$5:$H$2000,'Saisie hebdo'!$B$5:$B$2000,$A12) | G12: =IFERROR(AVERAGEIFS('Saisie hebdo'!$I$5:$I$2000,'Saisie hebdo'!$B$5:$B$2000,$A12),"") | H12: =IFERROR(AVERAGEIFS('Saisie hebdo'!$J$5:$J$2000,'Saisie hebdo'!$B$5:$B$2000,$A12),"") | I12: =SUMIFS('Saisie hebdo'!$K$5:$K$2000,'Saisie hebdo'!$B$5:$B$2000,$A12) | J12: =SUMIFS('Saisie hebdo'!$L$5:$L$2000,'Saisie hebdo'!$B$5:$B$2000,$A12) | K12: =SUMIFS('Saisie hebdo'!$M$5:$M$2000,'Saisie hebdo'!$B$5:$B$2000,$A12) | L12: =SUMIFS('Saisie hebdo'!$N$5:$N$2000,'Saisie hebdo'!$B$5:$B$2000,$A12) | M12: =SUMIFS('Saisie hebdo'!$O$5:$O$2000,'Saisie hebdo'!$B$5:$B$2000,$A12) | N12: =IF(N(D12)=0,"",E12/D12) | O12: =IF(N(E12)=0,"",C12/E12) | P12: =IF(N(E12)=0,"",F12/E12) | Q12: =IF(N(F12)=0,"",C12/F12) | R12: =IF(N(I12)=0,"",C12/I12) | S12: =IF(N(J12)=0,"",C12/J12) | T12: =IF(N(L12)=0,"",C12/L12) | U12: =IF(N(I12)=0,"",J12/I12) | V12: =IF(N(K12)=0,"",L12/K12) | W12: =IF(N(C12)=0,"",M12/C12)
A13: 46327 | B13: S-FR | Marque | C13: =SUMIFS('Saisie hebdo'!$E$5:$E$2000,'Saisie hebdo'!$B$5:$B$2000,$A13,'Saisie hebdo'!$C$5:$C$2000,$B13) | D13: =SUMIFS('Saisie hebdo'!$F$5:$F$2000,'Saisie hebdo'!$B$5:$B$2000,$A13,'Saisie hebdo'!$C$5:$C$2000,$B13) | E13: =SUMIFS('Saisie hebdo'!$G$5:$G$2000,'Saisie hebdo'!$B$5:$B$2000,$A13,'Saisie hebdo'!$C$5:$C$2000,$B13) | F13: =SUMIFS('Saisie hebdo'!$H$5:$H$2000,'Saisie hebdo'!$B$5:$B$2000,$A13,'Saisie hebdo'!$C$5:$C$2000,$B13) | G13: =IFERROR(AVERAGEIFS('Saisie hebdo'!$I$5:$I$2000,'Saisie hebdo'!$B$5:$B$2000,$A13,'Saisie hebdo'!$C$5:$C$2000,$B13),"") | H13: =IFERROR(AVERAGEIFS('Saisie hebdo'!$J$5:$J$2000,'Saisie hebdo'!$B$5:$B$2000,$A13,'Saisie hebdo'!$C$5:$C$2000,$B13),"") | I13: =SUMIFS('Saisie hebdo'!$K$5:$K$2000,'Saisie hebdo'!$B$5:$B$2000,$A13,'Saisie hebdo'!$C$5:$C$2000,$B13) | J13: =SUMIFS('Saisie hebdo'!$L$5:$L$2000,'Saisie hebdo'!$B$5:$B$2000,$A13,'Saisie hebdo'!$C$5:$C$2000,$B13) | K13: =SUMIFS('Saisie hebdo'!$M$5:$M$2000,'Saisie hebdo'!$B$5:$B$2000,$A13,'Saisie hebdo'!$C$5:$C$2000,$B13) | L13: =SUMIFS('Saisie hebdo'!$N$5:$N$2000,'Saisie hebdo'!$B$5:$B$2000,$A13,'Saisie hebdo'!$C$5:$C$2000,$B13) | M13: =SUMIFS('Saisie hebdo'!$O$5:$O$2000,'Saisie hebdo'!$B$5:$B$2000,$A13,'Saisie hebdo'!$C$5:$C$2000,$B13) | N13: =IF(N(D13)=0,"",E13/D13) | O13: =IF(N(E13)=0,"",C13/E13) | P13: =IF(N(E13)=0,"",F13/E13) | Q13: =IF(N(F13)=0,"",C13/F13) | R13: =IF(N(I13)=0,"",C13/I13) | S13: =IF(N(J13)=0,"",C13/J13) | T13: =IF(N(L13)=0,"",C13/L13) | U13: =IF(N(I13)=0,"",J13/I13) | V13: =IF(N(K13)=0,"",L13/K13) | W13: =IF(N(C13)=0,"",M13/C13)
A14: 46327 | B14: S-FR | Corporatif & Fêtes | C14: =SUMIFS('Saisie hebdo'!$E$5:$E$2000,'Saisie hebdo'!$B$5:$B$2000,$A14,'Saisie hebdo'!$C$5:$C$2000,$B14) | D14: =SUMIFS('Saisie hebdo'!$F$5:$F$2000,'Saisie hebdo'!$B$5:$B$2000,$A14,'Saisie hebdo'!$C$5:$C$2000,$B14) | E14: =SUMIFS('Saisie hebdo'!$G$5:$G$2000,'Saisie hebdo'!$B$5:$B$2000,$A14,'Saisie hebdo'!$C$5:$C$2000,$B14) | F14: =SUMIFS('Saisie hebdo'!$H$5:$H$2000,'Saisie hebdo'!$B$5:$B$2000,$A14,'Saisie hebdo'!$C$5:$C$2000,$B14) | G14: =IFERROR(AVERAGEIFS('Saisie hebdo'!$I$5:$I$2000,'Saisie hebdo'!$B$5:$B$2000,$A14,'Saisie hebdo'!$C$5:$C$2000,$B14),"") | H14: =IFERROR(AVERAGEIFS('Saisie hebdo'!$J$5:$J$2000,'Saisie hebdo'!$B$5:$B$2000,$A14,'Saisie hebdo'!$C$5:$C$2000,$B14),"") | I14: =SUMIFS('Saisie hebdo'!$K$5:$K$2000,'Saisie hebdo'!$B$5:$B$2000,$A14,'Saisie hebdo'!$C$5:$C$2000,$B14) | J14: =SUMIFS('Saisie hebdo'!$L$5:$L$2000,'Saisie hebdo'!$B$5:$B$2000,$A14,'Saisie hebdo'!$C$5:$C$2000,$B14) | K14: =SUMIFS('Saisie hebdo'!$M$5:$M$2000,'Saisie hebdo'!$B$5:$B$2000,$A14,'Saisie hebdo'!$C$5:$C$2000,$B14) | L14: =SUMIFS('Saisie hebdo'!$N$5:$N$2000,'Saisie hebdo'!$B$5:$B$2000,$A14,'Saisie hebdo'!$C$5:$C$2000,$B14) | M14: =SUMIFS('Saisie hebdo'!$O$5:$O$2000,'Saisie hebdo'!$B$5:$B$2000,$A14,'Saisie hebdo'!$C$5:$C$2000,$B14) | N14: =IF(N(D14)=0,"",E14/D14) | O14: =IF(N(E14)=0,"",C14/E14) | P14: =IF(N(E14)=0,"",F14/E14) | Q14: =IF(N(F14)=0,"",C14/F14) | R14: =IF(N(I14)=0,"",C14/I14) | S14: =IF(N(J14)=0,"",C14/J14) | T14: =IF(N(L14)=0,"",C14/L14) | U14: =IF(N(I14)=0,"",J14/I14) | V14: =IF(N(K14)=0,"",L14/K14) | W14: =IF(N(C14)=0,"",M14/C14)
A15: 46327 | B15: S-FR | Événements privés | C15: =SUMIFS('Saisie hebdo'!$E$5:$E$2000,'Saisie hebdo'!$B$5:$B$2000,$A15,'Saisie hebdo'!$C$5:$C$2000,$B15) | D15: =SUMIFS('Saisie hebdo'!$F$5:$F$2000,'Saisie hebdo'!$B$5:$B$2000,$A15,'Saisie hebdo'!$C$5:$C$2000,$B15) | E15: =SUMIFS('Saisie hebdo'!$G$5:$G$2000,'Saisie hebdo'!$B$5:$B$2000,$A15,'Saisie hebdo'!$C$5:$C$2000,$B15) | F15: =SUMIFS('Saisie hebdo'!$H$5:$H$2000,'Saisie hebdo'!$B$5:$B$2000,$A15,'Saisie hebdo'!$C$5:$C$2000,$B15) | G15: =IFERROR(AVERAGEIFS('Saisie hebdo'!$I$5:$I$2000,'Saisie hebdo'!$B$5:$B$2000,$A15,'Saisie hebdo'!$C$5:$C$2000,$B15),"") | H15: =IFERROR(AVERAGEIFS('Saisie hebdo'!$J$5:$J$2000,'Saisie hebdo'!$B$5:$B$2000,$A15,'Saisie hebdo'!$C$5:$C$2000,$B15),"") | I15: =SUMIFS('Saisie hebdo'!$K$5:$K$2000,'Saisie hebdo'!$B$5:$B$2000,$A15,'Saisie hebdo'!$C$5:$C$2000,$B15) | J15: =SUMIFS('Saisie hebdo'!$L$5:$L$2000,'Saisie hebdo'!$B$5:$B$2000,$A15,'Saisie hebdo'!$C$5:$C$2000,$B15) | K15: =SUMIFS('Saisie hebdo'!$M$5:$M$2000,'Saisie hebdo'!$B$5:$B$2000,$A15,'Saisie hebdo'!$C$5:$C$2000,$B15) | L15: =SUMIFS('Saisie hebdo'!$N$5:$N$2000,'Saisie hebdo'!$B$5:$B$2000,$A15,'Saisie hebdo'!$C$5:$C$2000,$B15) | M15: =SUMIFS('Saisie hebdo'!$O$5:$O$2000,'Saisie hebdo'!$B$5:$B$2000,$A15,'Saisie hebdo'!$C$5:$C$2000,$B15) | N15: =IF(N(D15)=0,"",E15/D15) | O15: =IF(N(E15)=0,"",C15/E15) | P15: =IF(N(E15)=0,"",F15/E15) | Q15: =IF(N(F15)=0,"",C15/F15) | R15: =IF(N(I15)=0,"",C15/I15) | S15: =IF(N(J15)=0,"",C15/J15) | T15: =IF(N(L15)=0,"",C15/L15) | U15: =IF(N(I15)=0,"",J15/I15) | V15: =IF(N(K15)=0,"",L15/K15) | W15: =IF(N(C15)=0,"",M15/C15)
A16: 46327 | B16: S-EN | Corporate Montréal | C16: =SUMIFS('Saisie hebdo'!$E$5:$E$2000,'Saisie hebdo'!$B$5:$B$2000,$A16,'Saisie hebdo'!$C$5:$C$2000,$B16) | D16: =SUMIFS('Saisie hebdo'!$F$5:$F$2000,'Saisie hebdo'!$B$5:$B$2000,$A16,'Saisie hebdo'!$C$5:$C$2000,$B16) | E16: =SUMIFS('Saisie hebdo'!$G$5:$G$2000,'Saisie hebdo'!$B$5:$B$2000,$A16,'Saisie hebdo'!$C$5:$C$2000,$B16) | F16: =SUMIFS('Saisie hebdo'!$H$5:$H$2000,'Saisie hebdo'!$B$5:$B$2000,$A16,'Saisie hebdo'!$C$5:$C$2000,$B16) | G16: =IFERROR(AVERAGEIFS('Saisie hebdo'!$I$5:$I$2000,'Saisie hebdo'!$B$5:$B$2000,$A16,'Saisie hebdo'!$C$5:$C$2000,$B16),"") | H16: =IFERROR(AVERAGEIFS('Saisie hebdo'!$J$5:$J$2000,'Saisie hebdo'!$B$5:$B$2000,$A16,'Saisie hebdo'!$C$5:$C$2000,$B16),"") | I16: =SUMIFS('Saisie hebdo'!$K$5:$K$2000,'Saisie hebdo'!$B$5:$B$2000,$A16,'Saisie hebdo'!$C$5:$C$2000,$B16) | J16: =SUMIFS('Saisie hebdo'!$L$5:$L$2000,'Saisie hebdo'!$B$5:$B$2000,$A16,'Saisie hebdo'!$C$5:$C$2000,$B16) | K16: =SUMIFS('Saisie hebdo'!$M$5:$M$2000,'Saisie hebdo'!$B$5:$B$2000,$A16,'Saisie hebdo'!$C$5:$C$2000,$B16) | L16: =SUMIFS('Saisie hebdo'!$N$5:$N$2000,'Saisie hebdo'!$B$5:$B$2000,$A16,'Saisie hebdo'!$C$5:$C$2000,$B16) | M16: =SUMIFS('Saisie hebdo'!$O$5:$O$2000,'Saisie hebdo'!$B$5:$B$2000,$A16,'Saisie hebdo'!$C$5:$C$2000,$B16) | N16: =IF(N(D16)=0,"",E16/D16) | O16: =IF(N(E16)=0,"",C16/E16) | P16: =IF(N(E16)=0,"",F16/E16) | Q16: =IF(N(F16)=0,"",C16/F16) | R16: =IF(N(I16)=0,"",C16/I16) | S16: =IF(N(J16)=0,"",C16/J16) | T16: =IF(N(L16)=0,"",C16/L16) | U16: =IF(N(I16)=0,"",J16/I16) | V16: =IF(N(K16)=0,"",L16/K16) | W16: =IF(N(C16)=0,"",M16/C16)
A17: 46327 | B17: S-FR | Québec-Lévis (test) | C17: =SUMIFS('Saisie hebdo'!$E$5:$E$2000,'Saisie hebdo'!$B$5:$B$2000,$A17,'Saisie hebdo'!$C$5:$C$2000,$B17) | D17: =SUMIFS('Saisie hebdo'!$F$5:$F$2000,'Saisie hebdo'!$B$5:$B$2000,$A17,'Saisie hebdo'!$C$5:$C$2000,$B17) | E17: =SUMIFS('Saisie hebdo'!$G$5:$G$2000,'Saisie hebdo'!$B$5:$B$2000,$A17,'Saisie hebdo'!$C$5:$C$2000,$B17) | F17: =SUMIFS('Saisie hebdo'!$H$5:$H$2000,'Saisie hebdo'!$B$5:$B$2000,$A17,'Saisie hebdo'!$C$5:$C$2000,$B17) | G17: =IFERROR(AVERAGEIFS('Saisie hebdo'!$I$5:$I$2000,'Saisie hebdo'!$B$5:$B$2000,$A17,'Saisie hebdo'!$C$5:$C$2000,$B17),"") | H17: =IFERROR(AVERAGEIFS('Saisie hebdo'!$J$5:$J$2000,'Saisie hebdo'!$B$5:$B$2000,$A17,'Saisie hebdo'!$C$5:$C$2000,$B17),"") | I17: =SUMIFS('Saisie hebdo'!$K$5:$K$2000,'Saisie hebdo'!$B$5:$B$2000,$A17,'Saisie hebdo'!$C$5:$C$2000,$B17) | J17: =SUMIFS('Saisie hebdo'!$L$5:$L$2000,'Saisie hebdo'!$B$5:$B$2000,$A17,'Saisie hebdo'!$C$5:$C$2000,$B17) | K17: =SUMIFS('Saisie hebdo'!$M$5:$M$2000,'Saisie hebdo'!$B$5:$B$2000,$A17,'Saisie hebdo'!$C$5:$C$2000,$B17) | L17: =SUMIFS('Saisie hebdo'!$N$5:$N$2000,'Saisie hebdo'!$B$5:$B$2000,$A17,'Saisie hebdo'!$C$5:$C$2000,$B17) | M17: =SUMIFS('Saisie hebdo'!$O$5:$O$2000,'Saisie hebdo'!$B$5:$B$2000,$A17,'Saisie hebdo'!$C$5:$C$2000,$B17) | N17: =IF(N(D17)=0,"",E17/D17) | O17: =IF(N(E17)=0,"",C17/E17) | P17: =IF(N(E17)=0,"",F17/E17) | Q17: =IF(N(F17)=0,"",C17/F17) | R17: =IF(N(I17)=0,"",C17/I17) | S17: =IF(N(J17)=0,"",C17/J17) | T17: =IF(N(L17)=0,"",C17/L17) | U17: =IF(N(I17)=0,"",J17/I17) | V17: =IF(N(K17)=0,"",L17/K17) | W17: =IF(N(C17)=0,"",M17/C17)
A18: 46327 | B18: Demand Gen | C18: =SUMIFS('Saisie hebdo'!$E$5:$E$2000,'Saisie hebdo'!$B$5:$B$2000,$A18,'Saisie hebdo'!$C$5:$C$2000,$B18) | D18: =SUMIFS('Saisie hebdo'!$F$5:$F$2000,'Saisie hebdo'!$B$5:$B$2000,$A18,'Saisie hebdo'!$C$5:$C$2000,$B18) | E18: =SUMIFS('Saisie hebdo'!$G$5:$G$2000,'Saisie hebdo'!$B$5:$B$2000,$A18,'Saisie hebdo'!$C$5:$C$2000,$B18) | F18: =SUMIFS('Saisie hebdo'!$H$5:$H$2000,'Saisie hebdo'!$B$5:$B$2000,$A18,'Saisie hebdo'!$C$5:$C$2000,$B18) | G18: =IFERROR(AVERAGEIFS('Saisie hebdo'!$I$5:$I$2000,'Saisie hebdo'!$B$5:$B$2000,$A18,'Saisie hebdo'!$C$5:$C$2000,$B18),"") | H18: =IFERROR(AVERAGEIFS('Saisie hebdo'!$J$5:$J$2000,'Saisie hebdo'!$B$5:$B$2000,$A18,'Saisie hebdo'!$C$5:$C$2000,$B18),"") | I18: =SUMIFS('Saisie hebdo'!$K$5:$K$2000,'Saisie hebdo'!$B$5:$B$2000,$A18,'Saisie hebdo'!$C$5:$C$2000,$B18) | J18: =SUMIFS('Saisie hebdo'!$L$5:$L$2000,'Saisie hebdo'!$B$5:$B$2000,$A18,'Saisie hebdo'!$C$5:$C$2000,$B18) | K18: =SUMIFS('Saisie hebdo'!$M$5:$M$2000,'Saisie hebdo'!$B$5:$B$2000,$A18,'Saisie hebdo'!$C$5:$C$2000,$B18) | L18: =SUMIFS('Saisie hebdo'!$N$5:$N$2000,'Saisie hebdo'!$B$5:$B$2000,$A18,'Saisie hebdo'!$C$5:$C$2000,$B18) | M18: =SUMIFS('Saisie hebdo'!$O$5:$O$2000,'Saisie hebdo'!$B$5:$B$2000,$A18,'Saisie hebdo'!$C$5:$C$2000,$B18) | N18: =IF(N(D18)=0,"",E18/D18) | O18: =IF(N(E18)=0,"",C18/E18) | P18: =IF(N(E18)=0,"",F18/E18) | Q18: =IF(N(F18)=0,"",C18/F18) | R18: =IF(N(I18)=0,"",C18/I18) | S18: =IF(N(J18)=0,"",C18/J18) | T18: =IF(N(L18)=0,"",C18/L18) | U18: =IF(N(I18)=0,"",J18/I18) | V18: =IF(N(K18)=0,"",L18/K18) | W18: =IF(N(C18)=0,"",M18/C18)
A19: 46327 | B19: Microsoft Ads | C19: =SUMIFS('Saisie hebdo'!$E$5:$E$2000,'Saisie hebdo'!$B$5:$B$2000,$A19,'Saisie hebdo'!$C$5:$C$2000,$B19) | D19: =SUMIFS('Saisie hebdo'!$F$5:$F$2000,'Saisie hebdo'!$B$5:$B$2000,$A19,'Saisie hebdo'!$C$5:$C$2000,$B19) | E19: =SUMIFS('Saisie hebdo'!$G$5:$G$2000,'Saisie hebdo'!$B$5:$B$2000,$A19,'Saisie hebdo'!$C$5:$C$2000,$B19) | F19: =SUMIFS('Saisie hebdo'!$H$5:$H$2000,'Saisie hebdo'!$B$5:$B$2000,$A19,'Saisie hebdo'!$C$5:$C$2000,$B19) | G19: =IFERROR(AVERAGEIFS('Saisie hebdo'!$I$5:$I$2000,'Saisie hebdo'!$B$5:$B$2000,$A19,'Saisie hebdo'!$C$5:$C$2000,$B19),"") | H19: =IFERROR(AVERAGEIFS('Saisie hebdo'!$J$5:$J$2000,'Saisie hebdo'!$B$5:$B$2000,$A19,'Saisie hebdo'!$C$5:$C$2000,$B19),"") | I19: =SUMIFS('Saisie hebdo'!$K$5:$K$2000,'Saisie hebdo'!$B$5:$B$2000,$A19,'Saisie hebdo'!$C$5:$C$2000,$B19) | J19: =SUMIFS('Saisie hebdo'!$L$5:$L$2000,'Saisie hebdo'!$B$5:$B$2000,$A19,'Saisie hebdo'!$C$5:$C$2000,$B19) | K19: =SUMIFS('Saisie hebdo'!$M$5:$M$2000,'Saisie hebdo'!$B$5:$B$2000,$A19,'Saisie hebdo'!$C$5:$C$2000,$B19) | L19: =SUMIFS('Saisie hebdo'!$N$5:$N$2000,'Saisie hebdo'!$B$5:$B$2000,$A19,'Saisie hebdo'!$C$5:$C$2000,$B19) | M19: =SUMIFS('Saisie hebdo'!$O$5:$O$2000,'Saisie hebdo'!$B$5:$B$2000,$A19,'Saisie hebdo'!$C$5:$C$2000,$B19) | N19: =IF(N(D19)=0,"",E19/D19) | O19: =IF(N(E19)=0,"",C19/E19) | P19: =IF(N(E19)=0,"",F19/E19) | Q19: =IF(N(F19)=0,"",C19/F19) | R19: =IF(N(I19)=0,"",C19/I19) | S19: =IF(N(J19)=0,"",C19/J19) | T19: =IF(N(L19)=0,"",C19/L19) | U19: =IF(N(I19)=0,"",J19/I19) | V19: =IF(N(K19)=0,"",L19/K19) | W19: =IF(N(C19)=0,"",M19/C19)
A20: 46327 | B20: Total du compte | C20: =SUMIFS('Saisie hebdo'!$E$5:$E$2000,'Saisie hebdo'!$B$5:$B$2000,$A20) | D20: =SUMIFS('Saisie hebdo'!$F$5:$F$2000,'Saisie hebdo'!$B$5:$B$2000,$A20) | E20: =SUMIFS('Saisie hebdo'!$G$5:$G$2000,'Saisie hebdo'!$B$5:$B$2000,$A20) | F20: =SUMIFS('Saisie hebdo'!$H$5:$H$2000,'Saisie hebdo'!$B$5:$B$2000,$A20) | G20: =IFERROR(AVERAGEIFS('Saisie hebdo'!$I$5:$I$2000,'Saisie hebdo'!$B$5:$B$2000,$A20),"") | H20: =IFERROR(AVERAGEIFS('Saisie hebdo'!$J$5:$J$2000,'Saisie hebdo'!$B$5:$B$2000,$A20),"") | I20: =SUMIFS('Saisie hebdo'!$K$5:$K$2000,'Saisie hebdo'!$B$5:$B$2000,$A20) | J20: =SUMIFS('Saisie hebdo'!$L$5:$L$2000,'Saisie hebdo'!$B$5:$B$2000,$A20) | K20: =SUMIFS('Saisie hebdo'!$M$5:$M$2000,'Saisie hebdo'!$B$5:$B$2000,$A20) | L20: =SUMIFS('Saisie hebdo'!$N$5:$N$2000,'Saisie hebdo'!$B$5:$B$2000,$A20) | M20: =SUMIFS('Saisie hebdo'!$O$5:$O$2000,'Saisie hebdo'!$B$5:$B$2000,$A20) | N20: =IF(N(D20)=0,"",E20/D20) | O20: =IF(N(E20)=0,"",C20/E20) | P20: =IF(N(E20)=0,"",F20/E20) | Q20: =IF(N(F20)=0,"",C20/F20) | R20: =IF(N(I20)=0,"",C20/I20) | S20: =IF(N(J20)=0,"",C20/J20) | T20: =IF(N(L20)=0,"",C20/L20) | U20: =IF(N(I20)=0,"",J20/I20) | V20: =IF(N(K20)=0,"",L20/K20) | W20: =IF(N(C20)=0,"",M20/C20)
A21: 46357 | B21: S-FR | Marque | C21: =SUMIFS('Saisie hebdo'!$E$5:$E$2000,'Saisie hebdo'!$B$5:$B$2000,$A21,'Saisie hebdo'!$C$5:$C$2000,$B21) | D21: =SUMIFS('Saisie hebdo'!$F$5:$F$2000,'Saisie hebdo'!$B$5:$B$2000,$A21,'Saisie hebdo'!$C$5:$C$2000,$B21) | E21: =SUMIFS('Saisie hebdo'!$G$5:$G$2000,'Saisie hebdo'!$B$5:$B$2000,$A21,'Saisie hebdo'!$C$5:$C$2000,$B21) | F21: =SUMIFS('Saisie hebdo'!$H$5:$H$2000,'Saisie hebdo'!$B$5:$B$2000,$A21,'Saisie hebdo'!$C$5:$C$2000,$B21) | G21: =IFERROR(AVERAGEIFS('Saisie hebdo'!$I$5:$I$2000,'Saisie hebdo'!$B$5:$B$2000,$A21,'Saisie hebdo'!$C$5:$C$2000,$B21),"") | H21: =IFERROR(AVERAGEIFS('Saisie hebdo'!$J$5:$J$2000,'Saisie hebdo'!$B$5:$B$2000,$A21,'Saisie hebdo'!$C$5:$C$2000,$B21),"") | I21: =SUMIFS('Saisie hebdo'!$K$5:$K$2000,'Saisie hebdo'!$B$5:$B$2000,$A21,'Saisie hebdo'!$C$5:$C$2000,$B21) | J21: =SUMIFS('Saisie hebdo'!$L$5:$L$2000,'Saisie hebdo'!$B$5:$B$2000,$A21,'Saisie hebdo'!$C$5:$C$2000,$B21) | K21: =SUMIFS('Saisie hebdo'!$M$5:$M$2000,'Saisie hebdo'!$B$5:$B$2000,$A21,'Saisie hebdo'!$C$5:$C$2000,$B21) | L21: =SUMIFS('Saisie hebdo'!$N$5:$N$2000,'Saisie hebdo'!$B$5:$B$2000,$A21,'Saisie hebdo'!$C$5:$C$2000,$B21) | M21: =SUMIFS('Saisie hebdo'!$O$5:$O$2000,'Saisie hebdo'!$B$5:$B$2000,$A21,'Saisie hebdo'!$C$5:$C$2000,$B21) | N21: =IF(N(D21)=0,"",E21/D21) | O21: =IF(N(E21)=0,"",C21/E21) | P21: =IF(N(E21)=0,"",F21/E21) | Q21: =IF(N(F21)=0,"",C21/F21) | R21: =IF(N(I21)=0,"",C21/I21) | S21: =IF(N(J21)=0,"",C21/J21) | T21: =IF(N(L21)=0,"",C21/L21) | U21: =IF(N(I21)=0,"",J21/I21) | V21: =IF(N(K21)=0,"",L21/K21) | W21: =IF(N(C21)=0,"",M21/C21)
A22: 46357 | B22: S-FR | Corporatif & Fêtes | C22: =SUMIFS('Saisie hebdo'!$E$5:$E$2000,'Saisie hebdo'!$B$5:$B$2000,$A22,'Saisie hebdo'!$C$5:$C$2000,$B22) | D22: =SUMIFS('Saisie hebdo'!$F$5:$F$2000,'Saisie hebdo'!$B$5:$B$2000,$A22,'Saisie hebdo'!$C$5:$C$2000,$B22) | E22: =SUMIFS('Saisie hebdo'!$G$5:$G$2000,'Saisie hebdo'!$B$5:$B$2000,$A22,'Saisie hebdo'!$C$5:$C$2000,$B22) | F22: =SUMIFS('Saisie hebdo'!$H$5:$H$2000,'Saisie hebdo'!$B$5:$B$2000,$A22,'Saisie hebdo'!$C$5:$C$2000,$B22) | G22: =IFERROR(AVERAGEIFS('Saisie hebdo'!$I$5:$I$2000,'Saisie hebdo'!$B$5:$B$2000,$A22,'Saisie hebdo'!$C$5:$C$2000,$B22),"") | H22: =IFERROR(AVERAGEIFS('Saisie hebdo'!$J$5:$J$2000,'Saisie hebdo'!$B$5:$B$2000,$A22,'Saisie hebdo'!$C$5:$C$2000,$B22),"") | I22: =SUMIFS('Saisie hebdo'!$K$5:$K$2000,'Saisie hebdo'!$B$5:$B$2000,$A22,'Saisie hebdo'!$C$5:$C$2000,$B22) | J22: =SUMIFS('Saisie hebdo'!$L$5:$L$2000,'Saisie hebdo'!$B$5:$B$2000,$A22,'Saisie hebdo'!$C$5:$C$2000,$B22) | K22: =SUMIFS('Saisie hebdo'!$M$5:$M$2000,'Saisie hebdo'!$B$5:$B$2000,$A22,'Saisie hebdo'!$C$5:$C$2000,$B22) | L22: =SUMIFS('Saisie hebdo'!$N$5:$N$2000,'Saisie hebdo'!$B$5:$B$2000,$A22,'Saisie hebdo'!$C$5:$C$2000,$B22) | M22: =SUMIFS('Saisie hebdo'!$O$5:$O$2000,'Saisie hebdo'!$B$5:$B$2000,$A22,'Saisie hebdo'!$C$5:$C$2000,$B22) | N22: =IF(N(D22)=0,"",E22/D22) | O22: =IF(N(E22)=0,"",C22/E22) | P22: =IF(N(E22)=0,"",F22/E22) | Q22: =IF(N(F22)=0,"",C22/F22) | R22: =IF(N(I22)=0,"",C22/I22) | S22: =IF(N(J22)=0,"",C22/J22) | T22: =IF(N(L22)=0,"",C22/L22) | U22: =IF(N(I22)=0,"",J22/I22) | V22: =IF(N(K22)=0,"",L22/K22) | W22: =IF(N(C22)=0,"",M22/C22)
A23: 46357 | B23: S-FR | Événements privés | C23: =SUMIFS('Saisie hebdo'!$E$5:$E$2000,'Saisie hebdo'!$B$5:$B$2000,$A23,'Saisie hebdo'!$C$5:$C$2000,$B23) | D23: =SUMIFS('Saisie hebdo'!$F$5:$F$2000,'Saisie hebdo'!$B$5:$B$2000,$A23,'Saisie hebdo'!$C$5:$C$2000,$B23) | E23: =SUMIFS('Saisie hebdo'!$G$5:$G$2000,'Saisie hebdo'!$B$5:$B$2000,$A23,'Saisie hebdo'!$C$5:$C$2000,$B23) | F23: =SUMIFS('Saisie hebdo'!$H$5:$H$2000,'Saisie hebdo'!$B$5:$B$2000,$A23,'Saisie hebdo'!$C$5:$C$2000,$B23) | G23: =IFERROR(AVERAGEIFS('Saisie hebdo'!$I$5:$I$2000,'Saisie hebdo'!$B$5:$B$2000,$A23,'Saisie hebdo'!$C$5:$C$2000,$B23),"") | H23: =IFERROR(AVERAGEIFS('Saisie hebdo'!$J$5:$J$2000,'Saisie hebdo'!$B$5:$B$2000,$A23,'Saisie hebdo'!$C$5:$C$2000,$B23),"") | I23: =SUMIFS('Saisie hebdo'!$K$5:$K$2000,'Saisie hebdo'!$B$5:$B$2000,$A23,'Saisie hebdo'!$C$5:$C$2000,$B23) | J23: =SUMIFS('Saisie hebdo'!$L$5:$L$2000,'Saisie hebdo'!$B$5:$B$2000,$A23,'Saisie hebdo'!$C$5:$C$2000,$B23) | K23: =SUMIFS('Saisie hebdo'!$M$5:$M$2000,'Saisie hebdo'!$B$5:$B$2000,$A23,'Saisie hebdo'!$C$5:$C$2000,$B23) | L23: =SUMIFS('Saisie hebdo'!$N$5:$N$2000,'Saisie hebdo'!$B$5:$B$2000,$A23,'Saisie hebdo'!$C$5:$C$2000,$B23) | M23: =SUMIFS('Saisie hebdo'!$O$5:$O$2000,'Saisie hebdo'!$B$5:$B$2000,$A23,'Saisie hebdo'!$C$5:$C$2000,$B23) | N23: =IF(N(D23)=0,"",E23/D23) | O23: =IF(N(E23)=0,"",C23/E23) | P23: =IF(N(E23)=0,"",F23/E23) | Q23: =IF(N(F23)=0,"",C23/F23) | R23: =IF(N(I23)=0,"",C23/I23) | S23: =IF(N(J23)=0,"",C23/J23) | T23: =IF(N(L23)=0,"",C23/L23) | U23: =IF(N(I23)=0,"",J23/I23) | V23: =IF(N(K23)=0,"",L23/K23) | W23: =IF(N(C23)=0,"",M23/C23)
A24: 46357 | B24: S-EN | Corporate Montréal | C24: =SUMIFS('Saisie hebdo'!$E$5:$E$2000,'Saisie hebdo'!$B$5:$B$2000,$A24,'Saisie hebdo'!$C$5:$C$2000,$B24) | D24: =SUMIFS('Saisie hebdo'!$F$5:$F$2000,'Saisie hebdo'!$B$5:$B$2000,$A24,'Saisie hebdo'!$C$5:$C$2000,$B24) | E24: =SUMIFS('Saisie hebdo'!$G$5:$G$2000,'Saisie hebdo'!$B$5:$B$2000,$A24,'Saisie hebdo'!$C$5:$C$2000,$B24) | F24: =SUMIFS('Saisie hebdo'!$H$5:$H$2000,'Saisie hebdo'!$B$5:$B$2000,$A24,'Saisie hebdo'!$C$5:$C$2000,$B24) | G24: =IFERROR(AVERAGEIFS('Saisie hebdo'!$I$5:$I$2000,'Saisie hebdo'!$B$5:$B$2000,$A24,'Saisie hebdo'!$C$5:$C$2000,$B24),"") | H24: =IFERROR(AVERAGEIFS('Saisie hebdo'!$J$5:$J$2000,'Saisie hebdo'!$B$5:$B$2000,$A24,'Saisie hebdo'!$C$5:$C$2000,$B24),"") | I24: =SUMIFS('Saisie hebdo'!$K$5:$K$2000,'Saisie hebdo'!$B$5:$B$2000,$A24,'Saisie hebdo'!$C$5:$C$2000,$B24) | J24: =SUMIFS('Saisie hebdo'!$L$5:$L$2000,'Saisie hebdo'!$B$5:$B$2000,$A24,'Saisie hebdo'!$C$5:$C$2000,$B24) | K24: =SUMIFS('Saisie hebdo'!$M$5:$M$2000,'Saisie hebdo'!$B$5:$B$2000,$A24,'Saisie hebdo'!$C$5:$C$2000,$B24) | L24: =SUMIFS('Saisie hebdo'!$N$5:$N$2000,'Saisie hebdo'!$B$5:$B$2000,$A24,'Saisie hebdo'!$C$5:$C$2000,$B24) | M24: =SUMIFS('Saisie hebdo'!$O$5:$O$2000,'Saisie hebdo'!$B$5:$B$2000,$A24,'Saisie hebdo'!$C$5:$C$2000,$B24) | N24: =IF(N(D24)=0,"",E24/D24) | O24: =IF(N(E24)=0,"",C24/E24) | P24: =IF(N(E24)=0,"",F24/E24) | Q24: =IF(N(F24)=0,"",C24/F24) | R24: =IF(N(I24)=0,"",C24/I24) | S24: =IF(N(J24)=0,"",C24/J24) | T24: =IF(N(L24)=0,"",C24/L24) | U24: =IF(N(I24)=0,"",J24/I24) | V24: =IF(N(K24)=0,"",L24/K24) | W24: =IF(N(C24)=0,"",M24/C24)
A25: 46357 | B25: S-FR | Québec-Lévis (test) | C25: =SUMIFS('Saisie hebdo'!$E$5:$E$2000,'Saisie hebdo'!$B$5:$B$2000,$A25,'Saisie hebdo'!$C$5:$C$2000,$B25) | D25: =SUMIFS('Saisie hebdo'!$F$5:$F$2000,'Saisie hebdo'!$B$5:$B$2000,$A25,'Saisie hebdo'!$C$5:$C$2000,$B25) | E25: =SUMIFS('Saisie hebdo'!$G$5:$G$2000,'Saisie hebdo'!$B$5:$B$2000,$A25,'Saisie hebdo'!$C$5:$C$2000,$B25) | F25: =SUMIFS('Saisie hebdo'!$H$5:$H$2000,'Saisie hebdo'!$B$5:$B$2000,$A25,'Saisie hebdo'!$C$5:$C$2000,$B25) | G25: =IFERROR(AVERAGEIFS('Saisie hebdo'!$I$5:$I$2000,'Saisie hebdo'!$B$5:$B$2000,$A25,'Saisie hebdo'!$C$5:$C$2000,$B25),"") | H25: =IFERROR(AVERAGEIFS('Saisie hebdo'!$J$5:$J$2000,'Saisie hebdo'!$B$5:$B$2000,$A25,'Saisie hebdo'!$C$5:$C$2000,$B25),"") | I25: =SUMIFS('Saisie hebdo'!$K$5:$K$2000,'Saisie hebdo'!$B$5:$B$2000,$A25,'Saisie hebdo'!$C$5:$C$2000,$B25) | J25: =SUMIFS('Saisie hebdo'!$L$5:$L$2000,'Saisie hebdo'!$B$5:$B$2000,$A25,'Saisie hebdo'!$C$5:$C$2000,$B25) | K25: =SUMIFS('Saisie hebdo'!$M$5:$M$2000,'Saisie hebdo'!$B$5:$B$2000,$A25,'Saisie hebdo'!$C$5:$C$2000,$B25) | L25: =SUMIFS('Saisie hebdo'!$N$5:$N$2000,'Saisie hebdo'!$B$5:$B$2000,$A25,'Saisie hebdo'!$C$5:$C$2000,$B25) | M25: =SUMIFS('Saisie hebdo'!$O$5:$O$2000,'Saisie hebdo'!$B$5:$B$2000,$A25,'Saisie hebdo'!$C$5:$C$2000,$B25) | N25: =IF(N(D25)=0,"",E25/D25) | O25: =IF(N(E25)=0,"",C25/E25) | P25: =IF(N(E25)=0,"",F25/E25) | Q25: =IF(N(F25)=0,"",C25/F25) | R25: =IF(N(I25)=0,"",C25/I25) | S25: =IF(N(J25)=0,"",C25/J25) | T25: =IF(N(L25)=0,"",C25/L25) | U25: =IF(N(I25)=0,"",J25/I25) | V25: =IF(N(K25)=0,"",L25/K25) | W25: =IF(N(C25)=0,"",M25/C25)
A26: 46357 | B26: Demand Gen | C26: =SUMIFS('Saisie hebdo'!$E$5:$E$2000,'Saisie hebdo'!$B$5:$B$2000,$A26,'Saisie hebdo'!$C$5:$C$2000,$B26) | D26: =SUMIFS('Saisie hebdo'!$F$5:$F$2000,'Saisie hebdo'!$B$5:$B$2000,$A26,'Saisie hebdo'!$C$5:$C$2000,$B26) | E26: =SUMIFS('Saisie hebdo'!$G$5:$G$2000,'Saisie hebdo'!$B$5:$B$2000,$A26,'Saisie hebdo'!$C$5:$C$2000,$B26) | F26: =SUMIFS('Saisie hebdo'!$H$5:$H$2000,'Saisie hebdo'!$B$5:$B$2000,$A26,'Saisie hebdo'!$C$5:$C$2000,$B26) | G26: =IFERROR(AVERAGEIFS('Saisie hebdo'!$I$5:$I$2000,'Saisie hebdo'!$B$5:$B$2000,$A26,'Saisie hebdo'!$C$5:$C$2000,$B26),"") | H26: =IFERROR(AVERAGEIFS('Saisie hebdo'!$J$5:$J$2000,'Saisie hebdo'!$B$5:$B$2000,$A26,'Saisie hebdo'!$C$5:$C$2000,$B26),"") | I26: =SUMIFS('Saisie hebdo'!$K$5:$K$2000,'Saisie hebdo'!$B$5:$B$2000,$A26,'Saisie hebdo'!$C$5:$C$2000,$B26) | J26: =SUMIFS('Saisie hebdo'!$L$5:$L$2000,'Saisie hebdo'!$B$5:$B$2000,$A26,'Saisie hebdo'!$C$5:$C$2000,$B26) | K26: =SUMIFS('Saisie hebdo'!$M$5:$M$2000,'Saisie hebdo'!$B$5:$B$2000,$A26,'Saisie hebdo'!$C$5:$C$2000,$B26) | L26: =SUMIFS('Saisie hebdo'!$N$5:$N$2000,'Saisie hebdo'!$B$5:$B$2000,$A26,'Saisie hebdo'!$C$5:$C$2000,$B26) | M26: =SUMIFS('Saisie hebdo'!$O$5:$O$2000,'Saisie hebdo'!$B$5:$B$2000,$A26,'Saisie hebdo'!$C$5:$C$2000,$B26) | N26: =IF(N(D26)=0,"",E26/D26) | O26: =IF(N(E26)=0,"",C26/E26) | P26: =IF(N(E26)=0,"",F26/E26) | Q26: =IF(N(F26)=0,"",C26/F26) | R26: =IF(N(I26)=0,"",C26/I26) | S26: =IF(N(J26)=0,"",C26/J26) | T26: =IF(N(L26)=0,"",C26/L26) | U26: =IF(N(I26)=0,"",J26/I26) | V26: =IF(N(K26)=0,"",L26/K26) | W26: =IF(N(C26)=0,"",M26/C26)
A27: 46357 | B27: Microsoft Ads | C27: =SUMIFS('Saisie hebdo'!$E$5:$E$2000,'Saisie hebdo'!$B$5:$B$2000,$A27,'Saisie hebdo'!$C$5:$C$2000,$B27) | D27: =SUMIFS('Saisie hebdo'!$F$5:$F$2000,'Saisie hebdo'!$B$5:$B$2000,$A27,'Saisie hebdo'!$C$5:$C$2000,$B27) | E27: =SUMIFS('Saisie hebdo'!$G$5:$G$2000,'Saisie hebdo'!$B$5:$B$2000,$A27,'Saisie hebdo'!$C$5:$C$2000,$B27) | F27: =SUMIFS('Saisie hebdo'!$H$5:$H$2000,'Saisie hebdo'!$B$5:$B$2000,$A27,'Saisie hebdo'!$C$5:$C$2000,$B27) | G27: =IFERROR(AVERAGEIFS('Saisie hebdo'!$I$5:$I$2000,'Saisie hebdo'!$B$5:$B$2000,$A27,'Saisie hebdo'!$C$5:$C$2000,$B27),"") | H27: =IFERROR(AVERAGEIFS('Saisie hebdo'!$J$5:$J$2000,'Saisie hebdo'!$B$5:$B$2000,$A27,'Saisie hebdo'!$C$5:$C$2000,$B27),"") | I27: =SUMIFS('Saisie hebdo'!$K$5:$K$2000,'Saisie hebdo'!$B$5:$B$2000,$A27,'Saisie hebdo'!$C$5:$C$2000,$B27) | J27: =SUMIFS('Saisie hebdo'!$L$5:$L$2000,'Saisie hebdo'!$B$5:$B$2000,$A27,'Saisie hebdo'!$C$5:$C$2000,$B27) | K27: =SUMIFS('Saisie hebdo'!$M$5:$M$2000,'Saisie hebdo'!$B$5:$B$2000,$A27,'Saisie hebdo'!$C$5:$C$2000,$B27) | L27: =SUMIFS('Saisie hebdo'!$N$5:$N$2000,'Saisie hebdo'!$B$5:$B$2000,$A27,'Saisie hebdo'!$C$5:$C$2000,$B27) | M27: =SUMIFS('Saisie hebdo'!$O$5:$O$2000,'Saisie hebdo'!$B$5:$B$2000,$A27,'Saisie hebdo'!$C$5:$C$2000,$B27) | N27: =IF(N(D27)=0,"",E27/D27) | O27: =IF(N(E27)=0,"",C27/E27) | P27: =IF(N(E27)=0,"",F27/E27) | Q27: =IF(N(F27)=0,"",C27/F27) | R27: =IF(N(I27)=0,"",C27/I27) | S27: =IF(N(J27)=0,"",C27/J27) | T27: =IF(N(L27)=0,"",C27/L27) | U27: =IF(N(I27)=0,"",J27/I27) | V27: =IF(N(K27)=0,"",L27/K27) | W27: =IF(N(C27)=0,"",M27/C27)
A28: 46357 | B28: Total du compte | C28: =SUMIFS('Saisie hebdo'!$E$5:$E$2000,'Saisie hebdo'!$B$5:$B$2000,$A28) | D28: =SUMIFS('Saisie hebdo'!$F$5:$F$2000,'Saisie hebdo'!$B$5:$B$2000,$A28) | E28: =SUMIFS('Saisie hebdo'!$G$5:$G$2000,'Saisie hebdo'!$B$5:$B$2000,$A28) | F28: =SUMIFS('Saisie hebdo'!$H$5:$H$2000,'Saisie hebdo'!$B$5:$B$2000,$A28) | G28: =IFERROR(AVERAGEIFS('Saisie hebdo'!$I$5:$I$2000,'Saisie hebdo'!$B$5:$B$2000,$A28),"") | H28: =IFERROR(AVERAGEIFS('Saisie hebdo'!$J$5:$J$2000,'Saisie hebdo'!$B$5:$B$2000,$A28),"") | I28: =SUMIFS('Saisie hebdo'!$K$5:$K$2000,'Saisie hebdo'!$B$5:$B$2000,$A28) | J28: =SUMIFS('Saisie hebdo'!$L$5:$L$2000,'Saisie hebdo'!$B$5:$B$2000,$A28) | K28: =SUMIFS('Saisie hebdo'!$M$5:$M$2000,'Saisie hebdo'!$B$5:$B$2000,$A28) | L28: =SUMIFS('Saisie hebdo'!$N$5:$N$2000,'Saisie hebdo'!$B$5:$B$2000,$A28) | M28: =SUMIFS('Saisie hebdo'!$O$5:$O$2000,'Saisie hebdo'!$B$5:$B$2000,$A28) | N28: =IF(N(D28)=0,"",E28/D28) | O28: =IF(N(E28)=0,"",C28/E28) | P28: =IF(N(E28)=0,"",F28/E28) | Q28: =IF(N(F28)=0,"",C28/F28) | R28: =IF(N(I28)=0,"",C28/I28) | S28: =IF(N(J28)=0,"",C28/J28) | T28: =IF(N(L28)=0,"",C28/L28) | U28: =IF(N(I28)=0,"",J28/I28) | V28: =IF(N(K28)=0,"",L28/K28) | W28: =IF(N(C28)=0,"",M28/C28)
A29: 46388 | B29: S-FR | Marque | C29: =SUMIFS('Saisie hebdo'!$E$5:$E$2000,'Saisie hebdo'!$B$5:$B$2000,$A29,'Saisie hebdo'!$C$5:$C$2000,$B29) | D29: =SUMIFS('Saisie hebdo'!$F$5:$F$2000,'Saisie hebdo'!$B$5:$B$2000,$A29,'Saisie hebdo'!$C$5:$C$2000,$B29) | E29: =SUMIFS('Saisie hebdo'!$G$5:$G$2000,'Saisie hebdo'!$B$5:$B$2000,$A29,'Saisie hebdo'!$C$5:$C$2000,$B29) | F29: =SUMIFS('Saisie hebdo'!$H$5:$H$2000,'Saisie hebdo'!$B$5:$B$2000,$A29,'Saisie hebdo'!$C$5:$C$2000,$B29) | G29: =IFERROR(AVERAGEIFS('Saisie hebdo'!$I$5:$I$2000,'Saisie hebdo'!$B$5:$B$2000,$A29,'Saisie hebdo'!$C$5:$C$2000,$B29),"") | H29: =IFERROR(AVERAGEIFS('Saisie hebdo'!$J$5:$J$2000,'Saisie hebdo'!$B$5:$B$2000,$A29,'Saisie hebdo'!$C$5:$C$2000,$B29),"") | I29: =SUMIFS('Saisie hebdo'!$K$5:$K$2000,'Saisie hebdo'!$B$5:$B$2000,$A29,'Saisie hebdo'!$C$5:$C$2000,$B29) | J29: =SUMIFS('Saisie hebdo'!$L$5:$L$2000,'Saisie hebdo'!$B$5:$B$2000,$A29,'Saisie hebdo'!$C$5:$C$2000,$B29) | K29: =SUMIFS('Saisie hebdo'!$M$5:$M$2000,'Saisie hebdo'!$B$5:$B$2000,$A29,'Saisie hebdo'!$C$5:$C$2000,$B29) | L29: =SUMIFS('Saisie hebdo'!$N$5:$N$2000,'Saisie hebdo'!$B$5:$B$2000,$A29,'Saisie hebdo'!$C$5:$C$2000,$B29) | M29: =SUMIFS('Saisie hebdo'!$O$5:$O$2000,'Saisie hebdo'!$B$5:$B$2000,$A29,'Saisie hebdo'!$C$5:$C$2000,$B29) | N29: =IF(N(D29)=0,"",E29/D29) | O29: =IF(N(E29)=0,"",C29/E29) | P29: =IF(N(E29)=0,"",F29/E29) | Q29: =IF(N(F29)=0,"",C29/F29) | R29: =IF(N(I29)=0,"",C29/I29) | S29: =IF(N(J29)=0,"",C29/J29) | T29: =IF(N(L29)=0,"",C29/L29) | U29: =IF(N(I29)=0,"",J29/I29) | V29: =IF(N(K29)=0,"",L29/K29) | W29: =IF(N(C29)=0,"",M29/C29)
A30: 46388 | B30: S-FR | Corporatif & Fêtes | C30: =SUMIFS('Saisie hebdo'!$E$5:$E$2000,'Saisie hebdo'!$B$5:$B$2000,$A30,'Saisie hebdo'!$C$5:$C$2000,$B30) | D30: =SUMIFS('Saisie hebdo'!$F$5:$F$2000,'Saisie hebdo'!$B$5:$B$2000,$A30,'Saisie hebdo'!$C$5:$C$2000,$B30) | E30: =SUMIFS('Saisie hebdo'!$G$5:$G$2000,'Saisie hebdo'!$B$5:$B$2000,$A30,'Saisie hebdo'!$C$5:$C$2000,$B30) | F30: =SUMIFS('Saisie hebdo'!$H$5:$H$2000,'Saisie hebdo'!$B$5:$B$2000,$A30,'Saisie hebdo'!$C$5:$C$2000,$B30) | G30: =IFERROR(AVERAGEIFS('Saisie hebdo'!$I$5:$I$2000,'Saisie hebdo'!$B$5:$B$2000,$A30,'Saisie hebdo'!$C$5:$C$2000,$B30),"") | H30: =IFERROR(AVERAGEIFS('Saisie hebdo'!$J$5:$J$2000,'Saisie hebdo'!$B$5:$B$2000,$A30,'Saisie hebdo'!$C$5:$C$2000,$B30),"") | I30: =SUMIFS('Saisie hebdo'!$K$5:$K$2000,'Saisie hebdo'!$B$5:$B$2000,$A30,'Saisie hebdo'!$C$5:$C$2000,$B30) | J30: =SUMIFS('Saisie hebdo'!$L$5:$L$2000,'Saisie hebdo'!$B$5:$B$2000,$A30,'Saisie hebdo'!$C$5:$C$2000,$B30) | K30: =SUMIFS('Saisie hebdo'!$M$5:$M$2000,'Saisie hebdo'!$B$5:$B$2000,$A30,'Saisie hebdo'!$C$5:$C$2000,$B30) | L30: =SUMIFS('Saisie hebdo'!$N$5:$N$2000,'Saisie hebdo'!$B$5:$B$2000,$A30,'Saisie hebdo'!$C$5:$C$2000,$B30) | M30: =SUMIFS('Saisie hebdo'!$O$5:$O$2000,'Saisie hebdo'!$B$5:$B$2000,$A30,'Saisie hebdo'!$C$5:$C$2000,$B30) | N30: =IF(N(D30)=0,"",E30/D30) | O30: =IF(N(E30)=0,"",C30/E30) | P30: =IF(N(E30)=0,"",F30/E30) | Q30: =IF(N(F30)=0,"",C30/F30) | R30: =IF(N(I30)=0,"",C30/I30) | S30: =IF(N(J30)=0,"",C30/J30) | T30: =IF(N(L30)=0,"",C30/L30) | U30: =IF(N(I30)=0,"",J30/I30) | V30: =IF(N(K30)=0,"",L30/K30) | W30: =IF(N(C30)=0,"",M30/C30)
A31: 46388 | B31: S-FR | Événements privés | C31: =SUMIFS('Saisie hebdo'!$E$5:$E$2000,'Saisie hebdo'!$B$5:$B$2000,$A31,'Saisie hebdo'!$C$5:$C$2000,$B31) | D31: =SUMIFS('Saisie hebdo'!$F$5:$F$2000,'Saisie hebdo'!$B$5:$B$2000,$A31,'Saisie hebdo'!$C$5:$C$2000,$B31) | E31: =SUMIFS('Saisie hebdo'!$G$5:$G$2000,'Saisie hebdo'!$B$5:$B$2000,$A31,'Saisie hebdo'!$C$5:$C$2000,$B31) | F31: =SUMIFS('Saisie hebdo'!$H$5:$H$2000,'Saisie hebdo'!$B$5:$B$2000,$A31,'Saisie hebdo'!$C$5:$C$2000,$B31) | G31: =IFERROR(AVERAGEIFS('Saisie hebdo'!$I$5:$I$2000,'Saisie hebdo'!$B$5:$B$2000,$A31,'Saisie hebdo'!$C$5:$C$2000,$B31),"") | H31: =IFERROR(AVERAGEIFS('Saisie hebdo'!$J$5:$J$2000,'Saisie hebdo'!$B$5:$B$2000,$A31,'Saisie hebdo'!$C$5:$C$2000,$B31),"") | I31: =SUMIFS('Saisie hebdo'!$K$5:$K$2000,'Saisie hebdo'!$B$5:$B$2000,$A31,'Saisie hebdo'!$C$5:$C$2000,$B31) | J31: =SUMIFS('Saisie hebdo'!$L$5:$L$2000,'Saisie hebdo'!$B$5:$B$2000,$A31,'Saisie hebdo'!$C$5:$C$2000,$B31) | K31: =SUMIFS('Saisie hebdo'!$M$5:$M$2000,'Saisie hebdo'!$B$5:$B$2000,$A31,'Saisie hebdo'!$C$5:$C$2000,$B31) | L31: =SUMIFS('Saisie hebdo'!$N$5:$N$2000,'Saisie hebdo'!$B$5:$B$2000,$A31,'Saisie hebdo'!$C$5:$C$2000,$B31) | M31: =SUMIFS('Saisie hebdo'!$O$5:$O$2000,'Saisie hebdo'!$B$5:$B$2000,$A31,'Saisie hebdo'!$C$5:$C$2000,$B31) | N31: =IF(N(D31)=0,"",E31/D31) | O31: =IF(N(E31)=0,"",C31/E31) | P31: =IF(N(E31)=0,"",F31/E31) | Q31: =IF(N(F31)=0,"",C31/F31) | R31: =IF(N(I31)=0,"",C31/I31) | S31: =IF(N(J31)=0,"",C31/J31) | T31: =IF(N(L31)=0,"",C31/L31) | U31: =IF(N(I31)=0,"",J31/I31) | V31: =IF(N(K31)=0,"",L31/K31) | W31: =IF(N(C31)=0,"",M31/C31)
A32: 46388 | B32: S-EN | Corporate Montréal | C32: =SUMIFS('Saisie hebdo'!$E$5:$E$2000,'Saisie hebdo'!$B$5:$B$2000,$A32,'Saisie hebdo'!$C$5:$C$2000,$B32) | D32: =SUMIFS('Saisie hebdo'!$F$5:$F$2000,'Saisie hebdo'!$B$5:$B$2000,$A32,'Saisie hebdo'!$C$5:$C$2000,$B32) | E32: =SUMIFS('Saisie hebdo'!$G$5:$G$2000,'Saisie hebdo'!$B$5:$B$2000,$A32,'Saisie hebdo'!$C$5:$C$2000,$B32) | F32: =SUMIFS('Saisie hebdo'!$H$5:$H$2000,'Saisie hebdo'!$B$5:$B$2000,$A32,'Saisie hebdo'!$C$5:$C$2000,$B32) | G32: =IFERROR(AVERAGEIFS('Saisie hebdo'!$I$5:$I$2000,'Saisie hebdo'!$B$5:$B$2000,$A32,'Saisie hebdo'!$C$5:$C$2000,$B32),"") | H32: =IFERROR(AVERAGEIFS('Saisie hebdo'!$J$5:$J$2000,'Saisie hebdo'!$B$5:$B$2000,$A32,'Saisie hebdo'!$C$5:$C$2000,$B32),"") | I32: =SUMIFS('Saisie hebdo'!$K$5:$K$2000,'Saisie hebdo'!$B$5:$B$2000,$A32,'Saisie hebdo'!$C$5:$C$2000,$B32) | J32: =SUMIFS('Saisie hebdo'!$L$5:$L$2000,'Saisie hebdo'!$B$5:$B$2000,$A32,'Saisie hebdo'!$C$5:$C$2000,$B32) | K32: =SUMIFS('Saisie hebdo'!$M$5:$M$2000,'Saisie hebdo'!$B$5:$B$2000,$A32,'Saisie hebdo'!$C$5:$C$2000,$B32) | L32: =SUMIFS('Saisie hebdo'!$N$5:$N$2000,'Saisie hebdo'!$B$5:$B$2000,$A32,'Saisie hebdo'!$C$5:$C$2000,$B32) | M32: =SUMIFS('Saisie hebdo'!$O$5:$O$2000,'Saisie hebdo'!$B$5:$B$2000,$A32,'Saisie hebdo'!$C$5:$C$2000,$B32) | N32: =IF(N(D32)=0,"",E32/D32) | O32: =IF(N(E32)=0,"",C32/E32) | P32: =IF(N(E32)=0,"",F32/E32) | Q32: =IF(N(F32)=0,"",C32/F32) | R32: =IF(N(I32)=0,"",C32/I32) | S32: =IF(N(J32)=0,"",C32/J32) | T32: =IF(N(L32)=0,"",C32/L32) | U32: =IF(N(I32)=0,"",J32/I32) | V32: =IF(N(K32)=0,"",L32/K32) | W32: =IF(N(C32)=0,"",M32/C32)
A33: 46388 | B33: S-FR | Québec-Lévis (test) | C33: =SUMIFS('Saisie hebdo'!$E$5:$E$2000,'Saisie hebdo'!$B$5:$B$2000,$A33,'Saisie hebdo'!$C$5:$C$2000,$B33) | D33: =SUMIFS('Saisie hebdo'!$F$5:$F$2000,'Saisie hebdo'!$B$5:$B$2000,$A33,'Saisie hebdo'!$C$5:$C$2000,$B33) | E33: =SUMIFS('Saisie hebdo'!$G$5:$G$2000,'Saisie hebdo'!$B$5:$B$2000,$A33,'Saisie hebdo'!$C$5:$C$2000,$B33) | F33: =SUMIFS('Saisie hebdo'!$H$5:$H$2000,'Saisie hebdo'!$B$5:$B$2000,$A33,'Saisie hebdo'!$C$5:$C$2000,$B33) | G33: =IFERROR(AVERAGEIFS('Saisie hebdo'!$I$5:$I$2000,'Saisie hebdo'!$B$5:$B$2000,$A33,'Saisie hebdo'!$C$5:$C$2000,$B33),"") | H33: =IFERROR(AVERAGEIFS('Saisie hebdo'!$J$5:$J$2000,'Saisie hebdo'!$B$5:$B$2000,$A33,'Saisie hebdo'!$C$5:$C$2000,$B33),"") | I33: =SUMIFS('Saisie hebdo'!$K$5:$K$2000,'Saisie hebdo'!$B$5:$B$2000,$A33,'Saisie hebdo'!$C$5:$C$2000,$B33) | J33: =SUMIFS('Saisie hebdo'!$L$5:$L$2000,'Saisie hebdo'!$B$5:$B$2000,$A33,'Saisie hebdo'!$C$5:$C$2000,$B33) | K33: =SUMIFS('Saisie hebdo'!$M$5:$M$2000,'Saisie hebdo'!$B$5:$B$2000,$A33,'Saisie hebdo'!$C$5:$C$2000,$B33) | L33: =SUMIFS('Saisie hebdo'!$N$5:$N$2000,'Saisie hebdo'!$B$5:$B$2000,$A33,'Saisie hebdo'!$C$5:$C$2000,$B33) | M33: =SUMIFS('Saisie hebdo'!$O$5:$O$2000,'Saisie hebdo'!$B$5:$B$2000,$A33,'Saisie hebdo'!$C$5:$C$2000,$B33) | N33: =IF(N(D33)=0,"",E33/D33) | O33: =IF(N(E33)=0,"",C33/E33) | P33: =IF(N(E33)=0,"",F33/E33) | Q33: =IF(N(F33)=0,"",C33/F33) | R33: =IF(N(I33)=0,"",C33/I33) | S33: =IF(N(J33)=0,"",C33/J33) | T33: =IF(N(L33)=0,"",C33/L33) | U33: =IF(N(I33)=0,"",J33/I33) | V33: =IF(N(K33)=0,"",L33/K33) | W33: =IF(N(C33)=0,"",M33/C33)
A34: 46388 | B34: Demand Gen | C34: =SUMIFS('Saisie hebdo'!$E$5:$E$2000,'Saisie hebdo'!$B$5:$B$2000,$A34,'Saisie hebdo'!$C$5:$C$2000,$B34) | D34: =SUMIFS('Saisie hebdo'!$F$5:$F$2000,'Saisie hebdo'!$B$5:$B$2000,$A34,'Saisie hebdo'!$C$5:$C$2000,$B34) | E34: =SUMIFS('Saisie hebdo'!$G$5:$G$2000,'Saisie hebdo'!$B$5:$B$2000,$A34,'Saisie hebdo'!$C$5:$C$2000,$B34) | F34: =SUMIFS('Saisie hebdo'!$H$5:$H$2000,'Saisie hebdo'!$B$5:$B$2000,$A34,'Saisie hebdo'!$C$5:$C$2000,$B34) | G34: =IFERROR(AVERAGEIFS('Saisie hebdo'!$I$5:$I$2000,'Saisie hebdo'!$B$5:$B$2000,$A34,'Saisie hebdo'!$C$5:$C$2000,$B34),"") | H34: =IFERROR(AVERAGEIFS('Saisie hebdo'!$J$5:$J$2000,'Saisie hebdo'!$B$5:$B$2000,$A34,'Saisie hebdo'!$C$5:$C$2000,$B34),"") | I34: =SUMIFS('Saisie hebdo'!$K$5:$K$2000,'Saisie hebdo'!$B$5:$B$2000,$A34,'Saisie hebdo'!$C$5:$C$2000,$B34) | J34: =SUMIFS('Saisie hebdo'!$L$5:$L$2000,'Saisie hebdo'!$B$5:$B$2000,$A34,'Saisie hebdo'!$C$5:$C$2000,$B34) | K34: =SUMIFS('Saisie hebdo'!$M$5:$M$2000,'Saisie hebdo'!$B$5:$B$2000,$A34,'Saisie hebdo'!$C$5:$C$2000,$B34) | L34: =SUMIFS('Saisie hebdo'!$N$5:$N$2000,'Saisie hebdo'!$B$5:$B$2000,$A34,'Saisie hebdo'!$C$5:$C$2000,$B34) | M34: =SUMIFS('Saisie hebdo'!$O$5:$O$2000,'Saisie hebdo'!$B$5:$B$2000,$A34,'Saisie hebdo'!$C$5:$C$2000,$B34) | N34: =IF(N(D34)=0,"",E34/D34) | O34: =IF(N(E34)=0,"",C34/E34) | P34: =IF(N(E34)=0,"",F34/E34) | Q34: =IF(N(F34)=0,"",C34/F34) | R34: =IF(N(I34)=0,"",C34/I34) | S34: =IF(N(J34)=0,"",C34/J34) | T34: =IF(N(L34)=0,"",C34/L34) | U34: =IF(N(I34)=0,"",J34/I34) | V34: =IF(N(K34)=0,"",L34/K34) | W34: =IF(N(C34)=0,"",M34/C34)
A35: 46388 | B35: Microsoft Ads | C35: =SUMIFS('Saisie hebdo'!$E$5:$E$2000,'Saisie hebdo'!$B$5:$B$2000,$A35,'Saisie hebdo'!$C$5:$C$2000,$B35) | D35: =SUMIFS('Saisie hebdo'!$F$5:$F$2000,'Saisie hebdo'!$B$5:$B$2000,$A35,'Saisie hebdo'!$C$5:$C$2000,$B35) | E35: =SUMIFS('Saisie hebdo'!$G$5:$G$2000,'Saisie hebdo'!$B$5:$B$2000,$A35,'Saisie hebdo'!$C$5:$C$2000,$B35) | F35: =SUMIFS('Saisie hebdo'!$H$5:$H$2000,'Saisie hebdo'!$B$5:$B$2000,$A35,'Saisie hebdo'!$C$5:$C$2000,$B35) | G35: =IFERROR(AVERAGEIFS('Saisie hebdo'!$I$5:$I$2000,'Saisie hebdo'!$B$5:$B$2000,$A35,'Saisie hebdo'!$C$5:$C$2000,$B35),"") | H35: =IFERROR(AVERAGEIFS('Saisie hebdo'!$J$5:$J$2000,'Saisie hebdo'!$B$5:$B$2000,$A35,'Saisie hebdo'!$C$5:$C$2000,$B35),"") | I35: =SUMIFS('Saisie hebdo'!$K$5:$K$2000,'Saisie hebdo'!$B$5:$B$2000,$A35,'Saisie hebdo'!$C$5:$C$2000,$B35) | J35: =SUMIFS('Saisie hebdo'!$L$5:$L$2000,'Saisie hebdo'!$B$5:$B$2000,$A35,'Saisie hebdo'!$C$5:$C$2000,$B35) | K35: =SUMIFS('Saisie hebdo'!$M$5:$M$2000,'Saisie hebdo'!$B$5:$B$2000,$A35,'Saisie hebdo'!$C$5:$C$2000,$B35) | L35: =SUMIFS('Saisie hebdo'!$N$5:$N$2000,'Saisie hebdo'!$B$5:$B$2000,$A35,'Saisie hebdo'!$C$5:$C$2000,$B35) | M35: =SUMIFS('Saisie hebdo'!$O$5:$O$2000,'Saisie hebdo'!$B$5:$B$2000,$A35,'Saisie hebdo'!$C$5:$C$2000,$B35) | N35: =IF(N(D35)=0,"",E35/D35) | O35: =IF(N(E35)=0,"",C35/E35) | P35: =IF(N(E35)=0,"",F35/E35) | Q35: =IF(N(F35)=0,"",C35/F35) | R35: =IF(N(I35)=0,"",C35/I35) | S35: =IF(N(J35)=0,"",C35/J35) | T35: =IF(N(L35)=0,"",C35/L35) | U35: =IF(N(I35)=0,"",J35/I35) | V35: =IF(N(K35)=0,"",L35/K35) | W35: =IF(N(C35)=0,"",M35/C35)
A36: 46388 | B36: Total du compte | C36: =SUMIFS('Saisie hebdo'!$E$5:$E$2000,'Saisie hebdo'!$B$5:$B$2000,$A36) | D36: =SUMIFS('Saisie hebdo'!$F$5:$F$2000,'Saisie hebdo'!$B$5:$B$2000,$A36) | E36: =SUMIFS('Saisie hebdo'!$G$5:$G$2000,'Saisie hebdo'!$B$5:$B$2000,$A36) | F36: =SUMIFS('Saisie hebdo'!$H$5:$H$2000,'Saisie hebdo'!$B$5:$B$2000,$A36) | G36: =IFERROR(AVERAGEIFS('Saisie hebdo'!$I$5:$I$2000,'Saisie hebdo'!$B$5:$B$2000,$A36),"") | H36: =IFERROR(AVERAGEIFS('Saisie hebdo'!$J$5:$J$2000,'Saisie hebdo'!$B$5:$B$2000,$A36),"") | I36: =SUMIFS('Saisie hebdo'!$K$5:$K$2000,'Saisie hebdo'!$B$5:$B$2000,$A36) | J36: =SUMIFS('Saisie hebdo'!$L$5:$L$2000,'Saisie hebdo'!$B$5:$B$2000,$A36) | K36: =SUMIFS('Saisie hebdo'!$M$5:$M$2000,'Saisie hebdo'!$B$5:$B$2000,$A36) | L36: =SUMIFS('Saisie hebdo'!$N$5:$N$2000,'Saisie hebdo'!$B$5:$B$2000,$A36) | M36: =SUMIFS('Saisie hebdo'!$O$5:$O$2000,'Saisie hebdo'!$B$5:$B$2000,$A36) | N36: =IF(N(D36)=0,"",E36/D36) | O36: =IF(N(E36)=0,"",C36/E36) | P36: =IF(N(E36)=0,"",F36/E36) | Q36: =IF(N(F36)=0,"",C36/F36) | R36: =IF(N(I36)=0,"",C36/I36) | S36: =IF(N(J36)=0,"",C36/J36) | T36: =IF(N(L36)=0,"",C36/L36) | U36: =IF(N(I36)=0,"",J36/I36) | V36: =IF(N(K36)=0,"",L36/K36) | W36: =IF(N(C36)=0,"",M36/C36)
A37: 46419 | B37: S-FR | Marque | C37: =SUMIFS('Saisie hebdo'!$E$5:$E$2000,'Saisie hebdo'!$B$5:$B$2000,$A37,'Saisie hebdo'!$C$5:$C$2000,$B37) | D37: =SUMIFS('Saisie hebdo'!$F$5:$F$2000,'Saisie hebdo'!$B$5:$B$2000,$A37,'Saisie hebdo'!$C$5:$C$2000,$B37) | E37: =SUMIFS('Saisie hebdo'!$G$5:$G$2000,'Saisie hebdo'!$B$5:$B$2000,$A37,'Saisie hebdo'!$C$5:$C$2000,$B37) | F37: =SUMIFS('Saisie hebdo'!$H$5:$H$2000,'Saisie hebdo'!$B$5:$B$2000,$A37,'Saisie hebdo'!$C$5:$C$2000,$B37) | G37: =IFERROR(AVERAGEIFS('Saisie hebdo'!$I$5:$I$2000,'Saisie hebdo'!$B$5:$B$2000,$A37,'Saisie hebdo'!$C$5:$C$2000,$B37),"") | H37: =IFERROR(AVERAGEIFS('Saisie hebdo'!$J$5:$J$2000,'Saisie hebdo'!$B$5:$B$2000,$A37,'Saisie hebdo'!$C$5:$C$2000,$B37),"") | I37: =SUMIFS('Saisie hebdo'!$K$5:$K$2000,'Saisie hebdo'!$B$5:$B$2000,$A37,'Saisie hebdo'!$C$5:$C$2000,$B37) | J37: =SUMIFS('Saisie hebdo'!$L$5:$L$2000,'Saisie hebdo'!$B$5:$B$2000,$A37,'Saisie hebdo'!$C$5:$C$2000,$B37) | K37: =SUMIFS('Saisie hebdo'!$M$5:$M$2000,'Saisie hebdo'!$B$5:$B$2000,$A37,'Saisie hebdo'!$C$5:$C$2000,$B37) | L37: =SUMIFS('Saisie hebdo'!$N$5:$N$2000,'Saisie hebdo'!$B$5:$B$2000,$A37,'Saisie hebdo'!$C$5:$C$2000,$B37) | M37: =SUMIFS('Saisie hebdo'!$O$5:$O$2000,'Saisie hebdo'!$B$5:$B$2000,$A37,'Saisie hebdo'!$C$5:$C$2000,$B37) | N37: =IF(N(D37)=0,"",E37/D37) | O37: =IF(N(E37)=0,"",C37/E37) | P37: =IF(N(E37)=0,"",F37/E37) | Q37: =IF(N(F37)=0,"",C37/F37) | R37: =IF(N(I37)=0,"",C37/I37) | S37: =IF(N(J37)=0,"",C37/J37) | T37: =IF(N(L37)=0,"",C37/L37) | U37: =IF(N(I37)=0,"",J37/I37) | V37: =IF(N(K37)=0,"",L37/K37) | W37: =IF(N(C37)=0,"",M37/C37)
A38: 46419 | B38: S-FR | Corporatif & Fêtes | C38: =SUMIFS('Saisie hebdo'!$E$5:$E$2000,'Saisie hebdo'!$B$5:$B$2000,$A38,'Saisie hebdo'!$C$5:$C$2000,$B38) | D38: =SUMIFS('Saisie hebdo'!$F$5:$F$2000,'Saisie hebdo'!$B$5:$B$2000,$A38,'Saisie hebdo'!$C$5:$C$2000,$B38) | E38: =SUMIFS('Saisie hebdo'!$G$5:$G$2000,'Saisie hebdo'!$B$5:$B$2000,$A38,'Saisie hebdo'!$C$5:$C$2000,$B38) | F38: =SUMIFS('Saisie hebdo'!$H$5:$H$2000,'Saisie hebdo'!$B$5:$B$2000,$A38,'Saisie hebdo'!$C$5:$C$2000,$B38) | G38: =IFERROR(AVERAGEIFS('Saisie hebdo'!$I$5:$I$2000,'Saisie hebdo'!$B$5:$B$2000,$A38,'Saisie hebdo'!$C$5:$C$2000,$B38),"") | H38: =IFERROR(AVERAGEIFS('Saisie hebdo'!$J$5:$J$2000,'Saisie hebdo'!$B$5:$B$2000,$A38,'Saisie hebdo'!$C$5:$C$2000,$B38),"") | I38: =SUMIFS('Saisie hebdo'!$K$5:$K$2000,'Saisie hebdo'!$B$5:$B$2000,$A38,'Saisie hebdo'!$C$5:$C$2000,$B38) | J38: =SUMIFS('Saisie hebdo'!$L$5:$L$2000,'Saisie hebdo'!$B$5:$B$2000,$A38,'Saisie hebdo'!$C$5:$C$2000,$B38) | K38: =SUMIFS('Saisie hebdo'!$M$5:$M$2000,'Saisie hebdo'!$B$5:$B$2000,$A38,'Saisie hebdo'!$C$5:$C$2000,$B38) | L38: =SUMIFS('Saisie hebdo'!$N$5:$N$2000,'Saisie hebdo'!$B$5:$B$2000,$A38,'Saisie hebdo'!$C$5:$C$2000,$B38) | M38: =SUMIFS('Saisie hebdo'!$O$5:$O$2000,'Saisie hebdo'!$B$5:$B$2000,$A38,'Saisie hebdo'!$C$5:$C$2000,$B38) | N38: =IF(N(D38)=0,"",E38/D38) | O38: =IF(N(E38)=0,"",C38/E38) | P38: =IF(N(E38)=0,"",F38/E38) | Q38: =IF(N(F38)=0,"",C38/F38) | R38: =IF(N(I38)=0,"",C38/I38) | S38: =IF(N(J38)=0,"",C38/J38) | T38: =IF(N(L38)=0,"",C38/L38) | U38: =IF(N(I38)=0,"",J38/I38) | V38: =IF(N(K38)=0,"",L38/K38) | W38: =IF(N(C38)=0,"",M38/C38)
A39: 46419 | B39: S-FR | Événements privés | C39: =SUMIFS('Saisie hebdo'!$E$5:$E$2000,'Saisie hebdo'!$B$5:$B$2000,$A39,'Saisie hebdo'!$C$5:$C$2000,$B39) | D39: =SUMIFS('Saisie hebdo'!$F$5:$F$2000,'Saisie hebdo'!$B$5:$B$2000,$A39,'Saisie hebdo'!$C$5:$C$2000,$B39) | E39: =SUMIFS('Saisie hebdo'!$G$5:$G$2000,'Saisie hebdo'!$B$5:$B$2000,$A39,'Saisie hebdo'!$C$5:$C$2000,$B39) | F39: =SUMIFS('Saisie hebdo'!$H$5:$H$2000,'Saisie hebdo'!$B$5:$B$2000,$A39,'Saisie hebdo'!$C$5:$C$2000,$B39) | G39: =IFERROR(AVERAGEIFS('Saisie hebdo'!$I$5:$I$2000,'Saisie hebdo'!$B$5:$B$2000,$A39,'Saisie hebdo'!$C$5:$C$2000,$B39),"") | H39: =IFERROR(AVERAGEIFS('Saisie hebdo'!$J$5:$J$2000,'Saisie hebdo'!$B$5:$B$2000,$A39,'Saisie hebdo'!$C$5:$C$2000,$B39),"") | I39: =SUMIFS('Saisie hebdo'!$K$5:$K$2000,'Saisie hebdo'!$B$5:$B$2000,$A39,'Saisie hebdo'!$C$5:$C$2000,$B39) | J39: =SUMIFS('Saisie hebdo'!$L$5:$L$2000,'Saisie hebdo'!$B$5:$B$2000,$A39,'Saisie hebdo'!$C$5:$C$2000,$B39) | K39: =SUMIFS('Saisie hebdo'!$M$5:$M$2000,'Saisie hebdo'!$B$5:$B$2000,$A39,'Saisie hebdo'!$C$5:$C$2000,$B39) | L39: =SUMIFS('Saisie hebdo'!$N$5:$N$2000,'Saisie hebdo'!$B$5:$B$2000,$A39,'Saisie hebdo'!$C$5:$C$2000,$B39) | M39: =SUMIFS('Saisie hebdo'!$O$5:$O$2000,'Saisie hebdo'!$B$5:$B$2000,$A39,'Saisie hebdo'!$C$5:$C$2000,$B39) | N39: =IF(N(D39)=0,"",E39/D39) | O39: =IF(N(E39)=0,"",C39/E39) | P39: =IF(N(E39)=0,"",F39/E39) | Q39: =IF(N(F39)=0,"",C39/F39) | R39: =IF(N(I39)=0,"",C39/I39) | S39: =IF(N(J39)=0,"",C39/J39) | T39: =IF(N(L39)=0,"",C39/L39) | U39: =IF(N(I39)=0,"",J39/I39) | V39: =IF(N(K39)=0,"",L39/K39) | W39: =IF(N(C39)=0,"",M39/C39)
A40: 46419 | B40: S-EN | Corporate Montréal | C40: =SUMIFS('Saisie hebdo'!$E$5:$E$2000,'Saisie hebdo'!$B$5:$B$2000,$A40,'Saisie hebdo'!$C$5:$C$2000,$B40) | D40: =SUMIFS('Saisie hebdo'!$F$5:$F$2000,'Saisie hebdo'!$B$5:$B$2000,$A40,'Saisie hebdo'!$C$5:$C$2000,$B40) | E40: =SUMIFS('Saisie hebdo'!$G$5:$G$2000,'Saisie hebdo'!$B$5:$B$2000,$A40,'Saisie hebdo'!$C$5:$C$2000,$B40) | F40: =SUMIFS('Saisie hebdo'!$H$5:$H$2000,'Saisie hebdo'!$B$5:$B$2000,$A40,'Saisie hebdo'!$C$5:$C$2000,$B40) | G40: =IFERROR(AVERAGEIFS('Saisie hebdo'!$I$5:$I$2000,'Saisie hebdo'!$B$5:$B$2000,$A40,'Saisie hebdo'!$C$5:$C$2000,$B40),"") | H40: =IFERROR(AVERAGEIFS('Saisie hebdo'!$J$5:$J$2000,'Saisie hebdo'!$B$5:$B$2000,$A40,'Saisie hebdo'!$C$5:$C$2000,$B40),"") | I40: =SUMIFS('Saisie hebdo'!$K$5:$K$2000,'Saisie hebdo'!$B$5:$B$2000,$A40,'Saisie hebdo'!$C$5:$C$2000,$B40) | J40: =SUMIFS('Saisie hebdo'!$L$5:$L$2000,'Saisie hebdo'!$B$5:$B$2000,$A40,'Saisie hebdo'!$C$5:$C$2000,$B40) | K40: =SUMIFS('Saisie hebdo'!$M$5:$M$2000,'Saisie hebdo'!$B$5:$B$2000,$A40,'Saisie hebdo'!$C$5:$C$2000,$B40) | L40: =SUMIFS('Saisie hebdo'!$N$5:$N$2000,'Saisie hebdo'!$B$5:$B$2000,$A40,'Saisie hebdo'!$C$5:$C$2000,$B40) | M40: =SUMIFS('Saisie hebdo'!$O$5:$O$2000,'Saisie hebdo'!$B$5:$B$2000,$A40,'Saisie hebdo'!$C$5:$C$2000,$B40) | N40: =IF(N(D40)=0,"",E40/D40) | O40: =IF(N(E40)=0,"",C40/E40) | P40: =IF(N(E40)=0,"",F40/E40) | Q40: =IF(N(F40)=0,"",C40/F40) | R40: =IF(N(I40)=0,"",C40/I40) | S40: =IF(N(J40)=0,"",C40/J40) | T40: =IF(N(L40)=0,"",C40/L40) | U40: =IF(N(I40)=0,"",J40/I40) | V40: =IF(N(K40)=0,"",L40/K40) | W40: =IF(N(C40)=0,"",M40/C40)
A41: 46419 | B41: S-FR | Québec-Lévis (test) | C41: =SUMIFS('Saisie hebdo'!$E$5:$E$2000,'Saisie hebdo'!$B$5:$B$2000,$A41,'Saisie hebdo'!$C$5:$C$2000,$B41) | D41: =SUMIFS('Saisie hebdo'!$F$5:$F$2000,'Saisie hebdo'!$B$5:$B$2000,$A41,'Saisie hebdo'!$C$5:$C$2000,$B41) | E41: =SUMIFS('Saisie hebdo'!$G$5:$G$2000,'Saisie hebdo'!$B$5:$B$2000,$A41,'Saisie hebdo'!$C$5:$C$2000,$B41) | F41: =SUMIFS('Saisie hebdo'!$H$5:$H$2000,'Saisie hebdo'!$B$5:$B$2000,$A41,'Saisie hebdo'!$C$5:$C$2000,$B41) | G41: =IFERROR(AVERAGEIFS('Saisie hebdo'!$I$5:$I$2000,'Saisie hebdo'!$B$5:$B$2000,$A41,'Saisie hebdo'!$C$5:$C$2000,$B41),"") | H41: =IFERROR(AVERAGEIFS('Saisie hebdo'!$J$5:$J$2000,'Saisie hebdo'!$B$5:$B$2000,$A41,'Saisie hebdo'!$C$5:$C$2000,$B41),"") | I41: =SUMIFS('Saisie hebdo'!$K$5:$K$2000,'Saisie hebdo'!$B$5:$B$2000,$A41,'Saisie hebdo'!$C$5:$C$2000,$B41) | J41: =SUMIFS('Saisie hebdo'!$L$5:$L$2000,'Saisie hebdo'!$B$5:$B$2000,$A41,'Saisie hebdo'!$C$5:$C$2000,$B41) | K41: =SUMIFS('Saisie hebdo'!$M$5:$M$2000,'Saisie hebdo'!$B$5:$B$2000,$A41,'Saisie hebdo'!$C$5:$C$2000,$B41) | L41: =SUMIFS('Saisie hebdo'!$N$5:$N$2000,'Saisie hebdo'!$B$5:$B$2000,$A41,'Saisie hebdo'!$C$5:$C$2000,$B41) | M41: =SUMIFS('Saisie hebdo'!$O$5:$O$2000,'Saisie hebdo'!$B$5:$B$2000,$A41,'Saisie hebdo'!$C$5:$C$2000,$B41) | N41: =IF(N(D41)=0,"",E41/D41) | O41: =IF(N(E41)=0,"",C41/E41) | P41: =IF(N(E41)=0,"",F41/E41) | Q41: =IF(N(F41)=0,"",C41/F41) | R41: =IF(N(I41)=0,"",C41/I41) | S41: =IF(N(J41)=0,"",C41/J41) | T41: =IF(N(L41)=0,"",C41/L41) | U41: =IF(N(I41)=0,"",J41/I41) | V41: =IF(N(K41)=0,"",L41/K41) | W41: =IF(N(C41)=0,"",M41/C41)
A42: 46419 | B42: Demand Gen | C42: =SUMIFS('Saisie hebdo'!$E$5:$E$2000,'Saisie hebdo'!$B$5:$B$2000,$A42,'Saisie hebdo'!$C$5:$C$2000,$B42) | D42: =SUMIFS('Saisie hebdo'!$F$5:$F$2000,'Saisie hebdo'!$B$5:$B$2000,$A42,'Saisie hebdo'!$C$5:$C$2000,$B42) | E42: =SUMIFS('Saisie hebdo'!$G$5:$G$2000,'Saisie hebdo'!$B$5:$B$2000,$A42,'Saisie hebdo'!$C$5:$C$2000,$B42) | F42: =SUMIFS('Saisie hebdo'!$H$5:$H$2000,'Saisie hebdo'!$B$5:$B$2000,$A42,'Saisie hebdo'!$C$5:$C$2000,$B42) | G42: =IFERROR(AVERAGEIFS('Saisie hebdo'!$I$5:$I$2000,'Saisie hebdo'!$B$5:$B$2000,$A42,'Saisie hebdo'!$C$5:$C$2000,$B42),"") | H42: =IFERROR(AVERAGEIFS('Saisie hebdo'!$J$5:$J$2000,'Saisie hebdo'!$B$5:$B$2000,$A42,'Saisie hebdo'!$C$5:$C$2000,$B42),"") | I42: =SUMIFS('Saisie hebdo'!$K$5:$K$2000,'Saisie hebdo'!$B$5:$B$2000,$A42,'Saisie hebdo'!$C$5:$C$2000,$B42) | J42: =SUMIFS('Saisie hebdo'!$L$5:$L$2000,'Saisie hebdo'!$B$5:$B$2000,$A42,'Saisie hebdo'!$C$5:$C$2000,$B42) | K42: =SUMIFS('Saisie hebdo'!$M$5:$M$2000,'Saisie hebdo'!$B$5:$B$2000,$A42,'Saisie hebdo'!$C$5:$C$2000,$B42) | L42: =SUMIFS('Saisie hebdo'!$N$5:$N$2000,'Saisie hebdo'!$B$5:$B$2000,$A42,'Saisie hebdo'!$C$5:$C$2000,$B42) | M42: =SUMIFS('Saisie hebdo'!$O$5:$O$2000,'Saisie hebdo'!$B$5:$B$2000,$A42,'Saisie hebdo'!$C$5:$C$2000,$B42) | N42: =IF(N(D42)=0,"",E42/D42) | O42: =IF(N(E42)=0,"",C42/E42) | P42: =IF(N(E42)=0,"",F42/E42) | Q42: =IF(N(F42)=0,"",C42/F42) | R42: =IF(N(I42)=0,"",C42/I42) | S42: =IF(N(J42)=0,"",C42/J42) | T42: =IF(N(L42)=0,"",C42/L42) | U42: =IF(N(I42)=0,"",J42/I42) | V42: =IF(N(K42)=0,"",L42/K42) | W42: =IF(N(C42)=0,"",M42/C42)
A43: 46419 | B43: Microsoft Ads | C43: =SUMIFS('Saisie hebdo'!$E$5:$E$2000,'Saisie hebdo'!$B$5:$B$2000,$A43,'Saisie hebdo'!$C$5:$C$2000,$B43) | D43: =SUMIFS('Saisie hebdo'!$F$5:$F$2000,'Saisie hebdo'!$B$5:$B$2000,$A43,'Saisie hebdo'!$C$5:$C$2000,$B43) | E43: =SUMIFS('Saisie hebdo'!$G$5:$G$2000,'Saisie hebdo'!$B$5:$B$2000,$A43,'Saisie hebdo'!$C$5:$C$2000,$B43) | F43: =SUMIFS('Saisie hebdo'!$H$5:$H$2000,'Saisie hebdo'!$B$5:$B$2000,$A43,'Saisie hebdo'!$C$5:$C$2000,$B43) | G43: =IFERROR(AVERAGEIFS('Saisie hebdo'!$I$5:$I$2000,'Saisie hebdo'!$B$5:$B$2000,$A43,'Saisie hebdo'!$C$5:$C$2000,$B43),"") | H43: =IFERROR(AVERAGEIFS('Saisie hebdo'!$J$5:$J$2000,'Saisie hebdo'!$B$5:$B$2000,$A43,'Saisie hebdo'!$C$5:$C$2000,$B43),"") | I43: =SUMIFS('Saisie hebdo'!$K$5:$K$2000,'Saisie hebdo'!$B$5:$B$2000,$A43,'Saisie hebdo'!$C$5:$C$2000,$B43) | J43: =SUMIFS('Saisie hebdo'!$L$5:$L$2000,'Saisie hebdo'!$B$5:$B$2000,$A43,'Saisie hebdo'!$C$5:$C$2000,$B43) | K43: =SUMIFS('Saisie hebdo'!$M$5:$M$2000,'Saisie hebdo'!$B$5:$B$2000,$A43,'Saisie hebdo'!$C$5:$C$2000,$B43) | L43: =SUMIFS('Saisie hebdo'!$N$5:$N$2000,'Saisie hebdo'!$B$5:$B$2000,$A43,'Saisie hebdo'!$C$5:$C$2000,$B43) | M43: =SUMIFS('Saisie hebdo'!$O$5:$O$2000,'Saisie hebdo'!$B$5:$B$2000,$A43,'Saisie hebdo'!$C$5:$C$2000,$B43) | N43: =IF(N(D43)=0,"",E43/D43) | O43: =IF(N(E43)=0,"",C43/E43) | P43: =IF(N(E43)=0,"",F43/E43) | Q43: =IF(N(F43)=0,"",C43/F43) | R43: =IF(N(I43)=0,"",C43/I43) | S43: =IF(N(J43)=0,"",C43/J43) | T43: =IF(N(L43)=0,"",C43/L43) | U43: =IF(N(I43)=0,"",J43/I43) | V43: =IF(N(K43)=0,"",L43/K43) | W43: =IF(N(C43)=0,"",M43/C43)
A44: 46419 | B44: Total du compte | C44: =SUMIFS('Saisie hebdo'!$E$5:$E$2000,'Saisie hebdo'!$B$5:$B$2000,$A44) | D44: =SUMIFS('Saisie hebdo'!$F$5:$F$2000,'Saisie hebdo'!$B$5:$B$2000,$A44) | E44: =SUMIFS('Saisie hebdo'!$G$5:$G$2000,'Saisie hebdo'!$B$5:$B$2000,$A44) | F44: =SUMIFS('Saisie hebdo'!$H$5:$H$2000,'Saisie hebdo'!$B$5:$B$2000,$A44) | G44: =IFERROR(AVERAGEIFS('Saisie hebdo'!$I$5:$I$2000,'Saisie hebdo'!$B$5:$B$2000,$A44),"") | H44: =IFERROR(AVERAGEIFS('Saisie hebdo'!$J$5:$J$2000,'Saisie hebdo'!$B$5:$B$2000,$A44),"") | I44: =SUMIFS('Saisie hebdo'!$K$5:$K$2000,'Saisie hebdo'!$B$5:$B$2000,$A44) | J44: =SUMIFS('Saisie hebdo'!$L$5:$L$2000,'Saisie hebdo'!$B$5:$B$2000,$A44) | K44: =SUMIFS('Saisie hebdo'!$M$5:$M$2000,'Saisie hebdo'!$B$5:$B$2000,$A44) | L44: =SUMIFS('Saisie hebdo'!$N$5:$N$2000,'Saisie hebdo'!$B$5:$B$2000,$A44) | M44: =SUMIFS('Saisie hebdo'!$O$5:$O$2000,'Saisie hebdo'!$B$5:$B$2000,$A44) | N44: =IF(N(D44)=0,"",E44/D44) | O44: =IF(N(E44)=0,"",C44/E44) | P44: =IF(N(E44)=0,"",F44/E44) | Q44: =IF(N(F44)=0,"",C44/F44) | R44: =IF(N(I44)=0,"",C44/I44) | S44: =IF(N(J44)=0,"",C44/J44) | T44: =IF(N(L44)=0,"",C44/L44) | U44: =IF(N(I44)=0,"",J44/I44) | V44: =IF(N(K44)=0,"",L44/K44) | W44: =IF(N(C44)=0,"",M44/C44)
A45: 46447 | B45: S-FR | Marque | C45: =SUMIFS('Saisie hebdo'!$E$5:$E$2000,'Saisie hebdo'!$B$5:$B$2000,$A45,'Saisie hebdo'!$C$5:$C$2000,$B45) | D45: =SUMIFS('Saisie hebdo'!$F$5:$F$2000,'Saisie hebdo'!$B$5:$B$2000,$A45,'Saisie hebdo'!$C$5:$C$2000,$B45) | E45: =SUMIFS('Saisie hebdo'!$G$5:$G$2000,'Saisie hebdo'!$B$5:$B$2000,$A45,'Saisie hebdo'!$C$5:$C$2000,$B45) | F45: =SUMIFS('Saisie hebdo'!$H$5:$H$2000,'Saisie hebdo'!$B$5:$B$2000,$A45,'Saisie hebdo'!$C$5:$C$2000,$B45) | G45: =IFERROR(AVERAGEIFS('Saisie hebdo'!$I$5:$I$2000,'Saisie hebdo'!$B$5:$B$2000,$A45,'Saisie hebdo'!$C$5:$C$2000,$B45),"") | H45: =IFERROR(AVERAGEIFS('Saisie hebdo'!$J$5:$J$2000,'Saisie hebdo'!$B$5:$B$2000,$A45,'Saisie hebdo'!$C$5:$C$2000,$B45),"") | I45: =SUMIFS('Saisie hebdo'!$K$5:$K$2000,'Saisie hebdo'!$B$5:$B$2000,$A45,'Saisie hebdo'!$C$5:$C$2000,$B45) | J45: =SUMIFS('Saisie hebdo'!$L$5:$L$2000,'Saisie hebdo'!$B$5:$B$2000,$A45,'Saisie hebdo'!$C$5:$C$2000,$B45) | K45: =SUMIFS('Saisie hebdo'!$M$5:$M$2000,'Saisie hebdo'!$B$5:$B$2000,$A45,'Saisie hebdo'!$C$5:$C$2000,$B45) | L45: =SUMIFS('Saisie hebdo'!$N$5:$N$2000,'Saisie hebdo'!$B$5:$B$2000,$A45,'Saisie hebdo'!$C$5:$C$2000,$B45) | M45: =SUMIFS('Saisie hebdo'!$O$5:$O$2000,'Saisie hebdo'!$B$5:$B$2000,$A45,'Saisie hebdo'!$C$5:$C$2000,$B45) | N45: =IF(N(D45)=0,"",E45/D45) | O45: =IF(N(E45)=0,"",C45/E45) | P45: =IF(N(E45)=0,"",F45/E45) | Q45: =IF(N(F45)=0,"",C45/F45) | R45: =IF(N(I45)=0,"",C45/I45) | S45: =IF(N(J45)=0,"",C45/J45) | T45: =IF(N(L45)=0,"",C45/L45) | U45: =IF(N(I45)=0,"",J45/I45) | V45: =IF(N(K45)=0,"",L45/K45) | W45: =IF(N(C45)=0,"",M45/C45)
A46: 46447 | B46: S-FR | Corporatif & Fêtes | C46: =SUMIFS('Saisie hebdo'!$E$5:$E$2000,'Saisie hebdo'!$B$5:$B$2000,$A46,'Saisie hebdo'!$C$5:$C$2000,$B46) | D46: =SUMIFS('Saisie hebdo'!$F$5:$F$2000,'Saisie hebdo'!$B$5:$B$2000,$A46,'Saisie hebdo'!$C$5:$C$2000,$B46) | E46: =SUMIFS('Saisie hebdo'!$G$5:$G$2000,'Saisie hebdo'!$B$5:$B$2000,$A46,'Saisie hebdo'!$C$5:$C$2000,$B46) | F46: =SUMIFS('Saisie hebdo'!$H$5:$H$2000,'Saisie hebdo'!$B$5:$B$2000,$A46,'Saisie hebdo'!$C$5:$C$2000,$B46) | G46: =IFERROR(AVERAGEIFS('Saisie hebdo'!$I$5:$I$2000,'Saisie hebdo'!$B$5:$B$2000,$A46,'Saisie hebdo'!$C$5:$C$2000,$B46),"") | H46: =IFERROR(AVERAGEIFS('Saisie hebdo'!$J$5:$J$2000,'Saisie hebdo'!$B$5:$B$2000,$A46,'Saisie hebdo'!$C$5:$C$2000,$B46),"") | I46: =SUMIFS('Saisie hebdo'!$K$5:$K$2000,'Saisie hebdo'!$B$5:$B$2000,$A46,'Saisie hebdo'!$C$5:$C$2000,$B46) | J46: =SUMIFS('Saisie hebdo'!$L$5:$L$2000,'Saisie hebdo'!$B$5:$B$2000,$A46,'Saisie hebdo'!$C$5:$C$2000,$B46) | K46: =SUMIFS('Saisie hebdo'!$M$5:$M$2000,'Saisie hebdo'!$B$5:$B$2000,$A46,'Saisie hebdo'!$C$5:$C$2000,$B46) | L46: =SUMIFS('Saisie hebdo'!$N$5:$N$2000,'Saisie hebdo'!$B$5:$B$2000,$A46,'Saisie hebdo'!$C$5:$C$2000,$B46) | M46: =SUMIFS('Saisie hebdo'!$O$5:$O$2000,'Saisie hebdo'!$B$5:$B$2000,$A46,'Saisie hebdo'!$C$5:$C$2000,$B46) | N46: =IF(N(D46)=0,"",E46/D46) | O46: =IF(N(E46)=0,"",C46/E46) | P46: =IF(N(E46)=0,"",F46/E46) | Q46: =IF(N(F46)=0,"",C46/F46) | R46: =IF(N(I46)=0,"",C46/I46) | S46: =IF(N(J46)=0,"",C46/J46) | T46: =IF(N(L46)=0,"",C46/L46) | U46: =IF(N(I46)=0,"",J46/I46) | V46: =IF(N(K46)=0,"",L46/K46) | W46: =IF(N(C46)=0,"",M46/C46)
A47: 46447 | B47: S-FR | Événements privés | C47: =SUMIFS('Saisie hebdo'!$E$5:$E$2000,'Saisie hebdo'!$B$5:$B$2000,$A47,'Saisie hebdo'!$C$5:$C$2000,$B47) | D47: =SUMIFS('Saisie hebdo'!$F$5:$F$2000,'Saisie hebdo'!$B$5:$B$2000,$A47,'Saisie hebdo'!$C$5:$C$2000,$B47) | E47: =SUMIFS('Saisie hebdo'!$G$5:$G$2000,'Saisie hebdo'!$B$5:$B$2000,$A47,'Saisie hebdo'!$C$5:$C$2000,$B47) | F47: =SUMIFS('Saisie hebdo'!$H$5:$H$2000,'Saisie hebdo'!$B$5:$B$2000,$A47,'Saisie hebdo'!$C$5:$C$2000,$B47) | G47: =IFERROR(AVERAGEIFS('Saisie hebdo'!$I$5:$I$2000,'Saisie hebdo'!$B$5:$B$2000,$A47,'Saisie hebdo'!$C$5:$C$2000,$B47),"") | H47: =IFERROR(AVERAGEIFS('Saisie hebdo'!$J$5:$J$2000,'Saisie hebdo'!$B$5:$B$2000,$A47,'Saisie hebdo'!$C$5:$C$2000,$B47),"") | I47: =SUMIFS('Saisie hebdo'!$K$5:$K$2000,'Saisie hebdo'!$B$5:$B$2000,$A47,'Saisie hebdo'!$C$5:$C$2000,$B47) | J47: =SUMIFS('Saisie hebdo'!$L$5:$L$2000,'Saisie hebdo'!$B$5:$B$2000,$A47,'Saisie hebdo'!$C$5:$C$2000,$B47) | K47: =SUMIFS('Saisie hebdo'!$M$5:$M$2000,'Saisie hebdo'!$B$5:$B$2000,$A47,'Saisie hebdo'!$C$5:$C$2000,$B47) | L47: =SUMIFS('Saisie hebdo'!$N$5:$N$2000,'Saisie hebdo'!$B$5:$B$2000,$A47,'Saisie hebdo'!$C$5:$C$2000,$B47) | M47: =SUMIFS('Saisie hebdo'!$O$5:$O$2000,'Saisie hebdo'!$B$5:$B$2000,$A47,'Saisie hebdo'!$C$5:$C$2000,$B47) | N47: =IF(N(D47)=0,"",E47/D47) | O47: =IF(N(E47)=0,"",C47/E47) | P47: =IF(N(E47)=0,"",F47/E47) | Q47: =IF(N(F47)=0,"",C47/F47) | R47: =IF(N(I47)=0,"",C47/I47) | S47: =IF(N(J47)=0,"",C47/J47) | T47: =IF(N(L47)=0,"",C47/L47) | U47: =IF(N(I47)=0,"",J47/I47) | V47: =IF(N(K47)=0,"",L47/K47) | W47: =IF(N(C47)=0,"",M47/C47)
A48: 46447 | B48: S-EN | Corporate Montréal | C48: =SUMIFS('Saisie hebdo'!$E$5:$E$2000,'Saisie hebdo'!$B$5:$B$2000,$A48,'Saisie hebdo'!$C$5:$C$2000,$B48) | D48: =SUMIFS('Saisie hebdo'!$F$5:$F$2000,'Saisie hebdo'!$B$5:$B$2000,$A48,'Saisie hebdo'!$C$5:$C$2000,$B48) | E48: =SUMIFS('Saisie hebdo'!$G$5:$G$2000,'Saisie hebdo'!$B$5:$B$2000,$A48,'Saisie hebdo'!$C$5:$C$2000,$B48) | F48: =SUMIFS('Saisie hebdo'!$H$5:$H$2000,'Saisie hebdo'!$B$5:$B$2000,$A48,'Saisie hebdo'!$C$5:$C$2000,$B48) | G48: =IFERROR(AVERAGEIFS('Saisie hebdo'!$I$5:$I$2000,'Saisie hebdo'!$B$5:$B$2000,$A48,'Saisie hebdo'!$C$5:$C$2000,$B48),"") | H48: =IFERROR(AVERAGEIFS('Saisie hebdo'!$J$5:$J$2000,'Saisie hebdo'!$B$5:$B$2000,$A48,'Saisie hebdo'!$C$5:$C$2000,$B48),"") | I48: =SUMIFS('Saisie hebdo'!$K$5:$K$2000,'Saisie hebdo'!$B$5:$B$2000,$A48,'Saisie hebdo'!$C$5:$C$2000,$B48) | J48: =SUMIFS('Saisie hebdo'!$L$5:$L$2000,'Saisie hebdo'!$B$5:$B$2000,$A48,'Saisie hebdo'!$C$5:$C$2000,$B48) | K48: =SUMIFS('Saisie hebdo'!$M$5:$M$2000,'Saisie hebdo'!$B$5:$B$2000,$A48,'Saisie hebdo'!$C$5:$C$2000,$B48) | L48: =SUMIFS('Saisie hebdo'!$N$5:$N$2000,'Saisie hebdo'!$B$5:$B$2000,$A48,'Saisie hebdo'!$C$5:$C$2000,$B48) | M48: =SUMIFS('Saisie hebdo'!$O$5:$O$2000,'Saisie hebdo'!$B$5:$B$2000,$A48,'Saisie hebdo'!$C$5:$C$2000,$B48) | N48: =IF(N(D48)=0,"",E48/D48) | O48: =IF(N(E48)=0,"",C48/E48) | P48: =IF(N(E48)=0,"",F48/E48) | Q48: =IF(N(F48)=0,"",C48/F48) | R48: =IF(N(I48)=0,"",C48/I48) | S48: =IF(N(J48)=0,"",C48/J48) | T48: =IF(N(L48)=0,"",C48/L48) | U48: =IF(N(I48)=0,"",J48/I48) | V48: =IF(N(K48)=0,"",L48/K48) | W48: =IF(N(C48)=0,"",M48/C48)
A49: 46447 | B49: S-FR | Québec-Lévis (test) | C49: =SUMIFS('Saisie hebdo'!$E$5:$E$2000,'Saisie hebdo'!$B$5:$B$2000,$A49,'Saisie hebdo'!$C$5:$C$2000,$B49) | D49: =SUMIFS('Saisie hebdo'!$F$5:$F$2000,'Saisie hebdo'!$B$5:$B$2000,$A49,'Saisie hebdo'!$C$5:$C$2000,$B49) | E49: =SUMIFS('Saisie hebdo'!$G$5:$G$2000,'Saisie hebdo'!$B$5:$B$2000,$A49,'Saisie hebdo'!$C$5:$C$2000,$B49) | F49: =SUMIFS('Saisie hebdo'!$H$5:$H$2000,'Saisie hebdo'!$B$5:$B$2000,$A49,'Saisie hebdo'!$C$5:$C$2000,$B49) | G49: =IFERROR(AVERAGEIFS('Saisie hebdo'!$I$5:$I$2000,'Saisie hebdo'!$B$5:$B$2000,$A49,'Saisie hebdo'!$C$5:$C$2000,$B49),"") | H49: =IFERROR(AVERAGEIFS('Saisie hebdo'!$J$5:$J$2000,'Saisie hebdo'!$B$5:$B$2000,$A49,'Saisie hebdo'!$C$5:$C$2000,$B49),"") | I49: =SUMIFS('Saisie hebdo'!$K$5:$K$2000,'Saisie hebdo'!$B$5:$B$2000,$A49,'Saisie hebdo'!$C$5:$C$2000,$B49) | J49: =SUMIFS('Saisie hebdo'!$L$5:$L$2000,'Saisie hebdo'!$B$5:$B$2000,$A49,'Saisie hebdo'!$C$5:$C$2000,$B49) | K49: =SUMIFS('Saisie hebdo'!$M$5:$M$2000,'Saisie hebdo'!$B$5:$B$2000,$A49,'Saisie hebdo'!$C$5:$C$2000,$B49) | L49: =SUMIFS('Saisie hebdo'!$N$5:$N$2000,'Saisie hebdo'!$B$5:$B$2000,$A49,'Saisie hebdo'!$C$5:$C$2000,$B49) | M49: =SUMIFS('Saisie hebdo'!$O$5:$O$2000,'Saisie hebdo'!$B$5:$B$2000,$A49,'Saisie hebdo'!$C$5:$C$2000,$B49) | N49: =IF(N(D49)=0,"",E49/D49) | O49: =IF(N(E49)=0,"",C49/E49) | P49: =IF(N(E49)=0,"",F49/E49) | Q49: =IF(N(F49)=0,"",C49/F49) | R49: =IF(N(I49)=0,"",C49/I49) | S49: =IF(N(J49)=0,"",C49/J49) | T49: =IF(N(L49)=0,"",C49/L49) | U49: =IF(N(I49)=0,"",J49/I49) | V49: =IF(N(K49)=0,"",L49/K49) | W49: =IF(N(C49)=0,"",M49/C49)
A50: 46447 | B50: Demand Gen | C50: =SUMIFS('Saisie hebdo'!$E$5:$E$2000,'Saisie hebdo'!$B$5:$B$2000,$A50,'Saisie hebdo'!$C$5:$C$2000,$B50) | D50: =SUMIFS('Saisie hebdo'!$F$5:$F$2000,'Saisie hebdo'!$B$5:$B$2000,$A50,'Saisie hebdo'!$C$5:$C$2000,$B50) | E50: =SUMIFS('Saisie hebdo'!$G$5:$G$2000,'Saisie hebdo'!$B$5:$B$2000,$A50,'Saisie hebdo'!$C$5:$C$2000,$B50) | F50: =SUMIFS('Saisie hebdo'!$H$5:$H$2000,'Saisie hebdo'!$B$5:$B$2000,$A50,'Saisie hebdo'!$C$5:$C$2000,$B50) | G50: =IFERROR(AVERAGEIFS('Saisie hebdo'!$I$5:$I$2000,'Saisie hebdo'!$B$5:$B$2000,$A50,'Saisie hebdo'!$C$5:$C$2000,$B50),"") | H50: =IFERROR(AVERAGEIFS('Saisie hebdo'!$J$5:$J$2000,'Saisie hebdo'!$B$5:$B$2000,$A50,'Saisie hebdo'!$C$5:$C$2000,$B50),"") | I50: =SUMIFS('Saisie hebdo'!$K$5:$K$2000,'Saisie hebdo'!$B$5:$B$2000,$A50,'Saisie hebdo'!$C$5:$C$2000,$B50) | J50: =SUMIFS('Saisie hebdo'!$L$5:$L$2000,'Saisie hebdo'!$B$5:$B$2000,$A50,'Saisie hebdo'!$C$5:$C$2000,$B50) | K50: =SUMIFS('Saisie hebdo'!$M$5:$M$2000,'Saisie hebdo'!$B$5:$B$2000,$A50,'Saisie hebdo'!$C$5:$C$2000,$B50) | L50: =SUMIFS('Saisie hebdo'!$N$5:$N$2000,'Saisie hebdo'!$B$5:$B$2000,$A50,'Saisie hebdo'!$C$5:$C$2000,$B50) | M50: =SUMIFS('Saisie hebdo'!$O$5:$O$2000,'Saisie hebdo'!$B$5:$B$2000,$A50,'Saisie hebdo'!$C$5:$C$2000,$B50) | N50: =IF(N(D50)=0,"",E50/D50) | O50: =IF(N(E50)=0,"",C50/E50) | P50: =IF(N(E50)=0,"",F50/E50) | Q50: =IF(N(F50)=0,"",C50/F50) | R50: =IF(N(I50)=0,"",C50/I50) | S50: =IF(N(J50)=0,"",C50/J50) | T50: =IF(N(L50)=0,"",C50/L50) | U50: =IF(N(I50)=0,"",J50/I50) | V50: =IF(N(K50)=0,"",L50/K50) | W50: =IF(N(C50)=0,"",M50/C50)
A51: 46447 | B51: Microsoft Ads | C51: =SUMIFS('Saisie hebdo'!$E$5:$E$2000,'Saisie hebdo'!$B$5:$B$2000,$A51,'Saisie hebdo'!$C$5:$C$2000,$B51) | D51: =SUMIFS('Saisie hebdo'!$F$5:$F$2000,'Saisie hebdo'!$B$5:$B$2000,$A51,'Saisie hebdo'!$C$5:$C$2000,$B51) | E51: =SUMIFS('Saisie hebdo'!$G$5:$G$2000,'Saisie hebdo'!$B$5:$B$2000,$A51,'Saisie hebdo'!$C$5:$C$2000,$B51) | F51: =SUMIFS('Saisie hebdo'!$H$5:$H$2000,'Saisie hebdo'!$B$5:$B$2000,$A51,'Saisie hebdo'!$C$5:$C$2000,$B51) | G51: =IFERROR(AVERAGEIFS('Saisie hebdo'!$I$5:$I$2000,'Saisie hebdo'!$B$5:$B$2000,$A51,'Saisie hebdo'!$C$5:$C$2000,$B51),"") | H51: =IFERROR(AVERAGEIFS('Saisie hebdo'!$J$5:$J$2000,'Saisie hebdo'!$B$5:$B$2000,$A51,'Saisie hebdo'!$C$5:$C$2000,$B51),"") | I51: =SUMIFS('Saisie hebdo'!$K$5:$K$2000,'Saisie hebdo'!$B$5:$B$2000,$A51,'Saisie hebdo'!$C$5:$C$2000,$B51) | J51: =SUMIFS('Saisie hebdo'!$L$5:$L$2000,'Saisie hebdo'!$B$5:$B$2000,$A51,'Saisie hebdo'!$C$5:$C$2000,$B51) | K51: =SUMIFS('Saisie hebdo'!$M$5:$M$2000,'Saisie hebdo'!$B$5:$B$2000,$A51,'Saisie hebdo'!$C$5:$C$2000,$B51) | L51: =SUMIFS('Saisie hebdo'!$N$5:$N$2000,'Saisie hebdo'!$B$5:$B$2000,$A51,'Saisie hebdo'!$C$5:$C$2000,$B51) | M51: =SUMIFS('Saisie hebdo'!$O$5:$O$2000,'Saisie hebdo'!$B$5:$B$2000,$A51,'Saisie hebdo'!$C$5:$C$2000,$B51) | N51: =IF(N(D51)=0,"",E51/D51) | O51: =IF(N(E51)=0,"",C51/E51) | P51: =IF(N(E51)=0,"",F51/E51) | Q51: =IF(N(F51)=0,"",C51/F51) | R51: =IF(N(I51)=0,"",C51/I51) | S51: =IF(N(J51)=0,"",C51/J51) | T51: =IF(N(L51)=0,"",C51/L51) | U51: =IF(N(I51)=0,"",J51/I51) | V51: =IF(N(K51)=0,"",L51/K51) | W51: =IF(N(C51)=0,"",M51/C51)
A52: 46447 | B52: Total du compte | C52: =SUMIFS('Saisie hebdo'!$E$5:$E$2000,'Saisie hebdo'!$B$5:$B$2000,$A52) | D52: =SUMIFS('Saisie hebdo'!$F$5:$F$2000,'Saisie hebdo'!$B$5:$B$2000,$A52) | E52: =SUMIFS('Saisie hebdo'!$G$5:$G$2000,'Saisie hebdo'!$B$5:$B$2000,$A52) | F52: =SUMIFS('Saisie hebdo'!$H$5:$H$2000,'Saisie hebdo'!$B$5:$B$2000,$A52) | G52: =IFERROR(AVERAGEIFS('Saisie hebdo'!$I$5:$I$2000,'Saisie hebdo'!$B$5:$B$2000,$A52),"") | H52: =IFERROR(AVERAGEIFS('Saisie hebdo'!$J$5:$J$2000,'Saisie hebdo'!$B$5:$B$2000,$A52),"") | I52: =SUMIFS('Saisie hebdo'!$K$5:$K$2000,'Saisie hebdo'!$B$5:$B$2000,$A52) | J52: =SUMIFS('Saisie hebdo'!$L$5:$L$2000,'Saisie hebdo'!$B$5:$B$2000,$A52) | K52: =SUMIFS('Saisie hebdo'!$M$5:$M$2000,'Saisie hebdo'!$B$5:$B$2000,$A52) | L52: =SUMIFS('Saisie hebdo'!$N$5:$N$2000,'Saisie hebdo'!$B$5:$B$2000,$A52) | M52: =SUMIFS('Saisie hebdo'!$O$5:$O$2000,'Saisie hebdo'!$B$5:$B$2000,$A52) | N52: =IF(N(D52)=0,"",E52/D52) | O52: =IF(N(E52)=0,"",C52/E52) | P52: =IF(N(E52)=0,"",F52/E52) | Q52: =IF(N(F52)=0,"",C52/F52) | R52: =IF(N(I52)=0,"",C52/I52) | S52: =IF(N(J52)=0,"",C52/J52) | T52: =IF(N(L52)=0,"",C52/L52) | U52: =IF(N(I52)=0,"",J52/I52) | V52: =IF(N(K52)=0,"",L52/K52) | W52: =IF(N(C52)=0,"",M52/C52)
A53: 46478 | B53: S-FR | Marque | C53: =SUMIFS('Saisie hebdo'!$E$5:$E$2000,'Saisie hebdo'!$B$5:$B$2000,$A53,'Saisie hebdo'!$C$5:$C$2000,$B53) | D53: =SUMIFS('Saisie hebdo'!$F$5:$F$2000,'Saisie hebdo'!$B$5:$B$2000,$A53,'Saisie hebdo'!$C$5:$C$2000,$B53) | E53: =SUMIFS('Saisie hebdo'!$G$5:$G$2000,'Saisie hebdo'!$B$5:$B$2000,$A53,'Saisie hebdo'!$C$5:$C$2000,$B53) | F53: =SUMIFS('Saisie hebdo'!$H$5:$H$2000,'Saisie hebdo'!$B$5:$B$2000,$A53,'Saisie hebdo'!$C$5:$C$2000,$B53) | G53: =IFERROR(AVERAGEIFS('Saisie hebdo'!$I$5:$I$2000,'Saisie hebdo'!$B$5:$B$2000,$A53,'Saisie hebdo'!$C$5:$C$2000,$B53),"") | H53: =IFERROR(AVERAGEIFS('Saisie hebdo'!$J$5:$J$2000,'Saisie hebdo'!$B$5:$B$2000,$A53,'Saisie hebdo'!$C$5:$C$2000,$B53),"") | I53: =SUMIFS('Saisie hebdo'!$K$5:$K$2000,'Saisie hebdo'!$B$5:$B$2000,$A53,'Saisie hebdo'!$C$5:$C$2000,$B53) | J53: =SUMIFS('Saisie hebdo'!$L$5:$L$2000,'Saisie hebdo'!$B$5:$B$2000,$A53,'Saisie hebdo'!$C$5:$C$2000,$B53) | K53: =SUMIFS('Saisie hebdo'!$M$5:$M$2000,'Saisie hebdo'!$B$5:$B$2000,$A53,'Saisie hebdo'!$C$5:$C$2000,$B53) | L53: =SUMIFS('Saisie hebdo'!$N$5:$N$2000,'Saisie hebdo'!$B$5:$B$2000,$A53,'Saisie hebdo'!$C$5:$C$2000,$B53) | M53: =SUMIFS('Saisie hebdo'!$O$5:$O$2000,'Saisie hebdo'!$B$5:$B$2000,$A53,'Saisie hebdo'!$C$5:$C$2000,$B53) | N53: =IF(N(D53)=0,"",E53/D53) | O53: =IF(N(E53)=0,"",C53/E53) | P53: =IF(N(E53)=0,"",F53/E53) | Q53: =IF(N(F53)=0,"",C53/F53) | R53: =IF(N(I53)=0,"",C53/I53) | S53: =IF(N(J53)=0,"",C53/J53) | T53: =IF(N(L53)=0,"",C53/L53) | U53: =IF(N(I53)=0,"",J53/I53) | V53: =IF(N(K53)=0,"",L53/K53) | W53: =IF(N(C53)=0,"",M53/C53)
A54: 46478 | B54: S-FR | Corporatif & Fêtes | C54: =SUMIFS('Saisie hebdo'!$E$5:$E$2000,'Saisie hebdo'!$B$5:$B$2000,$A54,'Saisie hebdo'!$C$5:$C$2000,$B54) | D54: =SUMIFS('Saisie hebdo'!$F$5:$F$2000,'Saisie hebdo'!$B$5:$B$2000,$A54,'Saisie hebdo'!$C$5:$C$2000,$B54) | E54: =SUMIFS('Saisie hebdo'!$G$5:$G$2000,'Saisie hebdo'!$B$5:$B$2000,$A54,'Saisie hebdo'!$C$5:$C$2000,$B54) | F54: =SUMIFS('Saisie hebdo'!$H$5:$H$2000,'Saisie hebdo'!$B$5:$B$2000,$A54,'Saisie hebdo'!$C$5:$C$2000,$B54) | G54: =IFERROR(AVERAGEIFS('Saisie hebdo'!$I$5:$I$2000,'Saisie hebdo'!$B$5:$B$2000,$A54,'Saisie hebdo'!$C$5:$C$2000,$B54),"") | H54: =IFERROR(AVERAGEIFS('Saisie hebdo'!$J$5:$J$2000,'Saisie hebdo'!$B$5:$B$2000,$A54,'Saisie hebdo'!$C$5:$C$2000,$B54),"") | I54: =SUMIFS('Saisie hebdo'!$K$5:$K$2000,'Saisie hebdo'!$B$5:$B$2000,$A54,'Saisie hebdo'!$C$5:$C$2000,$B54) | J54: =SUMIFS('Saisie hebdo'!$L$5:$L$2000,'Saisie hebdo'!$B$5:$B$2000,$A54,'Saisie hebdo'!$C$5:$C$2000,$B54) | K54: =SUMIFS('Saisie hebdo'!$M$5:$M$2000,'Saisie hebdo'!$B$5:$B$2000,$A54,'Saisie hebdo'!$C$5:$C$2000,$B54) | L54: =SUMIFS('Saisie hebdo'!$N$5:$N$2000,'Saisie hebdo'!$B$5:$B$2000,$A54,'Saisie hebdo'!$C$5:$C$2000,$B54) | M54: =SUMIFS('Saisie hebdo'!$O$5:$O$2000,'Saisie hebdo'!$B$5:$B$2000,$A54,'Saisie hebdo'!$C$5:$C$2000,$B54) | N54: =IF(N(D54)=0,"",E54/D54) | O54: =IF(N(E54)=0,"",C54/E54) | P54: =IF(N(E54)=0,"",F54/E54) | Q54: =IF(N(F54)=0,"",C54/F54) | R54: =IF(N(I54)=0,"",C54/I54) | S54: =IF(N(J54)=0,"",C54/J54) | T54: =IF(N(L54)=0,"",C54/L54) | U54: =IF(N(I54)=0,"",J54/I54) | V54: =IF(N(K54)=0,"",L54/K54) | W54: =IF(N(C54)=0,"",M54/C54)
A55: 46478 | B55: S-FR | Événements privés | C55: =SUMIFS('Saisie hebdo'!$E$5:$E$2000,'Saisie hebdo'!$B$5:$B$2000,$A55,'Saisie hebdo'!$C$5:$C$2000,$B55) | D55: =SUMIFS('Saisie hebdo'!$F$5:$F$2000,'Saisie hebdo'!$B$5:$B$2000,$A55,'Saisie hebdo'!$C$5:$C$2000,$B55) | E55: =SUMIFS('Saisie hebdo'!$G$5:$G$2000,'Saisie hebdo'!$B$5:$B$2000,$A55,'Saisie hebdo'!$C$5:$C$2000,$B55) | F55: =SUMIFS('Saisie hebdo'!$H$5:$H$2000,'Saisie hebdo'!$B$5:$B$2000,$A55,'Saisie hebdo'!$C$5:$C$2000,$B55) | G55: =IFERROR(AVERAGEIFS('Saisie hebdo'!$I$5:$I$2000,'Saisie hebdo'!$B$5:$B$2000,$A55,'Saisie hebdo'!$C$5:$C$2000,$B55),"") | H55: =IFERROR(AVERAGEIFS('Saisie hebdo'!$J$5:$J$2000,'Saisie hebdo'!$B$5:$B$2000,$A55,'Saisie hebdo'!$C$5:$C$2000,$B55),"") | I55: =SUMIFS('Saisie hebdo'!$K$5:$K$2000,'Saisie hebdo'!$B$5:$B$2000,$A55,'Saisie hebdo'!$C$5:$C$2000,$B55) | J55: =SUMIFS('Saisie hebdo'!$L$5:$L$2000,'Saisie hebdo'!$B$5:$B$2000,$A55,'Saisie hebdo'!$C$5:$C$2000,$B55) | K55: =SUMIFS('Saisie hebdo'!$M$5:$M$2000,'Saisie hebdo'!$B$5:$B$2000,$A55,'Saisie hebdo'!$C$5:$C$2000,$B55) | L55: =SUMIFS('Saisie hebdo'!$N$5:$N$2000,'Saisie hebdo'!$B$5:$B$2000,$A55,'Saisie hebdo'!$C$5:$C$2000,$B55) | M55: =SUMIFS('Saisie hebdo'!$O$5:$O$2000,'Saisie hebdo'!$B$5:$B$2000,$A55,'Saisie hebdo'!$C$5:$C$2000,$B55) | N55: =IF(N(D55)=0,"",E55/D55) | O55: =IF(N(E55)=0,"",C55/E55) | P55: =IF(N(E55)=0,"",F55/E55) | Q55: =IF(N(F55)=0,"",C55/F55) | R55: =IF(N(I55)=0,"",C55/I55) | S55: =IF(N(J55)=0,"",C55/J55) | T55: =IF(N(L55)=0,"",C55/L55) | U55: =IF(N(I55)=0,"",J55/I55) | V55: =IF(N(K55)=0,"",L55/K55) | W55: =IF(N(C55)=0,"",M55/C55)
A56: 46478 | B56: S-EN | Corporate Montréal | C56: =SUMIFS('Saisie hebdo'!$E$5:$E$2000,'Saisie hebdo'!$B$5:$B$2000,$A56,'Saisie hebdo'!$C$5:$C$2000,$B56) | D56: =SUMIFS('Saisie hebdo'!$F$5:$F$2000,'Saisie hebdo'!$B$5:$B$2000,$A56,'Saisie hebdo'!$C$5:$C$2000,$B56) | E56: =SUMIFS('Saisie hebdo'!$G$5:$G$2000,'Saisie hebdo'!$B$5:$B$2000,$A56,'Saisie hebdo'!$C$5:$C$2000,$B56) | F56: =SUMIFS('Saisie hebdo'!$H$5:$H$2000,'Saisie hebdo'!$B$5:$B$2000,$A56,'Saisie hebdo'!$C$5:$C$2000,$B56) | G56: =IFERROR(AVERAGEIFS('Saisie hebdo'!$I$5:$I$2000,'Saisie hebdo'!$B$5:$B$2000,$A56,'Saisie hebdo'!$C$5:$C$2000,$B56),"") | H56: =IFERROR(AVERAGEIFS('Saisie hebdo'!$J$5:$J$2000,'Saisie hebdo'!$B$5:$B$2000,$A56,'Saisie hebdo'!$C$5:$C$2000,$B56),"") | I56: =SUMIFS('Saisie hebdo'!$K$5:$K$2000,'Saisie hebdo'!$B$5:$B$2000,$A56,'Saisie hebdo'!$C$5:$C$2000,$B56) | J56: =SUMIFS('Saisie hebdo'!$L$5:$L$2000,'Saisie hebdo'!$B$5:$B$2000,$A56,'Saisie hebdo'!$C$5:$C$2000,$B56) | K56: =SUMIFS('Saisie hebdo'!$M$5:$M$2000,'Saisie hebdo'!$B$5:$B$2000,$A56,'Saisie hebdo'!$C$5:$C$2000,$B56) | L56: =SUMIFS('Saisie hebdo'!$N$5:$N$2000,'Saisie hebdo'!$B$5:$B$2000,$A56,'Saisie hebdo'!$C$5:$C$2000,$B56) | M56: =SUMIFS('Saisie hebdo'!$O$5:$O$2000,'Saisie hebdo'!$B$5:$B$2000,$A56,'Saisie hebdo'!$C$5:$C$2000,$B56) | N56: =IF(N(D56)=0,"",E56/D56) | O56: =IF(N(E56)=0,"",C56/E56) | P56: =IF(N(E56)=0,"",F56/E56) | Q56: =IF(N(F56)=0,"",C56/F56) | R56: =IF(N(I56)=0,"",C56/I56) | S56: =IF(N(J56)=0,"",C56/J56) | T56: =IF(N(L56)=0,"",C56/L56) | U56: =IF(N(I56)=0,"",J56/I56) | V56: =IF(N(K56)=0,"",L56/K56) | W56: =IF(N(C56)=0,"",M56/C56)
A57: 46478 | B57: S-FR | Québec-Lévis (test) | C57: =SUMIFS('Saisie hebdo'!$E$5:$E$2000,'Saisie hebdo'!$B$5:$B$2000,$A57,'Saisie hebdo'!$C$5:$C$2000,$B57) | D57: =SUMIFS('Saisie hebdo'!$F$5:$F$2000,'Saisie hebdo'!$B$5:$B$2000,$A57,'Saisie hebdo'!$C$5:$C$2000,$B57) | E57: =SUMIFS('Saisie hebdo'!$G$5:$G$2000,'Saisie hebdo'!$B$5:$B$2000,$A57,'Saisie hebdo'!$C$5:$C$2000,$B57) | F57: =SUMIFS('Saisie hebdo'!$H$5:$H$2000,'Saisie hebdo'!$B$5:$B$2000,$A57,'Saisie hebdo'!$C$5:$C$2000,$B57) | G57: =IFERROR(AVERAGEIFS('Saisie hebdo'!$I$5:$I$2000,'Saisie hebdo'!$B$5:$B$2000,$A57,'Saisie hebdo'!$C$5:$C$2000,$B57),"") | H57: =IFERROR(AVERAGEIFS('Saisie hebdo'!$J$5:$J$2000,'Saisie hebdo'!$B$5:$B$2000,$A57,'Saisie hebdo'!$C$5:$C$2000,$B57),"") | I57: =SUMIFS('Saisie hebdo'!$K$5:$K$2000,'Saisie hebdo'!$B$5:$B$2000,$A57,'Saisie hebdo'!$C$5:$C$2000,$B57) | J57: =SUMIFS('Saisie hebdo'!$L$5:$L$2000,'Saisie hebdo'!$B$5:$B$2000,$A57,'Saisie hebdo'!$C$5:$C$2000,$B57) | K57: =SUMIFS('Saisie hebdo'!$M$5:$M$2000,'Saisie hebdo'!$B$5:$B$2000,$A57,'Saisie hebdo'!$C$5:$C$2000,$B57) | L57: =SUMIFS('Saisie hebdo'!$N$5:$N$2000,'Saisie hebdo'!$B$5:$B$2000,$A57,'Saisie hebdo'!$C$5:$C$2000,$B57) | M57: =SUMIFS('Saisie hebdo'!$O$5:$O$2000,'Saisie hebdo'!$B$5:$B$2000,$A57,'Saisie hebdo'!$C$5:$C$2000,$B57) | N57: =IF(N(D57)=0,"",E57/D57) | O57: =IF(N(E57)=0,"",C57/E57) | P57: =IF(N(E57)=0,"",F57/E57) | Q57: =IF(N(F57)=0,"",C57/F57) | R57: =IF(N(I57)=0,"",C57/I57) | S57: =IF(N(J57)=0,"",C57/J57) | T57: =IF(N(L57)=0,"",C57/L57) | U57: =IF(N(I57)=0,"",J57/I57) | V57: =IF(N(K57)=0,"",L57/K57) | W57: =IF(N(C57)=0,"",M57/C57)
A58: 46478 | B58: Demand Gen | C58: =SUMIFS('Saisie hebdo'!$E$5:$E$2000,'Saisie hebdo'!$B$5:$B$2000,$A58,'Saisie hebdo'!$C$5:$C$2000,$B58) | D58: =SUMIFS('Saisie hebdo'!$F$5:$F$2000,'Saisie hebdo'!$B$5:$B$2000,$A58,'Saisie hebdo'!$C$5:$C$2000,$B58) | E58: =SUMIFS('Saisie hebdo'!$G$5:$G$2000,'Saisie hebdo'!$B$5:$B$2000,$A58,'Saisie hebdo'!$C$5:$C$2000,$B58) | F58: =SUMIFS('Saisie hebdo'!$H$5:$H$2000,'Saisie hebdo'!$B$5:$B$2000,$A58,'Saisie hebdo'!$C$5:$C$2000,$B58) | G58: =IFERROR(AVERAGEIFS('Saisie hebdo'!$I$5:$I$2000,'Saisie hebdo'!$B$5:$B$2000,$A58,'Saisie hebdo'!$C$5:$C$2000,$B58),"") | H58: =IFERROR(AVERAGEIFS('Saisie hebdo'!$J$5:$J$2000,'Saisie hebdo'!$B$5:$B$2000,$A58,'Saisie hebdo'!$C$5:$C$2000,$B58),"") | I58: =SUMIFS('Saisie hebdo'!$K$5:$K$2000,'Saisie hebdo'!$B$5:$B$2000,$A58,'Saisie hebdo'!$C$5:$C$2000,$B58) | J58: =SUMIFS('Saisie hebdo'!$L$5:$L$2000,'Saisie hebdo'!$B$5:$B$2000,$A58,'Saisie hebdo'!$C$5:$C$2000,$B58) | K58: =SUMIFS('Saisie hebdo'!$M$5:$M$2000,'Saisie hebdo'!$B$5:$B$2000,$A58,'Saisie hebdo'!$C$5:$C$2000,$B58) | L58: =SUMIFS('Saisie hebdo'!$N$5:$N$2000,'Saisie hebdo'!$B$5:$B$2000,$A58,'Saisie hebdo'!$C$5:$C$2000,$B58) | M58: =SUMIFS('Saisie hebdo'!$O$5:$O$2000,'Saisie hebdo'!$B$5:$B$2000,$A58,'Saisie hebdo'!$C$5:$C$2000,$B58) | N58: =IF(N(D58)=0,"",E58/D58) | O58: =IF(N(E58)=0,"",C58/E58) | P58: =IF(N(E58)=0,"",F58/E58) | Q58: =IF(N(F58)=0,"",C58/F58) | R58: =IF(N(I58)=0,"",C58/I58) | S58: =IF(N(J58)=0,"",C58/J58) | T58: =IF(N(L58)=0,"",C58/L58) | U58: =IF(N(I58)=0,"",J58/I58) | V58: =IF(N(K58)=0,"",L58/K58) | W58: =IF(N(C58)=0,"",M58/C58)
A59: 46478 | B59: Microsoft Ads | C59: =SUMIFS('Saisie hebdo'!$E$5:$E$2000,'Saisie hebdo'!$B$5:$B$2000,$A59,'Saisie hebdo'!$C$5:$C$2000,$B59) | D59: =SUMIFS('Saisie hebdo'!$F$5:$F$2000,'Saisie hebdo'!$B$5:$B$2000,$A59,'Saisie hebdo'!$C$5:$C$2000,$B59) | E59: =SUMIFS('Saisie hebdo'!$G$5:$G$2000,'Saisie hebdo'!$B$5:$B$2000,$A59,'Saisie hebdo'!$C$5:$C$2000,$B59) | F59: =SUMIFS('Saisie hebdo'!$H$5:$H$2000,'Saisie hebdo'!$B$5:$B$2000,$A59,'Saisie hebdo'!$C$5:$C$2000,$B59) | G59: =IFERROR(AVERAGEIFS('Saisie hebdo'!$I$5:$I$2000,'Saisie hebdo'!$B$5:$B$2000,$A59,'Saisie hebdo'!$C$5:$C$2000,$B59),"") | H59: =IFERROR(AVERAGEIFS('Saisie hebdo'!$J$5:$J$2000,'Saisie hebdo'!$B$5:$B$2000,$A59,'Saisie hebdo'!$C$5:$C$2000,$B59),"") | I59: =SUMIFS('Saisie hebdo'!$K$5:$K$2000,'Saisie hebdo'!$B$5:$B$2000,$A59,'Saisie hebdo'!$C$5:$C$2000,$B59) | J59: =SUMIFS('Saisie hebdo'!$L$5:$L$2000,'Saisie hebdo'!$B$5:$B$2000,$A59,'Saisie hebdo'!$C$5:$C$2000,$B59) | K59: =SUMIFS('Saisie hebdo'!$M$5:$M$2000,'Saisie hebdo'!$B$5:$B$2000,$A59,'Saisie hebdo'!$C$5:$C$2000,$B59) | L59: =SUMIFS('Saisie hebdo'!$N$5:$N$2000,'Saisie hebdo'!$B$5:$B$2000,$A59,'Saisie hebdo'!$C$5:$C$2000,$B59) | M59: =SUMIFS('Saisie hebdo'!$O$5:$O$2000,'Saisie hebdo'!$B$5:$B$2000,$A59,'Saisie hebdo'!$C$5:$C$2000,$B59) | N59: =IF(N(D59)=0,"",E59/D59) | O59: =IF(N(E59)=0,"",C59/E59) | P59: =IF(N(E59)=0,"",F59/E59) | Q59: =IF(N(F59)=0,"",C59/F59) | R59: =IF(N(I59)=0,"",C59/I59) | S59: =IF(N(J59)=0,"",C59/J59) | T59: =IF(N(L59)=0,"",C59/L59) | U59: =IF(N(I59)=0,"",J59/I59) | V59: =IF(N(K59)=0,"",L59/K59) | W59: =IF(N(C59)=0,"",M59/C59)
A60: 46478 | B60: Total du compte | C60: =SUMIFS('Saisie hebdo'!$E$5:$E$2000,'Saisie hebdo'!$B$5:$B$2000,$A60) | D60: =SUMIFS('Saisie hebdo'!$F$5:$F$2000,'Saisie hebdo'!$B$5:$B$2000,$A60) | E60: =SUMIFS('Saisie hebdo'!$G$5:$G$2000,'Saisie hebdo'!$B$5:$B$2000,$A60) | F60: =SUMIFS('Saisie hebdo'!$H$5:$H$2000,'Saisie hebdo'!$B$5:$B$2000,$A60) | G60: =IFERROR(AVERAGEIFS('Saisie hebdo'!$I$5:$I$2000,'Saisie hebdo'!$B$5:$B$2000,$A60),"") | H60: =IFERROR(AVERAGEIFS('Saisie hebdo'!$J$5:$J$2000,'Saisie hebdo'!$B$5:$B$2000,$A60),"") | I60: =SUMIFS('Saisie hebdo'!$K$5:$K$2000,'Saisie hebdo'!$B$5:$B$2000,$A60) | J60: =SUMIFS('Saisie hebdo'!$L$5:$L$2000,'Saisie hebdo'!$B$5:$B$2000,$A60) | K60: =SUMIFS('Saisie hebdo'!$M$5:$M$2000,'Saisie hebdo'!$B$5:$B$2000,$A60) | L60: =SUMIFS('Saisie hebdo'!$N$5:$N$2000,'Saisie hebdo'!$B$5:$B$2000,$A60) | M60: =SUMIFS('Saisie hebdo'!$O$5:$O$2000,'Saisie hebdo'!$B$5:$B$2000,$A60) | N60: =IF(N(D60)=0,"",E60/D60) | O60: =IF(N(E60)=0,"",C60/E60) | P60: =IF(N(E60)=0,"",F60/E60) | Q60: =IF(N(F60)=0,"",C60/F60) | R60: =IF(N(I60)=0,"",C60/I60) | S60: =IF(N(J60)=0,"",C60/J60) | T60: =IF(N(L60)=0,"",C60/L60) | U60: =IF(N(I60)=0,"",J60/I60) | V60: =IF(N(K60)=0,"",L60/K60) | W60: =IF(N(C60)=0,"",M60/C60)
A61: 46508 | B61: S-FR | Marque | C61: =SUMIFS('Saisie hebdo'!$E$5:$E$2000,'Saisie hebdo'!$B$5:$B$2000,$A61,'Saisie hebdo'!$C$5:$C$2000,$B61) | D61: =SUMIFS('Saisie hebdo'!$F$5:$F$2000,'Saisie hebdo'!$B$5:$B$2000,$A61,'Saisie hebdo'!$C$5:$C$2000,$B61) | E61: =SUMIFS('Saisie hebdo'!$G$5:$G$2000,'Saisie hebdo'!$B$5:$B$2000,$A61,'Saisie hebdo'!$C$5:$C$2000,$B61) | F61: =SUMIFS('Saisie hebdo'!$H$5:$H$2000,'Saisie hebdo'!$B$5:$B$2000,$A61,'Saisie hebdo'!$C$5:$C$2000,$B61) | G61: =IFERROR(AVERAGEIFS('Saisie hebdo'!$I$5:$I$2000,'Saisie hebdo'!$B$5:$B$2000,$A61,'Saisie hebdo'!$C$5:$C$2000,$B61),"") | H61: =IFERROR(AVERAGEIFS('Saisie hebdo'!$J$5:$J$2000,'Saisie hebdo'!$B$5:$B$2000,$A61,'Saisie hebdo'!$C$5:$C$2000,$B61),"") | I61: =SUMIFS('Saisie hebdo'!$K$5:$K$2000,'Saisie hebdo'!$B$5:$B$2000,$A61,'Saisie hebdo'!$C$5:$C$2000,$B61) | J61: =SUMIFS('Saisie hebdo'!$L$5:$L$2000,'Saisie hebdo'!$B$5:$B$2000,$A61,'Saisie hebdo'!$C$5:$C$2000,$B61) | K61: =SUMIFS('Saisie hebdo'!$M$5:$M$2000,'Saisie hebdo'!$B$5:$B$2000,$A61,'Saisie hebdo'!$C$5:$C$2000,$B61) | L61: =SUMIFS('Saisie hebdo'!$N$5:$N$2000,'Saisie hebdo'!$B$5:$B$2000,$A61,'Saisie hebdo'!$C$5:$C$2000,$B61) | M61: =SUMIFS('Saisie hebdo'!$O$5:$O$2000,'Saisie hebdo'!$B$5:$B$2000,$A61,'Saisie hebdo'!$C$5:$C$2000,$B61) | N61: =IF(N(D61)=0,"",E61/D61) | O61: =IF(N(E61)=0,"",C61/E61) | P61: =IF(N(E61)=0,"",F61/E61) | Q61: =IF(N(F61)=0,"",C61/F61) | R61: =IF(N(I61)=0,"",C61/I61) | S61: =IF(N(J61)=0,"",C61/J61) | T61: =IF(N(L61)=0,"",C61/L61) | U61: =IF(N(I61)=0,"",J61/I61) | V61: =IF(N(K61)=0,"",L61/K61) | W61: =IF(N(C61)=0,"",M61/C61)
A62: 46508 | B62: S-FR | Corporatif & Fêtes | C62: =SUMIFS('Saisie hebdo'!$E$5:$E$2000,'Saisie hebdo'!$B$5:$B$2000,$A62,'Saisie hebdo'!$C$5:$C$2000,$B62) | D62: =SUMIFS('Saisie hebdo'!$F$5:$F$2000,'Saisie hebdo'!$B$5:$B$2000,$A62,'Saisie hebdo'!$C$5:$C$2000,$B62) | E62: =SUMIFS('Saisie hebdo'!$G$5:$G$2000,'Saisie hebdo'!$B$5:$B$2000,$A62,'Saisie hebdo'!$C$5:$C$2000,$B62) | F62: =SUMIFS('Saisie hebdo'!$H$5:$H$2000,'Saisie hebdo'!$B$5:$B$2000,$A62,'Saisie hebdo'!$C$5:$C$2000,$B62) | G62: =IFERROR(AVERAGEIFS('Saisie hebdo'!$I$5:$I$2000,'Saisie hebdo'!$B$5:$B$2000,$A62,'Saisie hebdo'!$C$5:$C$2000,$B62),"") | H62: =IFERROR(AVERAGEIFS('Saisie hebdo'!$J$5:$J$2000,'Saisie hebdo'!$B$5:$B$2000,$A62,'Saisie hebdo'!$C$5:$C$2000,$B62),"") | I62: =SUMIFS('Saisie hebdo'!$K$5:$K$2000,'Saisie hebdo'!$B$5:$B$2000,$A62,'Saisie hebdo'!$C$5:$C$2000,$B62) | J62: =SUMIFS('Saisie hebdo'!$L$5:$L$2000,'Saisie hebdo'!$B$5:$B$2000,$A62,'Saisie hebdo'!$C$5:$C$2000,$B62) | K62: =SUMIFS('Saisie hebdo'!$M$5:$M$2000,'Saisie hebdo'!$B$5:$B$2000,$A62,'Saisie hebdo'!$C$5:$C$2000,$B62) | L62: =SUMIFS('Saisie hebdo'!$N$5:$N$2000,'Saisie hebdo'!$B$5:$B$2000,$A62,'Saisie hebdo'!$C$5:$C$2000,$B62) | M62: =SUMIFS('Saisie hebdo'!$O$5:$O$2000,'Saisie hebdo'!$B$5:$B$2000,$A62,'Saisie hebdo'!$C$5:$C$2000,$B62) | N62: =IF(N(D62)=0,"",E62/D62) | O62: =IF(N(E62)=0,"",C62/E62) | P62: =IF(N(E62)=0,"",F62/E62) | Q62: =IF(N(F62)=0,"",C62/F62) | R62: =IF(N(I62)=0,"",C62/I62) | S62: =IF(N(J62)=0,"",C62/J62) | T62: =IF(N(L62)=0,"",C62/L62) | U62: =IF(N(I62)=0,"",J62/I62) | V62: =IF(N(K62)=0,"",L62/K62) | W62: =IF(N(C62)=0,"",M62/C62)
A63: 46508 | B63: S-FR | Événements privés | C63: =SUMIFS('Saisie hebdo'!$E$5:$E$2000,'Saisie hebdo'!$B$5:$B$2000,$A63,'Saisie hebdo'!$C$5:$C$2000,$B63) | D63: =SUMIFS('Saisie hebdo'!$F$5:$F$2000,'Saisie hebdo'!$B$5:$B$2000,$A63,'Saisie hebdo'!$C$5:$C$2000,$B63) | E63: =SUMIFS('Saisie hebdo'!$G$5:$G$2000,'Saisie hebdo'!$B$5:$B$2000,$A63,'Saisie hebdo'!$C$5:$C$2000,$B63) | F63: =SUMIFS('Saisie hebdo'!$H$5:$H$2000,'Saisie hebdo'!$B$5:$B$2000,$A63,'Saisie hebdo'!$C$5:$C$2000,$B63) | G63: =IFERROR(AVERAGEIFS('Saisie hebdo'!$I$5:$I$2000,'Saisie hebdo'!$B$5:$B$2000,$A63,'Saisie hebdo'!$C$5:$C$2000,$B63),"") | H63: =IFERROR(AVERAGEIFS('Saisie hebdo'!$J$5:$J$2000,'Saisie hebdo'!$B$5:$B$2000,$A63,'Saisie hebdo'!$C$5:$C$2000,$B63),"") | I63: =SUMIFS('Saisie hebdo'!$K$5:$K$2000,'Saisie hebdo'!$B$5:$B$2000,$A63,'Saisie hebdo'!$C$5:$C$2000,$B63) | J63: =SUMIFS('Saisie hebdo'!$L$5:$L$2000,'Saisie hebdo'!$B$5:$B$2000,$A63,'Saisie hebdo'!$C$5:$C$2000,$B63) | K63: =SUMIFS('Saisie hebdo'!$M$5:$M$2000,'Saisie hebdo'!$B$5:$B$2000,$A63,'Saisie hebdo'!$C$5:$C$2000,$B63) | L63: =SUMIFS('Saisie hebdo'!$N$5:$N$2000,'Saisie hebdo'!$B$5:$B$2000,$A63,'Saisie hebdo'!$C$5:$C$2000,$B63) | M63: =SUMIFS('Saisie hebdo'!$O$5:$O$2000,'Saisie hebdo'!$B$5:$B$2000,$A63,'Saisie hebdo'!$C$5:$C$2000,$B63) | N63: =IF(N(D63)=0,"",E63/D63) | O63: =IF(N(E63)=0,"",C63/E63) | P63: =IF(N(E63)=0,"",F63/E63) | Q63: =IF(N(F63)=0,"",C63/F63) | R63: =IF(N(I63)=0,"",C63/I63) | S63: =IF(N(J63)=0,"",C63/J63) | T63: =IF(N(L63)=0,"",C63/L63) | U63: =IF(N(I63)=0,"",J63/I63) | V63: =IF(N(K63)=0,"",L63/K63) | W63: =IF(N(C63)=0,"",M63/C63)
A64: 46508 | B64: S-EN | Corporate Montréal | C64: =SUMIFS('Saisie hebdo'!$E$5:$E$2000,'Saisie hebdo'!$B$5:$B$2000,$A64,'Saisie hebdo'!$C$5:$C$2000,$B64) | D64: =SUMIFS('Saisie hebdo'!$F$5:$F$2000,'Saisie hebdo'!$B$5:$B$2000,$A64,'Saisie hebdo'!$C$5:$C$2000,$B64) | E64: =SUMIFS('Saisie hebdo'!$G$5:$G$2000,'Saisie hebdo'!$B$5:$B$2000,$A64,'Saisie hebdo'!$C$5:$C$2000,$B64) | F64: =SUMIFS('Saisie hebdo'!$H$5:$H$2000,'Saisie hebdo'!$B$5:$B$2000,$A64,'Saisie hebdo'!$C$5:$C$2000,$B64) | G64: =IFERROR(AVERAGEIFS('Saisie hebdo'!$I$5:$I$2000,'Saisie hebdo'!$B$5:$B$2000,$A64,'Saisie hebdo'!$C$5:$C$2000,$B64),"") | H64: =IFERROR(AVERAGEIFS('Saisie hebdo'!$J$5:$J$2000,'Saisie hebdo'!$B$5:$B$2000,$A64,'Saisie hebdo'!$C$5:$C$2000,$B64),"") | I64: =SUMIFS('Saisie hebdo'!$K$5:$K$2000,'Saisie hebdo'!$B$5:$B$2000,$A64,'Saisie hebdo'!$C$5:$C$2000,$B64) | J64: =SUMIFS('Saisie hebdo'!$L$5:$L$2000,'Saisie hebdo'!$B$5:$B$2000,$A64,'Saisie hebdo'!$C$5:$C$2000,$B64) | K64: =SUMIFS('Saisie hebdo'!$M$5:$M$2000,'Saisie hebdo'!$B$5:$B$2000,$A64,'Saisie hebdo'!$C$5:$C$2000,$B64) | L64: =SUMIFS('Saisie hebdo'!$N$5:$N$2000,'Saisie hebdo'!$B$5:$B$2000,$A64,'Saisie hebdo'!$C$5:$C$2000,$B64) | M64: =SUMIFS('Saisie hebdo'!$O$5:$O$2000,'Saisie hebdo'!$B$5:$B$2000,$A64,'Saisie hebdo'!$C$5:$C$2000,$B64) | N64: =IF(N(D64)=0,"",E64/D64) | O64: =IF(N(E64)=0,"",C64/E64) | P64: =IF(N(E64)=0,"",F64/E64) | Q64: =IF(N(F64)=0,"",C64/F64) | R64: =IF(N(I64)=0,"",C64/I64) | S64: =IF(N(J64)=0,"",C64/J64) | T64: =IF(N(L64)=0,"",C64/L64) | U64: =IF(N(I64)=0,"",J64/I64) | V64: =IF(N(K64)=0,"",L64/K64) | W64: =IF(N(C64)=0,"",M64/C64)
A65: 46508 | B65: S-FR | Québec-Lévis (test) | C65: =SUMIFS('Saisie hebdo'!$E$5:$E$2000,'Saisie hebdo'!$B$5:$B$2000,$A65,'Saisie hebdo'!$C$5:$C$2000,$B65) | D65: =SUMIFS('Saisie hebdo'!$F$5:$F$2000,'Saisie hebdo'!$B$5:$B$2000,$A65,'Saisie hebdo'!$C$5:$C$2000,$B65) | E65: =SUMIFS('Saisie hebdo'!$G$5:$G$2000,'Saisie hebdo'!$B$5:$B$2000,$A65,'Saisie hebdo'!$C$5:$C$2000,$B65) | F65: =SUMIFS('Saisie hebdo'!$H$5:$H$2000,'Saisie hebdo'!$B$5:$B$2000,$A65,'Saisie hebdo'!$C$5:$C$2000,$B65) | G65: =IFERROR(AVERAGEIFS('Saisie hebdo'!$I$5:$I$2000,'Saisie hebdo'!$B$5:$B$2000,$A65,'Saisie hebdo'!$C$5:$C$2000,$B65),"") | H65: =IFERROR(AVERAGEIFS('Saisie hebdo'!$J$5:$J$2000,'Saisie hebdo'!$B$5:$B$2000,$A65,'Saisie hebdo'!$C$5:$C$2000,$B65),"") | I65: =SUMIFS('Saisie hebdo'!$K$5:$K$2000,'Saisie hebdo'!$B$5:$B$2000,$A65,'Saisie hebdo'!$C$5:$C$2000,$B65) | J65: =SUMIFS('Saisie hebdo'!$L$5:$L$2000,'Saisie hebdo'!$B$5:$B$2000,$A65,'Saisie hebdo'!$C$5:$C$2000,$B65) | K65: =SUMIFS('Saisie hebdo'!$M$5:$M$2000,'Saisie hebdo'!$B$5:$B$2000,$A65,'Saisie hebdo'!$C$5:$C$2000,$B65) | L65: =SUMIFS('Saisie hebdo'!$N$5:$N$2000,'Saisie hebdo'!$B$5:$B$2000,$A65,'Saisie hebdo'!$C$5:$C$2000,$B65) | M65: =SUMIFS('Saisie hebdo'!$O$5:$O$2000,'Saisie hebdo'!$B$5:$B$2000,$A65,'Saisie hebdo'!$C$5:$C$2000,$B65) | N65: =IF(N(D65)=0,"",E65/D65) | O65: =IF(N(E65)=0,"",C65/E65) | P65: =IF(N(E65)=0,"",F65/E65) | Q65: =IF(N(F65)=0,"",C65/F65) | R65: =IF(N(I65)=0,"",C65/I65) | S65: =IF(N(J65)=0,"",C65/J65) | T65: =IF(N(L65)=0,"",C65/L65) | U65: =IF(N(I65)=0,"",J65/I65) | V65: =IF(N(K65)=0,"",L65/K65) | W65: =IF(N(C65)=0,"",M65/C65)
A66: 46508 | B66: Demand Gen | C66: =SUMIFS('Saisie hebdo'!$E$5:$E$2000,'Saisie hebdo'!$B$5:$B$2000,$A66,'Saisie hebdo'!$C$5:$C$2000,$B66) | D66: =SUMIFS('Saisie hebdo'!$F$5:$F$2000,'Saisie hebdo'!$B$5:$B$2000,$A66,'Saisie hebdo'!$C$5:$C$2000,$B66) | E66: =SUMIFS('Saisie hebdo'!$G$5:$G$2000,'Saisie hebdo'!$B$5:$B$2000,$A66,'Saisie hebdo'!$C$5:$C$2000,$B66) | F66: =SUMIFS('Saisie hebdo'!$H$5:$H$2000,'Saisie hebdo'!$B$5:$B$2000,$A66,'Saisie hebdo'!$C$5:$C$2000,$B66) | G66: =IFERROR(AVERAGEIFS('Saisie hebdo'!$I$5:$I$2000,'Saisie hebdo'!$B$5:$B$2000,$A66,'Saisie hebdo'!$C$5:$C$2000,$B66),"") | H66: =IFERROR(AVERAGEIFS('Saisie hebdo'!$J$5:$J$2000,'Saisie hebdo'!$B$5:$B$2000,$A66,'Saisie hebdo'!$C$5:$C$2000,$B66),"") | I66: =SUMIFS('Saisie hebdo'!$K$5:$K$2000,'Saisie hebdo'!$B$5:$B$2000,$A66,'Saisie hebdo'!$C$5:$C$2000,$B66) | J66: =SUMIFS('Saisie hebdo'!$L$5:$L$2000,'Saisie hebdo'!$B$5:$B$2000,$A66,'Saisie hebdo'!$C$5:$C$2000,$B66) | K66: =SUMIFS('Saisie hebdo'!$M$5:$M$2000,'Saisie hebdo'!$B$5:$B$2000,$A66,'Saisie hebdo'!$C$5:$C$2000,$B66) | L66: =SUMIFS('Saisie hebdo'!$N$5:$N$2000,'Saisie hebdo'!$B$5:$B$2000,$A66,'Saisie hebdo'!$C$5:$C$2000,$B66) | M66: =SUMIFS('Saisie hebdo'!$O$5:$O$2000,'Saisie hebdo'!$B$5:$B$2000,$A66,'Saisie hebdo'!$C$5:$C$2000,$B66) | N66: =IF(N(D66)=0,"",E66/D66) | O66: =IF(N(E66)=0,"",C66/E66) | P66: =IF(N(E66)=0,"",F66/E66) | Q66: =IF(N(F66)=0,"",C66/F66) | R66: =IF(N(I66)=0,"",C66/I66) | S66: =IF(N(J66)=0,"",C66/J66) | T66: =IF(N(L66)=0,"",C66/L66) | U66: =IF(N(I66)=0,"",J66/I66) | V66: =IF(N(K66)=0,"",L66/K66) | W66: =IF(N(C66)=0,"",M66/C66)
A67: 46508 | B67: Microsoft Ads | C67: =SUMIFS('Saisie hebdo'!$E$5:$E$2000,'Saisie hebdo'!$B$5:$B$2000,$A67,'Saisie hebdo'!$C$5:$C$2000,$B67) | D67: =SUMIFS('Saisie hebdo'!$F$5:$F$2000,'Saisie hebdo'!$B$5:$B$2000,$A67,'Saisie hebdo'!$C$5:$C$2000,$B67) | E67: =SUMIFS('Saisie hebdo'!$G$5:$G$2000,'Saisie hebdo'!$B$5:$B$2000,$A67,'Saisie hebdo'!$C$5:$C$2000,$B67) | F67: =SUMIFS('Saisie hebdo'!$H$5:$H$2000,'Saisie hebdo'!$B$5:$B$2000,$A67,'Saisie hebdo'!$C$5:$C$2000,$B67) | G67: =IFERROR(AVERAGEIFS('Saisie hebdo'!$I$5:$I$2000,'Saisie hebdo'!$B$5:$B$2000,$A67,'Saisie hebdo'!$C$5:$C$2000,$B67),"") | H67: =IFERROR(AVERAGEIFS('Saisie hebdo'!$J$5:$J$2000,'Saisie hebdo'!$B$5:$B$2000,$A67,'Saisie hebdo'!$C$5:$C$2000,$B67),"") | I67: =SUMIFS('Saisie hebdo'!$K$5:$K$2000,'Saisie hebdo'!$B$5:$B$2000,$A67,'Saisie hebdo'!$C$5:$C$2000,$B67) | J67: =SUMIFS('Saisie hebdo'!$L$5:$L$2000,'Saisie hebdo'!$B$5:$B$2000,$A67,'Saisie hebdo'!$C$5:$C$2000,$B67) | K67: =SUMIFS('Saisie hebdo'!$M$5:$M$2000,'Saisie hebdo'!$B$5:$B$2000,$A67,'Saisie hebdo'!$C$5:$C$2000,$B67) | L67: =SUMIFS('Saisie hebdo'!$N$5:$N$2000,'Saisie hebdo'!$B$5:$B$2000,$A67,'Saisie hebdo'!$C$5:$C$2000,$B67) | M67: =SUMIFS('Saisie hebdo'!$O$5:$O$2000,'Saisie hebdo'!$B$5:$B$2000,$A67,'Saisie hebdo'!$C$5:$C$2000,$B67) | N67: =IF(N(D67)=0,"",E67/D67) | O67: =IF(N(E67)=0,"",C67/E67) | P67: =IF(N(E67)=0,"",F67/E67) | Q67: =IF(N(F67)=0,"",C67/F67) | R67: =IF(N(I67)=0,"",C67/I67) | S67: =IF(N(J67)=0,"",C67/J67) | T67: =IF(N(L67)=0,"",C67/L67) | U67: =IF(N(I67)=0,"",J67/I67) | V67: =IF(N(K67)=0,"",L67/K67) | W67: =IF(N(C67)=0,"",M67/C67)
A68: 46508 | B68: Total du compte | C68: =SUMIFS('Saisie hebdo'!$E$5:$E$2000,'Saisie hebdo'!$B$5:$B$2000,$A68) | D68: =SUMIFS('Saisie hebdo'!$F$5:$F$2000,'Saisie hebdo'!$B$5:$B$2000,$A68) | E68: =SUMIFS('Saisie hebdo'!$G$5:$G$2000,'Saisie hebdo'!$B$5:$B$2000,$A68) | F68: =SUMIFS('Saisie hebdo'!$H$5:$H$2000,'Saisie hebdo'!$B$5:$B$2000,$A68) | G68: =IFERROR(AVERAGEIFS('Saisie hebdo'!$I$5:$I$2000,'Saisie hebdo'!$B$5:$B$2000,$A68),"") | H68: =IFERROR(AVERAGEIFS('Saisie hebdo'!$J$5:$J$2000,'Saisie hebdo'!$B$5:$B$2000,$A68),"") | I68: =SUMIFS('Saisie hebdo'!$K$5:$K$2000,'Saisie hebdo'!$B$5:$B$2000,$A68) | J68: =SUMIFS('Saisie hebdo'!$L$5:$L$2000,'Saisie hebdo'!$B$5:$B$2000,$A68) | K68: =SUMIFS('Saisie hebdo'!$M$5:$M$2000,'Saisie hebdo'!$B$5:$B$2000,$A68) | L68: =SUMIFS('Saisie hebdo'!$N$5:$N$2000,'Saisie hebdo'!$B$5:$B$2000,$A68) | M68: =SUMIFS('Saisie hebdo'!$O$5:$O$2000,'Saisie hebdo'!$B$5:$B$2000,$A68) | N68: =IF(N(D68)=0,"",E68/D68) | O68: =IF(N(E68)=0,"",C68/E68) | P68: =IF(N(E68)=0,"",F68/E68) | Q68: =IF(N(F68)=0,"",C68/F68) | R68: =IF(N(I68)=0,"",C68/I68) | S68: =IF(N(J68)=0,"",C68/J68) | T68: =IF(N(L68)=0,"",C68/L68) | U68: =IF(N(I68)=0,"",J68/I68) | V68: =IF(N(K68)=0,"",L68/K68) | W68: =IF(N(C68)=0,"",M68/C68)
A69: 46539 | B69: S-FR | Marque | C69: =SUMIFS('Saisie hebdo'!$E$5:$E$2000,'Saisie hebdo'!$B$5:$B$2000,$A69,'Saisie hebdo'!$C$5:$C$2000,$B69) | D69: =SUMIFS('Saisie hebdo'!$F$5:$F$2000,'Saisie hebdo'!$B$5:$B$2000,$A69,'Saisie hebdo'!$C$5:$C$2000,$B69) | E69: =SUMIFS('Saisie hebdo'!$G$5:$G$2000,'Saisie hebdo'!$B$5:$B$2000,$A69,'Saisie hebdo'!$C$5:$C$2000,$B69) | F69: =SUMIFS('Saisie hebdo'!$H$5:$H$2000,'Saisie hebdo'!$B$5:$B$2000,$A69,'Saisie hebdo'!$C$5:$C$2000,$B69) | G69: =IFERROR(AVERAGEIFS('Saisie hebdo'!$I$5:$I$2000,'Saisie hebdo'!$B$5:$B$2000,$A69,'Saisie hebdo'!$C$5:$C$2000,$B69),"") | H69: =IFERROR(AVERAGEIFS('Saisie hebdo'!$J$5:$J$2000,'Saisie hebdo'!$B$5:$B$2000,$A69,'Saisie hebdo'!$C$5:$C$2000,$B69),"") | I69: =SUMIFS('Saisie hebdo'!$K$5:$K$2000,'Saisie hebdo'!$B$5:$B$2000,$A69,'Saisie hebdo'!$C$5:$C$2000,$B69) | J69: =SUMIFS('Saisie hebdo'!$L$5:$L$2000,'Saisie hebdo'!$B$5:$B$2000,$A69,'Saisie hebdo'!$C$5:$C$2000,$B69) | K69: =SUMIFS('Saisie hebdo'!$M$5:$M$2000,'Saisie hebdo'!$B$5:$B$2000,$A69,'Saisie hebdo'!$C$5:$C$2000,$B69) | L69: =SUMIFS('Saisie hebdo'!$N$5:$N$2000,'Saisie hebdo'!$B$5:$B$2000,$A69,'Saisie hebdo'!$C$5:$C$2000,$B69) | M69: =SUMIFS('Saisie hebdo'!$O$5:$O$2000,'Saisie hebdo'!$B$5:$B$2000,$A69,'Saisie hebdo'!$C$5:$C$2000,$B69) | N69: =IF(N(D69)=0,"",E69/D69) | O69: =IF(N(E69)=0,"",C69/E69) | P69: =IF(N(E69)=0,"",F69/E69) | Q69: =IF(N(F69)=0,"",C69/F69) | R69: =IF(N(I69)=0,"",C69/I69) | S69: =IF(N(J69)=0,"",C69/J69) | T69: =IF(N(L69)=0,"",C69/L69) | U69: =IF(N(I69)=0,"",J69/I69) | V69: =IF(N(K69)=0,"",L69/K69) | W69: =IF(N(C69)=0,"",M69/C69)
A70: 46539 | B70: S-FR | Corporatif & Fêtes | C70: =SUMIFS('Saisie hebdo'!$E$5:$E$2000,'Saisie hebdo'!$B$5:$B$2000,$A70,'Saisie hebdo'!$C$5:$C$2000,$B70) | D70: =SUMIFS('Saisie hebdo'!$F$5:$F$2000,'Saisie hebdo'!$B$5:$B$2000,$A70,'Saisie hebdo'!$C$5:$C$2000,$B70) | E70: =SUMIFS('Saisie hebdo'!$G$5:$G$2000,'Saisie hebdo'!$B$5:$B$2000,$A70,'Saisie hebdo'!$C$5:$C$2000,$B70) | F70: =SUMIFS('Saisie hebdo'!$H$5:$H$2000,'Saisie hebdo'!$B$5:$B$2000,$A70,'Saisie hebdo'!$C$5:$C$2000,$B70) | G70: =IFERROR(AVERAGEIFS('Saisie hebdo'!$I$5:$I$2000,'Saisie hebdo'!$B$5:$B$2000,$A70,'Saisie hebdo'!$C$5:$C$2000,$B70),"") | H70: =IFERROR(AVERAGEIFS('Saisie hebdo'!$J$5:$J$2000,'Saisie hebdo'!$B$5:$B$2000,$A70,'Saisie hebdo'!$C$5:$C$2000,$B70),"") | I70: =SUMIFS('Saisie hebdo'!$K$5:$K$2000,'Saisie hebdo'!$B$5:$B$2000,$A70,'Saisie hebdo'!$C$5:$C$2000,$B70) | J70: =SUMIFS('Saisie hebdo'!$L$5:$L$2000,'Saisie hebdo'!$B$5:$B$2000,$A70,'Saisie hebdo'!$C$5:$C$2000,$B70) | K70: =SUMIFS('Saisie hebdo'!$M$5:$M$2000,'Saisie hebdo'!$B$5:$B$2000,$A70,'Saisie hebdo'!$C$5:$C$2000,$B70) | L70: =SUMIFS('Saisie hebdo'!$N$5:$N$2000,'Saisie hebdo'!$B$5:$B$2000,$A70,'Saisie hebdo'!$C$5:$C$2000,$B70) | M70: =SUMIFS('Saisie hebdo'!$O$5:$O$2000,'Saisie hebdo'!$B$5:$B$2000,$A70,'Saisie hebdo'!$C$5:$C$2000,$B70) | N70: =IF(N(D70)=0,"",E70/D70) | O70: =IF(N(E70)=0,"",C70/E70) | P70: =IF(N(E70)=0,"",F70/E70) | Q70: =IF(N(F70)=0,"",C70/F70) | R70: =IF(N(I70)=0,"",C70/I70) | S70: =IF(N(J70)=0,"",C70/J70) | T70: =IF(N(L70)=0,"",C70/L70) | U70: =IF(N(I70)=0,"",J70/I70) | V70: =IF(N(K70)=0,"",L70/K70) | W70: =IF(N(C70)=0,"",M70/C70)
A71: 46539 | B71: S-FR | Événements privés | C71: =SUMIFS('Saisie hebdo'!$E$5:$E$2000,'Saisie hebdo'!$B$5:$B$2000,$A71,'Saisie hebdo'!$C$5:$C$2000,$B71) | D71: =SUMIFS('Saisie hebdo'!$F$5:$F$2000,'Saisie hebdo'!$B$5:$B$2000,$A71,'Saisie hebdo'!$C$5:$C$2000,$B71) | E71: =SUMIFS('Saisie hebdo'!$G$5:$G$2000,'Saisie hebdo'!$B$5:$B$2000,$A71,'Saisie hebdo'!$C$5:$C$2000,$B71) | F71: =SUMIFS('Saisie hebdo'!$H$5:$H$2000,'Saisie hebdo'!$B$5:$B$2000,$A71,'Saisie hebdo'!$C$5:$C$2000,$B71) | G71: =IFERROR(AVERAGEIFS('Saisie hebdo'!$I$5:$I$2000,'Saisie hebdo'!$B$5:$B$2000,$A71,'Saisie hebdo'!$C$5:$C$2000,$B71),"") | H71: =IFERROR(AVERAGEIFS('Saisie hebdo'!$J$5:$J$2000,'Saisie hebdo'!$B$5:$B$2000,$A71,'Saisie hebdo'!$C$5:$C$2000,$B71),"") | I71: =SUMIFS('Saisie hebdo'!$K$5:$K$2000,'Saisie hebdo'!$B$5:$B$2000,$A71,'Saisie hebdo'!$C$5:$C$2000,$B71) | J71: =SUMIFS('Saisie hebdo'!$L$5:$L$2000,'Saisie hebdo'!$B$5:$B$2000,$A71,'Saisie hebdo'!$C$5:$C$2000,$B71) | K71: =SUMIFS('Saisie hebdo'!$M$5:$M$2000,'Saisie hebdo'!$B$5:$B$2000,$A71,'Saisie hebdo'!$C$5:$C$2000,$B71) | L71: =SUMIFS('Saisie hebdo'!$N$5:$N$2000,'Saisie hebdo'!$B$5:$B$2000,$A71,'Saisie hebdo'!$C$5:$C$2000,$B71) | M71: =SUMIFS('Saisie hebdo'!$O$5:$O$2000,'Saisie hebdo'!$B$5:$B$2000,$A71,'Saisie hebdo'!$C$5:$C$2000,$B71) | N71: =IF(N(D71)=0,"",E71/D71) | O71: =IF(N(E71)=0,"",C71/E71) | P71: =IF(N(E71)=0,"",F71/E71) | Q71: =IF(N(F71)=0,"",C71/F71) | R71: =IF(N(I71)=0,"",C71/I71) | S71: =IF(N(J71)=0,"",C71/J71) | T71: =IF(N(L71)=0,"",C71/L71) | U71: =IF(N(I71)=0,"",J71/I71) | V71: =IF(N(K71)=0,"",L71/K71) | W71: =IF(N(C71)=0,"",M71/C71)
A72: 46539 | B72: S-EN | Corporate Montréal | C72: =SUMIFS('Saisie hebdo'!$E$5:$E$2000,'Saisie hebdo'!$B$5:$B$2000,$A72,'Saisie hebdo'!$C$5:$C$2000,$B72) | D72: =SUMIFS('Saisie hebdo'!$F$5:$F$2000,'Saisie hebdo'!$B$5:$B$2000,$A72,'Saisie hebdo'!$C$5:$C$2000,$B72) | E72: =SUMIFS('Saisie hebdo'!$G$5:$G$2000,'Saisie hebdo'!$B$5:$B$2000,$A72,'Saisie hebdo'!$C$5:$C$2000,$B72) | F72: =SUMIFS('Saisie hebdo'!$H$5:$H$2000,'Saisie hebdo'!$B$5:$B$2000,$A72,'Saisie hebdo'!$C$5:$C$2000,$B72) | G72: =IFERROR(AVERAGEIFS('Saisie hebdo'!$I$5:$I$2000,'Saisie hebdo'!$B$5:$B$2000,$A72,'Saisie hebdo'!$C$5:$C$2000,$B72),"") | H72: =IFERROR(AVERAGEIFS('Saisie hebdo'!$J$5:$J$2000,'Saisie hebdo'!$B$5:$B$2000,$A72,'Saisie hebdo'!$C$5:$C$2000,$B72),"") | I72: =SUMIFS('Saisie hebdo'!$K$5:$K$2000,'Saisie hebdo'!$B$5:$B$2000,$A72,'Saisie hebdo'!$C$5:$C$2000,$B72) | J72: =SUMIFS('Saisie hebdo'!$L$5:$L$2000,'Saisie hebdo'!$B$5:$B$2000,$A72,'Saisie hebdo'!$C$5:$C$2000,$B72) | K72: =SUMIFS('Saisie hebdo'!$M$5:$M$2000,'Saisie hebdo'!$B$5:$B$2000,$A72,'Saisie hebdo'!$C$5:$C$2000,$B72) | L72: =SUMIFS('Saisie hebdo'!$N$5:$N$2000,'Saisie hebdo'!$B$5:$B$2000,$A72,'Saisie hebdo'!$C$5:$C$2000,$B72) | M72: =SUMIFS('Saisie hebdo'!$O$5:$O$2000,'Saisie hebdo'!$B$5:$B$2000,$A72,'Saisie hebdo'!$C$5:$C$2000,$B72) | N72: =IF(N(D72)=0,"",E72/D72) | O72: =IF(N(E72)=0,"",C72/E72) | P72: =IF(N(E72)=0,"",F72/E72) | Q72: =IF(N(F72)=0,"",C72/F72) | R72: =IF(N(I72)=0,"",C72/I72) | S72: =IF(N(J72)=0,"",C72/J72) | T72: =IF(N(L72)=0,"",C72/L72) | U72: =IF(N(I72)=0,"",J72/I72) | V72: =IF(N(K72)=0,"",L72/K72) | W72: =IF(N(C72)=0,"",M72/C72)
A73: 46539 | B73: S-FR | Québec-Lévis (test) | C73: =SUMIFS('Saisie hebdo'!$E$5:$E$2000,'Saisie hebdo'!$B$5:$B$2000,$A73,'Saisie hebdo'!$C$5:$C$2000,$B73) | D73: =SUMIFS('Saisie hebdo'!$F$5:$F$2000,'Saisie hebdo'!$B$5:$B$2000,$A73,'Saisie hebdo'!$C$5:$C$2000,$B73) | E73: =SUMIFS('Saisie hebdo'!$G$5:$G$2000,'Saisie hebdo'!$B$5:$B$2000,$A73,'Saisie hebdo'!$C$5:$C$2000,$B73) | F73: =SUMIFS('Saisie hebdo'!$H$5:$H$2000,'Saisie hebdo'!$B$5:$B$2000,$A73,'Saisie hebdo'!$C$5:$C$2000,$B73) | G73: =IFERROR(AVERAGEIFS('Saisie hebdo'!$I$5:$I$2000,'Saisie hebdo'!$B$5:$B$2000,$A73,'Saisie hebdo'!$C$5:$C$2000,$B73),"") | H73: =IFERROR(AVERAGEIFS('Saisie hebdo'!$J$5:$J$2000,'Saisie hebdo'!$B$5:$B$2000,$A73,'Saisie hebdo'!$C$5:$C$2000,$B73),"") | I73: =SUMIFS('Saisie hebdo'!$K$5:$K$2000,'Saisie hebdo'!$B$5:$B$2000,$A73,'Saisie hebdo'!$C$5:$C$2000,$B73) | J73: =SUMIFS('Saisie hebdo'!$L$5:$L$2000,'Saisie hebdo'!$B$5:$B$2000,$A73,'Saisie hebdo'!$C$5:$C$2000,$B73) | K73: =SUMIFS('Saisie hebdo'!$M$5:$M$2000,'Saisie hebdo'!$B$5:$B$2000,$A73,'Saisie hebdo'!$C$5:$C$2000,$B73) | L73: =SUMIFS('Saisie hebdo'!$N$5:$N$2000,'Saisie hebdo'!$B$5:$B$2000,$A73,'Saisie hebdo'!$C$5:$C$2000,$B73) | M73: =SUMIFS('Saisie hebdo'!$O$5:$O$2000,'Saisie hebdo'!$B$5:$B$2000,$A73,'Saisie hebdo'!$C$5:$C$2000,$B73) | N73: =IF(N(D73)=0,"",E73/D73) | O73: =IF(N(E73)=0,"",C73/E73) | P73: =IF(N(E73)=0,"",F73/E73) | Q73: =IF(N(F73)=0,"",C73/F73) | R73: =IF(N(I73)=0,"",C73/I73) | S73: =IF(N(J73)=0,"",C73/J73) | T73: =IF(N(L73)=0,"",C73/L73) | U73: =IF(N(I73)=0,"",J73/I73) | V73: =IF(N(K73)=0,"",L73/K73) | W73: =IF(N(C73)=0,"",M73/C73)
A74: 46539 | B74: Demand Gen | C74: =SUMIFS('Saisie hebdo'!$E$5:$E$2000,'Saisie hebdo'!$B$5:$B$2000,$A74,'Saisie hebdo'!$C$5:$C$2000,$B74) | D74: =SUMIFS('Saisie hebdo'!$F$5:$F$2000,'Saisie hebdo'!$B$5:$B$2000,$A74,'Saisie hebdo'!$C$5:$C$2000,$B74) | E74: =SUMIFS('Saisie hebdo'!$G$5:$G$2000,'Saisie hebdo'!$B$5:$B$2000,$A74,'Saisie hebdo'!$C$5:$C$2000,$B74) | F74: =SUMIFS('Saisie hebdo'!$H$5:$H$2000,'Saisie hebdo'!$B$5:$B$2000,$A74,'Saisie hebdo'!$C$5:$C$2000,$B74) | G74: =IFERROR(AVERAGEIFS('Saisie hebdo'!$I$5:$I$2000,'Saisie hebdo'!$B$5:$B$2000,$A74,'Saisie hebdo'!$C$5:$C$2000,$B74),"") | H74: =IFERROR(AVERAGEIFS('Saisie hebdo'!$J$5:$J$2000,'Saisie hebdo'!$B$5:$B$2000,$A74,'Saisie hebdo'!$C$5:$C$2000,$B74),"") | I74: =SUMIFS('Saisie hebdo'!$K$5:$K$2000,'Saisie hebdo'!$B$5:$B$2000,$A74,'Saisie hebdo'!$C$5:$C$2000,$B74) | J74: =SUMIFS('Saisie hebdo'!$L$5:$L$2000,'Saisie hebdo'!$B$5:$B$2000,$A74,'Saisie hebdo'!$C$5:$C$2000,$B74) | K74: =SUMIFS('Saisie hebdo'!$M$5:$M$2000,'Saisie hebdo'!$B$5:$B$2000,$A74,'Saisie hebdo'!$C$5:$C$2000,$B74) | L74: =SUMIFS('Saisie hebdo'!$N$5:$N$2000,'Saisie hebdo'!$B$5:$B$2000,$A74,'Saisie hebdo'!$C$5:$C$2000,$B74) | M74: =SUMIFS('Saisie hebdo'!$O$5:$O$2000,'Saisie hebdo'!$B$5:$B$2000,$A74,'Saisie hebdo'!$C$5:$C$2000,$B74) | N74: =IF(N(D74)=0,"",E74/D74) | O74: =IF(N(E74)=0,"",C74/E74) | P74: =IF(N(E74)=0,"",F74/E74) | Q74: =IF(N(F74)=0,"",C74/F74) | R74: =IF(N(I74)=0,"",C74/I74) | S74: =IF(N(J74)=0,"",C74/J74) | T74: =IF(N(L74)=0,"",C74/L74) | U74: =IF(N(I74)=0,"",J74/I74) | V74: =IF(N(K74)=0,"",L74/K74) | W74: =IF(N(C74)=0,"",M74/C74)
A75: 46539 | B75: Microsoft Ads | C75: =SUMIFS('Saisie hebdo'!$E$5:$E$2000,'Saisie hebdo'!$B$5:$B$2000,$A75,'Saisie hebdo'!$C$5:$C$2000,$B75) | D75: =SUMIFS('Saisie hebdo'!$F$5:$F$2000,'Saisie hebdo'!$B$5:$B$2000,$A75,'Saisie hebdo'!$C$5:$C$2000,$B75) | E75: =SUMIFS('Saisie hebdo'!$G$5:$G$2000,'Saisie hebdo'!$B$5:$B$2000,$A75,'Saisie hebdo'!$C$5:$C$2000,$B75) | F75: =SUMIFS('Saisie hebdo'!$H$5:$H$2000,'Saisie hebdo'!$B$5:$B$2000,$A75,'Saisie hebdo'!$C$5:$C$2000,$B75) | G75: =IFERROR(AVERAGEIFS('Saisie hebdo'!$I$5:$I$2000,'Saisie hebdo'!$B$5:$B$2000,$A75,'Saisie hebdo'!$C$5:$C$2000,$B75),"") | H75: =IFERROR(AVERAGEIFS('Saisie hebdo'!$J$5:$J$2000,'Saisie hebdo'!$B$5:$B$2000,$A75,'Saisie hebdo'!$C$5:$C$2000,$B75),"") | I75: =SUMIFS('Saisie hebdo'!$K$5:$K$2000,'Saisie hebdo'!$B$5:$B$2000,$A75,'Saisie hebdo'!$C$5:$C$2000,$B75) | J75: =SUMIFS('Saisie hebdo'!$L$5:$L$2000,'Saisie hebdo'!$B$5:$B$2000,$A75,'Saisie hebdo'!$C$5:$C$2000,$B75) | K75: =SUMIFS('Saisie hebdo'!$M$5:$M$2000,'Saisie hebdo'!$B$5:$B$2000,$A75,'Saisie hebdo'!$C$5:$C$2000,$B75) | L75: =SUMIFS('Saisie hebdo'!$N$5:$N$2000,'Saisie hebdo'!$B$5:$B$2000,$A75,'Saisie hebdo'!$C$5:$C$2000,$B75) | M75: =SUMIFS('Saisie hebdo'!$O$5:$O$2000,'Saisie hebdo'!$B$5:$B$2000,$A75,'Saisie hebdo'!$C$5:$C$2000,$B75) | N75: =IF(N(D75)=0,"",E75/D75) | O75: =IF(N(E75)=0,"",C75/E75) | P75: =IF(N(E75)=0,"",F75/E75) | Q75: =IF(N(F75)=0,"",C75/F75) | R75: =IF(N(I75)=0,"",C75/I75) | S75: =IF(N(J75)=0,"",C75/J75) | T75: =IF(N(L75)=0,"",C75/L75) | U75: =IF(N(I75)=0,"",J75/I75) | V75: =IF(N(K75)=0,"",L75/K75) | W75: =IF(N(C75)=0,"",M75/C75)
A76: 46539 | B76: Total du compte | C76: =SUMIFS('Saisie hebdo'!$E$5:$E$2000,'Saisie hebdo'!$B$5:$B$2000,$A76) | D76: =SUMIFS('Saisie hebdo'!$F$5:$F$2000,'Saisie hebdo'!$B$5:$B$2000,$A76) | E76: =SUMIFS('Saisie hebdo'!$G$5:$G$2000,'Saisie hebdo'!$B$5:$B$2000,$A76) | F76: =SUMIFS('Saisie hebdo'!$H$5:$H$2000,'Saisie hebdo'!$B$5:$B$2000,$A76) | G76: =IFERROR(AVERAGEIFS('Saisie hebdo'!$I$5:$I$2000,'Saisie hebdo'!$B$5:$B$2000,$A76),"") | H76: =IFERROR(AVERAGEIFS('Saisie hebdo'!$J$5:$J$2000,'Saisie hebdo'!$B$5:$B$2000,$A76),"") | I76: =SUMIFS('Saisie hebdo'!$K$5:$K$2000,'Saisie hebdo'!$B$5:$B$2000,$A76) | J76: =SUMIFS('Saisie hebdo'!$L$5:$L$2000,'Saisie hebdo'!$B$5:$B$2000,$A76) | K76: =SUMIFS('Saisie hebdo'!$M$5:$M$2000,'Saisie hebdo'!$B$5:$B$2000,$A76) | L76: =SUMIFS('Saisie hebdo'!$N$5:$N$2000,'Saisie hebdo'!$B$5:$B$2000,$A76) | M76: =SUMIFS('Saisie hebdo'!$O$5:$O$2000,'Saisie hebdo'!$B$5:$B$2000,$A76) | N76: =IF(N(D76)=0,"",E76/D76) | O76: =IF(N(E76)=0,"",C76/E76) | P76: =IF(N(E76)=0,"",F76/E76) | Q76: =IF(N(F76)=0,"",C76/F76) | R76: =IF(N(I76)=0,"",C76/I76) | S76: =IF(N(J76)=0,"",C76/J76) | T76: =IF(N(L76)=0,"",C76/L76) | U76: =IF(N(I76)=0,"",J76/I76) | V76: =IF(N(K76)=0,"",L76/K76) | W76: =IF(N(C76)=0,"",M76/C76)
A77: 46569 | B77: S-FR | Marque | C77: =SUMIFS('Saisie hebdo'!$E$5:$E$2000,'Saisie hebdo'!$B$5:$B$2000,$A77,'Saisie hebdo'!$C$5:$C$2000,$B77) | D77: =SUMIFS('Saisie hebdo'!$F$5:$F$2000,'Saisie hebdo'!$B$5:$B$2000,$A77,'Saisie hebdo'!$C$5:$C$2000,$B77) | E77: =SUMIFS('Saisie hebdo'!$G$5:$G$2000,'Saisie hebdo'!$B$5:$B$2000,$A77,'Saisie hebdo'!$C$5:$C$2000,$B77) | F77: =SUMIFS('Saisie hebdo'!$H$5:$H$2000,'Saisie hebdo'!$B$5:$B$2000,$A77,'Saisie hebdo'!$C$5:$C$2000,$B77) | G77: =IFERROR(AVERAGEIFS('Saisie hebdo'!$I$5:$I$2000,'Saisie hebdo'!$B$5:$B$2000,$A77,'Saisie hebdo'!$C$5:$C$2000,$B77),"") | H77: =IFERROR(AVERAGEIFS('Saisie hebdo'!$J$5:$J$2000,'Saisie hebdo'!$B$5:$B$2000,$A77,'Saisie hebdo'!$C$5:$C$2000,$B77),"") | I77: =SUMIFS('Saisie hebdo'!$K$5:$K$2000,'Saisie hebdo'!$B$5:$B$2000,$A77,'Saisie hebdo'!$C$5:$C$2000,$B77) | J77: =SUMIFS('Saisie hebdo'!$L$5:$L$2000,'Saisie hebdo'!$B$5:$B$2000,$A77,'Saisie hebdo'!$C$5:$C$2000,$B77) | K77: =SUMIFS('Saisie hebdo'!$M$5:$M$2000,'Saisie hebdo'!$B$5:$B$2000,$A77,'Saisie hebdo'!$C$5:$C$2000,$B77) | L77: =SUMIFS('Saisie hebdo'!$N$5:$N$2000,'Saisie hebdo'!$B$5:$B$2000,$A77,'Saisie hebdo'!$C$5:$C$2000,$B77) | M77: =SUMIFS('Saisie hebdo'!$O$5:$O$2000,'Saisie hebdo'!$B$5:$B$2000,$A77,'Saisie hebdo'!$C$5:$C$2000,$B77) | N77: =IF(N(D77)=0,"",E77/D77) | O77: =IF(N(E77)=0,"",C77/E77) | P77: =IF(N(E77)=0,"",F77/E77) | Q77: =IF(N(F77)=0,"",C77/F77) | R77: =IF(N(I77)=0,"",C77/I77) | S77: =IF(N(J77)=0,"",C77/J77) | T77: =IF(N(L77)=0,"",C77/L77) | U77: =IF(N(I77)=0,"",J77/I77) | V77: =IF(N(K77)=0,"",L77/K77) | W77: =IF(N(C77)=0,"",M77/C77)
A78: 46569 | B78: S-FR | Corporatif & Fêtes | C78: =SUMIFS('Saisie hebdo'!$E$5:$E$2000,'Saisie hebdo'!$B$5:$B$2000,$A78,'Saisie hebdo'!$C$5:$C$2000,$B78) | D78: =SUMIFS('Saisie hebdo'!$F$5:$F$2000,'Saisie hebdo'!$B$5:$B$2000,$A78,'Saisie hebdo'!$C$5:$C$2000,$B78) | E78: =SUMIFS('Saisie hebdo'!$G$5:$G$2000,'Saisie hebdo'!$B$5:$B$2000,$A78,'Saisie hebdo'!$C$5:$C$2000,$B78) | F78: =SUMIFS('Saisie hebdo'!$H$5:$H$2000,'Saisie hebdo'!$B$5:$B$2000,$A78,'Saisie hebdo'!$C$5:$C$2000,$B78) | G78: =IFERROR(AVERAGEIFS('Saisie hebdo'!$I$5:$I$2000,'Saisie hebdo'!$B$5:$B$2000,$A78,'Saisie hebdo'!$C$5:$C$2000,$B78),"") | H78: =IFERROR(AVERAGEIFS('Saisie hebdo'!$J$5:$J$2000,'Saisie hebdo'!$B$5:$B$2000,$A78,'Saisie hebdo'!$C$5:$C$2000,$B78),"") | I78: =SUMIFS('Saisie hebdo'!$K$5:$K$2000,'Saisie hebdo'!$B$5:$B$2000,$A78,'Saisie hebdo'!$C$5:$C$2000,$B78) | J78: =SUMIFS('Saisie hebdo'!$L$5:$L$2000,'Saisie hebdo'!$B$5:$B$2000,$A78,'Saisie hebdo'!$C$5:$C$2000,$B78) | K78: =SUMIFS('Saisie hebdo'!$M$5:$M$2000,'Saisie hebdo'!$B$5:$B$2000,$A78,'Saisie hebdo'!$C$5:$C$2000,$B78) | L78: =SUMIFS('Saisie hebdo'!$N$5:$N$2000,'Saisie hebdo'!$B$5:$B$2000,$A78,'Saisie hebdo'!$C$5:$C$2000,$B78) | M78: =SUMIFS('Saisie hebdo'!$O$5:$O$2000,'Saisie hebdo'!$B$5:$B$2000,$A78,'Saisie hebdo'!$C$5:$C$2000,$B78) | N78: =IF(N(D78)=0,"",E78/D78) | O78: =IF(N(E78)=0,"",C78/E78) | P78: =IF(N(E78)=0,"",F78/E78) | Q78: =IF(N(F78)=0,"",C78/F78) | R78: =IF(N(I78)=0,"",C78/I78) | S78: =IF(N(J78)=0,"",C78/J78) | T78: =IF(N(L78)=0,"",C78/L78) | U78: =IF(N(I78)=0,"",J78/I78) | V78: =IF(N(K78)=0,"",L78/K78) | W78: =IF(N(C78)=0,"",M78/C78)
A79: 46569 | B79: S-FR | Événements privés | C79: =SUMIFS('Saisie hebdo'!$E$5:$E$2000,'Saisie hebdo'!$B$5:$B$2000,$A79,'Saisie hebdo'!$C$5:$C$2000,$B79) | D79: =SUMIFS('Saisie hebdo'!$F$5:$F$2000,'Saisie hebdo'!$B$5:$B$2000,$A79,'Saisie hebdo'!$C$5:$C$2000,$B79) | E79: =SUMIFS('Saisie hebdo'!$G$5:$G$2000,'Saisie hebdo'!$B$5:$B$2000,$A79,'Saisie hebdo'!$C$5:$C$2000,$B79) | F79: =SUMIFS('Saisie hebdo'!$H$5:$H$2000,'Saisie hebdo'!$B$5:$B$2000,$A79,'Saisie hebdo'!$C$5:$C$2000,$B79) | G79: =IFERROR(AVERAGEIFS('Saisie hebdo'!$I$5:$I$2000,'Saisie hebdo'!$B$5:$B$2000,$A79,'Saisie hebdo'!$C$5:$C$2000,$B79),"") | H79: =IFERROR(AVERAGEIFS('Saisie hebdo'!$J$5:$J$2000,'Saisie hebdo'!$B$5:$B$2000,$A79,'Saisie hebdo'!$C$5:$C$2000,$B79),"") | I79: =SUMIFS('Saisie hebdo'!$K$5:$K$2000,'Saisie hebdo'!$B$5:$B$2000,$A79,'Saisie hebdo'!$C$5:$C$2000,$B79) | J79: =SUMIFS('Saisie hebdo'!$L$5:$L$2000,'Saisie hebdo'!$B$5:$B$2000,$A79,'Saisie hebdo'!$C$5:$C$2000,$B79) | K79: =SUMIFS('Saisie hebdo'!$M$5:$M$2000,'Saisie hebdo'!$B$5:$B$2000,$A79,'Saisie hebdo'!$C$5:$C$2000,$B79) | L79: =SUMIFS('Saisie hebdo'!$N$5:$N$2000,'Saisie hebdo'!$B$5:$B$2000,$A79,'Saisie hebdo'!$C$5:$C$2000,$B79) | M79: =SUMIFS('Saisie hebdo'!$O$5:$O$2000,'Saisie hebdo'!$B$5:$B$2000,$A79,'Saisie hebdo'!$C$5:$C$2000,$B79) | N79: =IF(N(D79)=0,"",E79/D79) | O79: =IF(N(E79)=0,"",C79/E79) | P79: =IF(N(E79)=0,"",F79/E79) | Q79: =IF(N(F79)=0,"",C79/F79) | R79: =IF(N(I79)=0,"",C79/I79) | S79: =IF(N(J79)=0,"",C79/J79) | T79: =IF(N(L79)=0,"",C79/L79) | U79: =IF(N(I79)=0,"",J79/I79) | V79: =IF(N(K79)=0,"",L79/K79) | W79: =IF(N(C79)=0,"",M79/C79)
A80: 46569 | B80: S-EN | Corporate Montréal | C80: =SUMIFS('Saisie hebdo'!$E$5:$E$2000,'Saisie hebdo'!$B$5:$B$2000,$A80,'Saisie hebdo'!$C$5:$C$2000,$B80) | D80: =SUMIFS('Saisie hebdo'!$F$5:$F$2000,'Saisie hebdo'!$B$5:$B$2000,$A80,'Saisie hebdo'!$C$5:$C$2000,$B80) | E80: =SUMIFS('Saisie hebdo'!$G$5:$G$2000,'Saisie hebdo'!$B$5:$B$2000,$A80,'Saisie hebdo'!$C$5:$C$2000,$B80) | F80: =SUMIFS('Saisie hebdo'!$H$5:$H$2000,'Saisie hebdo'!$B$5:$B$2000,$A80,'Saisie hebdo'!$C$5:$C$2000,$B80) | G80: =IFERROR(AVERAGEIFS('Saisie hebdo'!$I$5:$I$2000,'Saisie hebdo'!$B$5:$B$2000,$A80,'Saisie hebdo'!$C$5:$C$2000,$B80),"") | H80: =IFERROR(AVERAGEIFS('Saisie hebdo'!$J$5:$J$2000,'Saisie hebdo'!$B$5:$B$2000,$A80,'Saisie hebdo'!$C$5:$C$2000,$B80),"") | I80: =SUMIFS('Saisie hebdo'!$K$5:$K$2000,'Saisie hebdo'!$B$5:$B$2000,$A80,'Saisie hebdo'!$C$5:$C$2000,$B80) | J80: =SUMIFS('Saisie hebdo'!$L$5:$L$2000,'Saisie hebdo'!$B$5:$B$2000,$A80,'Saisie hebdo'!$C$5:$C$2000,$B80) | K80: =SUMIFS('Saisie hebdo'!$M$5:$M$2000,'Saisie hebdo'!$B$5:$B$2000,$A80,'Saisie hebdo'!$C$5:$C$2000,$B80) | L80: =SUMIFS('Saisie hebdo'!$N$5:$N$2000,'Saisie hebdo'!$B$5:$B$2000,$A80,'Saisie hebdo'!$C$5:$C$2000,$B80) | M80: =SUMIFS('Saisie hebdo'!$O$5:$O$2000,'Saisie hebdo'!$B$5:$B$2000,$A80,'Saisie hebdo'!$C$5:$C$2000,$B80) | N80: =IF(N(D80)=0,"",E80/D80) | O80: =IF(N(E80)=0,"",C80/E80) | P80: =IF(N(E80)=0,"",F80/E80) | Q80: =IF(N(F80)=0,"",C80/F80) | R80: =IF(N(I80)=0,"",C80/I80) | S80: =IF(N(J80)=0,"",C80/J80) | T80: =IF(N(L80)=0,"",C80/L80) | U80: =IF(N(I80)=0,"",J80/I80) | V80: =IF(N(K80)=0,"",L80/K80) | W80: =IF(N(C80)=0,"",M80/C80)
A81: 46569 | B81: S-FR | Québec-Lévis (test) | C81: =SUMIFS('Saisie hebdo'!$E$5:$E$2000,'Saisie hebdo'!$B$5:$B$2000,$A81,'Saisie hebdo'!$C$5:$C$2000,$B81) | D81: =SUMIFS('Saisie hebdo'!$F$5:$F$2000,'Saisie hebdo'!$B$5:$B$2000,$A81,'Saisie hebdo'!$C$5:$C$2000,$B81) | E81: =SUMIFS('Saisie hebdo'!$G$5:$G$2000,'Saisie hebdo'!$B$5:$B$2000,$A81,'Saisie hebdo'!$C$5:$C$2000,$B81) | F81: =SUMIFS('Saisie hebdo'!$H$5:$H$2000,'Saisie hebdo'!$B$5:$B$2000,$A81,'Saisie hebdo'!$C$5:$C$2000,$B81) | G81: =IFERROR(AVERAGEIFS('Saisie hebdo'!$I$5:$I$2000,'Saisie hebdo'!$B$5:$B$2000,$A81,'Saisie hebdo'!$C$5:$C$2000,$B81),"") | H81: =IFERROR(AVERAGEIFS('Saisie hebdo'!$J$5:$J$2000,'Saisie hebdo'!$B$5:$B$2000,$A81,'Saisie hebdo'!$C$5:$C$2000,$B81),"") | I81: =SUMIFS('Saisie hebdo'!$K$5:$K$2000,'Saisie hebdo'!$B$5:$B$2000,$A81,'Saisie hebdo'!$C$5:$C$2000,$B81) | J81: =SUMIFS('Saisie hebdo'!$L$5:$L$2000,'Saisie hebdo'!$B$5:$B$2000,$A81,'Saisie hebdo'!$C$5:$C$2000,$B81) | K81: =SUMIFS('Saisie hebdo'!$M$5:$M$2000,'Saisie hebdo'!$B$5:$B$2000,$A81,'Saisie hebdo'!$C$5:$C$2000,$B81) | L81: =SUMIFS('Saisie hebdo'!$N$5:$N$2000,'Saisie hebdo'!$B$5:$B$2000,$A81,'Saisie hebdo'!$C$5:$C$2000,$B81) | M81: =SUMIFS('Saisie hebdo'!$O$5:$O$2000,'Saisie hebdo'!$B$5:$B$2000,$A81,'Saisie hebdo'!$C$5:$C$2000,$B81) | N81: =IF(N(D81)=0,"",E81/D81) | O81: =IF(N(E81)=0,"",C81/E81) | P81: =IF(N(E81)=0,"",F81/E81) | Q81: =IF(N(F81)=0,"",C81/F81) | R81: =IF(N(I81)=0,"",C81/I81) | S81: =IF(N(J81)=0,"",C81/J81) | T81: =IF(N(L81)=0,"",C81/L81) | U81: =IF(N(I81)=0,"",J81/I81) | V81: =IF(N(K81)=0,"",L81/K81) | W81: =IF(N(C81)=0,"",M81/C81)
A82: 46569 | B82: Demand Gen | C82: =SUMIFS('Saisie hebdo'!$E$5:$E$2000,'Saisie hebdo'!$B$5:$B$2000,$A82,'Saisie hebdo'!$C$5:$C$2000,$B82) | D82: =SUMIFS('Saisie hebdo'!$F$5:$F$2000,'Saisie hebdo'!$B$5:$B$2000,$A82,'Saisie hebdo'!$C$5:$C$2000,$B82) | E82: =SUMIFS('Saisie hebdo'!$G$5:$G$2000,'Saisie hebdo'!$B$5:$B$2000,$A82,'Saisie hebdo'!$C$5:$C$2000,$B82) | F82: =SUMIFS('Saisie hebdo'!$H$5:$H$2000,'Saisie hebdo'!$B$5:$B$2000,$A82,'Saisie hebdo'!$C$5:$C$2000,$B82) | G82: =IFERROR(AVERAGEIFS('Saisie hebdo'!$I$5:$I$2000,'Saisie hebdo'!$B$5:$B$2000,$A82,'Saisie hebdo'!$C$5:$C$2000,$B82),"") | H82: =IFERROR(AVERAGEIFS('Saisie hebdo'!$J$5:$J$2000,'Saisie hebdo'!$B$5:$B$2000,$A82,'Saisie hebdo'!$C$5:$C$2000,$B82),"") | I82: =SUMIFS('Saisie hebdo'!$K$5:$K$2000,'Saisie hebdo'!$B$5:$B$2000,$A82,'Saisie hebdo'!$C$5:$C$2000,$B82) | J82: =SUMIFS('Saisie hebdo'!$L$5:$L$2000,'Saisie hebdo'!$B$5:$B$2000,$A82,'Saisie hebdo'!$C$5:$C$2000,$B82) | K82: =SUMIFS('Saisie hebdo'!$M$5:$M$2000,'Saisie hebdo'!$B$5:$B$2000,$A82,'Saisie hebdo'!$C$5:$C$2000,$B82) | L82: =SUMIFS('Saisie hebdo'!$N$5:$N$2000,'Saisie hebdo'!$B$5:$B$2000,$A82,'Saisie hebdo'!$C$5:$C$2000,$B82) | M82: =SUMIFS('Saisie hebdo'!$O$5:$O$2000,'Saisie hebdo'!$B$5:$B$2000,$A82,'Saisie hebdo'!$C$5:$C$2000,$B82) | N82: =IF(N(D82)=0,"",E82/D82) | O82: =IF(N(E82)=0,"",C82/E82) | P82: =IF(N(E82)=0,"",F82/E82) | Q82: =IF(N(F82)=0,"",C82/F82) | R82: =IF(N(I82)=0,"",C82/I82) | S82: =IF(N(J82)=0,"",C82/J82) | T82: =IF(N(L82)=0,"",C82/L82) | U82: =IF(N(I82)=0,"",J82/I82) | V82: =IF(N(K82)=0,"",L82/K82) | W82: =IF(N(C82)=0,"",M82/C82)
A83: 46569 | B83: Microsoft Ads | C83: =SUMIFS('Saisie hebdo'!$E$5:$E$2000,'Saisie hebdo'!$B$5:$B$2000,$A83,'Saisie hebdo'!$C$5:$C$2000,$B83) | D83: =SUMIFS('Saisie hebdo'!$F$5:$F$2000,'Saisie hebdo'!$B$5:$B$2000,$A83,'Saisie hebdo'!$C$5:$C$2000,$B83) | E83: =SUMIFS('Saisie hebdo'!$G$5:$G$2000,'Saisie hebdo'!$B$5:$B$2000,$A83,'Saisie hebdo'!$C$5:$C$2000,$B83) | F83: =SUMIFS('Saisie hebdo'!$H$5:$H$2000,'Saisie hebdo'!$B$5:$B$2000,$A83,'Saisie hebdo'!$C$5:$C$2000,$B83) | G83: =IFERROR(AVERAGEIFS('Saisie hebdo'!$I$5:$I$2000,'Saisie hebdo'!$B$5:$B$2000,$A83,'Saisie hebdo'!$C$5:$C$2000,$B83),"") | H83: =IFERROR(AVERAGEIFS('Saisie hebdo'!$J$5:$J$2000,'Saisie hebdo'!$B$5:$B$2000,$A83,'Saisie hebdo'!$C$5:$C$2000,$B83),"") | I83: =SUMIFS('Saisie hebdo'!$K$5:$K$2000,'Saisie hebdo'!$B$5:$B$2000,$A83,'Saisie hebdo'!$C$5:$C$2000,$B83) | J83: =SUMIFS('Saisie hebdo'!$L$5:$L$2000,'Saisie hebdo'!$B$5:$B$2000,$A83,'Saisie hebdo'!$C$5:$C$2000,$B83) | K83: =SUMIFS('Saisie hebdo'!$M$5:$M$2000,'Saisie hebdo'!$B$5:$B$2000,$A83,'Saisie hebdo'!$C$5:$C$2000,$B83) | L83: =SUMIFS('Saisie hebdo'!$N$5:$N$2000,'Saisie hebdo'!$B$5:$B$2000,$A83,'Saisie hebdo'!$C$5:$C$2000,$B83) | M83: =SUMIFS('Saisie hebdo'!$O$5:$O$2000,'Saisie hebdo'!$B$5:$B$2000,$A83,'Saisie hebdo'!$C$5:$C$2000,$B83) | N83: =IF(N(D83)=0,"",E83/D83) | O83: =IF(N(E83)=0,"",C83/E83) | P83: =IF(N(E83)=0,"",F83/E83) | Q83: =IF(N(F83)=0,"",C83/F83) | R83: =IF(N(I83)=0,"",C83/I83) | S83: =IF(N(J83)=0,"",C83/J83) | T83: =IF(N(L83)=0,"",C83/L83) | U83: =IF(N(I83)=0,"",J83/I83) | V83: =IF(N(K83)=0,"",L83/K83) | W83: =IF(N(C83)=0,"",M83/C83)
A84: 46569 | B84: Total du compte | C84: =SUMIFS('Saisie hebdo'!$E$5:$E$2000,'Saisie hebdo'!$B$5:$B$2000,$A84) | D84: =SUMIFS('Saisie hebdo'!$F$5:$F$2000,'Saisie hebdo'!$B$5:$B$2000,$A84) | E84: =SUMIFS('Saisie hebdo'!$G$5:$G$2000,'Saisie hebdo'!$B$5:$B$2000,$A84) | F84: =SUMIFS('Saisie hebdo'!$H$5:$H$2000,'Saisie hebdo'!$B$5:$B$2000,$A84) | G84: =IFERROR(AVERAGEIFS('Saisie hebdo'!$I$5:$I$2000,'Saisie hebdo'!$B$5:$B$2000,$A84),"") | H84: =IFERROR(AVERAGEIFS('Saisie hebdo'!$J$5:$J$2000,'Saisie hebdo'!$B$5:$B$2000,$A84),"") | I84: =SUMIFS('Saisie hebdo'!$K$5:$K$2000,'Saisie hebdo'!$B$5:$B$2000,$A84) | J84: =SUMIFS('Saisie hebdo'!$L$5:$L$2000,'Saisie hebdo'!$B$5:$B$2000,$A84) | K84: =SUMIFS('Saisie hebdo'!$M$5:$M$2000,'Saisie hebdo'!$B$5:$B$2000,$A84) | L84: =SUMIFS('Saisie hebdo'!$N$5:$N$2000,'Saisie hebdo'!$B$5:$B$2000,$A84) | M84: =SUMIFS('Saisie hebdo'!$O$5:$O$2000,'Saisie hebdo'!$B$5:$B$2000,$A84) | N84: =IF(N(D84)=0,"",E84/D84) | O84: =IF(N(E84)=0,"",C84/E84) | P84: =IF(N(E84)=0,"",F84/E84) | Q84: =IF(N(F84)=0,"",C84/F84) | R84: =IF(N(I84)=0,"",C84/I84) | S84: =IF(N(J84)=0,"",C84/J84) | T84: =IF(N(L84)=0,"",C84/L84) | U84: =IF(N(I84)=0,"",J84/I84) | V84: =IF(N(K84)=0,"",L84/K84) | W84: =IF(N(C84)=0,"",M84/C84)
A85: 46600 | B85: S-FR | Marque | C85: =SUMIFS('Saisie hebdo'!$E$5:$E$2000,'Saisie hebdo'!$B$5:$B$2000,$A85,'Saisie hebdo'!$C$5:$C$2000,$B85) | D85: =SUMIFS('Saisie hebdo'!$F$5:$F$2000,'Saisie hebdo'!$B$5:$B$2000,$A85,'Saisie hebdo'!$C$5:$C$2000,$B85) | E85: =SUMIFS('Saisie hebdo'!$G$5:$G$2000,'Saisie hebdo'!$B$5:$B$2000,$A85,'Saisie hebdo'!$C$5:$C$2000,$B85) | F85: =SUMIFS('Saisie hebdo'!$H$5:$H$2000,'Saisie hebdo'!$B$5:$B$2000,$A85,'Saisie hebdo'!$C$5:$C$2000,$B85) | G85: =IFERROR(AVERAGEIFS('Saisie hebdo'!$I$5:$I$2000,'Saisie hebdo'!$B$5:$B$2000,$A85,'Saisie hebdo'!$C$5:$C$2000,$B85),"") | H85: =IFERROR(AVERAGEIFS('Saisie hebdo'!$J$5:$J$2000,'Saisie hebdo'!$B$5:$B$2000,$A85,'Saisie hebdo'!$C$5:$C$2000,$B85),"") | I85: =SUMIFS('Saisie hebdo'!$K$5:$K$2000,'Saisie hebdo'!$B$5:$B$2000,$A85,'Saisie hebdo'!$C$5:$C$2000,$B85) | J85: =SUMIFS('Saisie hebdo'!$L$5:$L$2000,'Saisie hebdo'!$B$5:$B$2000,$A85,'Saisie hebdo'!$C$5:$C$2000,$B85) | K85: =SUMIFS('Saisie hebdo'!$M$5:$M$2000,'Saisie hebdo'!$B$5:$B$2000,$A85,'Saisie hebdo'!$C$5:$C$2000,$B85) | L85: =SUMIFS('Saisie hebdo'!$N$5:$N$2000,'Saisie hebdo'!$B$5:$B$2000,$A85,'Saisie hebdo'!$C$5:$C$2000,$B85) | M85: =SUMIFS('Saisie hebdo'!$O$5:$O$2000,'Saisie hebdo'!$B$5:$B$2000,$A85,'Saisie hebdo'!$C$5:$C$2000,$B85) | N85: =IF(N(D85)=0,"",E85/D85) | O85: =IF(N(E85)=0,"",C85/E85) | P85: =IF(N(E85)=0,"",F85/E85) | Q85: =IF(N(F85)=0,"",C85/F85) | R85: =IF(N(I85)=0,"",C85/I85) | S85: =IF(N(J85)=0,"",C85/J85) | T85: =IF(N(L85)=0,"",C85/L85) | U85: =IF(N(I85)=0,"",J85/I85) | V85: =IF(N(K85)=0,"",L85/K85) | W85: =IF(N(C85)=0,"",M85/C85)
A86: 46600 | B86: S-FR | Corporatif & Fêtes | C86: =SUMIFS('Saisie hebdo'!$E$5:$E$2000,'Saisie hebdo'!$B$5:$B$2000,$A86,'Saisie hebdo'!$C$5:$C$2000,$B86) | D86: =SUMIFS('Saisie hebdo'!$F$5:$F$2000,'Saisie hebdo'!$B$5:$B$2000,$A86,'Saisie hebdo'!$C$5:$C$2000,$B86) | E86: =SUMIFS('Saisie hebdo'!$G$5:$G$2000,'Saisie hebdo'!$B$5:$B$2000,$A86,'Saisie hebdo'!$C$5:$C$2000,$B86) | F86: =SUMIFS('Saisie hebdo'!$H$5:$H$2000,'Saisie hebdo'!$B$5:$B$2000,$A86,'Saisie hebdo'!$C$5:$C$2000,$B86) | G86: =IFERROR(AVERAGEIFS('Saisie hebdo'!$I$5:$I$2000,'Saisie hebdo'!$B$5:$B$2000,$A86,'Saisie hebdo'!$C$5:$C$2000,$B86),"") | H86: =IFERROR(AVERAGEIFS('Saisie hebdo'!$J$5:$J$2000,'Saisie hebdo'!$B$5:$B$2000,$A86,'Saisie hebdo'!$C$5:$C$2000,$B86),"") | I86: =SUMIFS('Saisie hebdo'!$K$5:$K$2000,'Saisie hebdo'!$B$5:$B$2000,$A86,'Saisie hebdo'!$C$5:$C$2000,$B86) | J86: =SUMIFS('Saisie hebdo'!$L$5:$L$2000,'Saisie hebdo'!$B$5:$B$2000,$A86,'Saisie hebdo'!$C$5:$C$2000,$B86) | K86: =SUMIFS('Saisie hebdo'!$M$5:$M$2000,'Saisie hebdo'!$B$5:$B$2000,$A86,'Saisie hebdo'!$C$5:$C$2000,$B86) | L86: =SUMIFS('Saisie hebdo'!$N$5:$N$2000,'Saisie hebdo'!$B$5:$B$2000,$A86,'Saisie hebdo'!$C$5:$C$2000,$B86) | M86: =SUMIFS('Saisie hebdo'!$O$5:$O$2000,'Saisie hebdo'!$B$5:$B$2000,$A86,'Saisie hebdo'!$C$5:$C$2000,$B86) | N86: =IF(N(D86)=0,"",E86/D86) | O86: =IF(N(E86)=0,"",C86/E86) | P86: =IF(N(E86)=0,"",F86/E86) | Q86: =IF(N(F86)=0,"",C86/F86) | R86: =IF(N(I86)=0,"",C86/I86) | S86: =IF(N(J86)=0,"",C86/J86) | T86: =IF(N(L86)=0,"",C86/L86) | U86: =IF(N(I86)=0,"",J86/I86) | V86: =IF(N(K86)=0,"",L86/K86) | W86: =IF(N(C86)=0,"",M86/C86)
A87: 46600 | B87: S-FR | Événements privés | C87: =SUMIFS('Saisie hebdo'!$E$5:$E$2000,'Saisie hebdo'!$B$5:$B$2000,$A87,'Saisie hebdo'!$C$5:$C$2000,$B87) | D87: =SUMIFS('Saisie hebdo'!$F$5:$F$2000,'Saisie hebdo'!$B$5:$B$2000,$A87,'Saisie hebdo'!$C$5:$C$2000,$B87) | E87: =SUMIFS('Saisie hebdo'!$G$5:$G$2000,'Saisie hebdo'!$B$5:$B$2000,$A87,'Saisie hebdo'!$C$5:$C$2000,$B87) | F87: =SUMIFS('Saisie hebdo'!$H$5:$H$2000,'Saisie hebdo'!$B$5:$B$2000,$A87,'Saisie hebdo'!$C$5:$C$2000,$B87) | G87: =IFERROR(AVERAGEIFS('Saisie hebdo'!$I$5:$I$2000,'Saisie hebdo'!$B$5:$B$2000,$A87,'Saisie hebdo'!$C$5:$C$2000,$B87),"") | H87: =IFERROR(AVERAGEIFS('Saisie hebdo'!$J$5:$J$2000,'Saisie hebdo'!$B$5:$B$2000,$A87,'Saisie hebdo'!$C$5:$C$2000,$B87),"") | I87: =SUMIFS('Saisie hebdo'!$K$5:$K$2000,'Saisie hebdo'!$B$5:$B$2000,$A87,'Saisie hebdo'!$C$5:$C$2000,$B87) | J87: =SUMIFS('Saisie hebdo'!$L$5:$L$2000,'Saisie hebdo'!$B$5:$B$2000,$A87,'Saisie hebdo'!$C$5:$C$2000,$B87) | K87: =SUMIFS('Saisie hebdo'!$M$5:$M$2000,'Saisie hebdo'!$B$5:$B$2000,$A87,'Saisie hebdo'!$C$5:$C$2000,$B87) | L87: =SUMIFS('Saisie hebdo'!$N$5:$N$2000,'Saisie hebdo'!$B$5:$B$2000,$A87,'Saisie hebdo'!$C$5:$C$2000,$B87) | M87: =SUMIFS('Saisie hebdo'!$O$5:$O$2000,'Saisie hebdo'!$B$5:$B$2000,$A87,'Saisie hebdo'!$C$5:$C$2000,$B87) | N87: =IF(N(D87)=0,"",E87/D87) | O87: =IF(N(E87)=0,"",C87/E87) | P87: =IF(N(E87)=0,"",F87/E87) | Q87: =IF(N(F87)=0,"",C87/F87) | R87: =IF(N(I87)=0,"",C87/I87) | S87: =IF(N(J87)=0,"",C87/J87) | T87: =IF(N(L87)=0,"",C87/L87) | U87: =IF(N(I87)=0,"",J87/I87) | V87: =IF(N(K87)=0,"",L87/K87) | W87: =IF(N(C87)=0,"",M87/C87)
A88: 46600 | B88: S-EN | Corporate Montréal | C88: =SUMIFS('Saisie hebdo'!$E$5:$E$2000,'Saisie hebdo'!$B$5:$B$2000,$A88,'Saisie hebdo'!$C$5:$C$2000,$B88) | D88: =SUMIFS('Saisie hebdo'!$F$5:$F$2000,'Saisie hebdo'!$B$5:$B$2000,$A88,'Saisie hebdo'!$C$5:$C$2000,$B88) | E88: =SUMIFS('Saisie hebdo'!$G$5:$G$2000,'Saisie hebdo'!$B$5:$B$2000,$A88,'Saisie hebdo'!$C$5:$C$2000,$B88) | F88: =SUMIFS('Saisie hebdo'!$H$5:$H$2000,'Saisie hebdo'!$B$5:$B$2000,$A88,'Saisie hebdo'!$C$5:$C$2000,$B88) | G88: =IFERROR(AVERAGEIFS('Saisie hebdo'!$I$5:$I$2000,'Saisie hebdo'!$B$5:$B$2000,$A88,'Saisie hebdo'!$C$5:$C$2000,$B88),"") | H88: =IFERROR(AVERAGEIFS('Saisie hebdo'!$J$5:$J$2000,'Saisie hebdo'!$B$5:$B$2000,$A88,'Saisie hebdo'!$C$5:$C$2000,$B88),"") | I88: =SUMIFS('Saisie hebdo'!$K$5:$K$2000,'Saisie hebdo'!$B$5:$B$2000,$A88,'Saisie hebdo'!$C$5:$C$2000,$B88) | J88: =SUMIFS('Saisie hebdo'!$L$5:$L$2000,'Saisie hebdo'!$B$5:$B$2000,$A88,'Saisie hebdo'!$C$5:$C$2000,$B88) | K88: =SUMIFS('Saisie hebdo'!$M$5:$M$2000,'Saisie hebdo'!$B$5:$B$2000,$A88,'Saisie hebdo'!$C$5:$C$2000,$B88) | L88: =SUMIFS('Saisie hebdo'!$N$5:$N$2000,'Saisie hebdo'!$B$5:$B$2000,$A88,'Saisie hebdo'!$C$5:$C$2000,$B88) | M88: =SUMIFS('Saisie hebdo'!$O$5:$O$2000,'Saisie hebdo'!$B$5:$B$2000,$A88,'Saisie hebdo'!$C$5:$C$2000,$B88) | N88: =IF(N(D88)=0,"",E88/D88) | O88: =IF(N(E88)=0,"",C88/E88) | P88: =IF(N(E88)=0,"",F88/E88) | Q88: =IF(N(F88)=0,"",C88/F88) | R88: =IF(N(I88)=0,"",C88/I88) | S88: =IF(N(J88)=0,"",C88/J88) | T88: =IF(N(L88)=0,"",C88/L88) | U88: =IF(N(I88)=0,"",J88/I88) | V88: =IF(N(K88)=0,"",L88/K88) | W88: =IF(N(C88)=0,"",M88/C88)
A89: 46600 | B89: S-FR | Québec-Lévis (test) | C89: =SUMIFS('Saisie hebdo'!$E$5:$E$2000,'Saisie hebdo'!$B$5:$B$2000,$A89,'Saisie hebdo'!$C$5:$C$2000,$B89) | D89: =SUMIFS('Saisie hebdo'!$F$5:$F$2000,'Saisie hebdo'!$B$5:$B$2000,$A89,'Saisie hebdo'!$C$5:$C$2000,$B89) | E89: =SUMIFS('Saisie hebdo'!$G$5:$G$2000,'Saisie hebdo'!$B$5:$B$2000,$A89,'Saisie hebdo'!$C$5:$C$2000,$B89) | F89: =SUMIFS('Saisie hebdo'!$H$5:$H$2000,'Saisie hebdo'!$B$5:$B$2000,$A89,'Saisie hebdo'!$C$5:$C$2000,$B89) | G89: =IFERROR(AVERAGEIFS('Saisie hebdo'!$I$5:$I$2000,'Saisie hebdo'!$B$5:$B$2000,$A89,'Saisie hebdo'!$C$5:$C$2000,$B89),"") | H89: =IFERROR(AVERAGEIFS('Saisie hebdo'!$J$5:$J$2000,'Saisie hebdo'!$B$5:$B$2000,$A89,'Saisie hebdo'!$C$5:$C$2000,$B89),"") | I89: =SUMIFS('Saisie hebdo'!$K$5:$K$2000,'Saisie hebdo'!$B$5:$B$2000,$A89,'Saisie hebdo'!$C$5:$C$2000,$B89) | J89: =SUMIFS('Saisie hebdo'!$L$5:$L$2000,'Saisie hebdo'!$B$5:$B$2000,$A89,'Saisie hebdo'!$C$5:$C$2000,$B89) | K89: =SUMIFS('Saisie hebdo'!$M$5:$M$2000,'Saisie hebdo'!$B$5:$B$2000,$A89,'Saisie hebdo'!$C$5:$C$2000,$B89) | L89: =SUMIFS('Saisie hebdo'!$N$5:$N$2000,'Saisie hebdo'!$B$5:$B$2000,$A89,'Saisie hebdo'!$C$5:$C$2000,$B89) | M89: =SUMIFS('Saisie hebdo'!$O$5:$O$2000,'Saisie hebdo'!$B$5:$B$2000,$A89,'Saisie hebdo'!$C$5:$C$2000,$B89) | N89: =IF(N(D89)=0,"",E89/D89) | O89: =IF(N(E89)=0,"",C89/E89) | P89: =IF(N(E89)=0,"",F89/E89) | Q89: =IF(N(F89)=0,"",C89/F89) | R89: =IF(N(I89)=0,"",C89/I89) | S89: =IF(N(J89)=0,"",C89/J89) | T89: =IF(N(L89)=0,"",C89/L89) | U89: =IF(N(I89)=0,"",J89/I89) | V89: =IF(N(K89)=0,"",L89/K89) | W89: =IF(N(C89)=0,"",M89/C89)
A90: 46600 | B90: Demand Gen | C90: =SUMIFS('Saisie hebdo'!$E$5:$E$2000,'Saisie hebdo'!$B$5:$B$2000,$A90,'Saisie hebdo'!$C$5:$C$2000,$B90) | D90: =SUMIFS('Saisie hebdo'!$F$5:$F$2000,'Saisie hebdo'!$B$5:$B$2000,$A90,'Saisie hebdo'!$C$5:$C$2000,$B90) | E90: =SUMIFS('Saisie hebdo'!$G$5:$G$2000,'Saisie hebdo'!$B$5:$B$2000,$A90,'Saisie hebdo'!$C$5:$C$2000,$B90) | F90: =SUMIFS('Saisie hebdo'!$H$5:$H$2000,'Saisie hebdo'!$B$5:$B$2000,$A90,'Saisie hebdo'!$C$5:$C$2000,$B90) | G90: =IFERROR(AVERAGEIFS('Saisie hebdo'!$I$5:$I$2000,'Saisie hebdo'!$B$5:$B$2000,$A90,'Saisie hebdo'!$C$5:$C$2000,$B90),"") | H90: =IFERROR(AVERAGEIFS('Saisie hebdo'!$J$5:$J$2000,'Saisie hebdo'!$B$5:$B$2000,$A90,'Saisie hebdo'!$C$5:$C$2000,$B90),"") | I90: =SUMIFS('Saisie hebdo'!$K$5:$K$2000,'Saisie hebdo'!$B$5:$B$2000,$A90,'Saisie hebdo'!$C$5:$C$2000,$B90) | J90: =SUMIFS('Saisie hebdo'!$L$5:$L$2000,'Saisie hebdo'!$B$5:$B$2000,$A90,'Saisie hebdo'!$C$5:$C$2000,$B90) | K90: =SUMIFS('Saisie hebdo'!$M$5:$M$2000,'Saisie hebdo'!$B$5:$B$2000,$A90,'Saisie hebdo'!$C$5:$C$2000,$B90) | L90: =SUMIFS('Saisie hebdo'!$N$5:$N$2000,'Saisie hebdo'!$B$5:$B$2000,$A90,'Saisie hebdo'!$C$5:$C$2000,$B90) | M90: =SUMIFS('Saisie hebdo'!$O$5:$O$2000,'Saisie hebdo'!$B$5:$B$2000,$A90,'Saisie hebdo'!$C$5:$C$2000,$B90) | N90: =IF(N(D90)=0,"",E90/D90) | O90: =IF(N(E90)=0,"",C90/E90) | P90: =IF(N(E90)=0,"",F90/E90) | Q90: =IF(N(F90)=0,"",C90/F90) | R90: =IF(N(I90)=0,"",C90/I90) | S90: =IF(N(J90)=0,"",C90/J90) | T90: =IF(N(L90)=0,"",C90/L90) | U90: =IF(N(I90)=0,"",J90/I90) | V90: =IF(N(K90)=0,"",L90/K90) | W90: =IF(N(C90)=0,"",M90/C90)
A91: 46600 | B91: Microsoft Ads | C91: =SUMIFS('Saisie hebdo'!$E$5:$E$2000,'Saisie hebdo'!$B$5:$B$2000,$A91,'Saisie hebdo'!$C$5:$C$2000,$B91) | D91: =SUMIFS('Saisie hebdo'!$F$5:$F$2000,'Saisie hebdo'!$B$5:$B$2000,$A91,'Saisie hebdo'!$C$5:$C$2000,$B91) | E91: =SUMIFS('Saisie hebdo'!$G$5:$G$2000,'Saisie hebdo'!$B$5:$B$2000,$A91,'Saisie hebdo'!$C$5:$C$2000,$B91) | F91: =SUMIFS('Saisie hebdo'!$H$5:$H$2000,'Saisie hebdo'!$B$5:$B$2000,$A91,'Saisie hebdo'!$C$5:$C$2000,$B91) | G91: =IFERROR(AVERAGEIFS('Saisie hebdo'!$I$5:$I$2000,'Saisie hebdo'!$B$5:$B$2000,$A91,'Saisie hebdo'!$C$5:$C$2000,$B91),"") | H91: =IFERROR(AVERAGEIFS('Saisie hebdo'!$J$5:$J$2000,'Saisie hebdo'!$B$5:$B$2000,$A91,'Saisie hebdo'!$C$5:$C$2000,$B91),"") | I91: =SUMIFS('Saisie hebdo'!$K$5:$K$2000,'Saisie hebdo'!$B$5:$B$2000,$A91,'Saisie hebdo'!$C$5:$C$2000,$B91) | J91: =SUMIFS('Saisie hebdo'!$L$5:$L$2000,'Saisie hebdo'!$B$5:$B$2000,$A91,'Saisie hebdo'!$C$5:$C$2000,$B91) | K91: =SUMIFS('Saisie hebdo'!$M$5:$M$2000,'Saisie hebdo'!$B$5:$B$2000,$A91,'Saisie hebdo'!$C$5:$C$2000,$B91) | L91: =SUMIFS('Saisie hebdo'!$N$5:$N$2000,'Saisie hebdo'!$B$5:$B$2000,$A91,'Saisie hebdo'!$C$5:$C$2000,$B91) | M91: =SUMIFS('Saisie hebdo'!$O$5:$O$2000,'Saisie hebdo'!$B$5:$B$2000,$A91,'Saisie hebdo'!$C$5:$C$2000,$B91) | N91: =IF(N(D91)=0,"",E91/D91) | O91: =IF(N(E91)=0,"",C91/E91) | P91: =IF(N(E91)=0,"",F91/E91) | Q91: =IF(N(F91)=0,"",C91/F91) | R91: =IF(N(I91)=0,"",C91/I91) | S91: =IF(N(J91)=0,"",C91/J91) | T91: =IF(N(L91)=0,"",C91/L91) | U91: =IF(N(I91)=0,"",J91/I91) | V91: =IF(N(K91)=0,"",L91/K91) | W91: =IF(N(C91)=0,"",M91/C91)
A92: 46600 | B92: Total du compte | C92: =SUMIFS('Saisie hebdo'!$E$5:$E$2000,'Saisie hebdo'!$B$5:$B$2000,$A92) | D92: =SUMIFS('Saisie hebdo'!$F$5:$F$2000,'Saisie hebdo'!$B$5:$B$2000,$A92) | E92: =SUMIFS('Saisie hebdo'!$G$5:$G$2000,'Saisie hebdo'!$B$5:$B$2000,$A92) | F92: =SUMIFS('Saisie hebdo'!$H$5:$H$2000,'Saisie hebdo'!$B$5:$B$2000,$A92) | G92: =IFERROR(AVERAGEIFS('Saisie hebdo'!$I$5:$I$2000,'Saisie hebdo'!$B$5:$B$2000,$A92),"") | H92: =IFERROR(AVERAGEIFS('Saisie hebdo'!$J$5:$J$2000,'Saisie hebdo'!$B$5:$B$2000,$A92),"") | I92: =SUMIFS('Saisie hebdo'!$K$5:$K$2000,'Saisie hebdo'!$B$5:$B$2000,$A92) | J92: =SUMIFS('Saisie hebdo'!$L$5:$L$2000,'Saisie hebdo'!$B$5:$B$2000,$A92) | K92: =SUMIFS('Saisie hebdo'!$M$5:$M$2000,'Saisie hebdo'!$B$5:$B$2000,$A92) | L92: =SUMIFS('Saisie hebdo'!$N$5:$N$2000,'Saisie hebdo'!$B$5:$B$2000,$A92) | M92: =SUMIFS('Saisie hebdo'!$O$5:$O$2000,'Saisie hebdo'!$B$5:$B$2000,$A92) | N92: =IF(N(D92)=0,"",E92/D92) | O92: =IF(N(E92)=0,"",C92/E92) | P92: =IF(N(E92)=0,"",F92/E92) | Q92: =IF(N(F92)=0,"",C92/F92) | R92: =IF(N(I92)=0,"",C92/I92) | S92: =IF(N(J92)=0,"",C92/J92) | T92: =IF(N(L92)=0,"",C92/L92) | U92: =IF(N(I92)=0,"",J92/I92) | V92: =IF(N(K92)=0,"",L92/K92) | W92: =IF(N(C92)=0,"",M92/C92)
A93: 46631 | B93: S-FR | Marque | C93: =SUMIFS('Saisie hebdo'!$E$5:$E$2000,'Saisie hebdo'!$B$5:$B$2000,$A93,'Saisie hebdo'!$C$5:$C$2000,$B93) | D93: =SUMIFS('Saisie hebdo'!$F$5:$F$2000,'Saisie hebdo'!$B$5:$B$2000,$A93,'Saisie hebdo'!$C$5:$C$2000,$B93) | E93: =SUMIFS('Saisie hebdo'!$G$5:$G$2000,'Saisie hebdo'!$B$5:$B$2000,$A93,'Saisie hebdo'!$C$5:$C$2000,$B93) | F93: =SUMIFS('Saisie hebdo'!$H$5:$H$2000,'Saisie hebdo'!$B$5:$B$2000,$A93,'Saisie hebdo'!$C$5:$C$2000,$B93) | G93: =IFERROR(AVERAGEIFS('Saisie hebdo'!$I$5:$I$2000,'Saisie hebdo'!$B$5:$B$2000,$A93,'Saisie hebdo'!$C$5:$C$2000,$B93),"") | H93: =IFERROR(AVERAGEIFS('Saisie hebdo'!$J$5:$J$2000,'Saisie hebdo'!$B$5:$B$2000,$A93,'Saisie hebdo'!$C$5:$C$2000,$B93),"") | I93: =SUMIFS('Saisie hebdo'!$K$5:$K$2000,'Saisie hebdo'!$B$5:$B$2000,$A93,'Saisie hebdo'!$C$5:$C$2000,$B93) | J93: =SUMIFS('Saisie hebdo'!$L$5:$L$2000,'Saisie hebdo'!$B$5:$B$2000,$A93,'Saisie hebdo'!$C$5:$C$2000,$B93) | K93: =SUMIFS('Saisie hebdo'!$M$5:$M$2000,'Saisie hebdo'!$B$5:$B$2000,$A93,'Saisie hebdo'!$C$5:$C$2000,$B93) | L93: =SUMIFS('Saisie hebdo'!$N$5:$N$2000,'Saisie hebdo'!$B$5:$B$2000,$A93,'Saisie hebdo'!$C$5:$C$2000,$B93) | M93: =SUMIFS('Saisie hebdo'!$O$5:$O$2000,'Saisie hebdo'!$B$5:$B$2000,$A93,'Saisie hebdo'!$C$5:$C$2000,$B93) | N93: =IF(N(D93)=0,"",E93/D93) | O93: =IF(N(E93)=0,"",C93/E93) | P93: =IF(N(E93)=0,"",F93/E93) | Q93: =IF(N(F93)=0,"",C93/F93) | R93: =IF(N(I93)=0,"",C93/I93) | S93: =IF(N(J93)=0,"",C93/J93) | T93: =IF(N(L93)=0,"",C93/L93) | U93: =IF(N(I93)=0,"",J93/I93) | V93: =IF(N(K93)=0,"",L93/K93) | W93: =IF(N(C93)=0,"",M93/C93)
A94: 46631 | B94: S-FR | Corporatif & Fêtes | C94: =SUMIFS('Saisie hebdo'!$E$5:$E$2000,'Saisie hebdo'!$B$5:$B$2000,$A94,'Saisie hebdo'!$C$5:$C$2000,$B94) | D94: =SUMIFS('Saisie hebdo'!$F$5:$F$2000,'Saisie hebdo'!$B$5:$B$2000,$A94,'Saisie hebdo'!$C$5:$C$2000,$B94) | E94: =SUMIFS('Saisie hebdo'!$G$5:$G$2000,'Saisie hebdo'!$B$5:$B$2000,$A94,'Saisie hebdo'!$C$5:$C$2000,$B94) | F94: =SUMIFS('Saisie hebdo'!$H$5:$H$2000,'Saisie hebdo'!$B$5:$B$2000,$A94,'Saisie hebdo'!$C$5:$C$2000,$B94) | G94: =IFERROR(AVERAGEIFS('Saisie hebdo'!$I$5:$I$2000,'Saisie hebdo'!$B$5:$B$2000,$A94,'Saisie hebdo'!$C$5:$C$2000,$B94),"") | H94: =IFERROR(AVERAGEIFS('Saisie hebdo'!$J$5:$J$2000,'Saisie hebdo'!$B$5:$B$2000,$A94,'Saisie hebdo'!$C$5:$C$2000,$B94),"") | I94: =SUMIFS('Saisie hebdo'!$K$5:$K$2000,'Saisie hebdo'!$B$5:$B$2000,$A94,'Saisie hebdo'!$C$5:$C$2000,$B94) | J94: =SUMIFS('Saisie hebdo'!$L$5:$L$2000,'Saisie hebdo'!$B$5:$B$2000,$A94,'Saisie hebdo'!$C$5:$C$2000,$B94) | K94: =SUMIFS('Saisie hebdo'!$M$5:$M$2000,'Saisie hebdo'!$B$5:$B$2000,$A94,'Saisie hebdo'!$C$5:$C$2000,$B94) | L94: =SUMIFS('Saisie hebdo'!$N$5:$N$2000,'Saisie hebdo'!$B$5:$B$2000,$A94,'Saisie hebdo'!$C$5:$C$2000,$B94) | M94: =SUMIFS('Saisie hebdo'!$O$5:$O$2000,'Saisie hebdo'!$B$5:$B$2000,$A94,'Saisie hebdo'!$C$5:$C$2000,$B94) | N94: =IF(N(D94)=0,"",E94/D94) | O94: =IF(N(E94)=0,"",C94/E94) | P94: =IF(N(E94)=0,"",F94/E94) | Q94: =IF(N(F94)=0,"",C94/F94) | R94: =IF(N(I94)=0,"",C94/I94) | S94: =IF(N(J94)=0,"",C94/J94) | T94: =IF(N(L94)=0,"",C94/L94) | U94: =IF(N(I94)=0,"",J94/I94) | V94: =IF(N(K94)=0,"",L94/K94) | W94: =IF(N(C94)=0,"",M94/C94)
A95: 46631 | B95: S-FR | Événements privés | C95: =SUMIFS('Saisie hebdo'!$E$5:$E$2000,'Saisie hebdo'!$B$5:$B$2000,$A95,'Saisie hebdo'!$C$5:$C$2000,$B95) | D95: =SUMIFS('Saisie hebdo'!$F$5:$F$2000,'Saisie hebdo'!$B$5:$B$2000,$A95,'Saisie hebdo'!$C$5:$C$2000,$B95) | E95: =SUMIFS('Saisie hebdo'!$G$5:$G$2000,'Saisie hebdo'!$B$5:$B$2000,$A95,'Saisie hebdo'!$C$5:$C$2000,$B95) | F95: =SUMIFS('Saisie hebdo'!$H$5:$H$2000,'Saisie hebdo'!$B$5:$B$2000,$A95,'Saisie hebdo'!$C$5:$C$2000,$B95) | G95: =IFERROR(AVERAGEIFS('Saisie hebdo'!$I$5:$I$2000,'Saisie hebdo'!$B$5:$B$2000,$A95,'Saisie hebdo'!$C$5:$C$2000,$B95),"") | H95: =IFERROR(AVERAGEIFS('Saisie hebdo'!$J$5:$J$2000,'Saisie hebdo'!$B$5:$B$2000,$A95,'Saisie hebdo'!$C$5:$C$2000,$B95),"") | I95: =SUMIFS('Saisie hebdo'!$K$5:$K$2000,'Saisie hebdo'!$B$5:$B$2000,$A95,'Saisie hebdo'!$C$5:$C$2000,$B95) | J95: =SUMIFS('Saisie hebdo'!$L$5:$L$2000,'Saisie hebdo'!$B$5:$B$2000,$A95,'Saisie hebdo'!$C$5:$C$2000,$B95) | K95: =SUMIFS('Saisie hebdo'!$M$5:$M$2000,'Saisie hebdo'!$B$5:$B$2000,$A95,'Saisie hebdo'!$C$5:$C$2000,$B95) | L95: =SUMIFS('Saisie hebdo'!$N$5:$N$2000,'Saisie hebdo'!$B$5:$B$2000,$A95,'Saisie hebdo'!$C$5:$C$2000,$B95) | M95: =SUMIFS('Saisie hebdo'!$O$5:$O$2000,'Saisie hebdo'!$B$5:$B$2000,$A95,'Saisie hebdo'!$C$5:$C$2000,$B95) | N95: =IF(N(D95)=0,"",E95/D95) | O95: =IF(N(E95)=0,"",C95/E95) | P95: =IF(N(E95)=0,"",F95/E95) | Q95: =IF(N(F95)=0,"",C95/F95) | R95: =IF(N(I95)=0,"",C95/I95) | S95: =IF(N(J95)=0,"",C95/J95) | T95: =IF(N(L95)=0,"",C95/L95) | U95: =IF(N(I95)=0,"",J95/I95) | V95: =IF(N(K95)=0,"",L95/K95) | W95: =IF(N(C95)=0,"",M95/C95)
A96: 46631 | B96: S-EN | Corporate Montréal | C96: =SUMIFS('Saisie hebdo'!$E$5:$E$2000,'Saisie hebdo'!$B$5:$B$2000,$A96,'Saisie hebdo'!$C$5:$C$2000,$B96) | D96: =SUMIFS('Saisie hebdo'!$F$5:$F$2000,'Saisie hebdo'!$B$5:$B$2000,$A96,'Saisie hebdo'!$C$5:$C$2000,$B96) | E96: =SUMIFS('Saisie hebdo'!$G$5:$G$2000,'Saisie hebdo'!$B$5:$B$2000,$A96,'Saisie hebdo'!$C$5:$C$2000,$B96) | F96: =SUMIFS('Saisie hebdo'!$H$5:$H$2000,'Saisie hebdo'!$B$5:$B$2000,$A96,'Saisie hebdo'!$C$5:$C$2000,$B96) | G96: =IFERROR(AVERAGEIFS('Saisie hebdo'!$I$5:$I$2000,'Saisie hebdo'!$B$5:$B$2000,$A96,'Saisie hebdo'!$C$5:$C$2000,$B96),"") | H96: =IFERROR(AVERAGEIFS('Saisie hebdo'!$J$5:$J$2000,'Saisie hebdo'!$B$5:$B$2000,$A96,'Saisie hebdo'!$C$5:$C$2000,$B96),"") | I96: =SUMIFS('Saisie hebdo'!$K$5:$K$2000,'Saisie hebdo'!$B$5:$B$2000,$A96,'Saisie hebdo'!$C$5:$C$2000,$B96) | J96: =SUMIFS('Saisie hebdo'!$L$5:$L$2000,'Saisie hebdo'!$B$5:$B$2000,$A96,'Saisie hebdo'!$C$5:$C$2000,$B96) | K96: =SUMIFS('Saisie hebdo'!$M$5:$M$2000,'Saisie hebdo'!$B$5:$B$2000,$A96,'Saisie hebdo'!$C$5:$C$2000,$B96) | L96: =SUMIFS('Saisie hebdo'!$N$5:$N$2000,'Saisie hebdo'!$B$5:$B$2000,$A96,'Saisie hebdo'!$C$5:$C$2000,$B96) | M96: =SUMIFS('Saisie hebdo'!$O$5:$O$2000,'Saisie hebdo'!$B$5:$B$2000,$A96,'Saisie hebdo'!$C$5:$C$2000,$B96) | N96: =IF(N(D96)=0,"",E96/D96) | O96: =IF(N(E96)=0,"",C96/E96) | P96: =IF(N(E96)=0,"",F96/E96) | Q96: =IF(N(F96)=0,"",C96/F96) | R96: =IF(N(I96)=0,"",C96/I96) | S96: =IF(N(J96)=0,"",C96/J96) | T96: =IF(N(L96)=0,"",C96/L96) | U96: =IF(N(I96)=0,"",J96/I96) | V96: =IF(N(K96)=0,"",L96/K96) | W96: =IF(N(C96)=0,"",M96/C96)
A97: 46631 | B97: S-FR | Québec-Lévis (test) | C97: =SUMIFS('Saisie hebdo'!$E$5:$E$2000,'Saisie hebdo'!$B$5:$B$2000,$A97,'Saisie hebdo'!$C$5:$C$2000,$B97) | D97: =SUMIFS('Saisie hebdo'!$F$5:$F$2000,'Saisie hebdo'!$B$5:$B$2000,$A97,'Saisie hebdo'!$C$5:$C$2000,$B97) | E97: =SUMIFS('Saisie hebdo'!$G$5:$G$2000,'Saisie hebdo'!$B$5:$B$2000,$A97,'Saisie hebdo'!$C$5:$C$2000,$B97) | F97: =SUMIFS('Saisie hebdo'!$H$5:$H$2000,'Saisie hebdo'!$B$5:$B$2000,$A97,'Saisie hebdo'!$C$5:$C$2000,$B97) | G97: =IFERROR(AVERAGEIFS('Saisie hebdo'!$I$5:$I$2000,'Saisie hebdo'!$B$5:$B$2000,$A97,'Saisie hebdo'!$C$5:$C$2000,$B97),"") | H97: =IFERROR(AVERAGEIFS('Saisie hebdo'!$J$5:$J$2000,'Saisie hebdo'!$B$5:$B$2000,$A97,'Saisie hebdo'!$C$5:$C$2000,$B97),"") | I97: =SUMIFS('Saisie hebdo'!$K$5:$K$2000,'Saisie hebdo'!$B$5:$B$2000,$A97,'Saisie hebdo'!$C$5:$C$2000,$B97) | J97: =SUMIFS('Saisie hebdo'!$L$5:$L$2000,'Saisie hebdo'!$B$5:$B$2000,$A97,'Saisie hebdo'!$C$5:$C$2000,$B97) | K97: =SUMIFS('Saisie hebdo'!$M$5:$M$2000,'Saisie hebdo'!$B$5:$B$2000,$A97,'Saisie hebdo'!$C$5:$C$2000,$B97) | L97: =SUMIFS('Saisie hebdo'!$N$5:$N$2000,'Saisie hebdo'!$B$5:$B$2000,$A97,'Saisie hebdo'!$C$5:$C$2000,$B97) | M97: =SUMIFS('Saisie hebdo'!$O$5:$O$2000,'Saisie hebdo'!$B$5:$B$2000,$A97,'Saisie hebdo'!$C$5:$C$2000,$B97) | N97: =IF(N(D97)=0,"",E97/D97) | O97: =IF(N(E97)=0,"",C97/E97) | P97: =IF(N(E97)=0,"",F97/E97) | Q97: =IF(N(F97)=0,"",C97/F97) | R97: =IF(N(I97)=0,"",C97/I97) | S97: =IF(N(J97)=0,"",C97/J97) | T97: =IF(N(L97)=0,"",C97/L97) | U97: =IF(N(I97)=0,"",J97/I97) | V97: =IF(N(K97)=0,"",L97/K97) | W97: =IF(N(C97)=0,"",M97/C97)
A98: 46631 | B98: Demand Gen | C98: =SUMIFS('Saisie hebdo'!$E$5:$E$2000,'Saisie hebdo'!$B$5:$B$2000,$A98,'Saisie hebdo'!$C$5:$C$2000,$B98) | D98: =SUMIFS('Saisie hebdo'!$F$5:$F$2000,'Saisie hebdo'!$B$5:$B$2000,$A98,'Saisie hebdo'!$C$5:$C$2000,$B98) | E98: =SUMIFS('Saisie hebdo'!$G$5:$G$2000,'Saisie hebdo'!$B$5:$B$2000,$A98,'Saisie hebdo'!$C$5:$C$2000,$B98) | F98: =SUMIFS('Saisie hebdo'!$H$5:$H$2000,'Saisie hebdo'!$B$5:$B$2000,$A98,'Saisie hebdo'!$C$5:$C$2000,$B98) | G98: =IFERROR(AVERAGEIFS('Saisie hebdo'!$I$5:$I$2000,'Saisie hebdo'!$B$5:$B$2000,$A98,'Saisie hebdo'!$C$5:$C$2000,$B98),"") | H98: =IFERROR(AVERAGEIFS('Saisie hebdo'!$J$5:$J$2000,'Saisie hebdo'!$B$5:$B$2000,$A98,'Saisie hebdo'!$C$5:$C$2000,$B98),"") | I98: =SUMIFS('Saisie hebdo'!$K$5:$K$2000,'Saisie hebdo'!$B$5:$B$2000,$A98,'Saisie hebdo'!$C$5:$C$2000,$B98) | J98: =SUMIFS('Saisie hebdo'!$L$5:$L$2000,'Saisie hebdo'!$B$5:$B$2000,$A98,'Saisie hebdo'!$C$5:$C$2000,$B98) | K98: =SUMIFS('Saisie hebdo'!$M$5:$M$2000,'Saisie hebdo'!$B$5:$B$2000,$A98,'Saisie hebdo'!$C$5:$C$2000,$B98) | L98: =SUMIFS('Saisie hebdo'!$N$5:$N$2000,'Saisie hebdo'!$B$5:$B$2000,$A98,'Saisie hebdo'!$C$5:$C$2000,$B98) | M98: =SUMIFS('Saisie hebdo'!$O$5:$O$2000,'Saisie hebdo'!$B$5:$B$2000,$A98,'Saisie hebdo'!$C$5:$C$2000,$B98) | N98: =IF(N(D98)=0,"",E98/D98) | O98: =IF(N(E98)=0,"",C98/E98) | P98: =IF(N(E98)=0,"",F98/E98) | Q98: =IF(N(F98)=0,"",C98/F98) | R98: =IF(N(I98)=0,"",C98/I98) | S98: =IF(N(J98)=0,"",C98/J98) | T98: =IF(N(L98)=0,"",C98/L98) | U98: =IF(N(I98)=0,"",J98/I98) | V98: =IF(N(K98)=0,"",L98/K98) | W98: =IF(N(C98)=0,"",M98/C98)
A99: 46631 | B99: Microsoft Ads | C99: =SUMIFS('Saisie hebdo'!$E$5:$E$2000,'Saisie hebdo'!$B$5:$B$2000,$A99,'Saisie hebdo'!$C$5:$C$2000,$B99) | D99: =SUMIFS('Saisie hebdo'!$F$5:$F$2000,'Saisie hebdo'!$B$5:$B$2000,$A99,'Saisie hebdo'!$C$5:$C$2000,$B99) | E99: =SUMIFS('Saisie hebdo'!$G$5:$G$2000,'Saisie hebdo'!$B$5:$B$2000,$A99,'Saisie hebdo'!$C$5:$C$2000,$B99) | F99: =SUMIFS('Saisie hebdo'!$H$5:$H$2000,'Saisie hebdo'!$B$5:$B$2000,$A99,'Saisie hebdo'!$C$5:$C$2000,$B99) | G99: =IFERROR(AVERAGEIFS('Saisie hebdo'!$I$5:$I$2000,'Saisie hebdo'!$B$5:$B$2000,$A99,'Saisie hebdo'!$C$5:$C$2000,$B99),"") | H99: =IFERROR(AVERAGEIFS('Saisie hebdo'!$J$5:$J$2000,'Saisie hebdo'!$B$5:$B$2000,$A99,'Saisie hebdo'!$C$5:$C$2000,$B99),"") | I99: =SUMIFS('Saisie hebdo'!$K$5:$K$2000,'Saisie hebdo'!$B$5:$B$2000,$A99,'Saisie hebdo'!$C$5:$C$2000,$B99) | J99: =SUMIFS('Saisie hebdo'!$L$5:$L$2000,'Saisie hebdo'!$B$5:$B$2000,$A99,'Saisie hebdo'!$C$5:$C$2000,$B99) | K99: =SUMIFS('Saisie hebdo'!$M$5:$M$2000,'Saisie hebdo'!$B$5:$B$2000,$A99,'Saisie hebdo'!$C$5:$C$2000,$B99) | L99: =SUMIFS('Saisie hebdo'!$N$5:$N$2000,'Saisie hebdo'!$B$5:$B$2000,$A99,'Saisie hebdo'!$C$5:$C$2000,$B99) | M99: =SUMIFS('Saisie hebdo'!$O$5:$O$2000,'Saisie hebdo'!$B$5:$B$2000,$A99,'Saisie hebdo'!$C$5:$C$2000,$B99) | N99: =IF(N(D99)=0,"",E99/D99) | O99: =IF(N(E99)=0,"",C99/E99) | P99: =IF(N(E99)=0,"",F99/E99) | Q99: =IF(N(F99)=0,"",C99/F99) | R99: =IF(N(I99)=0,"",C99/I99) | S99: =IF(N(J99)=0,"",C99/J99) | T99: =IF(N(L99)=0,"",C99/L99) | U99: =IF(N(I99)=0,"",J99/I99) | V99: =IF(N(K99)=0,"",L99/K99) | W99: =IF(N(C99)=0,"",M99/C99)
A100: 46631 | B100: Total du compte | C100: =SUMIFS('Saisie hebdo'!$E$5:$E$2000,'Saisie hebdo'!$B$5:$B$2000,$A100) | D100: =SUMIFS('Saisie hebdo'!$F$5:$F$2000,'Saisie hebdo'!$B$5:$B$2000,$A100) | E100: =SUMIFS('Saisie hebdo'!$G$5:$G$2000,'Saisie hebdo'!$B$5:$B$2000,$A100) | F100: =SUMIFS('Saisie hebdo'!$H$5:$H$2000,'Saisie hebdo'!$B$5:$B$2000,$A100) | G100: =IFERROR(AVERAGEIFS('Saisie hebdo'!$I$5:$I$2000,'Saisie hebdo'!$B$5:$B$2000,$A100),"") | H100: =IFERROR(AVERAGEIFS('Saisie hebdo'!$J$5:$J$2000,'Saisie hebdo'!$B$5:$B$2000,$A100),"") | I100: =SUMIFS('Saisie hebdo'!$K$5:$K$2000,'Saisie hebdo'!$B$5:$B$2000,$A100) | J100: =SUMIFS('Saisie hebdo'!$L$5:$L$2000,'Saisie hebdo'!$B$5:$B$2000,$A100) | K100: =SUMIFS('Saisie hebdo'!$M$5:$M$2000,'Saisie hebdo'!$B$5:$B$2000,$A100) | L100: =SUMIFS('Saisie hebdo'!$N$5:$N$2000,'Saisie hebdo'!$B$5:$B$2000,$A100) | M100: =SUMIFS('Saisie hebdo'!$O$5:$O$2000,'Saisie hebdo'!$B$5:$B$2000,$A100) | N100: =IF(N(D100)=0,"",E100/D100) | O100: =IF(N(E100)=0,"",C100/E100) | P100: =IF(N(E100)=0,"",F100/E100) | Q100: =IF(N(F100)=0,"",C100/F100) | R100: =IF(N(I100)=0,"",C100/I100) | S100: =IF(N(J100)=0,"",C100/J100) | T100: =IF(N(L100)=0,"",C100/L100) | U100: =IF(N(I100)=0,"",J100/I100) | V100: =IF(N(K100)=0,"",L100/K100) | W100: =IF(N(C100)=0,"",M100/C100)
A102: Cumul octobre 2026 à septembre 2027
...

Sheet Règles
A1: Règles de décision — statut automatique
A2: Basé sur les 4 dernières semaines saisies (≈ 30 jours) et, pour les contrats et le ROAS, sur le cumul (les contrats arrivent avec un délai). Seuils modifiables dans « Cibles ». Rouge = ALERTE (agir aujourd'hui) · Jaune = À FAIRE · Vert = OK · Gris = pas de données / sans objet.
A4: Dernière semaine saisie (auto) | B4: =SUMPRODUCT(MAX(('Saisie hebdo'!$E$5:$E$2000<>"")*'Saisie hebdo'!$A$5:$A$2000)) | C4: =IF(B4=0,"Aucune donnée saisie pour l'instant","") | E4: Alertes (rouge) | F4: =COUNTIF(E24:K36,"ALERTE*")
A5: Forcer une autre semaine (optionnel, un lundi) | E5: À faire (jaune) | F5: =COUNTIF(E24:K36,"À FAIRE*")
A6: Semaine de référence utilisée | B6: =IF(B5<>"",B5,B4) | E6: OK (vert) | F6: =COUNTIF(E24:K36,"OK*")
A7: Période 4 semaines (≈ 30 jours) | B7: =B6-21 | C7: =B6+6
A8: Période 2 semaines (14 jours) | B8: =B6-7 | C8: =B6+6
A10: 1. Indicateurs par campagne (calcul automatique)
A11: Campagne | B11: Coût 4 sem. | C11: Conversions Google 4 sem. | D11: Leads 4 sem. | E11: Qualifiés 4 sem. | F11: Contrats 4 sem. | G11: Valeur 4 sem. | H11: Coût par lead 4 sem. | I11: % qualifiés 4 sem. | J11: Part perdue classement (moy. 4 sem.) | K11: CPA Google 4 sem. | L11: CPA cible suggéré (+10 %) | M11: Coût 2 sem. | N11: Qualifiés 2 sem. | O11: Coût par lead qualifié 2 sem. | P11: CPC moyen semaine de réf. | Q11: Coût cumulé | R11: Leads cumulés | S11: Qualifiés cumulés | T11: Contrats cumulés | U11: Valeur cumulée | V11: Coût par lead cumulé | W11: Coût par contrat cumulé | X11: ROAS cumulé
A12: S-FR | Marque | B12: =SUMIFS('Saisie hebdo'!$E$5:$E$2000,'Saisie hebdo'!$C$5:$C$2000,$A12,'Saisie hebdo'!$A$5:$A$2000,">="&Debut4,'Saisie hebdo'!$A$5:$A$2000,"<="&Sem_ref) | C12: =SUMIFS('Saisie hebdo'!$H$5:$H$2000,'Saisie hebdo'!$C$5:$C$2000,$A12,'Saisie hebdo'!$A$5:$A$2000,">="&Debut4,'Saisie hebdo'!$A$5:$A$2000,"<="&Sem_ref) | D12: =SUMIFS('Saisie hebdo'!$K$5:$K$2000,'Saisie hebdo'!$C$5:$C$2000,$A12,'Saisie hebdo'!$A$5:$A$2000,">="&Debut4,'Saisie hebdo'!$A$5:$A$2000,"<="&Sem_ref) | E12: =SUMIFS('Saisie hebdo'!$L$5:$L$2000,'Saisie hebdo'!$C$5:$C$2000,$A12,'Saisie hebdo'!$A$5:$A$2000,">="&Debut4,'Saisie hebdo'!$A$5:$A$2000,"<="&Sem_ref) | F12: =SUMIFS('Saisie hebdo'!$N$5:$N$2000,'Saisie hebdo'!$C$5:$C$2000,$A12,'Saisie hebdo'!$A$5:$A$2000,">="&Debut4,'Saisie hebdo'!$A$5:$A$2000,"<="&Sem_ref) | G12: =SUMIFS('Saisie hebdo'!$O$5:$O$2000,'Saisie hebdo'!$C$5:$C$2000,$A12,'Saisie hebdo'!$A$5:$A$2000,">="&Debut4,'Saisie hebdo'!$A$5:$A$2000,"<="&Sem_ref) | H12: =IF(N(D12)=0,"",B12/D12) | I12: =IF(N(D12)=0,"",E12/D12) | J12: =IFERROR(AVERAGEIFS('Saisie hebdo'!$J$5:$J$2000,'Saisie hebdo'!$C$5:$C$2000,$A12,'Saisie hebdo'!$A$5:$A$2000,">="&Debut4,'Saisie hebdo'!$A$5:$A$2000,"<="&Sem_ref),"") | K12: =IF(N(C12)=0,"",B12/C12) | L12: =IF(K12="","",K12*(1+S_CPAmaj)) | M12: =SUMIFS('Saisie hebdo'!$E$5:$E$2000,'Saisie hebdo'!$C$5:$C$2000,$A12,'Saisie hebdo'!$A$5:$A$2000,">="&Debut2,'Saisie hebdo'!$A$5:$A$2000,"<="&Sem_ref) | N12: =SUMIFS('Saisie hebdo'!$L$5:$L$2000,'Saisie hebdo'!$C$5:$C$2000,$A12,'Saisie hebdo'!$A$5:$A$2000,">="&Debut2,'Saisie hebdo'!$A$5:$A$2000,"<="&Sem_ref) | O12: =IF(N(N12)=0,"",M12/N12) | P12: =IFERROR(SUMIFS('Saisie hebdo'!$E$5:$E$2000,'Saisie hebdo'!$C$5:$C$2000,$A12,'Saisie hebdo'!$A$5:$A$2000,Sem_ref)/SUMIFS('Saisie hebdo'!$G$5:$G$2000,'Saisie hebdo'!$C$5:$C$2000,$A12,'Saisie hebdo'!$A$5:$A$2000,Sem_ref),"") | Q12: =SUMIFS('Saisie hebdo'!$E$5:$E$2000,'Saisie hebdo'!$C$5:$C$2000,$A12,'Saisie hebdo'!$A$5:$A$2000,"<="&Sem_ref) | R12: =SUMIFS('Saisie hebdo'!$K$5:$K$2000,'Saisie hebdo'!$C$5:$C$2000,$A12,'Saisie hebdo'!$A$5:$A$2000,"<="&Sem_ref) | S12: =SUMIFS('Saisie hebdo'!$L$5:$L$2000,'Saisie hebdo'!$C$5:$C$2000,$A12,'Saisie hebdo'!$A$5:$A$2000,"<="&Sem_ref) | T12: =SUMIFS('Saisie hebdo'!$N$5:$N$2000,'Saisie hebdo'!$C$5:$C$2000,$A12,'Saisie hebdo'!$A$5:$A$2000,"<="&Sem_ref) | U12: =SUMIFS('Saisie hebdo'!$O$5:$O$2000,'Saisie hebdo'!$C$5:$C$2000,$A12,'Saisie hebdo'!$A$5:$A$2000,"<="&Sem_ref) | V12: =IF(N(R12)=0,"",Q12/R12) | W12: =IF(N(T12)=0,"",Q12/T12) | X12: =IF(N(Q12)=0,"",U12/Q12)
A13: S-FR | Corporatif & Fêtes | B13: =SUMIFS('Saisie hebdo'!$E$5:$E$2000,'Saisie hebdo'!$C$5:$C$2000,$A13,'Saisie hebdo'!$A$5:$A$2000,">="&Debut4,'Saisie hebdo'!$A$5:$A$2000,"<="&Sem_ref) | C13: =SUMIFS('Saisie hebdo'!$H$5:$H$2000,'Saisie hebdo'!$C$5:$C$2000,$A13,'Saisie hebdo'!$A$5:$A$2000,">="&Debut4,'Saisie hebdo'!$A$5:$A$2000,"<="&Sem_ref) | D13: =SUMIFS('Saisie hebdo'!$K$5:$K$2000,'Saisie hebdo'!$C$5:$C$2000,$A13,'Saisie hebdo'!$A$5:$A$2000,">="&Debut4,'Saisie hebdo'!$A$5:$A$2000,"<="&Sem_ref) | E13: =SUMIFS('Saisie hebdo'!$L$5:$L$2000,'Saisie hebdo'!$C$5:$C$2000,$A13,'Saisie hebdo'!$A$5:$A$2000,">="&Debut4,'Saisie hebdo'!$A$5:$A$2000,"<="&Sem_ref) | F13: =SUMIFS('Saisie hebdo'!$N$5:$N$2000,'Saisie hebdo'!$C$5:$C$2000,$A13,'Saisie hebdo'!$A$5:$A$2000,">="&Debut4,'Saisie hebdo'!$A$5:$A$2000,"<="&Sem_ref) | G13: =SUMIFS('Saisie hebdo'!$O$5:$O$2000,'Saisie hebdo'!$C$5:$C$2000,$A13,'Saisie hebdo'!$A$5:$A$2000,">="&Debut4,'Saisie hebdo'!$A$5:$A$2000,"<="&Sem_ref) | H13: =IF(N(D13)=0,"",B13/D13) | I13: =IF(N(D13)=0,"",E13/D13) | J13: =IFERROR(AVERAGEIFS('Saisie hebdo'!$J$5:$J$2000,'Saisie hebdo'!$C$5:$C$2000,$A13,'Saisie hebdo'!$A$5:$A$2000,">="&Debut4,'Saisie hebdo'!$A$5:$A$2000,"<="&Sem_ref),"") | K13: =IF(N(C13)=0,"",B13/C13) | L13: =IF(K13="","",K13*(1+S_CPAmaj)) | M13: =SUMIFS('Saisie hebdo'!$E$5:$E$2000,'Saisie hebdo'!$C$5:$C$2000,$A13,'Saisie hebdo'!$A$5:$A$2000,">="&Debut2,'Saisie hebdo'!$A$5:$A$2000,"<="&Sem_ref) | N13: =SUMIFS('Saisie hebdo'!$L$5:$L$2000,'Saisie hebdo'!$C$5:$C$2000,$A13,'Saisie hebdo'!$A$5:$A$2000,">="&Debut2,'Saisie hebdo'!$A$5:$A$2000,"<="&Sem_ref) | O13: =IF(N(N13)=0,"",M13/N13) | P13: =IFERROR(SUMIFS('Saisie hebdo'!$E$5:$E$2000,'Saisie hebdo'!$C$5:$C$2000,$A13,'Saisie hebdo'!$A$5:$A$2000,Sem_ref)/SUMIFS('Saisie hebdo'!$G$5:$G$2000,'Saisie hebdo'!$C$5:$C$2000,$A13,'Saisie hebdo'!$A$5:$A$2000,Sem_ref),"") | Q13: =SUMIFS('Saisie hebdo'!$E$5:$E$2000,'Saisie hebdo'!$C$5:$C$2000,$A13,'Saisie hebdo'!$A$5:$A$2000,"<="&Sem_ref) | R13: =SUMIFS('Saisie hebdo'!$K$5:$K$2000,'Saisie hebdo'!$C$5:$C$2000,$A13,'Saisie hebdo'!$A$5:$A$2000,"<="&Sem_ref) | S13: =SUMIFS('Saisie hebdo'!$L$5:$L$2000,'Saisie hebdo'!$C$5:$C$2000,$A13,'Saisie hebdo'!$A$5:$A$2000,"<="&Sem_ref) | T13: =SUMIFS('Saisie hebdo'!$N$5:$N$2000,'Saisie hebdo'!$C$5:$C$2000,$A13,'Saisie hebdo'!$A$5:$A$2000,"<="&Sem_ref) | U13: =SUMIFS('Saisie hebdo'!$O$5:$O$2000,'Saisie hebdo'!$C$5:$C$2000,$A13,'Saisie hebdo'!$A$5:$A$2000,"<="&Sem_ref) | V13: =IF(N(R13)=0,"",Q13/R13) | W13: =IF(N(T13)=0,"",Q13/T13) | X13: =IF(N(Q13)=0,"",U13/Q13)
A14: S-FR | Événements privés | B14: =SUMIFS('Saisie hebdo'!$E$5:$E$2000,'Saisie hebdo'!$C$5:$C$2000,$A14,'Saisie hebdo'!$A$5:$A$2000,">="&Debut4,'Saisie hebdo'!$A$5:$A$2000,"<="&Sem_ref) | C14: =SUMIFS('Saisie hebdo'!$H$5:$H$2000,'Saisie hebdo'!$C$5:$C$2000,$A14,'Saisie hebdo'!$A$5:$A$2000,">="&Debut4,'Saisie hebdo'!$A$5:$A$2000,"<="&Sem_ref) | D14: =SUMIFS('Saisie hebdo'!$K$5:$K$2000,'Saisie hebdo'!$C$5:$C$2000,$A14,'Saisie hebdo'!$A$5:$A$2000,">="&Debut4,'Saisie hebdo'!$A$5:$A$2000,"<="&Sem_ref) | E14: =SUMIFS('Saisie hebdo'!$L$5:$L$2000,'Saisie hebdo'!$C$5:$C$2000,$A14,'Saisie hebdo'!$A$5:$A$2000,">="&Debut4,'Saisie hebdo'!$A$5:$A$2000,"<="&Sem_ref) | F14: =SUMIFS('Saisie hebdo'!$N$5:$N$2000,'Saisie hebdo'!$C$5:$C$2000,$A14,'Saisie hebdo'!$A$5:$A$2000,">="&Debut4,'Saisie hebdo'!$A$5:$A$2000,"<="&Sem_ref) | G14: =SUMIFS('Saisie hebdo'!$O$5:$O$2000,'Saisie hebdo'!$C$5:$C$2000,$A14,'Saisie hebdo'!$A$5:$A$2000,">="&Debut4,'Saisie hebdo'!$A$5:$A$2000,"<="&Sem_ref) | H14: =IF(N(D14)=0,"",B14/D14) | I14: =IF(N(D14)=0,"",E14/D14) | J14: =IFERROR(AVERAGEIFS('Saisie hebdo'!$J$5:$J$2000,'Saisie hebdo'!$C$5:$C$2000,$A14,'Saisie hebdo'!$A$5:$A$2000,">="&Debut4,'Saisie hebdo'!$A$5:$A$2000,"<="&Sem_ref),"") | K14: =IF(N(C14)=0,"",B14/C14) | L14: =IF(K14="","",K14*(1+S_CPAmaj)) | M14: =SUMIFS('Saisie hebdo'!$E$5:$E$2000,'Saisie hebdo'!$C$5:$C$2000,$A14,'Saisie hebdo'!$A$5:$A$2000,">="&Debut2,'Saisie hebdo'!$A$5:$A$2000,"<="&Sem_ref) | N14: =SUMIFS('Saisie hebdo'!$L$5:$L$2000,'Saisie hebdo'!$C$5:$C$2000,$A14,'Saisie hebdo'!$A$5:$A$2000,">="&Debut2,'Saisie hebdo'!$A$5:$A$2000,"<="&Sem_ref) | O14: =IF(N(N14)=0,"",M14/N14) | P14: =IFERROR(SUMIFS('Saisie hebdo'!$E$5:$E$2000,'Saisie hebdo'!$C$5:$C$2000,$A14,'Saisie hebdo'!$A$5:$A$2000,Sem_ref)/SUMIFS('Saisie hebdo'!$G$5:$G$2000,'Saisie hebdo'!$C$5:$C$2000,$A14,'Saisie hebdo'!$A$5:$A$2000,Sem_ref),"") | Q14: =SUMIFS('Saisie hebdo'!$E$5:$E$2000,'Saisie hebdo'!$C$5:$C$2000,$A14,'Saisie hebdo'!$A$5:$A$2000,"<="&Sem_ref) | R14: =SUMIFS('Saisie hebdo'!$K$5:$K$2000,'Saisie hebdo'!$C$5:$C$2000,$A14,'Saisie hebdo'!$A$5:$A$2000,"<="&Sem_ref) | S14: =SUMIFS('Saisie hebdo'!$L$5:$L$2000,'Saisie hebdo'!$C$5:$C$2000,$A14,'Saisie hebdo'!$A$5:$A$2000,"<="&Sem_ref) | T14: =SUMIFS('Saisie hebdo'!$N$5:$N$2000,'Saisie hebdo'!$C$5:$C$2000,$A14,'Saisie hebdo'!$A$5:$A$2000,"<="&Sem_ref) | U14: =SUMIFS('Saisie hebdo'!$O$5:$O$2000,'Saisie hebdo'!$C$5:$C$2000,$A14,'Saisie hebdo'!$A$5:$A$2000,"<="&Sem_ref) | V14: =IF(N(R14)=0,"",Q14/R14) | W14: =IF(N(T14)=0,"",Q14/T14) | X14: =IF(N(Q14)=0,"",U14/Q14)
A15: S-EN | Corporate Montréal | B15: =SUMIFS('Saisie hebdo'!$E$5:$E$2000,'Saisie hebdo'!$C$5:$C$2000,$A15,'Saisie hebdo'!$A$5:$A$2000,">="&Debut4,'Saisie hebdo'!$A$5:$A$2000,"<="&Sem_ref) | C15: =SUMIFS('Saisie hebdo'!$H$5:$H$2000,'Saisie hebdo'!$C$5:$C$2000,$A15,'Saisie hebdo'!$A$5:$A$2000,">="&Debut4,'Saisie hebdo'!$A$5:$A$2000,"<="&Sem_ref) | D15: =SUMIFS('Saisie hebdo'!$K$5:$K$2000,'Saisie hebdo'!$C$5:$C$2000,$A15,'Saisie hebdo'!$A$5:$A$2000,">="&Debut4,'Saisie hebdo'!$A$5:$A$2000,"<="&Sem_ref) | E15: =SUMIFS('Saisie hebdo'!$L$5:$L$2000,'Saisie hebdo'!$C$5:$C$2000,$A15,'Saisie hebdo'!$A$5:$A$2000,">="&Debut4,'Saisie hebdo'!$A$5:$A$2000,"<="&Sem_ref) | F15: =SUMIFS('Saisie hebdo'!$N$5:$N$2000,'Saisie hebdo'!$C$5:$C$2000,$A15,'Saisie hebdo'!$A$5:$A$2000,">="&Debut4,'Saisie hebdo'!$A$5:$A$2000,"<="&Sem_ref) | G15: =SUMIFS('Saisie hebdo'!$O$5:$O$2000,'Saisie hebdo'!$C$5:$C$2000,$A15,'Saisie hebdo'!$A$5:$A$2000,">="&Debut4,'Saisie hebdo'!$A$5:$A$2000,"<="&Sem_ref) | H15: =IF(N(D15)=0,"",B15/D15) | I15: =IF(N(D15)=0,"",E15/D15) | J15: =IFERROR(AVERAGEIFS('Saisie hebdo'!$J$5:$J$2000,'Saisie hebdo'!$C$5:$C$2000,$A15,'Saisie hebdo'!$A$5:$A$2000,">="&Debut4,'Saisie hebdo'!$A$5:$A$2000,"<="&Sem_ref),"") | K15: =IF(N(C15)=0,"",B15/C15) | L15: =IF(K15="","",K15*(1+S_CPAmaj)) | M15: =SUMIFS('Saisie hebdo'!$E$5:$E$2000,'Saisie hebdo'!$C$5:$C$2000,$A15,'Saisie hebdo'!$A$5:$A$2000,">="&Debut2,'Saisie hebdo'!$A$5:$A$2000,"<="&Sem_ref) | N15: =SUMIFS('Saisie hebdo'!$L$5:$L$2000,'Saisie hebdo'!$C$5:$C$2000,$A15,'Saisie hebdo'!$A$5:$A$2000,">="&Debut2,'Saisie hebdo'!$A$5:$A$2000,"<="&Sem_ref) | O15: =IF(N(N15)=0,"",M15/N15) | P15: =IFERROR(SUMIFS('Saisie hebdo'!$E$5:$E$2000,'Saisie hebdo'!$C$5:$C$2000,$A15,'Saisie hebdo'!$A$5:$A$2000,Sem_ref)/SUMIFS('Saisie hebdo'!$G$5:$G$2000,'Saisie hebdo'!$C$5:$C$2000,$A15,'Saisie hebdo'!$A$5:$A$2000,Sem_ref),"") | Q15: =SUMIFS('Saisie hebdo'!$E$5:$E$2000,'Saisie hebdo'!$C$5:$C$2000,$A15,'Saisie hebdo'!$A$5:$A$2000,"<="&Sem_ref) | R15: =SUMIFS('Saisie hebdo'!$K$5:$K$2000,'Saisie hebdo'!$C$5:$C$2000,$A15,'Saisie hebdo'!$A$5:$A$2000,"<="&Sem_ref) | S15: =SUMIFS('Saisie hebdo'!$L$5:$L$2000,'Saisie hebdo'!$C$5:$C$2000,$A15,'Saisie hebdo'!$A$5:$A$2000,"<="&Sem_ref) | T15: =SUMIFS('Saisie hebdo'!$N$5:$N$2000,'Saisie hebdo'!$C$5:$C$2000,$A15,'Saisie hebdo'!$A$5:$A$2000,"<="&Sem_ref) | U15: =SUMIFS('Saisie hebdo'!$O$5:$O$2000,'Saisie hebdo'!$C$5:$C$2000,$A15,'Saisie hebdo'!$A$5:$A$2000,"<="&Sem_ref) | V15: =IF(N(R15)=0,"",Q15/R15) | W15: =IF(N(T15)=0,"",Q15/T15) | X15: =IF(N(Q15)=0,"",U15/Q15)
A16: S-FR | Québec-Lévis (test) | B16: =SUMIFS('Saisie hebdo'!$E$5:$E$2000,'Saisie hebdo'!$C$5:$C$2000,$A16,'Saisie hebdo'!$A$5:$A$2000,">="&Debut4,'Saisie hebdo'!$A$5:$A$2000,"<="&Sem_ref) | C16: =SUMIFS('Saisie hebdo'!$H$5:$H$2000,'Saisie hebdo'!$C$5:$C$2000,$A16,'Saisie hebdo'!$A$5:$A$2000,">="&Debut4,'Saisie hebdo'!$A$5:$A$2000,"<="&Sem_ref) | D16: =SUMIFS('Saisie hebdo'!$K$5:$K$2000,'Saisie hebdo'!$C$5:$C$2000,$A16,'Saisie hebdo'!$A$5:$A$2000,">="&Debut4,'Saisie hebdo'!$A$5:$A$2000,"<="&Sem_ref) | E16: =SUMIFS('Saisie hebdo'!$L$5:$L$2000,'Saisie hebdo'!$C$5:$C$2000,$A16,'Saisie hebdo'!$A$5:$A$2000,">="&Debut4,'Saisie hebdo'!$A$5:$A$2000,"<="&Sem_ref) | F16: =SUMIFS('Saisie hebdo'!$N$5:$N$2000,'Saisie hebdo'!$C$5:$C$2000,$A16,'Saisie hebdo'!$A$5:$A$2000,">="&Debut4,'Saisie hebdo'!$A$5:$A$2000,"<="&Sem_ref) | G16: =SUMIFS('Saisie hebdo'!$O$5:$O$2000,'Saisie hebdo'!$C$5:$C$2000,$A16,'Saisie hebdo'!$A$5:$A$2000,">="&Debut4,'Saisie hebdo'!$A$5:$A$2000,"<="&Sem_ref) | H16: =IF(N(D16)=0,"",B16/D16) | I16: =IF(N(D16)=0,"",E16/D16) | J16: =IFERROR(AVERAGEIFS('Saisie hebdo'!$J$5:$J$2000,'Saisie hebdo'!$C$5:$C$2000,$A16,'Saisie hebdo'!$A$5:$A$2000,">="&Debut4,'Saisie hebdo'!$A$5:$A$2000,"<="&Sem_ref),"") | K16: =IF(N(C16)=0,"",B16/C16) | L16: =IF(K16="","",K16*(1+S_CPAmaj)) | M16: =SUMIFS('Saisie hebdo'!$E$5:$E$2000,'Saisie hebdo'!$C$5:$C$2000,$A16,'Saisie hebdo'!$A$5:$A$2000,">="&Debut2,'Saisie hebdo'!$A$5:$A$2000,"<="&Sem_ref) | N16: =SUMIFS('Saisie hebdo'!$L$5:$L$2000,'Saisie hebdo'!$C$5:$C$2000,$A16,'Saisie hebdo'!$A$5:$A$2000,">="&Debut2,'Saisie hebdo'!$A$5:$A$2000,"<="&Sem_ref) | O16: =IF(N(N16)=0,"",M16/N16) | P16: =IFERROR(SUMIFS('Saisie hebdo'!$E$5:$E$2000,'Saisie hebdo'!$C$5:$C$2000,$A16,'Saisie hebdo'!$A$5:$A$2000,Sem_ref)/SUMIFS('Saisie hebdo'!$G$5:$G$2000,'Saisie hebdo'!$C$5:$C$2000,$A16,'Saisie hebdo'!$A$5:$A$2000,Sem_ref),"") | Q16: =SUMIFS('Saisie hebdo'!$E$5:$E$2000,'Saisie hebdo'!$C$5:$C$2000,$A16,'Saisie hebdo'!$A$5:$A$2000,"<="&Sem_ref) | R16: =SUMIFS('Saisie hebdo'!$K$5:$K$2000,'Saisie hebdo'!$C$5:$C$2000,$A16,'Saisie hebdo'!$A$5:$A$2000,"<="&Sem_ref) | S16: =SUMIFS('Saisie hebdo'!$L$5:$L$2000,'Saisie hebdo'!$C$5:$C$2000,$A16,'Saisie hebdo'!$A$5:$A$2000,"<="&Sem_ref) | T16: =SUMIFS('Saisie hebdo'!$N$5:$N$2000,'Saisie hebdo'!$C$5:$C$2000,$A16,'Saisie hebdo'!$A$5:$A$2000,"<="&Sem_ref) | U16: =SUMIFS('Saisie hebdo'!$O$5:$O$2000,'Saisie hebdo'!$C$5:$C$2000,$A16,'Saisie hebdo'!$A$5:$A$2000,"<="&Sem_ref) | V16: =IF(N(R16)=0,"",Q16/R16) | W16: =IF(N(T16)=0,"",Q16/T16) | X16: =IF(N(Q16)=0,"",U16/Q16)
A17: Demand Gen | B17: =SUMIFS('Saisie hebdo'!$E$5:$E$2000,'Saisie hebdo'!$C$5:$C$2000,$A17,'Saisie hebdo'!$A$5:$A$2000,">="&Debut4,'Saisie hebdo'!$A$5:$A$2000,"<="&Sem_ref) | C17: =SUMIFS('Saisie hebdo'!$H$5:$H$2000,'Saisie hebdo'!$C$5:$C$2000,$A17,'Saisie hebdo'!$A$5:$A$2000,">="&Debut4,'Saisie hebdo'!$A$5:$A$2000,"<="&Sem_ref) | D17: =SUMIFS('Saisie hebdo'!$K$5:$K$2000,'Saisie hebdo'!$C$5:$C$2000,$A17,'Saisie hebdo'!$A$5:$A$2000,">="&Debut4,'Saisie hebdo'!$A$5:$A$2000,"<="&Sem_ref) | E17: =SUMIFS('Saisie hebdo'!$L$5:$L$2000,'Saisie hebdo'!$C$5:$C$2000,$A17,'Saisie hebdo'!$A$5:$A$2000,">="&Debut4,'Saisie hebdo'!$A$5:$A$2000,"<="&Sem_ref) | F17: =SUMIFS('Saisie hebdo'!$N$5:$N$2000,'Saisie hebdo'!$C$5:$C$2000,$A17,'Saisie hebdo'!$A$5:$A$2000,">="&Debut4,'Saisie hebdo'!$A$5:$A$2000,"<="&Sem_ref) | G17: =SUMIFS('Saisie hebdo'!$O$5:$O$2000,'Saisie hebdo'!$C$5:$C$2000,$A17,'Saisie hebdo'!$A$5:$A$2000,">="&Debut4,'Saisie hebdo'!$A$5:$A$2000,"<="&Sem_ref) | H17: =IF(N(D17)=0,"",B17/D17) | I17: =IF(N(D17)=0,"",E17/D17) | J17: =IFERROR(AVERAGEIFS('Saisie hebdo'!$J$5:$J$2000,'Saisie hebdo'!$C$5:$C$2000,$A17,'Saisie hebdo'!$A$5:$A$2000,">="&Debut4,'Saisie hebdo'!$A$5:$A$2000,"<="&Sem_ref),"") | K17: =IF(N(C17)=0,"",B17/C17) | L17: =IF(K17="","",K17*(1+S_CPAmaj)) | M17: =SUMIFS('Saisie hebdo'!$E$5:$E$2000,'Saisie hebdo'!$C$5:$C$2000,$A17,'Saisie hebdo'!$A$5:$A$2000,">="&Debut2,'Saisie hebdo'!$A$5:$A$2000,"<="&Sem_ref) | N17: =SUMIFS('Saisie hebdo'!$L$5:$L$2000,'Saisie hebdo'!$C$5:$C$2000,$A17,'Saisie hebdo'!$A$5:$A$2000,">="&Debut2,'Saisie hebdo'!$A$5:$A$2000,"<="&Sem_ref) | O17: =IF(N(N17)=0,"",M17/N17) | P17: =IFERROR(SUMIFS('Saisie hebdo'!$E$5:$E$2000,'Saisie hebdo'!$C$5:$C$2000,$A17,'Saisie hebdo'!$A$5:$A$2000,Sem_ref)/SUMIFS('Saisie hebdo'!$G$5:$G$2000,'Saisie hebdo'!$C$5:$C$2000,$A17,'Saisie hebdo'!$A$5:$A$2000,Sem_ref),"") | Q17: =SUMIFS('Saisie hebdo'!$E$5:$E$2000,'Saisie hebdo'!$C$5:$C$2000,$A17,'Saisie hebdo'!$A$5:$A$2000,"<="&Sem_ref) | R17: =SUMIFS('Saisie hebdo'!$K$5:$K$2000,'Saisie hebdo'!$C$5:$C$2000,$A17,'Saisie hebdo'!$A$5:$A$2000,"<="&Sem_ref) | S17: =SUMIFS('Saisie hebdo'!$L$5:$L$2000,'Saisie hebdo'!$C$5:$C$2000,$A17,'Saisie hebdo'!$A$5:$A$2000,"<="&Sem_ref) | T17: =SUMIFS('Saisie hebdo'!$N$5:$N$2000,'Saisie hebdo'!$C$5:$C$2000,$A17,'Saisie hebdo'!$A$5:$A$2000,"<="&Sem_ref) | U17: =SUMIFS('Saisie hebdo'!$O$5:$O$2000,'Saisie hebdo'!$C$5:$C$2000,$A17,'Saisie hebdo'!$A$5:$A$2000,"<="&Sem_ref) | V17: =IF(N(R17)=0,"",Q17/R17) | W17: =IF(N(T17)=0,"",Q17/T17) | X17: =IF(N(Q17)=0,"",U17/Q17)
A18: Microsoft Ads | B18: =SUMIFS('Saisie hebdo'!$E$5:$E$2000,'Saisie hebdo'!$C$5:$C$2000,$A18,'Saisie hebdo'!$A$5:$A$2000,">="&Debut4,'Saisie hebdo'!$A$5:$A$2000,"<="&Sem_ref) | C18: =SUMIFS('Saisie hebdo'!$H$5:$H$2000,'Saisie hebdo'!$C$5:$C$2000,$A18,'Saisie hebdo'!$A$5:$A$2000,">="&Debut4,'Saisie hebdo'!$A$5:$A$2000,"<="&Sem_ref) | D18: =SUMIFS('Saisie hebdo'!$K$5:$K$2000,'Saisie hebdo'!$C$5:$C$2000,$A18,'Saisie hebdo'!$A$5:$A$2000,">="&Debut4,'Saisie hebdo'!$A$5:$A$2000,"<="&Sem_ref) | E18: =SUMIFS('Saisie hebdo'!$L$5:$L$2000,'Saisie hebdo'!$C$5:$C$2000,$A18,'Saisie hebdo'!$A$5:$A$2000,">="&Debut4,'Saisie hebdo'!$A$5:$A$2000,"<="&Sem_ref) | F18: =SUMIFS('Saisie hebdo'!$N$5:$N$2000,'Saisie hebdo'!$C$5:$C$2000,$A18,'Saisie hebdo'!$A$5:$A$2000,">="&Debut4,'Saisie hebdo'!$A$5:$A$2000,"<="&Sem_ref) | G18: =SUMIFS('Saisie hebdo'!$O$5:$O$2000,'Saisie hebdo'!$C$5:$C$2000,$A18,'Saisie hebdo'!$A$5:$A$2000,">="&Debut4,'Saisie hebdo'!$A$5:$A$2000,"<="&Sem_ref) | H18: =IF(N(D18)=0,"",B18/D18) | I18: =IF(N(D18)=0,"",E18/D18) | J18: =IFERROR(AVERAGEIFS('Saisie hebdo'!$J$5:$J$2000,'Saisie hebdo'!$C$5:$C$2000,$A18,'Saisie hebdo'!$A$5:$A$2000,">="&Debut4,'Saisie hebdo'!$A$5:$A$2000,"<="&Sem_ref),"") | K18: =IF(N(C18)=0,"",B18/C18) | L18: =IF(K18="","",K18*(1+S_CPAmaj)) | M18: =SUMIFS('Saisie hebdo'!$E$5:$E$2000,'Saisie hebdo'!$C$5:$C$2000,$A18,'Saisie hebdo'!$A$5:$A$2000,">="&Debut2,'Saisie hebdo'!$A$5:$A$2000,"<="&Sem_ref) | N18: =SUMIFS('Saisie hebdo'!$L$5:$L$2000,'Saisie hebdo'!$C$5:$C$2000,$A18,'Saisie hebdo'!$A$5:$A$2000,">="&Debut2,'Saisie hebdo'!$A$5:$A$2000,"<="&Sem_ref) | O18: =IF(N(N18)=0,"",M18/N18) | P18: =IFERROR(SUMIFS('Saisie hebdo'!$E$5:$E$2000,'Saisie hebdo'!$C$5:$C$2000,$A18,'Saisie hebdo'!$A$5:$A$2000,Sem_ref)/SUMIFS('Saisie hebdo'!$G$5:$G$2000,'Saisie hebdo'!$C$5:$C$2000,$A18,'Saisie hebdo'!$A$5:$A$2000,Sem_ref),"") | Q18: =SUMIFS('Saisie hebdo'!$E$5:$E$2000,'Saisie hebdo'!$C$5:$C$2000,$A18,'Saisie hebdo'!$A$5:$A$2000,"<="&Sem_ref) | R18: =SUMIFS('Saisie hebdo'!$K$5:$K$2000,'Saisie hebdo'!$C$5:$C$2000,$A18,'Saisie hebdo'!$A$5:$A$2000,"<="&Sem_ref) | S18: =SUMIFS('Saisie hebdo'!$L$5:$L$2000,'Saisie hebdo'!$C$5:$C$2000,$A18,'Saisie hebdo'!$A$5:$A$2000,"<="&Sem_ref) | T18: =SUMIFS('Saisie hebdo'!$N$5:$N$2000,'Saisie hebdo'!$C$5:$C$2000,$A18,'Saisie hebdo'!$A$5:$A$2000,"<="&Sem_ref) | U18: =SUMIFS('Saisie hebdo'!$O$5:$O$2000,'Saisie hebdo'!$C$5:$C$2000,$A18,'Saisie hebdo'!$A$5:$A$2000,"<="&Sem_ref) | V18: =IF(N(R18)=0,"",Q18/R18) | W18: =IF(N(T18)=0,"",Q18/T18) | X18: =IF(N(Q18)=0,"",U18/Q18)
A19: Total Google Search (5 campagnes) | B19: =SUM(B12:B16) | C19: =SUM(C12:C16) | D19: =SUM(D12:D16) | E19: =SUM(E12:E16) | F19: =SUM(F12:F16) | G19: =SUM(G12:G16) | H19: =IF(N(D19)=0,"",B19/D19) | I19: =IF(N(D19)=0,"",E19/D19) | J19: =IFERROR(AVERAGE(J12:J16),"") | K19: =IF(N(C19)=0,"",B19/C19) | L19: =IF(K19="","",K19*(1+S_CPAmaj)) | M19: =SUM(M12:M16) | N19: =SUM(N12:N16) | O19: =IF(N(N19)=0,"",M19/N19) | Q19: =SUM(Q12:Q16) | R19: =SUM(R12:R16) | S19: =SUM(S12:S16) | T19: =SUM(T12:T16) | U19: =SUM(U12:U16) | V19: =IF(N(R19)=0,"",Q19/R19) | W19: =IF(N(T19)=0,"",Q19/T19) | X19: =IF(N(Q19)=0,"",U19/Q19)
A20: Total du compte | B20: =SUM(B12:B18) | C20: =SUM(C12:C18) | D20: =SUM(D12:D18) | E20: =SUM(E12:E18) | F20: =SUM(F12:F18) | G20: =SUM(G12:G18) | H20: =IF(N(D20)=0,"",B20/D20) | I20: =IF(N(D20)=0,"",E20/D20) | J20: =IFERROR(AVERAGE(J12:J18),"") | K20: =IF(N(C20)=0,"",B20/C20) | L20: =IF(K20="","",K20*(1+S_CPAmaj)) | M20: =SUM(M12:M18) | N20: =SUM(N12:N18) | O20: =IF(N(N20)=0,"",M20/N20) | P20: =IFERROR(SUMIFS('Saisie hebdo'!$E$5:$E$2000,'Saisie hebdo'!$A$5:$A$2000,Sem_ref)/SUMIFS('Saisie hebdo'!$G$5:$G$2000,'Saisie hebdo'!$A$5:$A$2000,Sem_ref),"") | Q20: =SUM(Q12:Q18) | R20: =SUM(R12:R18) | S20: =SUM(S12:S18) | T20: =SUM(T12:T18) | U20: =SUM(U12:U18) | V20: =IF(N(R20)=0,"",Q20/R20) | W20: =IF(N(T20)=0,"",Q20/T20) | X20: =IF(N(Q20)=0,"",U20/Q20)
A22: 2. Règles du plan — que faire cette semaine ?
A23: Règle | B23: Déclencheur (seuil modifiable dans Cibles) | C23: Action prévue au plan | D23: Section | E23: S-FR | Marque | F23: S-FR | Corporatif & Fêtes | G23: S-FR | Événements privés | H23: S-EN | Corporate Montréal | I23: S-FR | Québec-Lévis (test) | J23: Demand Gen | K23: Microsoft Ads
A24: Passer en Max. conversions | B24: ="Conversions Google sur 4 sem. ≥ "&S_MaxConv | C24: Stratégie Max. conversions, sans cible (si pas déjà fait) | D24: 5 | E24: =IF($B$12=0,"— Pas de données",IF($C$12>=S_MaxConv,"À FAIRE : Passer en Max. conversions","OK — rester en Max. clics ("&ROUND($C$12,0)&"/"&S_MaxConv&")")) | F24: =IF($B$13=0,"— Pas de données",IF($C$13>=S_MaxConv,"À FAIRE : Passer en Max. conversions","OK — rester en Max. clics ("&ROUND($C$13,0)&"/"&S_MaxConv&")")) | G24: =IF($B$14=0,"— Pas de données",IF($C$14>=S_MaxConv,"À FAIRE : Passer en Max. conversions","OK — rester en Max. clics ("&ROUND($C$14,0)&"/"&S_MaxConv&")")) | H24: =IF($B$15=0,"— Pas de données",IF($C$15>=S_MaxConv,"À FAIRE : Passer en Max. conversions","OK — rester en Max. clics ("&ROUND($C$15,0)&"/"&S_MaxConv&")")) | I24: =IF($B$16=0,"— Pas de données",IF($C$16>=S_MaxConv,"À FAIRE : Passer en Max. conversions","OK — rester en Max. clics ("&ROUND($C$16,0)&"/"&S_MaxConv&")")) | J24: s.o. | K24: =IF($B$18=0,"— Pas de données",IF($C$18>=S_MaxConv,"À FAIRE : Passer en Max. conversions","OK — rester en Max. clics ("&ROUND($C$18,0)&"/"&S_MaxConv&")"))
A25: Passer en CPA cible | B25: ="Conversions Google sur 4 sem. ≥ "&S_CPAcible | C25: CPA cible = CPA 30 j + 10 %, puis −10 % toutes les 2-3 semaines | D25: 5 | E25: =IF($B$12=0,"— Pas de données",IF($C$12>=S_CPAcible,"À FAIRE : Passer en CPA cible ≈ "&ROUND($L$12,0)&" $","OK — pas encore ("&ROUND($C$12,0)&"/"&S_CPAcible&")")) | F25: =IF($B$13=0,"— Pas de données",IF($C$13>=S_CPAcible,"À FAIRE : Passer en CPA cible ≈ "&ROUND($L$13,0)&" $","OK — pas encore ("&ROUND($C$13,0)&"/"&S_CPAcible&")")) | G25: =IF($B$14=0,"— Pas de données",IF($C$14>=S_CPAcible,"À FAIRE : Passer en CPA cible ≈ "&ROUND($L$14,0)&" $","OK — pas encore ("&ROUND($C$14,0)&"/"&S_CPAcible&")")) | H25: =IF($B$15=0,"— Pas de données",IF($C$15>=S_CPAcible,"À FAIRE : Passer en CPA cible ≈ "&ROUND($L$15,0)&" $","OK — pas encore ("&ROUND($C$15,0)&"/"&S_CPAcible&")")) | I25: =IF($B$16=0,"— Pas de données",IF($C$16>=S_CPAcible,"À FAIRE : Passer en CPA cible ≈ "&ROUND($L$16,0)&" $","OK — pas encore ("&ROUND($C$16,0)&"/"&S_CPAcible&")")) | J25: s.o. | K25: =IF($B$18=0,"— Pas de données",IF($C$18>=S_CPAcible,"À FAIRE : Passer en CPA cible ≈ "&ROUND($L$18,0)&" $","OK — pas encore ("&ROUND($C$18,0)&"/"&S_CPAcible&")"))
A26: « Lead qualifié » en conversion principale | B26: ="Leads qualifiés sur 4 sem. ≥ "&S_Qualite | C26: Lead qualifié (import GCLID) = principale ; formulaire = secondaire | D26: 5 | E26: =IF($B$12=0,"— Pas de données",IF($E$12>=S_Qualite,"À FAIRE : Lead qualifié en conversion principale","OK — pas encore ("&$E$12&"/"&S_Qualite&")")) | F26: =IF($B$13=0,"— Pas de données",IF($E$13>=S_Qualite,"À FAIRE : Lead qualifié en conversion principale","OK — pas encore ("&$E$13&"/"&S_Qualite&")")) | G26: =IF($B$14=0,"— Pas de données",IF($E$14>=S_Qualite,"À FAIRE : Lead qualifié en conversion principale","OK — pas encore ("&$E$14&"/"&S_Qualite&")")) | H26: =IF($B$15=0,"— Pas de données",IF($E$15>=S_Qualite,"À FAIRE : Lead qualifié en conversion principale","OK — pas encore ("&$E$15&"/"&S_Qualite&")")) | I26: =IF($B$16=0,"— Pas de données",IF($E$16>=S_Qualite,"À FAIRE : Lead qualifié en conversion principale","OK — pas encore ("&$E$16&"/"&S_Qualite&")")) | J26: s.o. | K26: =IF($B$18=0,"— Pas de données",IF($E$18>=S_Qualite,"À FAIRE : Lead qualifié en conversion principale","OK — pas encore ("&$E$18&"/"&S_Qualite&")"))
A27: Passer en Max. valeur de conversion | B27: ="Contrats (conversions avec valeur) sur 4 sem. ≥ "&S_Valeur | C27: Max. valeur de conversion, puis ROAS cible | D27: 5 | E27: =IF($B$12=0,"— Pas de données",IF($F$12>=S_Valeur,"À FAIRE : Passer en Max. valeur de conversion","OK — pas encore ("&$F$12&"/"&S_Valeur&")")) | F27: =IF($B$13=0,"— Pas de données",IF($F$13>=S_Valeur,"À FAIRE : Passer en Max. valeur de conversion","OK — pas encore ("&$F$13&"/"&S_Valeur&")")) | G27: =IF($B$14=0,"— Pas de données",IF($F$14>=S_Valeur,"À FAIRE : Passer en Max. valeur de conversion","OK — pas encore ("&$F$14&"/"&S_Valeur&")")) | H27: =IF($B$15=0,"— Pas de données",IF($F$15>=S_Valeur,"À FAIRE : Passer en Max. valeur de conversion","OK — pas encore ("&$F$15&"/"&S_Valeur&")")) | I27: =IF($B$16=0,"— Pas de données",IF($F$16>=S_Valeur,"À FAIRE : Passer en Max. valeur de conversion","OK — pas encore ("&$F$16&"/"&S_Valeur&")")) | J27: s.o. | K27: =IF($B$18=0,"— Pas de données",IF($F$18>=S_Valeur,"À FAIRE : Passer en Max. valeur de conversion","OK — pas encore ("&$F$18&"/"&S_Valeur&")"))
A28: Coupe-circuit — coût par lead qualifié | B28: ="Coût par lead qualifié sur 2 sem. > "&S_CoupeCPLQ&" $" | C28: Revenir à l'étape d'enchères précédente | D28: 5 | E28: =IF($M$12=0,"— Pas de données",IF(IF($N$12=0,$M$12>S_CoupeCPLQ,$O$12>S_CoupeCPLQ),"ALERTE : Coupe-circuit — revenir à l'étape précédente","OK ("&IF($N$12=0,"0 qualifié",ROUND($O$12,0)&" $ / qualifié")&")")) | F28: =IF($M$13=0,"— Pas de données",IF(IF($N$13=0,$M$13>S_CoupeCPLQ,$O$13>S_CoupeCPLQ),"ALERTE : Coupe-circuit — revenir à l'étape précédente","OK ("&IF($N$13=0,"0 qualifié",ROUND($O$13,0)&" $ / qualifié")&")")) | G28: =IF($M$14=0,"— Pas de données",IF(IF($N$14=0,$M$14>S_CoupeCPLQ,$O$14>S_CoupeCPLQ),"ALERTE : Coupe-circuit — revenir à l'étape précédente","OK ("&IF($N$14=0,"0 qualifié",ROUND($O$14,0)&" $ / qualifié")&")")) | H28: =IF($M$15=0,"— Pas de données",IF(IF($N$15=0,$M$15>S_CoupeCPLQ,$O$15>S_CoupeCPLQ),"ALERTE : Coupe-circuit — revenir à l'étape précédente","OK ("&IF($N$15=0,"0 qualifié",ROUND($O$15,0)&" $ / qualifié")&")")) | I28: =IF($M$16=0,"— Pas de données",IF(IF($N$16=0,$M$16>S_CoupeCPLQ,$O$16>S_CoupeCPLQ),"ALERTE : Coupe-circuit — revenir à l'étape précédente","OK ("&IF($N$16=0,"0 qualifié",ROUND($O$16,0)&" $ / qualifié")&")")) | J28: =IF($M$17=0,"— Pas de données",IF(IF($N$17=0,$M$17>S_CoupeCPLQ,$O$17>S_CoupeCPLQ),"ALERTE : Coupe-circuit — revenir à l'étape précédente","OK ("&IF($N$17=0,"0 qualifié",ROUND($O$17,0)&" $ / qualifié")&")")) | K28: =IF($M$18=0,"— Pas de données",IF(IF($N$18=0,$M$18>S_CoupeCPLQ,$O$18>S_CoupeCPLQ),"ALERTE : Coupe-circuit — revenir à l'étape précédente","OK ("&IF($N$18=0,"0 qualifié",ROUND($O$18,0)&" $ / qualifié")&")"))
A29: Coupe-circuit — CPC | B29: ="CPC moyen de la semaine > "&S_CoupeCPC&" × CPC de référence" | C29: Revenir à l'étape d'enchères précédente (si 7 jours de suite) | D29: 5 | E29: =IF(Cibles!$C$36="","s.o.",IF($P$12="","— Pas de données",IF($P$12>S_CoupeCPC*Cibles!$C$36,"ALERTE : Coupe-circuit — CPC "&ROUND($P$12,2)&" $","OK ("&ROUND($P$12,2)&" $)"))) | F29: =IF(Cibles!$C$37="","s.o.",IF($P$13="","— Pas de données",IF($P$13>S_CoupeCPC*Cibles!$C$37,"ALERTE : Coupe-circuit — CPC "&ROUND($P$13,2)&" $","OK ("&ROUND($P$13,2)&" $)"))) | G29: =IF(Cibles!$C$38="","s.o.",IF($P$14="","— Pas de données",IF($P$14>S_CoupeCPC*Cibles!$C$38,"ALERTE : Coupe-circuit — CPC "&ROUND($P$14,2)&" $","OK ("&ROUND($P$14,2)&" $)"))) | H29: =IF(Cibles!$C$39="","s.o.",IF($P$15="","— Pas de données",IF($P$15>S_CoupeCPC*Cibles!$C$39,"ALERTE : Coupe-circuit — CPC "&ROUND($P$15,2)&" $","OK ("&ROUND($P$15,2)&" $)"))) | I29: =IF(Cibles!$C$40="","s.o.",IF($P$16="","— Pas de données",IF($P$16>S_CoupeCPC*Cibles!$C$40,"ALERTE : Coupe-circuit — CPC "&ROUND($P$16,2)&" $","OK ("&ROUND($P$16,2)&" $)"))) | J29: s.o. | K29: s.o.
A30: Qualité des leads | B30: ="% qualifiés (A/B/C) sur 4 sem. < "&ROUND(S_PctQual*100,0)&" %" | C30: Revoir mots-clés et négatifs (rapport Termes de recherche) | D30: 6 | E30: =IF($D$12=0,"— Pas de données",IF($I$12<S_PctQual,"À FAIRE : Revoir mots-clés/négatifs ("&ROUND($I$12*100,0)&" %)","OK ("&ROUND($I$12*100,0)&" % qualifiés)")) | F30: =IF($D$13=0,"— Pas de données",IF($I$13<S_PctQual,"À FAIRE : Revoir mots-clés/négatifs ("&ROUND($I$13*100,0)&" %)","OK ("&ROUND($I$13*100,0)&" % qualifiés)")) | G30: =IF($D$14=0,"— Pas de données",IF($I$14<S_PctQual,"À FAIRE : Revoir mots-clés/négatifs ("&ROUND($I$14*100,0)&" %)","OK ("&ROUND($I$14*100,0)&" % qualifiés)")) | H30: =IF($D$15=0,"— Pas de données",IF($I$15<S_PctQual,"À FAIRE : Revoir mots-clés/négatifs ("&ROUND($I$15*100,0)&" %)","OK ("&ROUND($I$15*100,0)&" % qualifiés)")) | I30: =IF($D$16=0,"— Pas de données",IF($I$16<S_PctQual,"À FAIRE : Revoir mots-clés/négatifs ("&ROUND($I$16*100,0)&" %)","OK ("&ROUND($I$16*100,0)&" % qualifiés)")) | J30: =IF($D$17=0,"— Pas de données",IF($I$17<S_PctQual,"À FAIRE : Revoir mots-clés/négatifs ("&ROUND($I$17*100,0)&" %)","OK ("&ROUND($I$17*100,0)&" % qualifiés)")) | K30: =IF($D$18=0,"— Pas de données",IF($I$18<S_PctQual,"À FAIRE : Revoir mots-clés/négatifs ("&ROUND($I$18*100,0)&" %)","OK ("&ROUND($I$18*100,0)&" % qualifiés)"))
A31: Coût par lead | B31: ="Coût par lead sur 4 sem. > "&Plafond_CPL&" $" | C31: Baisser les CPC max. ou resserrer les mots-clés | D31: Cibles | E31: =IF($B$12=0,"— Pas de données",IF($D$12=0,IF($B$12>Plafond_CPL,"À FAIRE : 0 lead pour "&ROUND($B$12,0)&" $ — vérifier le suivi","OK — trop tôt"),IF($H$12>Plafond_CPL,"À FAIRE : Coût par lead "&ROUND($H$12,0)&" $ > plafond","OK ("&ROUND($H$12,0)&" $ / lead)"))) | F31: =IF($B$13=0,"— Pas de données",IF($D$13=0,IF($B$13>Plafond_CPL,"À FAIRE : 0 lead pour "&ROUND($B$13,0)&" $ — vérifier le suivi","OK — trop tôt"),IF($H$13>Plafond_CPL,"À FAIRE : Coût par lead "&ROUND($H$13,0)&" $ > plafond","OK ("&ROUND($H$13,0)&" $ / lead)"))) | G31: =IF($B$14=0,"— Pas de données",IF($D$14=0,IF($B$14>Plafond_CPL,"À FAIRE : 0 lead pour "&ROUND($B$14,0)&" $ — vérifier le suivi","OK — trop tôt"),IF($H$14>Plafond_CPL,"À FAIRE : Coût par lead "&ROUND($H$14,0)&" $ > plafond","OK ("&ROUND($H$14,0)&" $ / lead)"))) | H31: =IF($B$15=0,"— Pas de données",IF($D$15=0,IF($B$15>Plafond_CPL,"À FAIRE : 0 lead pour "&ROUND($B$15,0)&" $ — vérifier le suivi","OK — trop tôt"),IF($H$15>Plafond_CPL,"À FAIRE : Coût par lead "&ROUND($H$15,0)&" $ > plafond","OK ("&ROUND($H$15,0)&" $ / lead)"))) | I31: =IF($B$16=0,"— Pas de données",IF($D$16=0,IF($B$16>Plafond_CPL,"À FAIRE : 0 lead pour "&ROUND($B$16,0)&" $ — vérifier le suivi","OK — trop tôt"),IF($H$16>Plafond_CPL,"À FAIRE : Coût par lead "&ROUND($H$16,0)&" $ > plafond","OK ("&ROUND($H$16,0)&" $ / lead)"))) | J31: =IF($B$17=0,"— Pas de données",IF($D$17=0,IF($B$17>Plafond_CPL,"À FAIRE : 0 lead pour "&ROUND($B$17,0)&" $ — vérifier le suivi","OK — trop tôt"),IF($H$17>Plafond_CPL,"À FAIRE : Coût par lead "&ROUND($H$17,0)&" $ > plafond","OK ("&ROUND($H$17,0)&" $ / lead)"))) | K31: =IF($B$18=0,"— Pas de données",IF($D$18=0,IF($B$18>Plafond_CPL,"À FAIRE : 0 lead pour "&ROUND($B$18,0)&" $ — vérifier le suivi","OK — trop tôt"),IF($H$18>Plafond_CPL,"À FAIRE : Coût par lead "&ROUND($H$18,0)&" $ > plafond","OK ("&ROUND($H$18,0)&" $ / lead)")))
A32: Hausser les CPC (levier 1) | B32: ="Part perdue (classement) > "&ROUND(S_PerdueClass*100,0)&" % et coût par lead ≤ "&Plafond_CPL&" $" | C32: Hausser CPC max. +20 %/sem. sur les mots-clés rentables (arrêt si CPA +25 %) | D32: 7 | E32: =IF($B$12=0,"— Pas de données",IF($J$12="","— Part perdue non saisie",IF(AND($J$12>S_PerdueClass,$D$12>0,N($H$12)<=Plafond_CPL),"À FAIRE : Hausser CPC +"&ROUND(S_HausseCPC*100,0)&" %",IF($J$12>S_PerdueClass,"OK — part perdue élevée mais CPA hors cible : ne pas hausser","OK")))) | F32: =IF($B$13=0,"— Pas de données",IF($J$13="","— Part perdue non saisie",IF(AND($J$13>S_PerdueClass,$D$13>0,N($H$13)<=Plafond_CPL),"À FAIRE : Hausser CPC +"&ROUND(S_HausseCPC*100,0)&" %",IF($J$13>S_PerdueClass,"OK — part perdue élevée mais CPA hors cible : ne pas hausser","OK")))) | G32: =IF($B$14=0,"— Pas de données",IF($J$14="","— Part perdue non saisie",IF(AND($J$14>S_PerdueClass,$D$14>0,N($H$14)<=Plafond_CPL),"À FAIRE : Hausser CPC +"&ROUND(S_HausseCPC*100,0)&" %",IF($J$14>S_PerdueClass,"OK — part perdue élevée mais CPA hors cible : ne pas hausser","OK")))) | H32: =IF($B$15=0,"— Pas de données",IF($J$15="","— Part perdue non saisie",IF(AND($J$15>S_PerdueClass,$D$15>0,N($H$15)<=Plafond_CPL),"À FAIRE : Hausser CPC +"&ROUND(S_HausseCPC*100,0)&" %",IF($J$15>S_PerdueClass,"OK — part perdue élevée mais CPA hors cible : ne pas hausser","OK")))) | I32: =IF($B$16=0,"— Pas de données",IF($J$16="","— Part perdue non saisie",IF(AND($J$16>S_PerdueClass,$D$16>0,N($H$16)<=Plafond_CPL),"À FAIRE : Hausser CPC +"&ROUND(S_HausseCPC*100,0)&" %",IF($J$16>S_PerdueClass,"OK — part perdue élevée mais CPA hors cible : ne pas hausser","OK")))) | J32: s.o. | K32: =IF($B$18=0,"— Pas de données",IF($J$18="","— Part perdue non saisie",IF(AND($J$18>S_PerdueClass,$D$18>0,N($H$18)<=Plafond_CPL),"À FAIRE : Hausser CPC +"&ROUND(S_HausseCPC*100,0)&" %",IF($J$18>S_PerdueClass,"OK — part perdue élevée mais CPA hors cible : ne pas hausser","OK"))))
A33: Coût par contrat | B33: ="Coût par contrat cumulé > "&ROUND(Plafond_contrat_pct*100,0)&" % du panier ("&ROUND(Plafond_contrat,0)&" $)" | C33: Revoir ciblage, annonces et suivi des leads (vitesse de rappel) | D33: Cibles | E33: =IF($Q$12=0,"— Pas de données",IF($T$12=0,IF($Q$12>Plafond_contrat,"À FAIRE : 0 contrat pour "&ROUND($Q$12,0)&" $ — relancer les soumissions","OK — trop tôt"),IF($W$12>Plafond_contrat,"ALERTE : "&ROUND($W$12,0)&" $ par contrat > plafond","OK ("&ROUND($W$12,0)&" $ / contrat)"))) | F33: =IF($Q$13=0,"— Pas de données",IF($T$13=0,IF($Q$13>Plafond_contrat,"À FAIRE : 0 contrat pour "&ROUND($Q$13,0)&" $ — relancer les soumissions","OK — trop tôt"),IF($W$13>Plafond_contrat,"ALERTE : "&ROUND($W$13,0)&" $ par contrat > plafond","OK ("&ROUND($W$13,0)&" $ / contrat)"))) | G33: =IF($Q$14=0,"— Pas de données",IF($T$14=0,IF($Q$14>Plafond_contrat,"À FAIRE : 0 contrat pour "&ROUND($Q$14,0)&" $ — relancer les soumissions","OK — trop tôt"),IF($W$14>Plafond_contrat,"ALERTE : "&ROUND($W$14,0)&" $ par contrat > plafond","OK ("&ROUND($W$14,0)&" $ / contrat)"))) | H33: =IF($Q$15=0,"— Pas de données",IF($T$15=0,IF($Q$15>Plafond_contrat,"À FAIRE : 0 contrat pour "&ROUND($Q$15,0)&" $ — relancer les soumissions","OK — trop tôt"),IF($W$15>Plafond_contrat,"ALERTE : "&ROUND($W$15,0)&" $ par contrat > plafond","OK ("&ROUND($W$15,0)&" $ / contrat)"))) | I33: =IF($Q$16=0,"— Pas de données",IF($T$16=0,IF($Q$16>Plafond_contrat,"À FAIRE : 0 contrat pour "&ROUND($Q$16,0)&" $ — relancer les soumissions","OK — trop tôt"),IF($W$16>Plafond_contrat,"ALERTE : "&ROUND($W$16,0)&" $ par contrat > plafond","OK ("&ROUND($W$16,0)&" $ / contrat)"))) | J33: =IF($Q$17=0,"— Pas de données",IF($T$17=0,IF($Q$17>Plafond_contrat,"À FAIRE : 0 contrat pour "&ROUND($Q$17,0)&" $ — relancer les soumissions","OK — trop tôt"),IF($W$17>Plafond_contrat,"ALERTE : "&ROUND($W$17,0)&" $ par contrat > plafond","OK ("&ROUND($W$17,0)&" $ / contrat)"))) | K33: =IF($Q$18=0,"— Pas de données",IF($T$18=0,IF($Q$18>Plafond_contrat,"À FAIRE : 0 contrat pour "&ROUND($Q$18,0)&" $ — relancer les soumissions","OK — trop tôt"),IF($W$18>Plafond_contrat,"ALERTE : "&ROUND($W$18,0)&" $ par contrat > plafond","OK ("&ROUND($W$18,0)&" $ / contrat)")))
A34: Rentabilité (ROAS) | B34: ="ROAS cumulé < "&ROAS_min&":1 (point mort "&ROUND(ROAS_point_mort,1)&":1)" | C34: Sous le point mort : réduire le budget de la campagne | D34: Cibles | E34: =IF($Q$12=0,"— Pas de données",IF(AND($T$12=0,$Q$12<2*Plafond_contrat),"OK — trop tôt (aucun contrat)",IF($X$12<ROAS_point_mort,"ALERTE : ROAS "&ROUND($X$12,1)&":1 sous le point mort",IF($X$12<ROAS_min,"À FAIRE : ROAS "&ROUND($X$12,1)&":1 sous la cible","OK (ROAS "&ROUND($X$12,1)&":1)")))) | F34: =IF($Q$13=0,"— Pas de données",IF(AND($T$13=0,$Q$13<2*Plafond_contrat),"OK — trop tôt (aucun contrat)",IF($X$13<ROAS_point_mort,"ALERTE : ROAS "&ROUND($X$13,1)&":1 sous le point mort",IF($X$13<ROAS_min,"À FAIRE : ROAS "&ROUND($X$13,1)&":1 sous la cible","OK (ROAS "&ROUND($X$13,1)&":1)")))) | G34: =IF($Q$14=0,"— Pas de données",IF(AND($T$14=0,$Q$14<2*Plafond_contrat),"OK — trop tôt (aucun contrat)",IF($X$14<ROAS_point_mort,"ALERTE : ROAS "&ROUND($X$14,1)&":1 sous le point mort",IF($X$14<ROAS_min,"À FAIRE : ROAS "&ROUND($X$14,1)&":1 sous la cible","OK (ROAS "&ROUND($X$14,1)&":1)")))) | H34: =IF($Q$15=0,"— Pas de données",IF(AND($T$15=0,$Q$15<2*Plafond_contrat),"OK — trop tôt (aucun contrat)",IF($X$15<ROAS_point_mort,"ALERTE : ROAS "&ROUND($X$15,1)&":1 sous le point mort",IF($X$15<ROAS_min,"À FAIRE : ROAS "&ROUND($X$15,1)&":1 sous la cible","OK (ROAS "&ROUND($X$15,1)&":1)")))) | I34: =IF($Q$16=0,"— Pas de données",IF(AND($T$16=0,$Q$16<2*Plafond_contrat),"OK — trop tôt (aucun contrat)",IF($X$16<ROAS_point_mort,"ALERTE : ROAS "&ROUND($X$16,1)&":1 sous le point mort",IF($X$16<ROAS_min,"À FAIRE : ROAS "&ROUND($X$16,1)&":1 sous la cible","OK (ROAS "&ROUND($X$16,1)&":1)")))) | J34: =IF($Q$17=0,"— Pas de données",IF(AND($T$17=0,$Q$17<2*Plafond_contrat),"OK — trop tôt (aucun contrat)",IF($X$17<ROAS_point_mort,"ALERTE : ROAS "&ROUND($X$17,1)&":1 sous le point mort",IF($X$17<ROAS_min,"À FAIRE : ROAS "&ROUND($X$17,1)&":1 sous la cible","OK (ROAS "&ROUND($X$17,1)&":1)")))) | K34: =IF($Q$18=0,"— Pas de données",IF(AND($T$18=0,$Q$18<2*Plafond_contrat),"OK — trop tôt (aucun contrat)",IF($X$18<ROAS_point_mort,"ALERTE : ROAS "&ROUND($X$18,1)&":1 sous le point mort",IF($X$18<ROAS_min,"À FAIRE : ROAS "&ROUND($X$18,1)&":1 sous la cible","OK (ROAS "&ROUND($X$18,1)&":1)"))))
A35: Pause Demand Gen (leviers 2 et 4) | B35: ="Coût cumulé ≥ "&S_DG&" $ et 0 lead qualifié" | C35: Mettre Demand Gen en pause (remarketing : seuil 1 000 $) | D35: 7 | E35: s.o. | F35: s.o. | G35: s.o. | H35: s.o. | I35: s.o. | J35: =IF($Q$17=0,"— Pas de données",IF(AND($Q$17>=S_DG,$S$17=0),"ALERTE : Pause Demand Gen","OK ("&ROUND($Q$17,0)&" $ / "&$S$17&" qualifié(s))")) | K35: s.o.
A36: Pause Microsoft Ads (levier 3) | B36: ="Coût par lead cumulé > "&S_MS&" × Google Search" | C36: Mettre Microsoft Ads en pause | D36: 7 | E36: s.o. | F36: s.o. | G36: s.o. | H36: s.o. | I36: s.o. | J36: s.o. | K36: =IF($Q$18=0,"— Pas de données",IF($R$18=0,"À FAIRE : 0 lead pour "&ROUND($Q$18,0)&" $",IF($V$19="","— Pas de référence Google",IF($V$18>S_MS*$V$19,"ALERTE : Pause Microsoft Ads","OK ("&ROUND($V$18,0)&" $ vs "&ROUND($V$19,0)&" $)"))))
A38: Note : la règle Max. conversions reste « À FAIRE » tant que le seuil est atteint ; ignorez-la si la campagne y est déjà. Les règles d'arrêt sont aussi au plan (CPA +25 % après une hausse de CPC : revenir en arrière).

Sheet Cibles
A1: Cibles et hypothèses — modifiables
A2: Cellules jaunes = à ajuster. La feuille « Règles » lit ces valeurs : changez-les ici, jamais dans les formules.
A4: Panier moyen par type d'événement | B4: Panier moyen ($) | C4: Source / note
A5: Party de Bureau | B5: 1995 | C5: Forfait tout inclus — evenox.ca, 7 oct. 2026
A6: 5 à 7 d'équipe | B6: 1195 | C6: Forfait tout inclus — evenox.ca
A7: Gala Signature | B7: 2495 | C7: Forfait tout inclus — evenox.ca
A8: Décor WOW | B8: 899 | C8: Mariage et événement — evenox.ca
A9: Soirée Signature | B9: 1449 | C9: Mariage et événement — evenox.ca
A10: Photobooth Signature 3 h | B10: 799 | C10: Location photobooth — evenox.ca
A11: Panier moyen de référence | B11: =AVERAGE(B5:B10) | C11: Moyenne simple des 6 forfaits. Remplacez par votre panier réel (Valeur des contrats ÷ Contrats) après 10 contrats.
A13: Rentabilité | B13: Valeur | C13: Note
A14: Marge brute | B14: 0.5 | C14: À confirmer avec ta comptabilité.
A15: Plafond coût par lead | B15: 90 | C15: Au-delà : baisser les CPC ou resserrer les mots-clés.
A16: Plafond coût par contrat (% du panier) | B16: 0.15 | C16: 15 % du panier moyen de référence.
A17: Plafond coût par contrat ($) | B17: =B16*Panier_ref | C17: Calculé : % × panier de référence.
A18: ROAS minimum (cible) | B18: 3 | C18: Valeur des contrats ÷ coût publicitaire.
A19: ROAS point mort | B19: =1/Marge_brute | C19: Calculé : 1 ÷ marge brute (2:1 à 50 % de marge).
A21: Seuils des règles (plan, sections 5 à 7) | B21: Valeur | C21: Section du plan
A22: Conversions sur 30 jours → Max. conversions | B22: 15 | C22: 5 — Apprentissage
A23: Conversions sur 30 jours → CPA cible | B23: 30 | C23: 5 — Efficacité
A24: Majoration du CPA cible (CPA 30 j + …) | B24: 0.1 | C24: 5 — Efficacité
A25: Leads qualifiés / 30 jours → « Lead qualifié » en conversion principale | B25: 15 | C25: 5 — Qualité
A26: Contrats (conversions avec valeur) / 30 jours → Max. valeur | B26: 30 | C26: 5 — Valeur
A27: Coupe-circuit : coût par lead qualifié sur 14 jours | B27: 150 | C27: 5 — Coupe-circuit
A28: Coupe-circuit : CPC moyen > N × CPC de référence (7 jours) | B28: 2 | C28: 5 — Coupe-circuit
A29: % de leads qualifiés minimum | B29: 0.5 | C29: 6 — Routine
A30: Part d'impressions perdue (classement) maximum | B30: 0.3 | C30: 7 — Levier 1
A31: Hausse des CPC max. par semaine | B31: 0.2 | C31: 7 — Levier 1
A32: Demand Gen prospection : dépense max. sans lead qualifié | B32: 1500 | C32: 7 — Levier 2 (remarketing : 1 000 $)
A33: Microsoft Ads : coût par lead max. vs Google (×) | B33: 1.5 | C33: 7 — Levier 3
A35: Campagne | B35: Budget plafond / jour | C35: CPC max. de référence | D35: Statut au lancement
A36: S-FR | Marque | B36: 10 | C36: 2.5 | D36: À activer
A37: S-FR | Corporatif & Fêtes | B37: 170 | C37: 4 | D37: À activer
A38: S-FR | Événements privés | B38: 120 | C38: 3 | D38: À activer
A39: S-EN | Corporate Montréal | B39: 30 | C39: 5 | D39: En pause (réserve)
A40: S-FR | Québec-Lévis (test) | B40: 20 | C40: 3 | D40: En pause (réserve)
A41: Demand Gen | B41: 50 | D41: Levier 2 / 4 (section 7)
A42: Microsoft Ads | B42: 18 | D42: Levier 3 (section 7)
